Workbook
Name INTERCEPT_SCALED: Coefficients!$B$32
Name BASELINE_SMM: Coefficients!$B$33
Name BASELINE_CPR: Coefficients!$B$34

Sheet README
A1: V6F Voluntary Prepayment Calculator
A3: Model: V6F (24-feature logistic regression, test AUC 0.7854)
A4: Training period: 201812 to 202602
A5: Training events: 7,686 voluntary prepays in 982,361 eligible loan-months
A7: Tabs
A8: Coefficients - 24 feature parameters + intercept + diagnostics. Edit at your own risk.
A9: Loan_Snapshot - one row per loan, current-period CPR + per-feature attribution.
A10: Paste new loans into rows below the existing data; formulas autopopulate.
A11: Deal_Aggregator - UPB-weighted deal-level rollup. Edit Deal_ID column in Loan_Snapshot to control grouping.
A13: Math (centered native form)
A14: contribution_j = beta_native_j * (x_j - mean_j)
A15: logit_z = intercept_scaled + SUM(contributions)
... A37: Model: model_data_v6e.json (snapshot 202603)

Sheet Coefficients
A1: V6F Voluntary Prepayment Model - Coefficients
A2: Edit at your own risk. Loan_Snapshot pulls mean/std/beta_native from this tab.
A4: # | B4: feature | C4: group | D4: beta_scaled | E4: beta_native | F4: mean | G4: std | H4: label
A5: 1 | B5: gross_refi_incentive_bps | C5: Rate & Penalty | D5: 0.570192 | E5: 0.00310379 | F5: 2.265188 | G5: 183.70832 | H5: Gross refi incentive (bp, penalty-neutral)
A6: 2 | B6: prepay_penalty_points | C6: Rate & Penalty | D6: -0.363185 | E6: -0.10008426 | F6: 5.076951 | G6: 3.628791 | H6: Prepay penalty points (continuous 0-10)
A7: 3 | B7: age_0_36 | C7: Seasoning (piecewise) | D7: 0.271688 | E7: 0.0319566 | F7: 32.292252 | G7: 8.501787 | H7: Age 0-36m (piecewise)
A8: 4 | B8: age_36_120 | C8: Seasoning (piecewise) | D8: 0.193293 | E8: 0.00577619 | F8: 40.759952 | G8: 33.463732 | H8: Age 36-120m (piecewise)
A9: 5 | B9: age_120plus | C9: Seasoning (piecewise) | D9: -0.098758 | E9: -0.00340313 | F9: 11.313631 | G9: 29.01982 | H9: Age 120m+ (piecewise)
A10: 6 | B10: months_to_maturity | C10: Maturity | D10: -0.032003 | E10: -0.00036144 | F10: 328.58708 | G10: 88.544231 | H10: Months to maturity
A11: 7 | B11: pre_maturity_flag | C11: Maturity | D11: 0.11705 | E11: 2.7884682 | F11: 0.001765 | G11: 0.041976 | H11: Within 0-24m of maturity (1/0)
A12: 8 | B12: months_since_lockout_end | C12: Post-lockout surge | D12: -0.012941 | E12: -0.0012261 | F12: 6.432159 | G12: 10.554518 | H12: Months since lockout end (cap 24)
A13: 9 | B13: log_upb | C13: Size | D13: 0.41296 | E13: 0.33366269 | F13: 15.369157 | G13: 1.237657 | H13: Log UPB
A14: 10 | B14: small_loan | C14: Size | D14: -0.101312 | E14: -0.23837744 | F14: 0.236621 | G14: 0.425007 | H14: UPB < $2M (1/0)
A15: 11 | B15: large_loan | C15: Size | D15: -0.04312 | E15: -0.38151918 | F15: 0.012941 | G15: 0.113021 | H15: UPB > $50M (1/0)
A16: 12 | B16: burn_ratio | C16: Burnout & Regime | D16: 0.178127 | E16: 0.72898702 | F16: 0.195122 | G16: 0.244349 | H16: Burnout ratio (cum_itm / age)
... A28: 24 | B28: gross_refi__x__prepay_pen | C28: Interactions | D28: 0.637551 | E28: 0.00059719 | F28: -65.148699 | G28: 1067.5759 | H28: Interaction: gross_refi_incentive_bps x prepay_penalty_points
A31: Model constants
A32: intercept_scaled | B32: -5.525031
A33: baseline_SMM (sigmoid of intercept_scaled) | B33: =1/(1+EXP(-B32))
A34: baseline_CPR (annualized from baseline_SMM) | B34: =1-(1-B33)^12
A36: Diagnostics
A37: test_AUC | B37: 0.7854
A38: panel_mean_CPR | B38: 0.089951
A39: training_pop_n | B39: 982361
A40: training_events | B40: 7686
A41: panel_period_range | B41: 201812 - 202602

Sheet Loan_Snapshot
A1: Loan Identifiers | I1: Raw Inputs (editable) | V1: V6E Feature Values (formulas - do not edit) | AT1: Logit Contributions (β_native × (x − mean)) | BR1: CPR Summary | BV1: CPR Attribution (proportional method) | CT1: Check
A2: loan_id | B2: deal_id | C2: pool_cusip | D2: issuer_name | E2: fha_category | F2: loan_purpose | G2: vintage_year | H2: period | I2: upb | J2: loan_rate_pct | K2: plc_rate_bps | L2: prepay_penalty_points | M2: loan_age_months_in | N2: cum_itm_in | O2: loan_maturity_yyyymm | P2: lockout_end_yyyymm | Q2: issuer_number_str | R2: is_hc_232_raw | S2: is_223a7_raw | T2: is_538_raw | U2: is_new_construction_raw | V2: gross_refi_incentive_bps | W2: prepay_penalty_points | X2: age_0_36 | Y2: age_36_120 | Z2: age_120plus | AA2: months_to_maturity | AB2: pre_maturity_flag | AC2: months_since_lockout_end | AD2: log_upb | AE2: small_loan | AF2: large_loan | AG2: burn_ratio | AH2: is_post_covid | AI2: is_223a7 | AJ2: is_538 | AK2: is_hc_232 | AL2: lp_NC | AM2: iss_capital_funding | AN2: iss_pnc | AO2: iss_wells_fargo | AP2: iss_dwight | AQ2: iss_greystone | AR2: iss_lument_combined | AS2: gross_refi__x__prepay_pen | AT2: contrib_gross_refi_incentive_bps | AU2: contrib_prepay_penalty_points | AV2: contrib_age_0_36 | AW2: contrib_age_36_120 | AX2: contrib_age_120plus | AY2: contrib_months_to_maturity | AZ2: contrib_pre_maturity_flag | BA2: contrib_months_since_lockout_end | BB2: contrib_log_upb | BC2: contrib_small_loan | BD2: contrib_large_loan | BE2: contrib_burn_ratio | BF2: contrib_is_post_covid | BG2: contrib_is_223a7 | BH2: contrib_is_538 | BI2: contrib_is_hc_232 | BJ2: contrib_lp_NC | BK2: contrib_iss_capital_funding | BL2: contrib_iss_pnc | BM2: contrib_iss_wells_fargo | BN2: contrib_iss_dwight | BO2: contrib_iss_greystone | BP2: contrib_iss_lument_combined | BQ2: contrib_gross_refi__x__prepay_pen | BR2: total_logit_dev | BS2: logit_z | BT2: SMM | BU2: pred_CPR | BV2: attr_gross_refi_incentive_bps | BW2: attr_prepay_penalty_points | BX2: attr_age_0_36 | BY2: attr_age_36_120 | BZ2: attr_age_120plus | CA2: attr_months_to_maturity | CB2: attr_pre_maturity_flag | CC2: attr_months_since_lockout_end | CD2: attr_log_upb | CE2: attr_small_loan | CF2: attr_large_loan | CG2: attr_burn_ratio | CH2: attr_is_post_covid | CI2: attr_is_223a7 | CJ2: attr_is_538 | CK2: attr_is_hc_232 | CL2: attr_lp_NC | CM2: attr_iss_capital_funding | CN2: attr_iss_pnc | CO2: attr_iss_wells_fargo | CP2: attr_iss_dwight | CQ2: attr_iss_greystone | CR2: attr_iss_lument_combined | CS2: attr_gross_refi__x__prepay_pen | CT2: Sanity
A3: mean | V3: =Coefficients!$F$5 | W3: =Coefficients!$F$6 | X3: =Coefficients!$F$7 | Y3: =Coefficients!$F$8 | Z3: =Coefficients!$F$9 | AA3: =Coefficients!$F$10 | AB3: =Coefficients!$F$11 | AC3: =Coefficients!$F$12 | AD3: =Coefficients!$F$13 | AE3: =Coefficients!$F$14 | AF3: =Coefficients!$F$15 | AG3: =Coefficients!$F$16 | AH3: =Coefficients!$F$17 | AI3: =Coefficients!$F$18 | AJ3: =Coefficients!$F$19 | AK3: =Coefficients!$F$20 | AL3: =Coefficients!$F$21 | AM3: =Coefficients!$F$22 | AN3: =Coefficients!$F$23 | AO3: =Coefficients!$F$24 | AP3: =Coefficients!$F$25 | AQ3: =Coefficients!$F$26 | AR3: =Coefficients!$F$27 | AS3: =Coefficients!$F$28
A4: β_native | V4: =Coefficients!$E$5 | W4: =Coefficients!$E$6 | X4: =Coefficients!$E$7 | Y4: =Coefficients!$E$8 | Z4: =Coefficients!$E$9 | AA4: =Coefficients!$E$10 | AB4: =Coefficients!$E$11 | AC4: =Coefficients!$E$12 | AD4: =Coefficients!$E$13 | AE4: =Coefficients!$E$14 | AF4: =Coefficients!$E$15 | AG4: =Coefficients!$E$16 | AH4: =Coefficients!$E$17 | AI4: =Coefficients!$E$18 | AJ4: =Coefficients!$E$19 | AK4: =Coefficients!$E$20 | AL4: =Coefficients!$E$21 | AM4: =Coefficients!$E$22 | AN4: =Coefficients!$E$23 | AO4: =Coefficients!$E$24 | AP4: =Coefficients!$E$25 | AQ4: =Coefficients!$E$26 | AR4: =Coefficients!$E$27 | AS4: =Coefficients!$E$28
A5: 3617UAX72_000000012211373 | B5: LUMENT_PRE21 | C5: 3617UAX72 | D5: LUMENT REAL ESTATE CAPITAL,LLC | E5: 223f | F5: RP | G5: 2015 | H5: 202602 | I5: 4746336.8 | J5: 2.96 | K5: 447 | L5: 5 | M5: 122 | N5: 1 | O5: 205101 | Q5: 3896 | R5: 0 | S5: 0 | T5: 0 | U5: 0 | V5: =J5*100-K5 | W5: =L5 | X5: =MIN(M5,36) | Y5: =MIN(MAX(M5-36,0),84) | Z5: =MAX(M5-120,0) | AA5: =IF(OR(O5="",NOT(ISNUMBER(O5))),360,MAX(0,MIN(480,(INT(O5/100)-INT(VALUE(H5)/100))*12+MOD(O5,100)-MOD(VALUE(H5),100)))) | AB5: =IF(AND(AA5>0,AA5<=24),1,0) | AC5: =IF(OR(P5="",NOT(ISNUMBER(P5))),0,MAX(0,MIN(24,(INT(VALUE(H5)/100)-INT(P5/100))*12+MOD(VALUE(H5),100)-MOD(P5,100)))) | AD5: =LN(1+I5) | AE5: =IF(I5<2000000,1,0) | AF5: =IF(I5>50000000,1,0) | AG5: =IF(ISNUMBER(M5),N5/MAX(M5,1),0) | AH5: =IF(G5>=2021,1,0) | AI5: =S5 | AJ5: =T5 | AK5: =R5 | AL5: =U5 | AM5: =IF(ISNUMBER(SEARCH("CAPITAL FUNDING",D5)),1,0) | AN5: =IF(ISNUMBER(SEARCH("PNC",D5)),1,0) | AO5: =IF(ISNUMBER(SEARCH("WELLS FARGO",D5)),1,0) | AP5: =IF(ISNUMBER(SEARCH("DWIGHT",D5)),1,0) | AQ5: =IF(ISNUMBER(SEARCH("GREYSTONE",D5)),1,0) | AR5: =IF(OR(Q5="3896",Q5="3557"),1,0) | AS5: =V5*W5 | AT5: =V$4*(V5-V$3) | AU5: =W$4*(W5-W$3) | AV5: =X$4*(X5-X$3) | AW5: =Y$4*(Y5-Y$3) | AX5: =Z$4*(Z5-Z$3) | AY5: =AA$4*(AA5-AA$3) | AZ5: =AB$4*(AB5-AB$3) | BA5: =AC$4*(AC5-AC$3) | ... BQ5: =AS$4*(AS5-AS$3) | BR5: =SUM(AT5:BQ5) | BS5: =INTERCEPT_SCALED+BR5 | BT5: =1/(1+EXP(-BS5)) | BU5: =1-(1-BT5)^12 | BV5: =IFERROR(AT5/BR5*(BU5-BASELINE_CPR),0) | BW5: =IFERROR(AU5/BR5*(BU5-BASELINE_CPR),0) | BX5: =IFERROR(AV5/BR5*(BU5-BASELINE_CPR),0) | BY5: =IFERROR(AW5/BR5*(BU5-BASELINE_CPR),0) | BZ5: =IFERROR(AX5/BR5*(BU5-BASELINE_CPR),0) | CA5: =IFERROR(AY5/BR5*(BU5-BASELINE_CPR),0) | CB5: =IFERROR(AZ5/BR5*(BU5-BASELINE_CPR),0) | CC5: =IFERROR(BA5/BR5*(BU5-BASELINE_CPR),0) | CD5: =IFERROR(BB5/BR5*(BU5-BASELINE_CPR),0) | CE5: =IFERROR(BC5/BR5*(BU5-BASELINE_CPR),0) | CF5: =IFERROR(BD5/BR5*(BU5-BASELINE_CPR),0) | CG5: =IFERROR(BE5/BR5*(BU5-BASELINE_CPR),0) | CH5: =IFERROR(BF5/BR5*(BU5-BASELINE_CPR),0) | CI5: =IFERROR(BG5/BR5*(BU5-BASELINE_CPR),0) | CJ5: =IFERROR(BH5/BR5*(BU5-BASELINE_CPR),0) | CK5: =IFERROR(BI5/BR5*(BU5-BASELINE_CPR),0) | CL5: =IFERROR(BJ5/BR5*(BU5-BASELINE_CPR),0) | CM5: =IFERROR(BK5/BR5*(BU5-BASELINE_CPR),0) | CN5: =IFERROR(BL5/BR5*(BU5-BASELINE_CPR),0) | CO5: =IFERROR(BM5/BR5*(BU5-BASELINE_CPR),0) | CP5: =IFERROR(BN5/BR5*(BU5-BASELINE_CPR),0) | CQ5: =IFERROR(BO5/BR5*(BU5-BASELINE_CPR),0) | CR5: =IFERROR(BP5/BR5*(BU5-BASELINE_CPR),0) | CS5: =IFERROR(BQ5/BR5*(BU5-BASELINE_CPR),0) | CT5: =BASELINE_CPR+SUM(BV5:CS5)-BU5
A6: 3617H4UL3_000000012322093 | B6: LUMENT_PRE21 | C6: 3617H4UL3 | D6: LUMENT REAL ESTATE CAPITAL,LLC | E6: 232 | F6: RP | G6: 2018 | H6: 202602 | I6: 11482585 | J6: 4.35 | K6: 447 | L6: 0 | M6: 91 | N6: 35 | O6: 205308 | Q6: 3896 | R6: 1 | S6: 0 | T6: 0 | U6: 0 | V6: =J6*100-K6 | W6: =L6 | X6: =MIN(M6,36) | Y6: =MIN(MAX(M6-36,0),84) | Z6: =MAX(M6-120,0) | AA6: =IF(OR(O6="",NOT(ISNUMBER(O6))),360,MAX(0,MIN(480,(INT(O6/100)-INT(VALUE(H6)/100))*12+MOD(O6,100)-MOD(VALUE(H6),100)))) | AB6: =IF(AND(AA6>0,AA6<=24),1,0) | AC6: =IF(OR(P6="",NOT(ISNUMBER(P6))),0,MAX(0,MIN(24,(INT(VALUE(H6)/100)-INT(P6/100))*12+MOD(VALUE(H6),100)-MOD(P6,100)))) | AD6: =LN(1+I6) | AE6: =IF(I6<2000000,1,0) | AF6: =IF(I6>50000000,1,0) | AG6: =IF(ISNUMBER(M6),N6/MAX(M6,1),0) | AH6: =IF(G6>=2021,1,0) | AI6: =S6 | AJ6: =T6 | AK6: =R6 | AL6: =U6 | AM6: =IF(ISNUMBER(SEARCH("CAPITAL FUNDING",D6)),1,0) | AN6: =IF(ISNUMBER(SEARCH("PNC",D6)),1,0) | AO6: =IF(ISNUMBER(SEARCH("WELLS FARGO",D6)),1,0) | AP6: =IF(ISNUMBER(SEARCH("DWIGHT",D6)),1,0) | AQ6: =IF(ISNUMBER(SEARCH("GREYSTONE",D6)),1,0) | AR6: =IF(OR(Q6="3896",Q6="3557"),1,0) | AS6: =V6*W6 | AT6: =V$4*(V6-V$3) | AU6: =W$4*(W6-W$3) | AV6: =X$4*(X6-X$3) | AW6: =Y$4*(Y6-Y$3) | AX6: =Z$4*(Z6-Z$3) | AY6: =AA$4*(AA6-AA$3) | AZ6: =AB$4*(AB6-AB$3) | BA6: =AC$4*(AC6-AC$3) | ... BQ6: =AS$4*(AS6-AS$3) | BR6: =SUM(AT6:BQ6) | BS6: =INTERCEPT_SCALED+BR6 | BT6: =1/(1+EXP(-BS6)) | BU6: =1-(1-BT6)^12 | BV6: =IFERROR(AT6/BR6*(BU6-BASELINE_CPR),0) | BW6: =IFERROR(AU6/BR6*(BU6-BASELINE_CPR),0) | BX6: =IFERROR(AV6/BR6*(BU6-BASELINE_CPR),0) | BY6: =IFERROR(AW6/BR6*(BU6-BASELINE_CPR),0) | BZ6: =IFERROR(AX6/BR6*(BU6-BASELINE_CPR),0) | CA6: =IFERROR(AY6/BR6*(BU6-BASELINE_CPR),0) | CB6: =IFERROR(AZ6/BR6*(BU6-BASELINE_CPR),0) | CC6: =IFERROR(BA6/BR6*(BU6-BASELINE_CPR),0) | CD6: =IFERROR(BB6/BR6*(BU6-BASELINE_CPR),0) | CE6: =IFERROR(BC6/BR6*(BU6-BASELINE_CPR),0) | CF6: =IFERROR(BD6/BR6*(BU6-BASELINE_CPR),0) | CG6: =IFERROR(BE6/BR6*(BU6-BASELINE_CPR),0) | CH6: =IFERROR(BF6/BR6*(BU6-BASELINE_CPR),0) | CI6: =IFERROR(BG6/BR6*(BU6-BASELINE_CPR),0) | CJ6: =IFERROR(BH6/BR6*(BU6-BASELINE_CPR),0) | CK6: =IFERROR(BI6/BR6*(BU6-BASELINE_CPR),0) | CL6: =IFERROR(BJ6/BR6*(BU6-BASELINE_CPR),0) | CM6: =IFERROR(BK6/BR6*(BU6-BASELINE_CPR),0) | CN6: =IFERROR(BL6/BR6*(BU6-BASELINE_CPR),0) | CO6: =IFERROR(BM6/BR6*(BU6-BASELINE_CPR),0) | CP6: =IFERROR(BN6/BR6*(BU6-BASELINE_CPR),0) | CQ6: =IFERROR(BO6/BR6*(BU6-BASELINE_CPR),0) | CR6: =IFERROR(BP6/BR6*(BU6-BASELINE_CPR),0) | CS6: =IFERROR(BQ6/BR6*(BU6-BASELINE_CPR),0) | CT6: =BASELINE_CPR+SUM(BV6:CS6)-BU6
A7: 3617QRGV6_000000002311435 | B7: LUMENT_PRE21 | C7: 3617QRGV6 | D7: LUMENT REAL ESTATE CAPITAL,LLC | E7: 223f | F7: RP | G7: 2017 | H7: 202602 | I7: 13751711 | J7: 3.15 | K7: 447 | L7: 5 | M7: 106 | N7: 9 | O7: 205205 | Q7: 3896 | R7: 0 | S7: 0 | T7: 0 | U7: 0 | V7: =J7*100-K7 | W7: =L7 | X7: =MIN(M7,36) | Y7: =MIN(MAX(M7-36,0),84) | Z7: =MAX(M7-120,0) | AA7: =IF(OR(O7="",NOT(ISNUMBER(O7))),360,MAX(0,MIN(480,(INT(O7/100)-INT(VALUE(H7)/100))*12+MOD(O7,100)-MOD(VALUE(H7),100)))) | AB7: =IF(AND(AA7>0,AA7<=24),1,0) | AC7: =IF(OR(P7="",NOT(ISNUMBER(P7))),0,MAX(0,MIN(24,(INT(VALUE(H7)/100)-INT(P7/100))*12+MOD(VALUE(H7),100)-MOD(P7,100)))) | AD7: =LN(1+I7) | AE7: =IF(I7<2000000,1,0) | AF7: =IF(I7>50000000,1,0) | AG7: =IF(ISNUMBER(M7),N7/MAX(M7,1),0) | AH7: =IF(G7>=2021,1,0) | AI7: =S7 | AJ7: =T7 | AK7: =R7 | AL7: =U7 | AM7: =IF(ISNUMBER(SEARCH("CAPITAL FUNDING",D7)),1,0) | AN7: =IF(ISNUMBER(SEARCH("PNC",D7)),1,0) | AO7: =IF(ISNUMBER(SEARCH("WELLS FARGO",D7)),1,0) | AP7: =IF(ISNUMBER(SEARCH("DWIGHT",D7)),1,0) | AQ7: =IF(ISNUMBER(SEARCH("GREYSTONE",D7)),1,0) | AR7: =IF(OR(Q7="3896",Q7="3557"),1,0) | AS7: =V7*W7 | AT7: =V$4*(V7-V$3) | AU7: =W$4*(W7-W$3) | AV7: =X$4*(X7-X$3) | AW7: =Y$4*(Y7-Y$3) | AX7: =Z$4*(Z7-Z$3) | AY7: =AA$4*(AA7-AA$3) | AZ7: =AB$4*(AB7-AB$3) | BA7: =AC$4*(AC7-AC$3) | ... BQ7: =AS$4*(AS7-AS$3) | BR7: =SUM(AT7:BQ7) | BS7: =INTERCEPT_SCALED+BR7 | BT7: =1/(1+EXP(-BS7)) | BU7: =1-(1-BT7)^12 | BV7: =IFERROR(AT7/BR7*(BU7-BASELINE_CPR),0) | BW7: =IFERROR(AU7/BR7*(BU7-BASELINE_CPR),0) | BX7: =IFERROR(AV7/BR7*(BU7-BASELINE_CPR),0) | BY7: =IFERROR(AW7/BR7*(BU7-BASELINE_CPR),0) | BZ7: =IFERROR(AX7/BR7*(BU7-BASELINE_CPR),0) | CA7: =IFERROR(AY7/BR7*(BU7-BASELINE_CPR),0) | CB7: =IFERROR(AZ7/BR7*(BU7-BASELINE_CPR),0) | CC7: =IFERROR(BA7/BR7*(BU7-BASELINE_CPR),0) | CD7: =IFERROR(BB7/BR7*(BU7-BASELINE_CPR),0) | CE7: =IFERROR(BC7/BR7*(BU7-BASELINE_CPR),0) | CF7: =IFERROR(BD7/BR7*(BU7-BASELINE_CPR),0) | CG7: =IFERROR(BE7/BR7*(BU7-BASELINE_CPR),0) | CH7: =IFERROR(BF7/BR7*(BU7-BASELINE_CPR),0) | CI7: =IFERROR(BG7/BR7*(BU7-BASELINE_CPR),0) | CJ7: =IFERROR(BH7/BR7*(BU7-BASELINE_CPR),0) | CK7: =IFERROR(BI7/BR7*(BU7-BASELINE_CPR),0) | CL7: =IFERROR(BJ7/BR7*(BU7-BASELINE_CPR),0) | CM7: =IFERROR(BK7/BR7*(BU7-BASELINE_CPR),0) | CN7: =IFERROR(BL7/BR7*(BU7-BASELINE_CPR),0) | CO7: =IFERROR(BM7/BR7*(BU7-BASELINE_CPR),0) | CP7: =IFERROR(BN7/BR7*(BU7-BASELINE_CPR),0) | CQ7: =IFERROR(BO7/BR7*(BU7-BASELINE_CPR),0) | CR7: =IFERROR(BP7/BR7*(BU7-BASELINE_CPR),0) | CS7: =IFERROR(BQ7/BR7*(BU7-BASELINE_CPR),0) | CT7: =BASELINE_CPR+SUM(BV7:CS7)-BU7
A8: 3617GAE46_000000007122391 | B8: LUMENT_PRE21 | C8: 3617GAE46 | D8: LUMENT REAL ESTATE CAPITAL,LLC | E8: 232 | F8: RP | G8: 2018 | H8: 202602 | I8: 9767084.7 | J8: 3.58 | K8: 447 | L8: 4 | M8: 95 | N8: 27 | O8: 205304 | Q8: 3896 | R8: 1 | S8: 0 | T8: 0 | U8: 0 | V8: =J8*100-K8 | W8: =L8 | X8: =MIN(M8,36) | Y8: =MIN(MAX(M8-36,0),84) | Z8: =MAX(M8-120,0) | AA8: =IF(OR(O8="",NOT(ISNUMBER(O8))),360,MAX(0,MIN(480,(INT(O8/100)-INT(VALUE(H8)/100))*12+MOD(O8,100)-MOD(VALUE(H8),100)))) | AB8: =IF(AND(AA8>0,AA8<=24),1,0) | AC8: =IF(OR(P8="",NOT(ISNUMBER(P8))),0,MAX(0,MIN(24,(INT(VALUE(H8)/100)-INT(P8/100))*12+MOD(VALUE(H8),100)-MOD(P8,100)))) | AD8: =LN(1+I8) | AE8: =IF(I8<2000000,1,0) | AF8: =IF(I8>50000000,1,0) | AG8: =IF(ISNUMBER(M8),N8/MAX(M8,1),0) | AH8: =IF(G8>=2021,1,0) | AI8: =S8 | AJ8: =T8 | AK8: =R8 | AL8: =U8 | AM8: =IF(ISNUMBER(SEARCH("CAPITAL FUNDING",D8)),1,0) | AN8: =IF(ISNUMBER(SEARCH("PNC",D8)),1,0) | AO8: =IF(ISNUMBER(SEARCH("WELLS FARGO",D8)),1,0) | AP8: =IF(ISNUMBER(SEARCH("DWIGHT",D8)),1,0) | AQ8: =IF(ISNUMBER(SEARCH("GREYSTONE",D8)),1,0) | AR8: =IF(OR(Q8="3896",Q8="3557"),1,0) | AS8: =V8*W8 | AT8: =V$4*(V8-V$3) | AU8: =W$4*(W8-W$3) | AV8: =X$4*(X8-X$3) | AW8: =Y$4*(Y8-Y$3) | AX8: =Z$4*(Z8-Z$3) | AY8: =AA$4*(AA8-AA$3) | AZ8: =AB$4*(AB8-AB$3) | BA8: =AC$4*(AC8-AC$3) | ... BQ8: =AS$4*(AS8-AS$3) | BR8: =SUM(AT8:BQ8) | BS8: =INTERCEPT_SCALED+BR8 | BT8: =1/(1+EXP(-BS8)) | BU8: =1-(1-BT8)^12 | BV8: =IFERROR(AT8/BR8*(BU8-BASELINE_CPR),0) | BW8: =IFERROR(AU8/BR8*(BU8-BASELINE_CPR),0) | BX8: =IFERROR(AV8/BR8*(BU8-BASELINE_CPR),0) | BY8: =IFERROR(AW8/BR8*(BU8-BASELINE_CPR),0) | BZ8: =IFERROR(AX8/BR8*(BU8-BASELINE_CPR),0) | CA8: =IFERROR(AY8/BR8*(BU8-BASELINE_CPR),0) | CB8: =IFERROR(AZ8/BR8*(BU8-BASELINE_CPR),0) | CC8: =IFERROR(BA8/BR8*(BU8-BASELINE_CPR),0) | CD8: =IFERROR(BB8/BR8*(BU8-BASELINE_CPR),0) | CE8: =IFERROR(BC8/BR8*(BU8-BASELINE_CPR),0) | CF8: =IFERROR(BD8/BR8*(BU8-BASELINE_CPR),0) | CG8: =IFERROR(BE8/BR8*(BU8-BASELINE_CPR),0) | CH8: =IFERROR(BF8/BR8*(BU8-BASELINE_CPR),0) | CI8: =IFERROR(BG8/BR8*(BU8-BASELINE_CPR),0) | CJ8: =IFERROR(BH8/BR8*(BU8-BASELINE_CPR),0) | CK8: =IFERROR(BI8/BR8*(BU8-BASELINE_CPR),0) | CL8: =IFERROR(BJ8/BR8*(BU8-BASELINE_CPR),0) | CM8: =IFERROR(BK8/BR8*(BU8-BASELINE_CPR),0) | CN8: =IFERROR(BL8/BR8*(BU8-BASELINE_CPR),0) | CO8: =IFERROR(BM8/BR8*(BU8-BASELINE_CPR),0) | CP8: =IFERROR(BN8/BR8*(BU8-BASELINE_CPR),0) | CQ8: =IFERROR(BO8/BR8*(BU8-BASELINE_CPR),0) | CR8: =IFERROR(BP8/BR8*(BU8-BASELINE_CPR),0) | CS8: =IFERROR(BQ8/BR8*(BU8-BASELINE_CPR),0) | CT8: =BASELINE_CPR+SUM(BV8:CS8)-BU8
A9: 3617X72J4_000000003422052 | B9: LUMENT_PRE21 | C9: 3617X72J4 | D9: LUMENT REAL ESTATE CAPITAL,LLC | E9: 232 | F9: RP | G9: 2011 | H9: 202602 | I9: 5069016.5 | J9: 3.05 | K9: 447 | L9: 6 | M9: 176 | N9: 0 | O9: 204607 | Q9: 3896 | R9: 1 | S9: 0 | T9: 0 | U9: 0 | V9: =J9*100-K9 | W9: =L9 | X9: =MIN(M9,36) | Y9: =MIN(MAX(M9-36,0),84) | Z9: =MAX(M9-120,0) | AA9: =IF(OR(O9="",NOT(ISNUMBER(O9))),360,MAX(0,MIN(480,(INT(O9/100)-INT(VALUE(H9)/100))*12+MOD(O9,100)-MOD(VALUE(H9),100)))) | AB9: =IF(AND(AA9>0,AA9<=24),1,0) | AC9: =IF(OR(P9="",NOT(ISNUMBER(P9))),0,MAX(0,MIN(24,(INT(VALUE(H9)/100)-INT(P9/100))*12+MOD(VALUE(H9),100)-MOD(P9,100)))) | AD9: =LN(1+I9) | AE9: =IF(I9<2000000,1,0) | AF9: =IF(I9>50000000,1,0) | AG9: =IF(ISNUMBER(M9),N9/MAX(M9,1),0) | AH9: =IF(G9>=2021,1,0) | AI9: =S9 | AJ9: =T9 | AK9: =R9 | AL9: =U9 | AM9: =IF(ISNUMBER(SEARCH("CAPITAL FUNDING",D9)),1,0) | AN9: =IF(ISNUMBER(SEARCH("PNC",D9)),1,0) | AO9: =IF(ISNUMBER(SEARCH("WELLS FARGO",D9)),1,0) | AP9: =IF(ISNUMBER(SEARCH("DWIGHT",D9)),1,0) | AQ9: =IF(ISNUMBER(SEARCH("GREYSTONE",D9)),1,0) | AR9: =IF(OR(Q9="3896",Q9="3557"),1,0) | AS9: =V9*W9 | AT9: =V$4*(V9-V$3) | AU9: =W$4*(W9-W$3) | AV9: =X$4*(X9-X$3) | AW9: =Y$4*(Y9-Y$3) | AX9: =Z$4*(Z9-Z$3) | AY9: =AA$4*(AA9-AA$3) | AZ9: =AB$4*(AB9-AB$3) | BA9: =AC$4*(AC9-AC$3) | ... BQ9: =AS$4*(AS9-AS$3) | BR9: =SUM(AT9:BQ9) | BS9: =INTERCEPT_SCALED+BR9 | BT9: =1/(1+EXP(-BS9)) | BU9: =1-(1-BT9)^12 | BV9: =IFERROR(AT9/BR9*(BU9-BASELINE_CPR),0) | BW9: =IFERROR(AU9/BR9*(BU9-BASELINE_CPR),0) | BX9: =IFERROR(AV9/BR9*(BU9-BASELINE_CPR),0) | BY9: =IFERROR(AW9/BR9*(BU9-BASELINE_CPR),0) | BZ9: =IFERROR(AX9/BR9*(BU9-BASELINE_CPR),0) | CA9: =IFERROR(AY9/BR9*(BU9-BASELINE_CPR),0) | CB9: =IFERROR(AZ9/BR9*(BU9-BASELINE_CPR),0) | CC9: =IFERROR(BA9/BR9*(BU9-BASELINE_CPR),0) | CD9: =IFERROR(BB9/BR9*(BU9-BASELINE_CPR),0) | CE9: =IFERROR(BC9/BR9*(BU9-BASELINE_CPR),0) | CF9: =IFERROR(BD9/BR9*(BU9-BASELINE_CPR),0) | CG9: =IFERROR(BE9/BR9*(BU9-BASELINE_CPR),0) | CH9: =IFERROR(BF9/BR9*(BU9-BASELINE_CPR),0) | CI9: =IFERROR(BG9/BR9*(BU9-BASELINE_CPR),0) | CJ9: =IFERROR(BH9/BR9*(BU9-BASELINE_CPR),0) | CK9: =IFERROR(BI9/BR9*(BU9-BASELINE_CPR),0) | CL9: =IFERROR(BJ9/BR9*(BU9-BASELINE_CPR),0) | CM9: =IFERROR(BK9/BR9*(BU9-BASELINE_CPR),0) | CN9: =IFERROR(BL9/BR9*(BU9-BASELINE_CPR),0) | CO9: =IFERROR(BM9/BR9*(BU9-BASELINE_CPR),0) | CP9: =IFERROR(BN9/BR9*(BU9-BASELINE_CPR),0) | CQ9: =IFERROR(BO9/BR9*(BU9-BASELINE_CPR),0) | CR9: =IFERROR(BP9/BR9*(BU9-BASELINE_CPR),0) | CS9: =IFERROR(BQ9/BR9*(BU9-BASELINE_CPR),0) | CT9: =BASELINE_CPR+SUM(BV9:CS9)-BU9
A10: 3617X74P8_000000007343145 | B10: LUMENT_PRE21 | C10: 3617X74P8 | D10: LUMENT REAL ESTATE CAPITAL,LLC | E10: 232 | F10: RP | G10: 2013 | H10: 202602 | I10: 11587614 | J10: 3.42 | K10: 447 | L10: 6 | M10: 148 | N10: 1 | O10: 205108 | Q10: 3896 | R10: 1 | S10: 1 | T10: 0 | U10: 0 | V10: =J10*100-K10 | W10: =L10 | X10: =MIN(M10,36) | Y10: =MIN(MAX(M10-36,0),84) | Z10: =MAX(M10-120,0) | AA10: =IF(OR(O10="",NOT(ISNUMBER(O10))),360,MAX(0,MIN(480,(INT(O10/100)-INT(VALUE(H10)/100))*12+MOD(O10,100)-MOD(VALUE(H10),100)))) | AB10: =IF(AND(AA10>0,AA10<=24),1,0) | AC10: =IF(OR(P10="",NOT(ISNUMBER(P10))),0,MAX(0,MIN(24,(INT(VALUE(H10)/100)-INT(P10/100))*12+MOD(VALUE(H10),100)-MOD(P10,100)))) | AD10: =LN(1+I10) | AE10: =IF(I10<2000000,1,0) | AF10: =IF(I10>50000000,1,0) | AG10: =IF(ISNUMBER(M10),N10/MAX(M10,1),0) | AH10: =IF(G10>=2021,1,0) | AI10: =S10 | AJ10: =T10 | AK10: =R10 | AL10: =U10 | AM10: =IF(ISNUMBER(SEARCH("CAPITAL FUNDING",D10)),1,0) | AN10: =IF(ISNUMBER(SEARCH("PNC",D10)),1,0) | AO10: =IF(ISNUMBER(SEARCH("WELLS FARGO",D10)),1,0) | AP10: =IF(ISNUMBER(SEARCH("DWIGHT",D10)),1,0) | AQ10: =IF(ISNUMBER(SEARCH("GREYSTONE",D10)),1,0) | AR10: =IF(OR(Q10="3896",Q10="3557"),1,0) | AS10: =V10*W10 | AT10: =V$4*(V10-V$3) | AU10: =W$4*(W10-W$3) | AV10: =X$4*(X10-X$3) | AW10: =Y$4*(Y10-Y$3) | AX10: =Z$4*(Z10-Z$3) | AY10: =AA$4*(AA10-AA$3) | AZ10: =AB$4*(AB10-AB$3) | BA10: =AC$4*(AC10-AC$3) | ... BQ10: =AS$4*(AS10-AS$3) | BR10: =SUM(AT10:BQ10) | BS10: =INTERCEPT_SCALED+BR10 | BT10: =1/(1+EXP(-BS10)) | BU10: =1-(1-BT10)^12 | BV10: =IFERROR(AT10/BR10*(BU10-BASELINE_CPR),0) | BW10: =IFERROR(AU10/BR10*(BU10-BASELINE_CPR),0) | BX10: =IFERROR(AV10/BR10*(BU10-BASELINE_CPR),0) | BY10: =IFERROR(AW10/BR10*(BU10-BASELINE_CPR),0) | BZ10: =IFERROR(AX10/BR10*(BU10-BASELINE_CPR),0) | CA10: =IFERROR(AY10/BR10*(BU10-BASELINE_CPR),0) | CB10: =IFERROR(AZ10/BR10*(BU10-BASELINE_CPR),0) | CC10: =IFERROR(BA10/BR10*(BU10-BASELINE_CPR),0) | CD10: =IFERROR(BB10/BR10*(BU10-BASELINE_CPR),0) | CE10: =IFERROR(BC10/BR10*(BU10-BASELINE_CPR),0) | CF10: =IFERROR(BD10/BR10*(BU10-BASELINE_CPR),0) | CG10: =IFERROR(BE10/BR10*(BU10-BASELINE_CPR),0) | CH10: =IFERROR(BF10/BR10*(BU10-BASELINE_CPR),0) | CI10: =IFERROR(BG10/BR10*(BU10-BASELINE_CPR),0) | CJ10: =IFERROR(BH10/BR10*(BU10-BASELINE_CPR),0) | CK10: =IFERROR(BI10/BR10*(BU10-BASELINE_CPR),0) | CL10: =IFERROR(BJ10/BR10*(BU10-BASELINE_CPR),0) | CM10: =IFERROR(BK10/BR10*(BU10-BASELINE_CPR),0) | CN10: =IFERROR(BL10/BR10*(BU10-BASELINE_CPR),0) | CO10: =IFERROR(BM10/BR10*(BU10-BASELINE_CPR),0) | CP10: =IFERROR(BN10/BR10*(BU10-BASELINE_CPR),0) | CQ10: =IFERROR(BO10/BR10*(BU10-BASELINE_CPR),0) | CR10: =IFERROR(BP10/BR10*(BU10-BASELINE_CPR),0) | CS10: =IFERROR(BQ10/BR10*(BU10-BASELINE_CPR),0) | CT10: =BASELINE_CPR+SUM(BV10:CS10)-BU10
A11: 3620AEYZ7_000000010535179 | B11: LUMENT_PRE21 | C11: 3620AEYZ7 | D11: LUMENT REAL ESTATE CAPITAL,LLC | E11: OTHER | F11: OTHER | G11: 2010 | H11: 202602 | I11: 7782165.9 | J11: 3.38 | K11: 447 | L11: 0 | M11: 182 | N11: 36 | O11: 205206 | Q11: 3896 | R11: 0 | S11: 0 | T11: 0 | U11: 0 | V11: =J11*100-K11 | W11: =L11 | X11: =MIN(M11,36) | Y11: =MIN(MAX(M11-36,0),84) | Z11: =MAX(M11-120,0) | AA11: =IF(OR(O11="",NOT(ISNUMBER(O11))),360,MAX(0,MIN(480,(INT(O11/100)-INT(VALUE(H11)/100))*12+MOD(O11,100)-MOD(VALUE(H11),100)))) | AB11: =IF(AND(AA11>0,AA11<=24),1,0) | AC11: =IF(OR(P11="",NOT(ISNUMBER(P11))),0,MAX(0,MIN(24,(INT(VALUE(H11)/100)-INT(P11/100))*12+MOD(VALUE(H11),100)-MOD(P11,100)))) | AD11: =LN(1+I11) | AE11: =IF(I11<2000000,1,0) | AF11: =IF(I11>50000000,1,0) | AG11: =IF(ISNUMBER(M11),N11/MAX(M11,1),0) | AH11: =IF(G11>=2021,1,0) | AI11: =S11 | AJ11: =T11 | AK11: =R11 | AL11: =U11 | AM11: =IF(ISNUMBER(SEARCH("CAPITAL FUNDING",D11)),1,0) | AN11: =IF(ISNUMBER(SEARCH("PNC",D11)),1,0) | AO11: =IF(ISNUMBER(SEARCH("WELLS FARGO",D11)),1,0) | AP11: =IF(ISNUMBER(SEARCH("DWIGHT",D11)),1,0) | AQ11: =IF(ISNUMBER(SEARCH("GREYSTONE",D11)),1,0) | AR11: =IF(OR(Q11="3896",Q11="3557"),1,0) | AS11: =V11*W11 | AT11: =V$4*(V11-V$3) | AU11: =W$4*(W11-W$3) | AV11: =X$4*(X11-X$3) | AW11: =Y$4*(Y11-Y$3) | AX11: =Z$4*(Z11-Z$3) | AY11: =AA$4*(AA11-AA$3) | AZ11: =AB$4*(AB11-AB$3) | BA11: =AC$4*(AC11-AC$3) | ... BQ11: =AS$4*(AS11-AS$3) | BR11: =SUM(AT11:BQ11) | BS11: =INTERCEPT_SCALED+BR11 | BT11: =1/(1+EXP(-BS11)) | BU11: =1-(1-BT11)^12 | BV11: =IFERROR(AT11/BR11*(BU11-BASELINE_CPR),0) | BW11: =IFERROR(AU11/BR11*(BU11-BASELINE_CPR),0) | BX11: =IFERROR(AV11/BR11*(BU11-BASELINE_CPR),0) | BY11: =IFERROR(AW11/BR11*(BU11-BASELINE_CPR),0) | BZ11: =IFERROR(AX11/BR11*(BU11-BASELINE_CPR),0) | CA11: =IFERROR(AY11/BR11*(BU11-BASELINE_CPR),0) | CB11: =IFERROR(AZ11/BR11*(BU11-BASELINE_CPR),0) | CC11: =IFERROR(BA11/BR11*(BU11-BASELINE_CPR),0) | CD11: =IFERROR(BB11/BR11*(BU11-BASELINE_CPR),0) | CE11: =IFERROR(BC11/BR11*(BU11-BASELINE_CPR),0) | CF11: =IFERROR(BD11/BR11*(BU11-BASELINE_CPR),0) | CG11: =IFERROR(BE11/BR11*(BU11-BASELINE_CPR),0) | CH11: =IFERROR(BF11/BR11*(BU11-BASELINE_CPR),0) | CI11: =IFERROR(BG11/BR11*(BU11-BASELINE_CPR),0) | CJ11: =IFERROR(BH11/BR11*(BU11-BASELINE_CPR),0) | CK11: =IFERROR(BI11/BR11*(BU11-BASELINE_CPR),0) | CL11: =IFERROR(BJ11/BR11*(BU11-BASELINE_CPR),0) | CM11: =IFERROR(BK11/BR11*(BU11-BASELINE_CPR),0) | CN11: =IFERROR(BL11/BR11*(BU11-BASELINE_CPR),0) | CO11: =IFERROR(BM11/BR11*(BU11-BASELINE_CPR),0) | CP11: =IFERROR(BN11/BR11*(BU11-BASELINE_CPR),0) | CQ11: =IFERROR(BO11/BR11*(BU11-BASELINE_CPR),0) | CR11: =IFERROR(BP11/BR11*(BU11-BASELINE_CPR),0) | CS11: =IFERROR(BQ11/BR11*(BU11-BASELINE_CPR),0) | CT11: =BASELINE_CPR+SUM(BV11:CS11)-BU11
A12: 3618BNC43_000000001211581 | B12: LUMENT_POST21 | C12: 3618BNC43 | D12: LUMENT REAL ESTATE CAPITAL,LLC | E12: 223f | F12: RP | G12: 2023 | H12: 202602 | I12: 30791262 | J12: 5.36 | K12: 447 | L12: 8 | M12: 32 | N12: 0 | O12: 205707 | Q12: 3896 | R12: 0 | S12: 0 | T12: 0 | U12: 0 | V12: =J12*100-K12 | W12: =L12 | X12: =MIN(M12,36) | Y12: =MIN(MAX(M12-36,0),84) | Z12: =MAX(M12-120,0) | AA12: =IF(OR(O12="",NOT(ISNUMBER(O12))),360,MAX(0,MIN(480,(INT(O12/100)-INT(VALUE(H12)/100))*12+MOD(O12,100)-MOD(VALUE(H12),100)))) | AB12: =IF(AND(AA12>0,AA12<=24),1,0) | AC12: =IF(OR(P12="",NOT(ISNUMBER(P12))),0,MAX(0,MIN(24,(INT(VALUE(H12)/100)-INT(P12/100))*12+MOD(VALUE(H12),100)-MOD(P12,100)))) | AD12: =LN(1+I12) | AE12: =IF(I12<2000000,1,0) | AF12: =IF(I12>50000000,1,0) | AG12: =IF(ISNUMBER(M12),N12/MAX(M12,1),0) | AH12: =IF(G12>=2021,1,0) | AI12: =S12 | AJ12: =T12 | AK12: =R12 | AL12: =U12 | AM12: =IF(ISNUMBER(SEARCH("CAPITAL FUNDING",D12)),1,0) | AN12: =IF(ISNUMBER(SEARCH("PNC",D12)),1,0) | AO12: =IF(ISNUMBER(SEARCH("WELLS FARGO",D12)),1,0) | AP12: =IF(ISNUMBER(SEARCH("DWIGHT",D12)),1,0) | AQ12: =IF(ISNUMBER(SEARCH("GREYSTONE",D12)),1,0) | AR12: =IF(OR(Q12="3896",Q12="3557"),1,0) | AS12: =V12*W12 | AT12: =V$4*(V12-V$3) | AU12: =W$4*(W12-W$3) | AV12: =X$4*(X12-X$3) | AW12: =Y$4*(Y12-Y$3) | AX12: =Z$4*(Z12-Z$3) | AY12: =AA$4*(AA12-AA$3) | AZ12: =AB$4*(AB12-AB$3) | BA12: =AC$4*(AC12-AC$3) | ... BQ12: =AS$4*(AS12-AS$3) | BR12: =SUM(AT12:BQ12) | BS12: =INTERCEPT_SCALED+BR12 | BT12: =1/(1+EXP(-BS12)) | BU12: =1-(1-BT12)^12 | BV12: =IFERROR(AT12/BR12*(BU12-BASELINE_CPR),0) | BW12: =IFERROR(AU12/BR12*(BU12-BASELINE_CPR),0) | BX12: =IFERROR(AV12/BR12*(BU12-BASELINE_CPR),0) | BY12: =IFERROR(AW12/BR12*(BU12-BASELINE_CPR),0) | BZ12: =IFERROR(AX12/BR12*(BU12-BASELINE_CPR),0) | CA12: =IFERROR(AY12/BR12*(BU12-BASELINE_CPR),0) | CB12: =IFERROR(AZ12/BR12*(BU12-BASELINE_CPR),0) | CC12: =IFERROR(BA12/BR12*(BU12-BASELINE_CPR),0) | CD12: =IFERROR(BB12/BR12*(BU12-BASELINE_CPR),0) | CE12: =IFERROR(BC12/BR12*(BU12-BASELINE_CPR),0) | CF12: =IFERROR(BD12/BR12*(BU12-BASELINE_CPR),0) | CG12: =IFERROR(BE12/BR12*(BU12-BASELINE_CPR),0) | CH12: =IFERROR(BF12/BR12*(BU12-BASELINE_CPR),0) | CI12: =IFERROR(BG12/BR12*(BU12-BASELINE_CPR),0) | CJ12: =IFERROR(BH12/BR12*(BU12-BASELINE_CPR),0) | CK12: =IFERROR(BI12/BR12*(BU12-BASELINE_CPR),0) | CL12: =IFERROR(BJ12/BR12*(BU12-BASELINE_CPR),0) | CM12: =IFERROR(BK12/BR12*(BU12-BASELINE_CPR),0) | CN12: =IFERROR(BL12/BR12*(BU12-BASELINE_CPR),0) | CO12: =IFERROR(BM12/BR12*(BU12-BASELINE_CPR),0) | CP12: =IFERROR(BN12/BR12*(BU12-BASELINE_CPR),0) | CQ12: =IFERROR(BO12/BR12*(BU12-BASELINE_CPR),0) | CR12: =IFERROR(BP12/BR12*(BU12-BASELINE_CPR),0) | CS12: =IFERROR(BQ12/BR12*(BU12-BASELINE_CPR),0) | CT12: =BASELINE_CPR+SUM(BV12:CS12)-BU12
A13: 3618KLMG9_000000001211630 | B13: LUMENT_POST21 | C13: 3618KLMG9 | D13: LUMENT REAL ESTATE CAPITAL,LLC | E13: 223f | F13: RP | G13: 2025 | H13: 202602 | I13: 59508580 | J13: 5.65 | K13: 447 | L13: 10 | M13: 4 | N13: 0 | O13: 206011 | Q13: 3896 | R13: 0 | S13: 0 | T13: 0 | U13: 0 | V13: =J13*100-K13 | W13: =L13 | X13: =MIN(M13,36) | Y13: =MIN(MAX(M13-36,0),84) | Z13: =MAX(M13-120,0) | AA13: =IF(OR(O13="",NOT(ISNUMBER(O13))),360,MAX(0,MIN(480,(INT(O13/100)-INT(VALUE(H13)/100))*12+MOD(O13,100)-MOD(VALUE(H13),100)))) | AB13: =IF(AND(AA13>0,AA13<=24),1,0) | AC13: =IF(OR(P13="",NOT(ISNUMBER(P13))),0,MAX(0,MIN(24,(INT(VALUE(H13)/100)-INT(P13/100))*12+MOD(VALUE(H13),100)-MOD(P13,100)))) | AD13: =LN(1+I13) | AE13: =IF(I13<2000000,1,0) | AF13: =IF(I13>50000000,1,0) | AG13: =IF(ISNUMBER(M13),N13/MAX(M13,1),0) | AH13: =IF(G13>=2021,1,0) | AI13: =S13 | AJ13: =T13 | AK13: =R13 | AL13: =U13 | AM13: =IF(ISNUMBER(SEARCH("CAPITAL FUNDING",D13)),1,0) | AN13: =IF(ISNUMBER(SEARCH("PNC",D13)),1,0) | AO13: =IF(ISNUMBER(SEARCH("WELLS FARGO",D13)),1,0) | AP13: =IF(ISNUMBER(SEARCH("DWIGHT",D13)),1,0) | AQ13: =IF(ISNUMBER(SEARCH("GREYSTONE",D13)),1,0) | AR13: =IF(OR(Q13="3896",Q13="3557"),1,0) | AS13: =V13*W13 | AT13: =V$4*(V13-V$3) | AU13: =W$4*(W13-W$3) | AV13: =X$4*(X13-X$3) | AW13: =Y$4*(Y13-Y$3) | AX13: =Z$4*(Z13-Z$3) | AY13: =AA$4*(AA13-AA$3) | AZ13: =AB$4*(AB13-AB$3) | BA13: =AC$4*(AC13-AC$3) | ... BQ13: =AS$4*(AS13-AS$3) | BR13: =SUM(AT13:BQ13) | BS13: =INTERCEPT_SCALED+BR13 | BT13: =1/(1+EXP(-BS13)) | BU13: =1-(1-BT13)^12 | BV13: =IFERROR(AT13/BR13*(BU13-BASELINE_CPR),0) | BW13: =IFERROR(AU13/BR13*(BU13-BASELINE_CPR),0) | BX13: =IFERROR(AV13/BR13*(BU13-BASELINE_CPR),0) | BY13: =IFERROR(AW13/BR13*(BU13-BASELINE_CPR),0) | BZ13: =IFERROR(AX13/BR13*(BU13-BASELINE_CPR),0) | CA13: =IFERROR(AY13/BR13*(BU13-BASELINE_CPR),0) | CB13: =IFERROR(AZ13/BR13*(BU13-BASELINE_CPR),0) | CC13: =IFERROR(BA13/BR13*(BU13-BASELINE_CPR),0) | CD13: =IFERROR(BB13/BR13*(BU13-BASELINE_CPR),0) | CE13: =IFERROR(BC13/BR13*(BU13-BASELINE_CPR),0) | CF13: =IFERROR(BD13/BR13*(BU13-BASELINE_CPR),0) | CG13: =IFERROR(BE13/BR13*(BU13-BASELINE_CPR),0) | CH13: =IFERROR(BF13/BR13*(BU13-BASELINE_CPR),0) | CI13: =IFERROR(BG13/BR13*(BU13-BASELINE_CPR),0) | CJ13: =IFERROR(BH13/BR13*(BU13-BASELINE_CPR),0) | CK13: =IFERROR(BI13/BR13*(BU13-BASELINE_CPR),0) | CL13: =IFERROR(BJ13/BR13*(BU13-BASELINE_CPR),0) | CM13: =IFERROR(BK13/BR13*(BU13-BASELINE_CPR),0) | CN13: =IFERROR(BL13/BR13*(BU13-BASELINE_CPR),0) | CO13: =IFERROR(BM13/BR13*(BU13-BASELINE_CPR),0) | CP13: =IFERROR(BN13/BR13*(BU13-BASELINE_CPR),0) | CQ13: =IFERROR(BO13/BR13*(BU13-BASELINE_CPR),0) | CR13: =IFERROR(BP13/BR13*(BU13-BASELINE_CPR),0) | CS13: =IFERROR(BQ13/BR13*(BU13-BASELINE_CPR),0) | CT13: =BASELINE_CPR+SUM(BV13:CS13)-BU13
A14: 36297HB49_000000010222024 | B14: LUMENT_PRE21 | C14: 36297HB49 | D14: LUMENT REAL ESTATE CAPITAL,LLC | E14: 232 | F14: RP | G14: 2009 | H14: 202602 | I14: 2318598.5 | J14: 5.65 | K14: 447 | L14: 0 | M14: 200 | N14: 84 | O14: 203907 | P14: 201108 | Q14: 3896 | R14: 1 | S14: 0 | T14: 0 | U14: 0 | V14: =J14*100-K14 | W14: =L14 | X14: =MIN(M14,36) | Y14: =MIN(MAX(M14-36,0),84) | Z14: =MAX(M14-120,0) | AA14: =IF(OR(O14="",NOT(ISNUMBER(O14))),360,MAX(0,MIN(480,(INT(O14/100)-INT(VALUE(H14)/100))*12+MOD(O14,100)-MOD(VALUE(H14),100)))) | AB14: =IF(AND(AA14>0,AA14<=24),1,0) | AC14: =IF(OR(P14="",NOT(ISNUMBER(P14))),0,MAX(0,MIN(24,(INT(VALUE(H14)/100)-INT(P14/100))*12+MOD(VALUE(H14),100)-MOD(P14,100)))) | AD14: =LN(1+I14) | AE14: =IF(I14<2000000,1,0) | AF14: =IF(I14>50000000,1,0) | AG14: =IF(ISNUMBER(M14),N14/MAX(M14,1),0) | AH14: =IF(G14>=2021,1,0) | AI14: =S14 | AJ14: =T14 | AK14: =R14 | AL14: =U14 | AM14: =IF(ISNUMBER(SEARCH("CAPITAL FUNDING",D14)),1,0) | AN14: =IF(ISNUMBER(SEARCH("PNC",D14)),1,0) | AO14: =IF(ISNUMBER(SEARCH("WELLS FARGO",D14)),1,0) | AP14: =IF(ISNUMBER(SEARCH("DWIGHT",D14)),1,0) | AQ14: =IF(ISNUMBER(SEARCH("GREYSTONE",D14)),1,0) | AR14: =IF(OR(Q14="3896",Q14="3557"),1,0) | AS14: =V14*W14 | AT14: =V$4*(V14-V$3) | AU14: =W$4*(W14-W$3) | AV14: =X$4*(X14-X$3) | AW14: =Y$4*(Y14-Y$3) | AX14: =Z$4*(Z14-Z$3) | AY14: =AA$4*(AA14-AA$3) | AZ14: =AB$4*(AB14-AB$3) | BA14: =AC$4*(AC14-AC$3) | ... BQ14: =AS$4*(AS14-AS$3) | BR14: =SUM(AT14:BQ14) | BS14: =INTERCEPT_SCALED+BR14 | BT14: =1/(1+EXP(-BS14)) | BU14: =1-(1-BT14)^12 | BV14: =IFERROR(AT14/BR14*(BU14-BASELINE_CPR),0) | BW14: =IFERROR(AU14/BR14*(BU14-BASELINE_CPR),0) | BX14: =IFERROR(AV14/BR14*(BU14-BASELINE_CPR),0) | BY14: =IFERROR(AW14/BR14*(BU14-BASELINE_CPR),0) | BZ14: =IFERROR(AX14/BR14*(BU14-BASELINE_CPR),0) | CA14: =IFERROR(AY14/BR14*(BU14-BASELINE_CPR),0) | CB14: =IFERROR(AZ14/BR14*(BU14-BASELINE_CPR),0) | CC14: =IFERROR(BA14/BR14*(BU14-BASELINE_CPR),0) | CD14: =IFERROR(BB14/BR14*(BU14-BASELINE_CPR),0) | CE14: =IFERROR(BC14/BR14*(BU14-BASELINE_CPR),0) | CF14: =IFERROR(BD14/BR14*(BU14-BASELINE_CPR),0) | CG14: =IFERROR(BE14/BR14*(BU14-BASELINE_CPR),0) | CH14: =IFERROR(BF14/BR14*(BU14-BASELINE_CPR),0) | CI14: =IFERROR(BG14/BR14*(BU14-BASELINE_CPR),0) | CJ14: =IFERROR(BH14/BR14*(BU14-BASELINE_CPR),0) | CK14: =IFERROR(BI14/BR14*(BU14-BASELINE_CPR),0) | CL14: =IFERROR(BJ14/BR14*(BU14-BASELINE_CPR),0) | CM14: =IFERROR(BK14/BR14*(BU14-BASELINE_CPR),0) | CN14: =IFERROR(BL14/BR14*(BU14-BASELINE_CPR),0) | CO14: =IFERROR(BM14/BR14*(BU14-BASELINE_CPR),0) | CP14: =IFERROR(BN14/BR14*(BU14-BASELINE_CPR),0) | CQ14: =IFERROR(BO14/BR14*(BU14-BASELINE_CPR),0) | CR14: =IFERROR(BP14/BR14*(BU14-BASELINE_CPR),0) | CS14: =IFERROR(BQ14/BR14*(BU14-BASELINE_CPR),0) | CT14: =BASELINE_CPR+SUM(BV14:CS14)-BU14
A15: 3618HNAN7_000000006122229 | B15: LUMENT_POST21 | C15: 3618HNAN7 | D15: LUMENT REAL ESTATE CAPITAL,LLC | E15: 232 | F15: RP | G15: 2024 | H15: 202602 | I15: 10649283 | J15: 5.35 | K15: 447 | L15: 9 | M15: 14 | N15: 0 | O15: 206001 | Q15: 3896 | R15: 1 | S15: 0 | T15: 0 | U15: 0 | V15: =J15*100-K15 | W15: =L15 | X15: =MIN(M15,36) | Y15: =MIN(MAX(M15-36,0),84) | Z15: =MAX(M15-120,0) | AA15: =IF(OR(O15="",NOT(ISNUMBER(O15))),360,MAX(0,MIN(480,(INT(O15/100)-INT(VALUE(H15)/100))*12+MOD(O15,100)-MOD(VALUE(H15),100)))) | AB15: =IF(AND(AA15>0,AA15<=24),1,0) | AC15: =IF(OR(P15="",NOT(ISNUMBER(P15))),0,MAX(0,MIN(24,(INT(VALUE(H15)/100)-INT(P15/100))*12+MOD(VALUE(H15),100)-MOD(P15,100)))) | AD15: =LN(1+I15) | AE15: =IF(I15<2000000,1,0) | AF15: =IF(I15>50000000,1,0) | AG15: =IF(ISNUMBER(M15),N15/MAX(M15,1),0) | AH15: =IF(G15>=2021,1,0) | AI15: =S15 | AJ15: =T15 | AK15: =R15 | AL15: =U15 | AM15: =IF(ISNUMBER(SEARCH("CAPITAL FUNDING",D15)),1,0) | AN15: =IF(ISNUMBER(SEARCH("PNC",D15)),1,0) | AO15: =IF(ISNUMBER(SEARCH("WELLS FARGO",D15)),1,0) | AP15: =IF(ISNUMBER(SEARCH("DWIGHT",D15)),1,0) | AQ15: =IF(ISNUMBER(SEARCH("GREYSTONE",D15)),1,0) | AR15: =IF(OR(Q15="3896",Q15="3557"),1,0) | AS15: =V15*W15 | AT15: =V$4*(V15-V$3) | AU15: =W$4*(W15-W$3) | AV15: =X$4*(X15-X$3) | AW15: =Y$4*(Y15-Y$3) | AX15: =Z$4*(Z15-Z$3) | AY15: =AA$4*(AA15-AA$3) | AZ15: =AB$4*(AB15-AB$3) | BA15: =AC$4*(AC15-AC$3) | ... BQ15: =AS$4*(AS15-AS$3) | BR15: =SUM(AT15:BQ15) | BS15: =INTERCEPT_SCALED+BR15 | BT15: =1/(1+EXP(-BS15)) | BU15: =1-(1-BT15)^12 | BV15: =IFERROR(AT15/BR15*(BU15-BASELINE_CPR),0) | BW15: =IFERROR(AU15/BR15*(BU15-BASELINE_CPR),0) | BX15: =IFERROR(AV15/BR15*(BU15-BASELINE_CPR),0) | BY15: =IFERROR(AW15/BR15*(BU15-BASELINE_CPR),0) | BZ15: =IFERROR(AX15/BR15*(BU15-BASELINE_CPR),0) | CA15: =IFERROR(AY15/BR15*(BU15-BASELINE_CPR),0) | CB15: =IFERROR(AZ15/BR15*(BU15-BASELINE_CPR),0) | CC15: =IFERROR(BA15/BR15*(BU15-BASELINE_CPR),0) | CD15: =IFERROR(BB15/BR15*(BU15-BASELINE_CPR),0) | CE15: =IFERROR(BC15/BR15*(BU15-BASELINE_CPR),0) | CF15: =IFERROR(BD15/BR15*(BU15-BASELINE_CPR),0) | CG15: =IFERROR(BE15/BR15*(BU15-BASELINE_CPR),0) | CH15: =IFERROR(BF15/BR15*(BU15-BASELINE_CPR),0) | CI15: =IFERROR(BG15/BR15*(BU15-BASELINE_CPR),0) | CJ15: =IFERROR(BH15/BR15*(BU15-BASELINE_CPR),0) | CK15: =IFERROR(BI15/BR15*(BU15-BASELINE_CPR),0) | CL15: =IFERROR(BJ15/BR15*(BU15-BASELINE_CPR),0) | CM15: =IFERROR(BK15/BR15*(BU15-BASELINE_CPR),0) | CN15: =IFERROR(BL15/BR15*(BU15-BASELINE_CPR),0) | CO15: =IFERROR(BM15/BR15*(BU15-BASELINE_CPR),0) | CP15: =IFERROR(BN15/BR15*(BU15-BASELINE_CPR),0) | CQ15: =IFERROR(BO15/BR15*(BU15-BASELINE_CPR),0) | CR15: =IFERROR(BP15/BR15*(BU15-BASELINE_CPR),0) | CS15: =IFERROR(BQ15/BR15*(BU15-BASELINE_CPR),0) | CT15: =BASELINE_CPR+SUM(BV15:CS15)-BU15
A16: 3617LC5T1_000000004611186 | B16: LUMENT_PRE21 | C16: 3617LC5T1 | D16: LUMENT REAL ESTATE CAPITAL,LLC | E16: 223f | F16: RP | G16: 2019 | H16: 202602 | I16: 14083196 | J16: 2.95 | K16: 447 | L16: 4 | M16: 75 | N16: 7 | O16: 205412 | Q16: 3896 | R16: 0 | S16: 0 | T16: 0 | U16: 0 | V16: =J16*100-K16 | W16: =L16 | X16: =MIN(M16,36) | Y16: =MIN(MAX(M16-36,0),84) | Z16: =MAX(M16-120,0) | AA16: =IF(OR(O16="",NOT(ISNUMBER(O16))),360,MAX(0,MIN(480,(INT(O16/100)-INT(VALUE(H16)/100))*12+MOD(O16,100)-MOD(VALUE(H16),100)))) | AB16: =IF(AND(AA16>0,AA16<=24),1,0) | AC16: =IF(OR(P16="",NOT(ISNUMBER(P16))),0,MAX(0,MIN(24,(INT(VALUE(H16)/100)-INT(P16/100))*12+MOD(VALUE(H16),100)-MOD(P16,100)))) | AD16: =LN(1+I16) | AE16: =IF(I16<2000000,1,0) | AF16: =IF(I16>50000000,1,0) | AG16: =IF(ISNUMBER(M16),N16/MAX(M16,1),0) | AH16: =IF(G16>=2021,1,0) | AI16: =S16 | AJ16: =T16 | AK16: =R16 | AL16: =U16 | AM16: =IF(ISNUMBER(SEARCH("CAPITAL FUNDING",D16)),1,0) | AN16: =IF(ISNUMBER(SEARCH("PNC",D16)),1,0) | AO16: =IF(ISNUMBER(SEARCH("WELLS FARGO",D16)),1,0) | AP16: =IF(ISNUMBER(SEARCH("DWIGHT",D16)),1,0) | AQ16: =IF(ISNUMBER(SEARCH("GREYSTONE",D16)),1,0) | AR16: =IF(OR(Q16="3896",Q16="3557"),1,0) | AS16: =V16*W16 | AT16: =V$4*(V16-V$3) | AU16: =W$4*(W16-W$3) | AV16: =X$4*(X16-X$3) | AW16: =Y$4*(Y16-Y$3) | AX16: =Z$4*(Z16-Z$3) | AY16: =AA$4*(AA16-AA$3) | AZ16: =AB$4*(AB16-AB$3) | BA16: =AC$4*(AC16-AC$3) | ... BQ16: =AS$4*(AS16-AS$3) | BR16: =SUM(AT16:BQ16) | BS16: =INTERCEPT_SCALED+BR16 | BT16: =1/(1+EXP(-BS16)) | BU16: =1-(1-BT16)^12 | BV16: =IFERROR(AT16/BR16*(BU16-BASELINE_CPR),0) | BW16: =IFERROR(AU16/BR16*(BU16-BASELINE_CPR),0) | BX16: =IFERROR(AV16/BR16*(BU16-BASELINE_CPR),0) | BY16: =IFERROR(AW16/BR16*(BU16-BASELINE_CPR),0) | BZ16: =IFERROR(AX16/BR16*(BU16-BASELINE_CPR),0) | CA16: =IFERROR(AY16/BR16*(BU16-BASELINE_CPR),0) | CB16: =IFERROR(AZ16/BR16*(BU16-BASELINE_CPR),0) | CC16: =IFERROR(BA16/BR16*(BU16-BASELINE_CPR),0) | CD16: =IFERROR(BB16/BR16*(BU16-BASELINE_CPR),0) | CE16: =IFERROR(BC16/BR16*(BU16-BASELINE_CPR),0) | CF16: =IFERROR(BD16/BR16*(BU16-BASELINE_CPR),0) | CG16: =IFERROR(BE16/BR16*(BU16-BASELINE_CPR),0) | CH16: =IFERROR(BF16/BR16*(BU16-BASELINE_CPR),0) | CI16: =IFERROR(BG16/BR16*(BU16-BASELINE_CPR),0) | CJ16: =IFERROR(BH16/BR16*(BU16-BASELINE_CPR),0) | CK16: =IFERROR(BI16/BR16*(BU16-BASELINE_CPR),0) | CL16: =IFERROR(BJ16/BR16*(BU16-BASELINE_CPR),0) | CM16: =IFERROR(BK16/BR16*(BU16-BASELINE_CPR),0) | CN16: =IFERROR(BL16/BR16*(BU16-BASELINE_CPR),0) | CO16: =IFERROR(BM16/BR16*(BU16-BASELINE_CPR),0) | CP16: =IFERROR(BN16/BR16*(BU16-BASELINE_CPR),0) | CQ16: =IFERROR(BO16/BR16*(BU16-BASELINE_CPR),0) | CR16: =IFERROR(BP16/BR16*(BU16-BASELINE_CPR),0) | CS16: =IFERROR(BQ16/BR16*(BU16-BASELINE_CPR),0) | CT16: =BASELINE_CPR+SUM(BV16:CS16)-BU16
A17: 3617J9LY2_000000001411271 | B17: LUMENT_PRE21 | C17: 3617J9LY2 | D17: LUMENT REAL ESTATE CAPITAL,LLC | E17: 223f | F17: RP | G17: 2019 | H17: 202602 | I17: 6145581.9 | J17: 4.3 | K17: 447 | L17: 4 | M17: 82 | N17: 35 | O17: 205405 | Q17: 3896 | R17: 0 | S17: 0 | T17: 0 | U17: 0 | V17: =J17*100-K17 | W17: =L17 | X17: =MIN(M17,36) | Y17: =MIN(MAX(M17-36,0),84) | Z17: =MAX(M17-120,0) | AA17: =IF(OR(O17="",NOT(ISNUMBER(O17))),360,MAX(0,MIN(480,(INT(O17/100)-INT(VALUE(H17)/100))*12+MOD(O17,100)-MOD(VALUE(H17),100)))) | AB17: =IF(AND(AA17>0,AA17<=24),1,0) | AC17: =IF(OR(P17="",NOT(ISNUMBER(P17))),0,MAX(0,MIN(24,(INT(VALUE(H17)/100)-INT(P17/100))*12+MOD(VALUE(H17),100)-MOD(P17,100)))) | AD17: =LN(1+I17) | AE17: =IF(I17<2000000,1,0) | AF17: =IF(I17>50000000,1,0) | AG17: =IF(ISNUMBER(M17),N17/MAX(M17,1),0) | AH17: =IF(G17>=2021,1,0) | AI17: =S17 | AJ17: =T17 | AK17: =R17 | AL17: =U17 | AM17: =IF(ISNUMBER(SEARCH("CAPITAL FUNDING",D17)),1,0) | AN17: =IF(ISNUMBER(SEARCH("PNC",D17)),1,0) | AO17: =IF(ISNUMBER(SEARCH("WELLS FARGO",D17)),1,0) | AP17: =IF(ISNUMBER(SEARCH("DWIGHT",D17)),1,0) | AQ17: =IF(ISNUMBER(SEARCH("GREYSTONE",D17)),1,0) | AR17: =IF(OR(Q17="3896",Q17="3557"),1,0) | AS17: =V17*W17 | AT17: =V$4*(V17-V$3) | AU17: =W$4*(W17-W$3) | AV17: =X$4*(X17-X$3) | AW17: =Y$4*(Y17-Y$3) | AX17: =Z$4*(Z17-Z$3) | AY17: =AA$4*(AA17-AA$3) | AZ17: =AB$4*(AB17-AB$3) | BA17: =AC$4*(AC17-AC$3) | ... BQ17: =AS$4*(AS17-AS$3) | BR17: =SUM(AT17:BQ17) | BS17: =INTERCEPT_SCALED+BR17 | BT17: =1/(1+EXP(-BS17)) | BU17: =1-(1-BT17)^12 | BV17: =IFERROR(AT17/BR17*(BU17-BASELINE_CPR),0) | BW17: =IFERROR(AU17/BR17*(BU17-BASELINE_CPR),0) | BX17: =IFERROR(AV17/BR17*(BU17-BASELINE_CPR),0) | BY17: =IFERROR(AW17/BR17*(BU17-BASELINE_CPR),0) | BZ17: =IFERROR(AX17/BR17*(BU17-BASELINE_CPR),0) | CA17: =IFERROR(AY17/BR17*(BU17-BASELINE_CPR),0) | CB17: =IFERROR(AZ17/BR17*(BU17-BASELINE_CPR),0) | CC17: =IFERROR(BA17/BR17*(BU17-BASELINE_CPR),0) | CD17: =IFERROR(BB17/BR17*(BU17-BASELINE_CPR),0) | CE17: =IFERROR(BC17/BR17*(BU17-BASELINE_CPR),0) | CF17: =IFERROR(BD17/BR17*(BU17-BASELINE_CPR),0) | CG17: =IFERROR(BE17/BR17*(BU17-BASELINE_CPR),0) | CH17: =IFERROR(BF17/BR17*(BU17-BASELINE_CPR),0) | CI17: =IFERROR(BG17/BR17*(BU17-BASELINE_CPR),0) | CJ17: =IFERROR(BH17/BR17*(BU17-BASELINE_CPR),0) | CK17: =IFERROR(BI17/BR17*(BU17-BASELINE_CPR),0) | CL17: =IFERROR(BJ17/BR17*(BU17-BASELINE_CPR),0) | CM17: =IFERROR(BK17/BR17*(BU17-BASELINE_CPR),0) | CN17: =IFERROR(BL17/BR17*(BU17-BASELINE_CPR),0) | CO17: =IFERROR(BM17/BR17*(BU17-BASELINE_CPR),0) | CP17: =IFERROR(BN17/BR17*(BU17-BASELINE_CPR),0) | CQ17: =IFERROR(BO17/BR17*(BU17-BASELINE_CPR),0) | CR17: =IFERROR(BP17/BR17*(BU17-BASELINE_CPR),0) | CS17: =IFERROR(BQ17/BR17*(BU17-BASELINE_CPR),0) | CT17: =BASELINE_CPR+SUM(BV17:CS17)-BU17
A18: 3617FTDM7_000000008311235 | B18: LUMENT_POST21 | C18: 3617FTDM7 | D18: LUMENT REAL ESTATE CAPITAL,LLC | E18: 223f | F18: RP | G18: 2023 | H18: 202602 | I18: 15752462 | J18: 5.1 | K18: 447 | L18: 8 | M18: 34 | N18: 0 | O18: 205805 | Q18: 3896 | R18: 0 | S18: 0 | T18: 0 | U18: 0 | V18: =J18*100-K18 | W18: =L18 | X18: =MIN(M18,36) | Y18: =MIN(MAX(M18-36,0),84) | Z18: =MAX(M18-120,0) | AA18: =IF(OR(O18="",NOT(ISNUMBER(O18))),360,MAX(0,MIN(480,(INT(O18/100)-INT(VALUE(H18)/100))*12+MOD(O18,100)-MOD(VALUE(H18),100)))) | AB18: =IF(AND(AA18>0,AA18<=24),1,0) | AC18: =IF(OR(P18="",NOT(ISNUMBER(P18))),0,MAX(0,MIN(24,(INT(VALUE(H18)/100)-INT(P18/100))*12+MOD(VALUE(H18),100)-MOD(P18,100)))) | AD18: =LN(1+I18) | AE18: =IF(I18<2000000,1,0) | AF18: =IF(I18>50000000,1,0) | AG18: =IF(ISNUMBER(M18),N18/MAX(M18,1),0) | AH18: =IF(G18>=2021,1,0) | AI18: =S18 | AJ18: =T18 | AK18: =R18 | AL18: =U18 | AM18: =IF(ISNUMBER(SEARCH("CAPITAL FUNDING",D18)),1,0) | AN18: =IF(ISNUMBER(SEARCH("PNC",D18)),1,0) | AO18: =IF(ISNUMBER(SEARCH("WELLS FARGO",D18)),1,0) | AP18: =IF(ISNUMBER(SEARCH("DWIGHT",D18)),1,0) | AQ18: =IF(ISNUMBER(SEARCH("GREYSTONE",D18)),1,0) | AR18: =IF(OR(Q18="3896",Q18="3557"),1,0) | AS18: =V18*W18 | AT18: =V$4*(V18-V$3) | AU18: =W$4*(W18-W$3) | AV18: =X$4*(X18-X$3) | AW18: =Y$4*(Y18-Y$3) | AX18: =Z$4*(Z18-Z$3) | AY18: =AA$4*(AA18-AA$3) | AZ18: =AB$4*(AB18-AB$3) | BA18: =AC$4*(AC18-AC$3) | ... BQ18: =AS$4*(AS18-AS$3) | BR18: =SUM(AT18:BQ18) | BS18: =INTERCEPT_SCALED+BR18 | BT18: =1/(1+EXP(-BS18)) | BU18: =1-(1-BT18)^12 | BV18: =IFERROR(AT18/BR18*(BU18-BASELINE_CPR),0) | BW18: =IFERROR(AU18/BR18*(BU18-BASELINE_CPR),0) | BX18: =IFERROR(AV18/BR18*(BU18-BASELINE_CPR),0) | BY18: =IFERROR(AW18/BR18*(BU18-BASELINE_CPR),0) | BZ18: =IFERROR(AX18/BR18*(BU18-BASELINE_CPR),0) | CA18: =IFERROR(AY18/BR18*(BU18-BASELINE_CPR),0) | CB18: =IFERROR(AZ18/BR18*(BU18-BASELINE_CPR),0) | CC18: =IFERROR(BA18/BR18*(BU18-BASELINE_CPR),0) | CD18: =IFERROR(BB18/BR18*(BU18-BASELINE_CPR),0) | CE18: =IFERROR(BC18/BR18*(BU18-BASELINE_CPR),0) | CF18: =IFERROR(BD18/BR18*(BU18-BASELINE_CPR),0) | CG18: =IFERROR(BE18/BR18*(BU18-BASELINE_CPR),0) | CH18: =IFERROR(BF18/BR18*(BU18-BASELINE_CPR),0) | CI18: =IFERROR(BG18/BR18*(BU18-BASELINE_CPR),0) | CJ18: =IFERROR(BH18/BR18*(BU18-BASELINE_CPR),0) | CK18: =IFERROR(BI18/BR18*(BU18-BASELINE_CPR),0) | CL18: =IFERROR(BJ18/BR18*(BU18-BASELINE_CPR),0) | CM18: =IFERROR(BK18/BR18*(BU18-BASELINE_CPR),0) | CN18: =IFERROR(BL18/BR18*(BU18-BASELINE_CPR),0) | CO18: =IFERROR(BM18/BR18*(BU18-BASELINE_CPR),0) | CP18: =IFERROR(BN18/BR18*(BU18-BASELINE_CPR),0) | CQ18: =IFERROR(BO18/BR18*(BU18-BASELINE_CPR),0) | CR18: =IFERROR(BP18/BR18*(BU18-BASELINE_CPR),0) | CS18: =IFERROR(BQ18/BR18*(BU18-BASELINE_CPR),0) | CT18: =BASELINE_CPR+SUM(BV18:CS18)-BU18
A19: 36187SCA3_000000001411159 | B19: LUMENT_PRE21 | C19: 36187SCA3 | D19: LUMENT REAL ESTATE CAPITAL,LLC | E19: 223f | F19: RP | G19: 2009 | H19: 202602 | I19: 1334344.3 | J19: 4.29 | K19: 447 | L19: 0 | M19: 205 | N19: 38 | O19: 204403 | Q19: 3896 | R19: 0 | S19: 0 | T19: 0 | U19: 0 | V19: =J19*100-K19 | W19: =L19 | X19: =MIN(M19,36) | Y19: =MIN(MAX(M19-36,0),84) | Z19: =MAX(M19-120,0) | AA19: =IF(OR(O19="",NOT(ISNUMBER(O19))),360,MAX(0,MIN(480,(INT(O19/100)-INT(VALUE(H19)/100))*12+MOD(O19,100)-MOD(VALUE(H19),100)))) | AB19: =IF(AND(AA19>0,AA19<=24),1,0) | AC19: =IF(OR(P19="",NOT(ISNUMBER(P19))),0,MAX(0,MIN(24,(INT(VALUE(H19)/100)-INT(P19/100))*12+MOD(VALUE(H19),100)-MOD(P19,100)))) | AD19: =LN(1+I19) | AE19: =IF(I19<2000000,1,0) | AF19: =IF(I19>50000000,1,0) | AG19: =IF(ISNUMBER(M19),N19/MAX(M19,1),0) | AH19: =IF(G19>=2021,1,0) | AI19: =S19 | AJ19: =T19 | AK19: =R19 | AL19: =U19 | AM19: =IF(ISNUMBER(SEARCH("CAPITAL FUNDING",D19)),1,0) | AN19: =IF(ISNUMBER(SEARCH("PNC",D19)),1,0) | AO19: =IF(ISNUMBER(SEARCH("WELLS FARGO",D19)),1,0) | AP19: =IF(ISNUMBER(SEARCH("DWIGHT",D19)),1,0) | AQ19: =IF(ISNUMBER(SEARCH("GREYSTONE",D19)),1,0) | AR19: =IF(OR(Q19="3896",Q19="3557"),1,0) | AS19: =V19*W19 | AT19: =V$4*(V19-V$3) | AU19: =W$4*(W19-W$3) | AV19: =X$4*(X19-X$3) | AW19: =Y$4*(Y19-Y$3) | AX19: =Z$4*(Z19-Z$3) | AY19: =AA$4*(AA19-AA$3) | AZ19: =AB$4*(AB19-AB$3) | BA19: =AC$4*(AC19-AC$3) | ... BQ19: =AS$4*(AS19-AS$3) | BR19: =SUM(AT19:BQ19) | BS19: =INTERCEPT_SCALED+BR19 | BT19: =1/(1+EXP(-BS19)) | BU19: =1-(1-BT19)^12 | BV19: =IFERROR(AT19/BR19*(BU19-BASELINE_CPR),0) | BW19: =IFERROR(AU19/BR19*(BU19-BASELINE_CPR),0) | BX19: =IFERROR(AV19/BR19*(BU19-BASELINE_CPR),0) | BY19: =IFERROR(AW19/BR19*(BU19-BASELINE_CPR),0) | BZ19: =IFERROR(AX19/BR19*(BU19-BASELINE_CPR),0) | CA19: =IFERROR(AY19/BR19*(BU19-BASELINE_CPR),0) | CB19: =IFERROR(AZ19/BR19*(BU19-BASELINE_CPR),0) | CC19: =IFERROR(BA19/BR19*(BU19-BASELINE_CPR),0) | CD19: =IFERROR(BB19/BR19*(BU19-BASELINE_CPR),0) | CE19: =IFERROR(BC19/BR19*(BU19-BASELINE_CPR),0) | CF19: =IFERROR(BD19/BR19*(BU19-BASELINE_CPR),0) | CG19: =IFERROR(BE19/BR19*(BU19-BASELINE_CPR),0) | CH19: =IFERROR(BF19/BR19*(BU19-BASELINE_CPR),0) | CI19: =IFERROR(BG19/BR19*(BU19-BASELINE_CPR),0) | CJ19: =IFERROR(BH19/BR19*(BU19-BASELINE_CPR),0) | CK19: =IFERROR(BI19/BR19*(BU19-BASELINE_CPR),0) | CL19: =IFERROR(BJ19/BR19*(BU19-BASELINE_CPR),0) | CM19: =IFERROR(BK19/BR19*(BU19-BASELINE_CPR),0) | CN19: =IFERROR(BL19/BR19*(BU19-BASELINE_CPR),0) | CO19: =IFERROR(BM19/BR19*(BU19-BASELINE_CPR),0) | CP19: =IFERROR(BN19/BR19*(BU19-BASELINE_CPR),0) | CQ19: =IFERROR(BO19/BR19*(BU19-BASELINE_CPR),0) | CR19: =IFERROR(BP19/BR19*(BU19-BASELINE_CPR),0) | CS19: =IFERROR(BQ19/BR19*(BU19-BASELINE_CPR),0) | CT19: =BASELINE_CPR+SUM(BV19:CS19)-BU19
A20: 3617AVUR7_049031028004210 | B20: LUMENT_PRE21 | C20: 3617AVUR7 | D20: LUMENT REAL ESTATE CAPITAL,LLC | E20: 538 | F20: 538 | G20: 2017 | H20: 202602 | I20: 1419192.9 | J20: 3.89 | K20: 447 | L20: 3 | M20: 103 | N20: 31 | O20: 204708 | Q20: 3896 | R20: 0 | S20: 0 | T20: 1 | U20: 0 | V20: =J20*100-K20 | W20: =L20 | X20: =MIN(M20,36) | Y20: =MIN(MAX(M20-36,0),84) | Z20: =MAX(M20-120,0) | AA20: =IF(OR(O20="",NOT(ISNUMBER(O20))),360,MAX(0,MIN(480,(INT(O20/100)-INT(VALUE(H20)/100))*12+MOD(O20,100)-MOD(VALUE(H20),100)))) | AB20: =IF(AND(AA20>0,AA20<=24),1,0) | AC20: =IF(OR(P20="",NOT(ISNUMBER(P20))),0,MAX(0,MIN(24,(INT(VALUE(H20)/100)-INT(P20/100))*12+MOD(VALUE(H20),100)-MOD(P20,100)))) | AD20: =LN(1+I20) | AE20: =IF(I20<2000000,1,0) | AF20: =IF(I20>50000000,1,0) | AG20: =IF(ISNUMBER(M20),N20/MAX(M20,1),0) | AH20: =IF(G20>=2021,1,0) | AI20: =S20 | AJ20: =T20 | AK20: =R20 | AL20: =U20 | AM20: =IF(ISNUMBER(SEARCH("CAPITAL FUNDING",D20)),1,0) | AN20: =IF(ISNUMBER(SEARCH("PNC",D20)),1,0) | AO20: =IF(ISNUMBER(SEARCH("WELLS FARGO",D20)),1,0) | AP20: =IF(ISNUMBER(SEARCH("DWIGHT",D20)),1,0) | AQ20: =IF(ISNUMBER(SEARCH("GREYSTONE",D20)),1,0) | AR20: =IF(OR(Q20="3896",Q20="3557"),1,0) | AS20: =V20*W20 | AT20: =V$4*(V20-V$3) | AU20: =W$4*(W20-W$3) | AV20: =X$4*(X20-X$3) | AW20: =Y$4*(Y20-Y$3) | AX20: =Z$4*(Z20-Z$3) | AY20: =AA$4*(AA20-AA$3) | AZ20: =AB$4*(AB20-AB$3) | BA20: =AC$4*(AC20-AC$3) | ... BQ20: =AS$4*(AS20-AS$3) | BR20: =SUM(AT20:BQ20) | BS20: =INTERCEPT_SCALED+BR20 | BT20: =1/(1+EXP(-BS20)) | BU20: =1-(1-BT20)^12 | BV20: =IFERROR(AT20/BR20*(BU20-BASELINE_CPR),0) | BW20: =IFERROR(AU20/BR20*(BU20-BASELINE_CPR),0) | BX20: =IFERROR(AV20/BR20*(BU20-BASELINE_CPR),0) | BY20: =IFERROR(AW20/BR20*(BU20-BASELINE_CPR),0) | BZ20: =IFERROR(AX20/BR20*(BU20-BASELINE_CPR),0) | CA20: =IFERROR(AY20/BR20*(BU20-BASELINE_CPR),0) | CB20: =IFERROR(AZ20/BR20*(BU20-BASELINE_CPR),0) | CC20: =IFERROR(BA20/BR20*(BU20-BASELINE_CPR),0) | CD20: =IFERROR(BB20/BR20*(BU20-BASELINE_CPR),0) | CE20: =IFERROR(BC20/BR20*(BU20-BASELINE_CPR),0) | CF20: =IFERROR(BD20/BR20*(BU20-BASELINE_CPR),0) | CG20: =IFERROR(BE20/BR20*(BU20-BASELINE_CPR),0) | CH20: =IFERROR(BF20/BR20*(BU20-BASELINE_CPR),0) | CI20: =IFERROR(BG20/BR20*(BU20-BASELINE_CPR),0) | CJ20: =IFERROR(BH20/BR20*(BU20-BASELINE_CPR),0) | CK20: =IFERROR(BI20/BR20*(BU20-BASELINE_CPR),0) | CL20: =IFERROR(BJ20/BR20*(BU20-BASELINE_CPR),0) | CM20: =IFERROR(BK20/BR20*(BU20-BASELINE_CPR),0) | CN20: =IFERROR(BL20/BR20*(BU20-BASELINE_CPR),0) | CO20: =IFERROR(BM20/BR20*(BU20-BASELINE_CPR),0) | CP20: =IFERROR(BN20/BR20*(BU20-BASELINE_CPR),0) | CQ20: =IFERROR(BO20/BR20*(BU20-BASELINE_CPR),0) | CR20: =IFERROR(BP20/BR20*(BU20-BASELINE_CPR),0) | CS20: =IFERROR(BQ20/BR20*(BU20-BASELINE_CPR),0) | CT20: =BASELINE_CPR+SUM(BV20:CS20)-BU20
A21: 3617GKP67_000000002411077 | B21: LUMENT_PRE21 | C21: 3617GKP67 | D21: LUMENT REAL ESTATE CAPITAL,LLC | E21: 223f | F21: RP | G21: 2018 | H21: 202602 | I21: 5685256.4 | J21: 4.02 | K21: 447 | L21: 3 | M21: 93 | N21: 32 | O21: 205306 | Q21: 3896 | R21: 0 | S21: 0 | T21: 0 | U21: 0 | V21: =J21*100-K21 | W21: =L21 | X21: =MIN(M21,36) | Y21: =MIN(MAX(M21-36,0),84) | Z21: =MAX(M21-120,0) | AA21: =IF(OR(O21="",NOT(ISNUMBER(O21))),360,MAX(0,MIN(480,(INT(O21/100)-INT(VALUE(H21)/100))*12+MOD(O21,100)-MOD(VALUE(H21),100)))) | AB21: =IF(AND(AA21>0,AA21<=24),1,0) | AC21: =IF(OR(P21="",NOT(ISNUMBER(P21))),0,MAX(0,MIN(24,(INT(VALUE(H21)/100)-INT(P21/100))*12+MOD(VALUE(H21),100)-MOD(P21,100)))) | AD21: =LN(1+I21) | AE21: =IF(I21<2000000,1,0) | AF21: =IF(I21>50000000,1,0) | AG21: =IF(ISNUMBER(M21),N21/MAX(M21,1),0) | AH21: =IF(G21>=2021,1,0) | AI21: =S21 | AJ21: =T21 | AK21: =R21 | AL21: =U21 | AM21: =IF(ISNUMBER(SEARCH("CAPITAL FUNDING",D21)),1,0) | AN21: =IF(ISNUMBER(SEARCH("PNC",D21)),1,0) | AO21: =IF(ISNUMBER(SEARCH("WELLS FARGO",D21)),1,0) | AP21: =IF(ISNUMBER(SEARCH("DWIGHT",D21)),1,0) | AQ21: =IF(ISNUMBER(SEARCH("GREYSTONE",D21)),1,0) | AR21: =IF(OR(Q21="3896",Q21="3557"),1,0) | AS21: =V21*W21 | AT21: =V$4*(V21-V$3) | AU21: =W$4*(W21-W$3) | AV21: =X$4*(X21-X$3) | AW21: =Y$4*(Y21-Y$3) | AX21: =Z$4*(Z21-Z$3) | AY21: =AA$4*(AA21-AA$3) | AZ21: =AB$4*(AB21-AB$3) | BA21: =AC$4*(AC21-AC$3) | ... BQ21: =AS$4*(AS21-AS$3) | BR21: =SUM(AT21:BQ21) | BS21: =INTERCEPT_SCALED+BR21 | BT21: =1/(1+EXP(-BS21)) | BU21: =1-(1-BT21)^12 | BV21: =IFERROR(AT21/BR21*(BU21-BASELINE_CPR),0) | BW21: =IFERROR(AU21/BR21*(BU21-BASELINE_CPR),0) | BX21: =IFERROR(AV21/BR21*(BU21-BASELINE_CPR),0) | BY21: =IFERROR(AW21/BR21*(BU21-BASELINE_CPR),0) | BZ21: =IFERROR(AX21/BR21*(BU21-BASELINE_CPR),0) | CA21: =IFERROR(AY21/BR21*(BU21-BASELINE_CPR),0) | CB21: =IFERROR(AZ21/BR21*(BU21-BASELINE_CPR),0) | CC21: =IFERROR(BA21/BR21*(BU21-BASELINE_CPR),0) | CD21: =IFERROR(BB21/BR21*(BU21-BASELINE_CPR),0) | CE21: =IFERROR(BC21/BR21*(BU21-BASELINE_CPR),0) | CF21: =IFERROR(BD21/BR21*(BU21-BASELINE_CPR),0) | CG21: =IFERROR(BE21/BR21*(BU21-BASELINE_CPR),0) | CH21: =IFERROR(BF21/BR21*(BU21-BASELINE_CPR),0) | CI21: =IFERROR(BG21/BR21*(BU21-BASELINE_CPR),0) | CJ21: =IFERROR(BH21/BR21*(BU21-BASELINE_CPR),0) | CK21: =IFERROR(BI21/BR21*(BU21-BASELINE_CPR),0) | CL21: =IFERROR(BJ21/BR21*(BU21-BASELINE_CPR),0) | CM21: =IFERROR(BK21/BR21*(BU21-BASELINE_CPR),0) | CN21: =IFERROR(BL21/BR21*(BU21-BASELINE_CPR),0) | CO21: =IFERROR(BM21/BR21*(BU21-BASELINE_CPR),0) | CP21: =IFERROR(BN21/BR21*(BU21-BASELINE_CPR),0) | CQ21: =IFERROR(BO21/BR21*(BU21-BASELINE_CPR),0) | CR21: =IFERROR(BP21/BR21*(BU21-BASELINE_CPR),0) | CS21: =IFERROR(BQ21/BR21*(BU21-BASELINE_CPR),0) | CT21: =BASELINE_CPR+SUM(BV21:CS21)-BU21
A22: 36180QCV8_000000010535250 | B22: LUMENT_PRE21 | C22: 36180QCV8 | D22: LUMENT REAL ESTATE CAPITAL,LLC | E22: 221d4 | F22: NC | G22: 2015 | H22: 202602 | I22: 2808410.9 | J22: 3.35 | K22: 447 | L22: 1 | M22: 128 | N22: 27 | O22: 205604 | Q22: 3896 | R22: 0 | S22: 0 | T22: 0 | U22: 1 | V22: =J22*100-K22 | W22: =L22 | X22: =MIN(M22,36) | Y22: =MIN(MAX(M22-36,0),84) | Z22: =MAX(M22-120,0) | AA22: =IF(OR(O22="",NOT(ISNUMBER(O22))),360,MAX(0,MIN(480,(INT(O22/100)-INT(VALUE(H22)/100))*12+MOD(O22,100)-MOD(VALUE(H22),100)))) | AB22: =IF(AND(AA22>0,AA22<=24),1,0) | AC22: =IF(OR(P22="",NOT(ISNUMBER(P22))),0,MAX(0,MIN(24,(INT(VALUE(H22)/100)-INT(P22/100))*12+MOD(VALUE(H22),100)-MOD(P22,100)))) | AD22: =LN(1+I22) | AE22: =IF(I22<2000000,1,0) | AF22: =IF(I22>50000000,1,0) | AG22: =IF(ISNUMBER(M22),N22/MAX(M22,1),0) | AH22: =IF(G22>=2021,1,0) | AI22: =S22 | AJ22: =T22 | AK22: =R22 | AL22: =U22 | AM22: =IF(ISNUMBER(SEARCH("CAPITAL FUNDING",D22)),1,0) | AN22: =IF(ISNUMBER(SEARCH("PNC",D22)),1,0) | AO22: =IF(ISNUMBER(SEARCH("WELLS FARGO",D22)),1,0) | AP22: =IF(ISNUMBER(SEARCH("DWIGHT",D22)),1,0) | AQ22: =IF(ISNUMBER(SEARCH("GREYSTONE",D22)),1,0) | AR22: =IF(OR(Q22="3896",Q22="3557"),1,0) | AS22: =V22*W22 | AT22: =V$4*(V22-V$3) | AU22: =W$4*(W22-W$3) | AV22: =X$4*(X22-X$3) | AW22: =Y$4*(Y22-Y$3) | AX22: =Z$4*(Z22-Z$3) | AY22: =AA$4*(AA22-AA$3) | AZ22: =AB$4*(AB22-AB$3) | BA22: =AC$4*(AC22-AC$3) | ... BQ22: =AS$4*(AS22-AS$3) | BR22: =SUM(AT22:BQ22) | BS22: =INTERCEPT_SCALED+BR22 | BT22: =1/(1+EXP(-BS22)) | BU22: =1-(1-BT22)^12 | BV22: =IFERROR(AT22/BR22*(BU22-BASELINE_CPR),0) | BW22: =IFERROR(AU22/BR22*(BU22-BASELINE_CPR),0) | BX22: =IFERROR(AV22/BR22*(BU22-BASELINE_CPR),0) | BY22: =IFERROR(AW22/BR22*(BU22-BASELINE_CPR),0) | BZ22: =IFERROR(AX22/BR22*(BU22-BASELINE_CPR),0) | CA22: =IFERROR(AY22/BR22*(BU22-BASELINE_CPR),0) | CB22: =IFERROR(AZ22/BR22*(BU22-BASELINE_CPR),0) | CC22: =IFERROR(BA22/BR22*(BU22-BASELINE_CPR),0) | CD22: =IFERROR(BB22/BR22*(BU22-BASELINE_CPR),0) | CE22: =IFERROR(BC22/BR22*(BU22-BASELINE_CPR),0) | CF22: =IFERROR(BD22/BR22*(BU22-BASELINE_CPR),0) | CG22: =IFERROR(BE22/BR22*(BU22-BASELINE_CPR),0) | CH22: =IFERROR(BF22/BR22*(BU22-BASELINE_CPR),0) | CI22: =IFERROR(BG22/BR22*(BU22-BASELINE_CPR),0) | CJ22: =IFERROR(BH22/BR22*(BU22-BASELINE_CPR),0) | CK22: =IFERROR(BI22/BR22*(BU22-BASELINE_CPR),0) | CL22: =IFERROR(BJ22/BR22*(BU22-BASELINE_CPR),0) | CM22: =IFERROR(BK22/BR22*(BU22-BASELINE_CPR),0) | CN22: =IFERROR(BL22/BR22*(BU22-BASELINE_CPR),0) | CO22: =IFERROR(BM22/BR22*(BU22-BASELINE_CPR),0) | CP22: =IFERROR(BN22/BR22*(BU22-BASELINE_CPR),0) | CQ22: =IFERROR(BO22/BR22*(BU22-BASELINE_CPR),0) | CR22: =IFERROR(BP22/BR22*(BU22-BASELINE_CPR),0) | CS22: =IFERROR(BQ22/BR22*(BU22-BASELINE_CPR),0) | CT22: =BASELINE_CPR+SUM(BV22:CS22)-BU22
A23: 3617X76V3_000000012211483 | B23: LUMENT_POST21 | C23: 3617X76V3 | D23: LUMENT REAL ESTATE CAPITAL,LLC | E23: 223f | F23: RP | G23: 2022 | H23: 202602 | I23: 11152291 | J23: 2.6 | K23: 447 | L23: 7 | M23: 47 | N23: 0 | O23: 205704 | Q23: 3896 | R23: 0 | S23: 0 | T23: 0 | U23: 0 | V23: =J23*100-K23 | W23: =L23 | X23: =MIN(M23,36) | Y23: =MIN(MAX(M23-36,0),84) | Z23: =MAX(M23-120,0) | AA23: =IF(OR(O23="",NOT(ISNUMBER(O23))),360,MAX(0,MIN(480,(INT(O23/100)-INT(VALUE(H23)/100))*12+MOD(O23,100)-MOD(VALUE(H23),100)))) | AB23: =IF(AND(AA23>0,AA23<=24),1,0) | AC23: =IF(OR(P23="",NOT(ISNUMBER(P23))),0,MAX(0,MIN(24,(INT(VALUE(H23)/100)-INT(P23/100))*12+MOD(VALUE(H23),100)-MOD(P23,100)))) | AD23: =LN(1+I23) | AE23: =IF(I23<2000000,1,0) | AF23: =IF(I23>50000000,1,0) | AG23: =IF(ISNUMBER(M23),N23/MAX(M23,1),0) | AH23: =IF(G23>=2021,1,0) | AI23: =S23 | AJ23: =T23 | AK23: =R23 | AL23: =U23 | AM23: =IF(ISNUMBER(SEARCH("CAPITAL FUNDING",D23)),1,0) | AN23: =IF(ISNUMBER(SEARCH("PNC",D23)),1,0) | AO23: =IF(ISNUMBER(SEARCH("WELLS FARGO",D23)),1,0) | AP23: =IF(ISNUMBER(SEARCH("DWIGHT",D23)),1,0) | AQ23: =IF(ISNUMBER(SEARCH("GREYSTONE",D23)),1,0) | AR23: =IF(OR(Q23="3896",Q23="3557"),1,0) | AS23: =V23*W23 | AT23: =V$4*(V23-V$3) | AU23: =W$4*(W23-W$3) | AV23: =X$4*(X23-X$3) | AW23: =Y$4*(Y23-Y$3) | AX23: =Z$4*(Z23-Z$3) | AY23: =AA$4*(AA23-AA$3) | AZ23: =AB$4*(AB23-AB$3) | BA23: =AC$4*(AC23-AC$3) | ... BQ23: =AS$4*(AS23-AS$3) | BR23: =SUM(AT23:BQ23) | BS23: =INTERCEPT_SCALED+BR23 | BT23: =1/(1+EXP(-BS23)) | BU23: =1-(1-BT23)^12 | BV23: =IFERROR(AT23/BR23*(BU23-BASELINE_CPR),0) | BW23: =IFERROR(AU23/BR23*(BU23-BASELINE_CPR),0) | BX23: =IFERROR(AV23/BR23*(BU23-BASELINE_CPR),0) | BY23: =IFERROR(AW23/BR23*(BU23-BASELINE_CPR),0) | BZ23: =IFERROR(AX23/BR23*(BU23-BASELINE_CPR),0) | CA23: =IFERROR(AY23/BR23*(BU23-BASELINE_CPR),0) | CB23: =IFERROR(AZ23/BR23*(BU23-BASELINE_CPR),0) | CC23: =IFERROR(BA23/BR23*(BU23-BASELINE_CPR),0) | CD23: =IFERROR(BB23/BR23*(BU23-BASELINE_CPR),0) | CE23: =IFERROR(BC23/BR23*(BU23-BASELINE_CPR),0) | CF23: =IFERROR(BD23/BR23*(BU23-BASELINE_CPR),0) | CG23: =IFERROR(BE23/BR23*(BU23-BASELINE_CPR),0) | CH23: =IFERROR(BF23/BR23*(BU23-BASELINE_CPR),0) | CI23: =IFERROR(BG23/BR23*(BU23-BASELINE_CPR),0) | CJ23: =IFERROR(BH23/BR23*(BU23-BASELINE_CPR),0) | CK23: =IFERROR(BI23/BR23*(BU23-BASELINE_CPR),0) | CL23: =IFERROR(BJ23/BR23*(BU23-BASELINE_CPR),0) | CM23: =IFERROR(BK23/BR23*(BU23-BASELINE_CPR),0) | CN23: =IFERROR(BL23/BR23*(BU23-BASELINE_CPR),0) | CO23: =IFERROR(BM23/BR23*(BU23-BASELINE_CPR),0) | CP23: =IFERROR(BN23/BR23*(BU23-BASELINE_CPR),0) | CQ23: =IFERROR(BO23/BR23*(BU23-BASELINE_CPR),0) | CR23: =IFERROR(BP23/BR23*(BU23-BASELINE_CPR),0) | CS23: =IFERROR(BQ23/BR23*(BU23-BASELINE_CPR),0) | CT23: =BASELINE_CPR+SUM(BV23:CS23)-BU23
A24: 3617W8NP6_000000011335648 | B24: LUMENT_PRE21 | C24: 3617W8NP6 | D24: LUMENT REAL ESTATE CAPITAL,LLC | E24: 221d4 | F24: NC | G24: 2016 | H24: 202602 | I24: 17567640 | J24: 2.65 | K24: 447 | L24: 6 | M24: 114 | N24: 0 | O24: 205802 | Q24: 3896 | R24: 0 | S24: 0 | T24: 0 | U24: 1 | V24: =J24*100-K24 | W24: =L24 | X24: =MIN(M24,36) | Y24: =MIN(MAX(M24-36,0),84) | Z24: =MAX(M24-120,0) | AA24: =IF(OR(O24="",NOT(ISNUMBER(O24))),360,MAX(0,MIN(480,(INT(O24/100)-INT(VALUE(H24)/100))*12+MOD(O24,100)-MOD(VALUE(H24),100)))) | AB24: =IF(AND(AA24>0,AA24<=24),1,0) | AC24: =IF(OR(P24="",NOT(ISNUMBER(P24))),0,MAX(0,MIN(24,(INT(VALUE(H24)/100)-INT(P24/100))*12+MOD(VALUE(H24),100)-MOD(P24,100)))) | AD24: =LN(1+I24) | AE24: =IF(I24<2000000,1,0) | AF24: =IF(I24>50000000,1,0) | AG24: =IF(ISNUMBER(M24),N24/MAX(M24,1),0) | AH24: =IF(G24>=2021,1,0) | AI24: =S24 | AJ24: =T24 | AK24: =R24 | AL24: =U24 | AM24: =IF(ISNUMBER(SEARCH("CAPITAL FUNDING",D24)),1,0) | AN24: =IF(ISNUMBER(SEARCH("PNC",D24)),1,0) | AO24: =IF(ISNUMBER(SEARCH("WELLS FARGO",D24)),1,0) | AP24: =IF(ISNUMBER(SEARCH("DWIGHT",D24)),1,0) | AQ24: =IF(ISNUMBER(SEARCH("GREYSTONE",D24)),1,0) | AR24: =IF(OR(Q24="3896",Q24="3557"),1,0) | AS24: =V24*W24 | AT24: =V$4*(V24-V$3) | AU24: =W$4*(W24-W$3) | AV24: =X$4*(X24-X$3) | AW24: =Y$4*(Y24-Y$3) | AX24: =Z$4*(Z24-Z$3) | AY24: =AA$4*(AA24-AA$3) | AZ24: =AB$4*(AB24-AB$3) | BA24: =AC$4*(AC24-AC$3) | ... BQ24: =AS$4*(AS24-AS$3) | BR24: =SUM(AT24:BQ24) | BS24: =INTERCEPT_SCALED+BR24 | BT24: =1/(1+EXP(-BS24)) | BU24: =1-(1-BT24)^12 | BV24: =IFERROR(AT24/BR24*(BU24-BASELINE_CPR),0) | BW24: =IFERROR(AU24/BR24*(BU24-BASELINE_CPR),0) | BX24: =IFERROR(AV24/BR24*(BU24-BASELINE_CPR),0) | BY24: =IFERROR(AW24/BR24*(BU24-BASELINE_CPR),0) | BZ24: =IFERROR(AX24/BR24*(BU24-BASELINE_CPR),0) | CA24: =IFERROR(AY24/BR24*(BU24-BASELINE_CPR),0) | CB24: =IFERROR(AZ24/BR24*(BU24-BASELINE_CPR),0) | CC24: =IFERROR(BA24/BR24*(BU24-BASELINE_CPR),0) | CD24: =IFERROR(BB24/BR24*(BU24-BASELINE_CPR),0) | CE24: =IFERROR(BC24/BR24*(BU24-BASELINE_CPR),0) | CF24: =IFERROR(BD24/BR24*(BU24-BASELINE_CPR),0) | CG24: =IFERROR(BE24/BR24*(BU24-BASELINE_CPR),0) | CH24: =IFERROR(BF24/BR24*(BU24-BASELINE_CPR),0) | CI24: =IFERROR(BG24/BR24*(BU24-BASELINE_CPR),0) | CJ24: =IFERROR(BH24/BR24*(BU24-BASELINE_CPR),0) | CK24: =IFERROR(BI24/BR24*(BU24-BASELINE_CPR),0) | CL24: =IFERROR(BJ24/BR24*(BU24-BASELINE_CPR),0) | CM24: =IFERROR(BK24/BR24*(BU24-BASELINE_CPR),0) | CN24: =IFERROR(BL24/BR24*(BU24-BASELINE_CPR),0) | CO24: =IFERROR(BM24/BR24*(BU24-BASELINE_CPR),0) | CP24: =IFERROR(BN24/BR24*(BU24-BASELINE_CPR),0) | CQ24: =IFERROR(BO24/BR24*(BU24-BASELINE_CPR),0) | CR24: =IFERROR(BP24/BR24*(BU24-BASELINE_CPR),0) | CS24: =IFERROR(BQ24/BR24*(BU24-BASELINE_CPR),0) | CT24: =BASELINE_CPR+SUM(BV24:CS24)-BU24
A25: 3617AVU89_000000003222025 | B25: LUMENT_PRE21 | C25: 3617AVU89 | D25: LUMENT REAL ESTATE CAPITAL,LLC | E25: 232 | F25: RP | G25: 2017 | H25: 202602 | I25: 18702496 | J25: 3.48 | K25: 447 | L25: 3 | M25: 101 | N25: 25 | O25: 205210 | Q25: 3896 | R25: 1 | S25: 0 | T25: 0 | U25: 0 | V25: =J25*100-K25 | W25: =L25 | X25: =MIN(M25,36) | Y25: =MIN(MAX(M25-36,0),84) | Z25: =MAX(M25-120,0) | AA25: =IF(OR(O25="",NOT(ISNUMBER(O25))),360,MAX(0,MIN(480,(INT(O25/100)-INT(VALUE(H25)/100))*12+MOD(O25,100)-MOD(VALUE(H25),100)))) | AB25: =IF(AND(AA25>0,AA25<=24),1,0) | AC25: =IF(OR(P25="",NOT(ISNUMBER(P25))),0,MAX(0,MIN(24,(INT(VALUE(H25)/100)-INT(P25/100))*12+MOD(VALUE(H25),100)-MOD(P25,100)))) | AD25: =LN(1+I25) | AE25: =IF(I25<2000000,1,0) | AF25: =IF(I25>50000000,1,0) | AG25: =IF(ISNUMBER(M25),N25/MAX(M25,1),0) | AH25: =IF(G25>=2021,1,0) | AI25: =S25 | AJ25: =T25 | AK25: =R25 | AL25: =U25 | AM25: =IF(ISNUMBER(SEARCH("CAPITAL FUNDING",D25)),1,0) | AN25: =IF(ISNUMBER(SEARCH("PNC",D25)),1,0) | AO25: =IF(ISNUMBER(SEARCH("WELLS FARGO",D25)),1,0) | AP25: =IF(ISNUMBER(SEARCH("DWIGHT",D25)),1,0) | AQ25: =IF(ISNUMBER(SEARCH("GREYSTONE",D25)),1,0) | AR25: =IF(OR(Q25="3896",Q25="3557"),1,0) | AS25: =V25*W25 | AT25: =V$4*(V25-V$3) | AU25: =W$4*(W25-W$3) | AV25: =X$4*(X25-X$3) | AW25: =Y$4*(Y25-Y$3) | AX25: =Z$4*(Z25-Z$3) | AY25: =AA$4*(AA25-AA$3) | AZ25: =AB$4*(AB25-AB$3) | BA25: =AC$4*(AC25-AC$3) | ... BQ25: =AS$4*(AS25-AS$3) | BR25: =SUM(AT25:BQ25) | BS25: =INTERCEPT_SCALED+BR25 | BT25: =1/(1+EXP(-BS25)) | BU25: =1-(1-BT25)^12 | BV25: =IFERROR(AT25/BR25*(BU25-BASELINE_CPR),0) | BW25: =IFERROR(AU25/BR25*(BU25-BASELINE_CPR),0) | BX25: =IFERROR(AV25/BR25*(BU25-BASELINE_CPR),0) | BY25: =IFERROR(AW25/BR25*(BU25-BASELINE_CPR),0) | BZ25: =IFERROR(AX25/BR25*(BU25-BASELINE_CPR),0) | CA25: =IFERROR(AY25/BR25*(BU25-BASELINE_CPR),0) | CB25: =IFERROR(AZ25/BR25*(BU25-BASELINE_CPR),0) | CC25: =IFERROR(BA25/BR25*(BU25-BASELINE_CPR),0) | CD25: =IFERROR(BB25/BR25*(BU25-BASELINE_CPR),0) | CE25: =IFERROR(BC25/BR25*(BU25-BASELINE_CPR),0) | CF25: =IFERROR(BD25/BR25*(BU25-BASELINE_CPR),0) | CG25: =IFERROR(BE25/BR25*(BU25-BASELINE_CPR),0) | CH25: =IFERROR(BF25/BR25*(BU25-BASELINE_CPR),0) | CI25: =IFERROR(BG25/BR25*(BU25-BASELINE_CPR),0) | CJ25: =IFERROR(BH25/BR25*(BU25-BASELINE_CPR),0) | CK25: =IFERROR(BI25/BR25*(BU25-BASELINE_CPR),0) | CL25: =IFERROR(BJ25/BR25*(BU25-BASELINE_CPR),0) | CM25: =IFERROR(BK25/BR25*(BU25-BASELINE_CPR),0) | CN25: =IFERROR(BL25/BR25*(BU25-BASELINE_CPR),0) | CO25: =IFERROR(BM25/BR25*(BU25-BASELINE_CPR),0) | CP25: =IFERROR(BN25/BR25*(BU25-BASELINE_CPR),0) | CQ25: =IFERROR(BO25/BR25*(BU25-BASELINE_CPR),0) | CR25: =IFERROR(BP25/BR25*(BU25-BASELINE_CPR),0) | CS25: =IFERROR(BQ25/BR25*(BU25-BASELINE_CPR),0) | CT25: =BASELINE_CPR+SUM(BV25:CS25)-BU25
A26: 3617UAXY3_000000010522063 | B26: LUMENT_PRE21 | C26: 3617UAXY3 | D26: LUMENT REAL ESTATE CAPITAL,LLC | E26: 232 | F26: RP | G26: 2015 | H26: 202602 | I26: 8582540 | J26: 2.8 | K26: 447 | L26: 10 | M26: 124 | N26: 0 | O26: 205011 | Q26: 3896 | R26: 1 | S26: 0 | T26: 0 | U26: 0 | V26: =J26*100-K26 | W26: =L26 | X26: =MIN(M26,36) | Y26: =MIN(MAX(M26-36,0),84) | Z26: =MAX(M26-120,0) | AA26: =IF(OR(O26="",NOT(ISNUMBER(O26))),360,MAX(0,MIN(480,(INT(O26/100)-INT(VALUE(H26)/100))*12+MOD(O26,100)-MOD(VALUE(H26),100)))) | AB26: =IF(AND(AA26>0,AA26<=24),1,0) | AC26: =IF(OR(P26="",NOT(ISNUMBER(P26))),0,MAX(0,MIN(24,(INT(VALUE(H26)/100)-INT(P26/100))*12+MOD(VALUE(H26),100)-MOD(P26,100)))) | AD26: =LN(1+I26) | AE26: =IF(I26<2000000,1,0) | AF26: =IF(I26>50000000,1,0) | AG26: =IF(ISNUMBER(M26),N26/MAX(M26,1),0) | AH26: =IF(G26>=2021,1,0) | AI26: =S26 | AJ26: =T26 | AK26: =R26 | AL26: =U26 | AM26: =IF(ISNUMBER(SEARCH("CAPITAL FUNDING",D26)),1,0) | AN26: =IF(ISNUMBER(SEARCH("PNC",D26)),1,0) | AO26: =IF(ISNUMBER(SEARCH("WELLS FARGO",D26)),1,0) | AP26: =IF(ISNUMBER(SEARCH("DWIGHT",D26)),1,0) | AQ26: =IF(ISNUMBER(SEARCH("GREYSTONE",D26)),1,0) | AR26: =IF(OR(Q26="3896",Q26="3557"),1,0) | AS26: =V26*W26 | AT26: =V$4*(V26-V$3) | AU26: =W$4*(W26-W$3) | AV26: =X$4*(X26-X$3) | AW26: =Y$4*(Y26-Y$3) | AX26: =Z$4*(Z26-Z$3) | AY26: =AA$4*(AA26-AA$3) | AZ26: =AB$4*(AB26-AB$3) | BA26: =AC$4*(AC26-AC$3) | ... BQ26: =AS$4*(AS26-AS$3) | BR26: =SUM(AT26:BQ26) | BS26: =INTERCEPT_SCALED+BR26 | BT26: =1/(1+EXP(-BS26)) | BU26: =1-(1-BT26)^12 | BV26: =IFERROR(AT26/BR26*(BU26-BASELINE_CPR),0) | BW26: =IFERROR(AU26/BR26*(BU26-BASELINE_CPR),0) | BX26: =IFERROR(AV26/BR26*(BU26-BASELINE_CPR),0) | BY26: =IFERROR(AW26/BR26*(BU26-BASELINE_CPR),0) | BZ26: =IFERROR(AX26/BR26*(BU26-BASELINE_CPR),0) | CA26: =IFERROR(AY26/BR26*(BU26-BASELINE_CPR),0) | CB26: =IFERROR(AZ26/BR26*(BU26-BASELINE_CPR),0) | CC26: =IFERROR(BA26/BR26*(BU26-BASELINE_CPR),0) | CD26: =IFERROR(BB26/BR26*(BU26-BASELINE_CPR),0) | CE26: =IFERROR(BC26/BR26*(BU26-BASELINE_CPR),0) | CF26: =IFERROR(BD26/BR26*(BU26-BASELINE_CPR),0) | CG26: =IFERROR(BE26/BR26*(BU26-BASELINE_CPR),0) | CH26: =IFERROR(BF26/BR26*(BU26-BASELINE_CPR),0) | CI26: =IFERROR(BG26/BR26*(BU26-BASELINE_CPR),0) | CJ26: =IFERROR(BH26/BR26*(BU26-BASELINE_CPR),0) | CK26: =IFERROR(BI26/BR26*(BU26-BASELINE_CPR),0) | CL26: =IFERROR(BJ26/BR26*(BU26-BASELINE_CPR),0) | CM26: =IFERROR(BK26/BR26*(BU26-BASELINE_CPR),0) | CN26: =IFERROR(BL26/BR26*(BU26-BASELINE_CPR),0) | CO26: =IFERROR(BM26/BR26*(BU26-BASELINE_CPR),0) | CP26: =IFERROR(BN26/BR26*(BU26-BASELINE_CPR),0) | CQ26: =IFERROR(BO26/BR26*(BU26-BASELINE_CPR),0) | CR26: =IFERROR(BP26/BR26*(BU26-BASELINE_CPR),0) | CS26: =IFERROR(BQ26/BR26*(BU26-BASELINE_CPR),0) | CT26: =BASELINE_CPR+SUM(BV26:CS26)-BU26
... A41: 36189MGT9_000000007111384 | B41: BERKADIA_PRE21 | C41: 36189MGT9 | D41: BERKADIA COMMERCIAL MORTGAGE, LLC | E41: 223f | F41: RP | G41: 2015 | H41: 202602 | I41: 3434607.5 | J41: 3.25 | K41: 447 | L41: 0 | M41: 125 | N41: 25 | O41: 205101 | Q41: 4082 | R41: 0 | S41: 0 | T41: 0 | U41: 0 | V41: =J41*100-K41 | W41: =L41 | X41: =MIN(M41,36) | Y41: =MIN(MAX(M41-36,0),84) | Z41: =MAX(M41-120,0) | AA41: =IF(OR(O41="",NOT(ISNUMBER(O41))),360,MAX(0,MIN(480,(INT(O41/100)-INT(VALUE(H41)/100))*12+MOD(O41,100)-MOD(VALUE(H41),100)))) | AB41: =IF(AND(AA41>0,AA41<=24),1,0) | AC41: =IF(OR(P41="",NOT(ISNUMBER(P41))),0,MAX(0,MIN(24,(INT(VALUE(H41)/100)-INT(P41/100))*12+MOD(VALUE(H41),100)-MOD(P41,100)))) | AD41: =LN(1+I41) | AE41: =IF(I41<2000000,1,0) | AF41: =IF(I41>50000000,1,0) | AG41: =IF(ISNUMBER(M41),N41/MAX(M41,1),0) | AH41: =IF(G41>=2021,1,0) | AI41: =S41 | AJ41: =T41 | AK41: =R41 | AL41: =U41 | AM41: =IF(ISNUMBER(SEARCH("CAPITAL FUNDING",D41)),1,0) | AN41: =IF(ISNUMBER(SEARCH("PNC",D41)),1,0) | AO41: =IF(ISNUMBER(SEARCH("WELLS FARGO",D41)),1,0) | AP41: =IF(ISNUMBER(SEARCH("DWIGHT",D41)),1,0) | AQ41: =IF(ISNUMBER(SEARCH("GREYSTONE",D41)),1,0) | AR41: =IF(OR(Q41="3896",Q41="3557"),1,0) | AS41: =V41*W41 | AT41: =V$4*(V41-V$3) | AU41: =W$4*(W41-W$3) | AV41: =X$4*(X41-X$3) | AW41: =Y$4*(Y41-Y$3) | AX41: =Z$4*(Z41-Z$3) | AY41: =AA$4*(AA41-AA$3) | AZ41: =AB$4*(AB41-AB$3) | BA41: =AC$4*(AC41-AC$3) | ... BQ41: =AS$4*(AS41-AS$3) | BR41: =SUM(AT41:BQ41) | BS41: =INTERCEPT_SCALED+BR41 | BT41: =1/(1+EXP(-BS41)) | BU41: =1-(1-BT41)^12 | BV41: =IFERROR(AT41/BR41*(BU41-BASELINE_CPR),0) | BW41: =IFERROR(AU41/BR41*(BU41-BASELINE_CPR),0) | BX41: =IFERROR(AV41/BR41*(BU41-BASELINE_CPR),0) | BY41: =IFERROR(AW41/BR41*(BU41-BASELINE_CPR),0) | BZ41: =IFERROR(AX41/BR41*(BU41-BASELINE_CPR),0) | CA41: =IFERROR(AY41/BR41*(BU41-BASELINE_CPR),0) | CB41: =IFERROR(AZ41/BR41*(BU41-BASELINE_CPR),0) | CC41: =IFERROR(BA41/BR41*(BU41-BASELINE_CPR),0) | CD41: =IFERROR(BB41/BR41*(BU41-BASELINE_CPR),0) | CE41: =IFERROR(BC41/BR41*(BU41-BASELINE_CPR),0) | CF41: =IFERROR(BD41/BR41*(BU41-BASELINE_CPR),0) | CG41: =IFERROR(BE41/BR41*(BU41-BASELINE_CPR),0) | CH41: =IFERROR(BF41/BR41*(BU41-BASELINE_CPR),0) | CI41: =IFERROR(BG41/BR41*(BU41-BASELINE_CPR),0) | CJ41: =IFERROR(BH41/BR41*(BU41-BASELINE_CPR),0) | CK41: =IFERROR(BI41/BR41*(BU41-BASELINE_CPR),0) | CL41: =IFERROR(BJ41/BR41*(BU41-BASELINE_CPR),0) | CM41: =IFERROR(BK41/BR41*(BU41-BASELINE_CPR),0) | CN41: =IFERROR(BL41/BR41*(BU41-BASELINE_CPR),0) | CO41: =IFERROR(BM41/BR41*(BU41-BASELINE_CPR),0) | CP41: =IFERROR(BN41/BR41*(BU41-BASELINE_CPR),0) | CQ41: =IFERROR(BO41/BR41*(BU41-BASELINE_CPR),0) | CR41: =IFERROR(BP41/BR41*(BU41-BASELINE_CPR),0) | CS41: =IFERROR(BQ41/BR41*(BU41-BASELINE_CPR),0) | CT41: =BASELINE_CPR+SUM(BV41:CS41)-BU41
A42: 36177YET9_000000006311078 | B42: BERKADIA_PRE21 | C42: 36177YET9 | D42: BERKADIA COMMERCIAL MORTGAGE, LLC | E42: 223f | F42: RP | G42: 2012 | H42: 202602 | I42: 8184805 | J42: 3.2 | K42: 447 | L42: 0 | M42: 167 | N42: 30 | O42: 204708 | P42: 201409 | Q42: 4082 | R42: 0 | S42: 0 | T42: 0 | U42: 0 | V42: =J42*100-K42 | W42: =L42 | X42: =MIN(M42,36) | Y42: =MIN(MAX(M42-36,0),84) | Z42: =MAX(M42-120,0) | AA42: =IF(OR(O42="",NOT(ISNUMBER(O42))),360,MAX(0,MIN(480,(INT(O42/100)-INT(VALUE(H42)/100))*12+MOD(O42,100)-MOD(VALUE(H42),100)))) | AB42: =IF(AND(AA42>0,AA42<=24),1,0) | AC42: =IF(OR(P42="",NOT(ISNUMBER(P42))),0,MAX(0,MIN(24,(INT(VALUE(H42)/100)-INT(P42/100))*12+MOD(VALUE(H42),100)-MOD(P42,100)))) | AD42: =LN(1+I42) | AE42: =IF(I42<2000000,1,0) | AF42: =IF(I42>50000000,1,0) | AG42: =IF(ISNUMBER(M42),N42/MAX(M42,1),0) | AH42: =IF(G42>=2021,1,0) | AI42: =S42 | AJ42: =T42 | AK42: =R42 | AL42: =U42 | AM42: =IF(ISNUMBER(SEARCH("CAPITAL FUNDING",D42)),1,0) | AN42: =IF(ISNUMBER(SEARCH("PNC",D42)),1,0) | AO42: =IF(ISNUMBER(SEARCH("WELLS FARGO",D42)),1,0) | AP42: =IF(ISNUMBER(SEARCH("DWIGHT",D42)),1,0) | AQ42: =IF(ISNUMBER(SEARCH("GREYSTONE",D42)),1,0) | AR42: =IF(OR(Q42="3896",Q42="3557"),1,0) | AS42: =V42*W42 | AT42: =V$4*(V42-V$3) | AU42: =W$4*(W42-W$3) | AV42: =X$4*(X42-X$3) | AW42: =Y$4*(Y42-Y$3) | AX42: =Z$4*(Z42-Z$3) | AY42: =AA$4*(AA42-AA$3) | AZ42: =AB$4*(AB42-AB$3) | BA42: =AC$4*(AC42-AC$3) | ... BQ42: =AS$4*(AS42-AS$3) | BR42: =SUM(AT42:BQ42) | BS42: =INTERCEPT_SCALED+BR42 | BT42: =1/(1+EXP(-BS42)) | BU42: =1-(1-BT42)^12 | BV42: =IFERROR(AT42/BR42*(BU42-BASELINE_CPR),0) | BW42: =IFERROR(AU42/BR42*(BU42-BASELINE_CPR),0) | BX42: =IFERROR(AV42/BR42*(BU42-BASELINE_CPR),0) | BY42: =IFERROR(AW42/BR42*(BU42-BASELINE_CPR),0) | BZ42: =IFERROR(AX42/BR42*(BU42-BASELINE_CPR),0) | CA42: =IFERROR(AY42/BR42*(BU42-BASELINE_CPR),0) | CB42: =IFERROR(AZ42/BR42*(BU42-BASELINE_CPR),0) | CC42: =IFERROR(BA42/BR42*(BU42-BASELINE_CPR),0) | CD42: =IFERROR(BB42/BR42*(BU42-BASELINE_CPR),0) | CE42: =IFERROR(BC42/BR42*(BU42-BASELINE_CPR),0) | CF42: =IFERROR(BD42/BR42*(BU42-BASELINE_CPR),0) | CG42: =IFERROR(BE42/BR42*(BU42-BASELINE_CPR),0) | CH42: =IFERROR(BF42/BR42*(BU42-BASELINE_CPR),0) | CI42: =IFERROR(BG42/BR42*(BU42-BASELINE_CPR),0) | CJ42: =IFERROR(BH42/BR42*(BU42-BASELINE_CPR),0) | CK42: =IFERROR(BI42/BR42*(BU42-BASELINE_CPR),0) | CL42: =IFERROR(BJ42/BR42*(BU42-BASELINE_CPR),0) | CM42: =IFERROR(BK42/BR42*(BU42-BASELINE_CPR),0) | CN42: =IFERROR(BL42/BR42*(BU42-BASELINE_CPR),0) | CO42: =IFERROR(BM42/BR42*(BU42-BASELINE_CPR),0) | CP42: =IFERROR(BN42/BR42*(BU42-BASELINE_CPR),0) | CQ42: =IFERROR(BO42/BR42*(BU42-BASELINE_CPR),0) | CR42: =IFERROR(BP42/BR42*(BU42-BASELINE_CPR),0) | CS42: =IFERROR(BQ42/BR42*(BU42-BASELINE_CPR),0) | CT42: =BASELINE_CPR+SUM(BV42:CS42)-BU42
A43: 3617F6YS1_000000005111525 | B43: BERKADIA_POST21 | C43: 3617F6YS1 | D43: BERKADIA COMMERCIAL MORTGAGE, LLC | E43: 223f | F43: RP | G43: 2022 | H43: 202602 | I43: 19717396 | J43: 4.45 | K43: 447 | L43: 8 | M43: 43 | N43: 1 | O43: 205711 | Q43: 4082 | R43: 0 | S43: 0 | T43: 0 | U43: 0 | V43: =J43*100-K43 | W43: =L43 | X43: =MIN(M43,36) | Y43: =MIN(MAX(M43-36,0),84) | Z43: =MAX(M43-120,0) | AA43: =IF(OR(O43="",NOT(ISNUMBER(O43))),360,MAX(0,MIN(480,(INT(O43/100)-INT(VALUE(H43)/100))*12+MOD(O43,100)-MOD(VALUE(H43),100)))) | AB43: =IF(AND(AA43>0,AA43<=24),1,0) | AC43: =IF(OR(P43="",NOT(ISNUMBER(P43))),0,MAX(0,MIN(24,(INT(VALUE(H43)/100)-INT(P43/100))*12+MOD(VALUE(H43),100)-MOD(P43,100)))) | AD43: =LN(1+I43) | AE43: =IF(I43<2000000,1,0) | AF43: =IF(I43>50000000,1,0) | AG43: =IF(ISNUMBER(M43),N43/MAX(M43,1),0) | AH43: =IF(G43>=2021,1,0) | AI43: =S43 | AJ43: =T43 | AK43: =R43 | AL43: =U43 | AM43: =IF(ISNUMBER(SEARCH("CAPITAL FUNDING",D43)),1,0) | AN43: =IF(ISNUMBER(SEARCH("PNC",D43)),1,0) | AO43: =IF(ISNUMBER(SEARCH("WELLS FARGO",D43)),1,0) | AP43: =IF(ISNUMBER(SEARCH("DWIGHT",D43)),1,0) | AQ43: =IF(ISNUMBER(SEARCH("GREYSTONE",D43)),1,0) | AR43: =IF(OR(Q43="3896",Q43="3557"),1,0) | AS43: =V43*W43 | AT43: =V$4*(V43-V$3) | AU43: =W$4*(W43-W$3) | AV43: =X$4*(X43-X$3) | AW43: =Y$4*(Y43-Y$3) | AX43: =Z$4*(Z43-Z$3) | AY43: =AA$4*(AA43-AA$3) | AZ43: =AB$4*(AB43-AB$3) | BA43: =AC$4*(AC43-AC$3) | ... BQ43: =AS$4*(AS43-AS$3) | BR43: =SUM(AT43:BQ43) | BS43: =INTERCEPT_SCALED+BR43 | BT43: =1/(1+EXP(-BS43)) | BU43: =1-(1-BT43)^12 | BV43: =IFERROR(AT43/BR43*(BU43-BASELINE_CPR),0) | BW43: =IFERROR(AU43/BR43*(BU43-BASELINE_CPR),0) | BX43: =IFERROR(AV43/BR43*(BU43-BASELINE_CPR),0) | BY43: =IFERROR(AW43/BR43*(BU43-BASELINE_CPR),0) | BZ43: =IFERROR(AX43/BR43*(BU43-BASELINE_CPR),0) | CA43: =IFERROR(AY43/BR43*(BU43-BASELINE_CPR),0) | CB43: =IFERROR(AZ43/BR43*(BU43-BASELINE_CPR),0) | CC43: =IFERROR(BA43/BR43*(BU43-BASELINE_CPR),0) | CD43: =IFERROR(BB43/BR43*(BU43-BASELINE_CPR),0) | CE43: =IFERROR(BC43/BR43*(BU43-BASELINE_CPR),0) | CF43: =IFERROR(BD43/BR43*(BU43-BASELINE_CPR),0) | CG43: =IFERROR(BE43/BR43*(BU43-BASELINE_CPR),0) | CH43: =IFERROR(BF43/BR43*(BU43-BASELINE_CPR),0) | CI43: =IFERROR(BG43/BR43*(BU43-BASELINE_CPR),0) | CJ43: =IFERROR(BH43/BR43*(BU43-BASELINE_CPR),0) | CK43: =IFERROR(BI43/BR43*(BU43-BASELINE_CPR),0) | CL43: =IFERROR(BJ43/BR43*(BU43-BASELINE_CPR),0) | CM43: =IFERROR(BK43/BR43*(BU43-BASELINE_CPR),0) | CN43: =IFERROR(BL43/BR43*(BU43-BASELINE_CPR),0) | CO43: =IFERROR(BM43/BR43*(BU43-BASELINE_CPR),0) | CP43: =IFERROR(BN43/BR43*(BU43-BASELINE_CPR),0) | CQ43: =IFERROR(BO43/BR43*(BU43-BASELINE_CPR),0) | CR43: =IFERROR(BP43/BR43*(BU43-BASELINE_CPR),0) | CS43: =IFERROR(BQ43/BR43*(BU43-BASELINE_CPR),0) | CT43: =BASELINE_CPR+SUM(BV43:CS43)-BU43
A44: 3617VFMT4_000000004711152 | B44: BERKADIA_PRE21 | C44: 3617VFMT4 | D44: BERKADIA COMMERCIAL MORTGAGE, LLC | E44: 223f | F44: RP | G44: 2013 | H44: 202602 | I44: 345445.31 | J44: 2.9 | K44: 447 | L44: 7 | M44: 149 | N44: 9 | O44: 203401 | Q44: 4082 | R44: 0 | S44: 0 | T44: 0 | U44: 0 | V44: =J44*100-K44 | W44: =L44 | X44: =MIN(M44,36) | Y44: =MIN(MAX(M44-36,0),84) | Z44: =MAX(M44-120,0) | AA44: =IF(OR(O44="",NOT(ISNUMBER(O44))),360,MAX(0,MIN(480,(INT(O44/100)-INT(VALUE(H44)/100))*12+MOD(O44,100)-MOD(VALUE(H44),100)))) | AB44: =IF(AND(AA44>0,AA44<=24),1,0) | AC44: =IF(OR(P44="",NOT(ISNUMBER(P44))),0,MAX(0,MIN(24,(INT(VALUE(H44)/100)-INT(P44/100))*12+MOD(VALUE(H44),100)-MOD(P44,100)))) | AD44: =LN(1+I44) | AE44: =IF(I44<2000000,1,0) | AF44: =IF(I44>50000000,1,0) | AG44: =IF(ISNUMBER(M44),N44/MAX(M44,1),0) | AH44: =IF(G44>=2021,1,0) | AI44: =S44 | AJ44: =T44 | AK44: =R44 | AL44: =U44 | AM44: =IF(ISNUMBER(SEARCH("CAPITAL FUNDING",D44)),1,0) | AN44: =IF(ISNUMBER(SEARCH("PNC",D44)),1,0) | AO44: =IF(ISNUMBER(SEARCH("WELLS FARGO",D44)),1,0) | AP44: =IF(ISNUMBER(SEARCH("DWIGHT",D44)),1,0) | AQ44: =IF(ISNUMBER(SEARCH("GREYSTONE",D44)),1,0) | AR44: =IF(OR(Q44="3896",Q44="3557"),1,0) | AS44: =V44*W44 | AT44: =V$4*(V44-V$3) | AU44: =W$4*(W44-W$3) | AV44: =X$4*(X44-X$3) | AW44: =Y$4*(Y44-Y$3) | AX44: =Z$4*(Z44-Z$3) | AY44: =AA$4*(AA44-AA$3) | AZ44: =AB$4*(AB44-AB$3) | BA44: =AC$4*(AC44-AC$3) | ... BQ44: =AS$4*(AS44-AS$3) | BR44: =SUM(AT44:BQ44) | BS44: =INTERCEPT_SCALED+BR44 | BT44: =1/(1+EXP(-BS44)) | BU44: =1-(1-BT44)^12 | BV44: =IFERROR(AT44/BR44*(BU44-BASELINE_CPR),0) | BW44: =IFERROR(AU44/BR44*(BU44-BASELINE_CPR),0) | BX44: =IFERROR(AV44/BR44*(BU44-BASELINE_CPR),0) | BY44: =IFERROR(AW44/BR44*(BU44-BASELINE_CPR),0) | BZ44: =IFERROR(AX44/BR44*(BU44-BASELINE_CPR),0) | CA44: =IFERROR(AY44/BR44*(BU44-BASELINE_CPR),0) | CB44: =IFERROR(AZ44/BR44*(BU44-BASELINE_CPR),0) | CC44: =IFERROR(BA44/BR44*(BU44-BASELINE_CPR),0) | CD44: =IFERROR(BB44/BR44*(BU44-BASELINE_CPR),0) | CE44: =IFERROR(BC44/BR44*(BU44-BASELINE_CPR),0) | CF44: =IFERROR(BD44/BR44*(BU44-BASELINE_CPR),0) | CG44: =IFERROR(BE44/BR44*(BU44-BASELINE_CPR),0) | CH44: =IFERROR(BF44/BR44*(BU44-BASELINE_CPR),0) | CI44: =IFERROR(BG44/BR44*(BU44-BASELINE_CPR),0) | CJ44: =IFERROR(BH44/BR44*(BU44-BASELINE_CPR),0) | CK44: =IFERROR(BI44/BR44*(BU44-BASELINE_CPR),0) | CL44: =IFERROR(BJ44/BR44*(BU44-BASELINE_CPR),0) | CM44: =IFERROR(BK44/BR44*(BU44-BASELINE_CPR),0) | CN44: =IFERROR(BL44/BR44*(BU44-BASELINE_CPR),0) | CO44: =IFERROR(BM44/BR44*(BU44-BASELINE_CPR),0) | CP44: =IFERROR(BN44/BR44*(BU44-BASELINE_CPR),0) | CQ44: =IFERROR(BO44/BR44*(BU44-BASELINE_CPR),0) | CR44: =IFERROR(BP44/BR44*(BU44-BASELINE_CPR),0) | CS44: =IFERROR(BQ44/BR44*(BU44-BASELINE_CPR),0) | CT44: =BASELINE_CPR+SUM(BV44:CS44)-BU44
A45: 3617XJ2A7_000000004811084 | B45: BERKADIA_POST21 | C45: 3617XJ2A7 | D45: BERKADIA COMMERCIAL MORTGAGE, LLC | E45: 223f | F45: RP | G45: 2021 | H45: 202602 | I45: 6267503.1 | J45: 2.15 | K45: 447 | L45: 8 | M45: 51 | N45: 0 | O45: 205703 | Q45: 4082 | R45: 0 | S45: 0 | T45: 0 | U45: 0 | V45: =J45*100-K45 | W45: =L45 | X45: =MIN(M45,36) | Y45: =MIN(MAX(M45-36,0),84) | Z45: =MAX(M45-120,0) | AA45: =IF(OR(O45="",NOT(ISNUMBER(O45))),360,MAX(0,MIN(480,(INT(O45/100)-INT(VALUE(H45)/100))*12+MOD(O45,100)-MOD(VALUE(H45),100)))) | AB45: =IF(AND(AA45>0,AA45<=24),1,0) | AC45: =IF(OR(P45="",NOT(ISNUMBER(P45))),0,MAX(0,MIN(24,(INT(VALUE(H45)/100)-INT(P45/100))*12+MOD(VALUE(H45),100)-MOD(P45,100)))) | AD45: =LN(1+I45) | AE45: =IF(I45<2000000,1,0) | AF45: =IF(I45>50000000,1,0) | AG45: =IF(ISNUMBER(M45),N45/MAX(M45,1),0) | AH45: =IF(G45>=2021,1,0) | AI45: =S45 | AJ45: =T45 | AK45: =R45 | AL45: =U45 | AM45: =IF(ISNUMBER(SEARCH("CAPITAL FUNDING",D45)),1,0) | AN45: =IF(ISNUMBER(SEARCH("PNC",D45)),1,0) | AO45: =IF(ISNUMBER(SEARCH("WELLS FARGO",D45)),1,0) | AP45: =IF(ISNUMBER(SEARCH("DWIGHT",D45)),1,0) | AQ45: =IF(ISNUMBER(SEARCH("GREYSTONE",D45)),1,0) | AR45: =IF(OR(Q45="3896",Q45="3557"),1,0) | AS45: =V45*W45 | AT45: =V$4*(V45-V$3) | AU45: =W$4*(W45-W$3) | AV45: =X$4*(X45-X$3) | AW45: =Y$4*(Y45-Y$3) | AX45: =Z$4*(Z45-Z$3) | AY45: =AA$4*(AA45-AA$3) | AZ45: =AB$4*(AB45-AB$3) | BA45: =AC$4*(AC45-AC$3) | ... BQ45: =AS$4*(AS45-AS$3) | BR45: =SUM(AT45:BQ45) | BS45: =INTERCEPT_SCALED+BR45 | BT45: =1/(1+EXP(-BS45)) | BU45: =1-(1-BT45)^12 | BV45: =IFERROR(AT45/BR45*(BU45-BASELINE_CPR),0) | BW45: =IFERROR(AU45/BR45*(BU45-BASELINE_CPR),0) | BX45: =IFERROR(AV45/BR45*(BU45-BASELINE_CPR),0) | BY45: =IFERROR(AW45/BR45*(BU45-BASELINE_CPR),0) | BZ45: =IFERROR(AX45/BR45*(BU45-BASELINE_CPR),0) | CA45: =IFERROR(AY45/BR45*(BU45-BASELINE_CPR),0) | CB45: =IFERROR(AZ45/BR45*(BU45-BASELINE_CPR),0) | CC45: =IFERROR(BA45/BR45*(BU45-BASELINE_CPR),0) | CD45: =IFERROR(BB45/BR45*(BU45-BASELINE_CPR),0) | CE45: =IFERROR(BC45/BR45*(BU45-BASELINE_CPR),0) | CF45: =IFERROR(BD45/BR45*(BU45-BASELINE_CPR),0) | CG45: =IFERROR(BE45/BR45*(BU45-BASELINE_CPR),0) | CH45: =IFERROR(BF45/BR45*(BU45-BASELINE_CPR),0) | CI45: =IFERROR(BG45/BR45*(BU45-BASELINE_CPR),0) | CJ45: =IFERROR(BH45/BR45*(BU45-BASELINE_CPR),0) | CK45: =IFERROR(BI45/BR45*(BU45-BASELINE_CPR),0) | CL45: =IFERROR(BJ45/BR45*(BU45-BASELINE_CPR),0) | CM45: =IFERROR(BK45/BR45*(BU45-BASELINE_CPR),0) | CN45: =IFERROR(BL45/BR45*(BU45-BASELINE_CPR),0) | CO45: =IFERROR(BM45/BR45*(BU45-BASELINE_CPR),0) | CP45: =IFERROR(BN45/BR45*(BU45-BASELINE_CPR),0) | CQ45: =IFERROR(BO45/BR45*(BU45-BASELINE_CPR),0) | CR45: =IFERROR(BP45/BR45*(BU45-BASELINE_CPR),0) | CS45: =IFERROR(BQ45/BR45*(BU45-BASELINE_CPR),0) | CT45: =BASELINE_CPR+SUM(BV45:CS45)-BU45
A46: 3617NEBN1_000000006722139 | B46: BERKADIA_PRE21 | C46: 3617NEBN1 | D46: BERKADIA COMMERCIAL MORTGAGE, LLC | E46: 232 | F46: RP | G46: 2013 | H46: 202602 | I46: 8404084.8 | J46: 2.95 | K46: 447 | L46: 6 | M46: 148 | N46: 14 | O46: 204508 | Q46: 4082 | R46: 1 | S46: 0 | T46: 0 | U46: 0 | V46: =J46*100-K46 | W46: =L46 | X46: =MIN(M46,36) | Y46: =MIN(MAX(M46-36,0),84) | Z46: =MAX(M46-120,0) | AA46: =IF(OR(O46="",NOT(ISNUMBER(O46))),360,MAX(0,MIN(480,(INT(O46/100)-INT(VALUE(H46)/100))*12+MOD(O46,100)-MOD(VALUE(H46),100)))) | AB46: =IF(AND(AA46>0,AA46<=24),1,0) | AC46: =IF(OR(P46="",NOT(ISNUMBER(P46))),0,MAX(0,MIN(24,(INT(VALUE(H46)/100)-INT(P46/100))*12+MOD(VALUE(H46),100)-MOD(P46,100)))) | AD46: =LN(1+I46) | AE46: =IF(I46<2000000,1,0) | AF46: =IF(I46>50000000,1,0) | AG46: =IF(ISNUMBER(M46),N46/MAX(M46,1),0) | AH46: =IF(G46>=2021,1,0) | AI46: =S46 | AJ46: =T46 | AK46: =R46 | AL46: =U46 | AM46: =IF(ISNUMBER(SEARCH("CAPITAL FUNDING",D46)),1,0) | AN46: =IF(ISNUMBER(SEARCH("PNC",D46)),1,0) | AO46: =IF(ISNUMBER(SEARCH("WELLS FARGO",D46)),1,0) | AP46: =IF(ISNUMBER(SEARCH("DWIGHT",D46)),1,0) | AQ46: =IF(ISNUMBER(SEARCH("GREYSTONE",D46)),1,0) | AR46: =IF(OR(Q46="3896",Q46="3557"),1,0) | AS46: =V46*W46 | AT46: =V$4*(V46-V$3) | AU46: =W$4*(W46-W$3) | AV46: =X$4*(X46-X$3) | AW46: =Y$4*(Y46-Y$3) | AX46: =Z$4*(Z46-Z$3) | AY46: =AA$4*(AA46-AA$3) | AZ46: =AB$4*(AB46-AB$3) | BA46: =AC$4*(AC46-AC$3) | ... BQ46: =AS$4*(AS46-AS$3) | BR46: =SUM(AT46:BQ46) | BS46: =INTERCEPT_SCALED+BR46 | BT46: =1/(1+EXP(-BS46)) | BU46: =1-(1-BT46)^12 | BV46: =IFERROR(AT46/BR46*(BU46-BASELINE_CPR),0) | BW46: =IFERROR(AU46/BR46*(BU46-BASELINE_CPR),0) | BX46: =IFERROR(AV46/BR46*(BU46-BASELINE_CPR),0) | BY46: =IFERROR(AW46/BR46*(BU46-BASELINE_CPR),0) | BZ46: =IFERROR(AX46/BR46*(BU46-BASELINE_CPR),0) | CA46: =IFERROR(AY46/BR46*(BU46-BASELINE_CPR),0) | CB46: =IFERROR(AZ46/BR46*(BU46-BASELINE_CPR),0) | CC46: =IFERROR(BA46/BR46*(BU46-BASELINE_CPR),0) | CD46: =IFERROR(BB46/BR46*(BU46-BASELINE_CPR),0) | CE46: =IFERROR(BC46/BR46*(BU46-BASELINE_CPR),0) | CF46: =IFERROR(BD46/BR46*(BU46-BASELINE_CPR),0) | CG46: =IFERROR(BE46/BR46*(BU46-BASELINE_CPR),0) | CH46: =IFERROR(BF46/BR46*(BU46-BASELINE_CPR),0) | CI46: =IFERROR(BG46/BR46*(BU46-BASELINE_CPR),0) | CJ46: =IFERROR(BH46/BR46*(BU46-BASELINE_CPR),0) | CK46: =IFERROR(BI46/BR46*(BU46-BASELINE_CPR),0) | CL46: =IFERROR(BJ46/BR46*(BU46-BASELINE_CPR),0) | CM46: =IFERROR(BK46/BR46*(BU46-BASELINE_CPR),0) | CN46: =IFERROR(BL46/BR46*(BU46-BASELINE_CPR),0) | CO46: =IFERROR(BM46/BR46*(BU46-BASELINE_CPR),0) | CP46: =IFERROR(BN46/BR46*(BU46-BASELINE_CPR),0) | CQ46: =IFERROR(BO46/BR46*(BU46-BASELINE_CPR),0) | CR46: =IFERROR(BP46/BR46*(BU46-BASELINE_CPR),0) | CS46: =IFERROR(BQ46/BR46*(BU46-BASELINE_CPR),0) | CT46: =BASELINE_CPR+SUM(BV46:CS46)-BU46
A47: 3617XJY61_000000012122239 | B47: BERKADIA_POST21 | C47: 3617XJY61 | D47: BERKADIA COMMERCIAL MORTGAGE, LLC | E47: 232 | F47: RP | G47: 2021 | H47: 202602 | I47: 4130019.2 | J47: 2.58 | K47: 447 | L47: 8 | M47: 53 | N47: 0 | O47: 204206 | Q47: 4082 | R47: 1 | S47: 1 | T47: 0 | U47: 0 | V47: =J47*100-K47 | W47: =L47 | X47: =MIN(M47,36) | Y47: =MIN(MAX(M47-36,0),84) | Z47: =MAX(M47-120,0) | AA47: =IF(OR(O47="",NOT(ISNUMBER(O47))),360,MAX(0,MIN(480,(INT(O47/100)-INT(VALUE(H47)/100))*12+MOD(O47,100)-MOD(VALUE(H47),100)))) | AB47: =IF(AND(AA47>0,AA47<=24),1,0) | AC47: =IF(OR(P47="",NOT(ISNUMBER(P47))),0,MAX(0,MIN(24,(INT(VALUE(H47)/100)-INT(P47/100))*12+MOD(VALUE(H47),100)-MOD(P47,100)))) | AD47: =LN(1+I47) | AE47: =IF(I47<2000000,1,0) | AF47: =IF(I47>50000000,1,0) | AG47: =IF(ISNUMBER(M47),N47/MAX(M47,1),0) | AH47: =IF(G47>=2021,1,0) | AI47: =S47 | AJ47: =T47 | AK47: =R47 | AL47: =U47 | AM47: =IF(ISNUMBER(SEARCH("CAPITAL FUNDING",D47)),1,0) | AN47: =IF(ISNUMBER(SEARCH("PNC",D47)),1,0) | AO47: =IF(ISNUMBER(SEARCH("WELLS FARGO",D47)),1,0) | AP47: =IF(ISNUMBER(SEARCH("DWIGHT",D47)),1,0) | AQ47: =IF(ISNUMBER(SEARCH("GREYSTONE",D47)),1,0) | AR47: =IF(OR(Q47="3896",Q47="3557"),1,0) | AS47: =V47*W47 | AT47: =V$4*(V47-V$3) | AU47: =W$4*(W47-W$3) | AV47: =X$4*(X47-X$3) | AW47: =Y$4*(Y47-Y$3) | AX47: =Z$4*(Z47-Z$3) | AY47: =AA$4*(AA47-AA$3) | AZ47: =AB$4*(AB47-AB$3) | BA47: =AC$4*(AC47-AC$3) | ... BQ47: =AS$4*(AS47-AS$3) | BR47: =SUM(AT47:BQ47) | BS47: =INTERCEPT_SCALED+BR47 | BT47: =1/(1+EXP(-BS47)) | BU47: =1-(1-BT47)^12 | BV47: =IFERROR(AT47/BR47*(BU47-BASELINE_CPR),0) | BW47: =IFERROR(AU47/BR47*(BU47-BASELINE_CPR),0) | BX47: =IFERROR(AV47/BR47*(BU47-BASELINE_CPR),0) | BY47: =IFERROR(AW47/BR47*(BU47-BASELINE_CPR),0) | BZ47: =IFERROR(AX47/BR47*(BU47-BASELINE_CPR),0) | CA47: =IFERROR(AY47/BR47*(BU47-BASELINE_CPR),0) | CB47: =IFERROR(AZ47/BR47*(BU47-BASELINE_CPR),0) | CC47: =IFERROR(BA47/BR47*(BU47-BASELINE_CPR),0) | CD47: =IFERROR(BB47/BR47*(BU47-BASELINE_CPR),0) | CE47: =IFERROR(BC47/BR47*(BU47-BASELINE_CPR),0) | CF47: =IFERROR(BD47/BR47*(BU47-BASELINE_CPR),0) | CG47: =IFERROR(BE47/BR47*(BU47-BASELINE_CPR),0) | CH47: =IFERROR(BF47/BR47*(BU47-BASELINE_CPR),0) | CI47: =IFERROR(BG47/BR47*(BU47-BASELINE_CPR),0) | CJ47: =IFERROR(BH47/BR47*(BU47-BASELINE_CPR),0) | CK47: =IFERROR(BI47/BR47*(BU47-BASELINE_CPR),0) | CL47: =IFERROR(BJ47/BR47*(BU47-BASELINE_CPR),0) | CM47: =IFERROR(BK47/BR47*(BU47-BASELINE_CPR),0) | CN47: =IFERROR(BL47/BR47*(BU47-BASELINE_CPR),0) | CO47: =IFERROR(BM47/BR47*(BU47-BASELINE_CPR),0) | CP47: =IFERROR(BN47/BR47*(BU47-BASELINE_CPR),0) | CQ47: =IFERROR(BO47/BR47*(BU47-BASELINE_CPR),0) | CR47: =IFERROR(BP47/BR47*(BU47-BASELINE_CPR),0) | CS47: =IFERROR(BQ47/BR47*(BU47-BASELINE_CPR),0) | CT47: =BASELINE_CPR+SUM(BV47:CS47)-BU47
A48: 3617BRKN5_000000005111395 | B48: BERKADIA_PRE21 | C48: 3617BRKN5 | D48: BERKADIA COMMERCIAL MORTGAGE, LLC | E48: 223f | F48: RP | G48: 2017 | H48: 202602 | I48: 6113588.5 | J48: 3.13 | K48: 447 | L48: 4 | M48: 98 | N48: 19 | O48: 205303 | Q48: 4082 | R48: 0 | S48: 0 | T48: 0 | U48: 0 | V48: =J48*100-K48 | W48: =L48 | X48: =MIN(M48,36) | Y48: =MIN(MAX(M48-36,0),84) | Z48: =MAX(M48-120,0) | AA48: =IF(OR(O48="",NOT(ISNUMBER(O48))),360,MAX(0,MIN(480,(INT(O48/100)-INT(VALUE(H48)/100))*12+MOD(O48,100)-MOD(VALUE(H48),100)))) | AB48: =IF(AND(AA48>0,AA48<=24),1,0) | AC48: =IF(OR(P48="",NOT(ISNUMBER(P48))),0,MAX(0,MIN(24,(INT(VALUE(H48)/100)-INT(P48/100))*12+MOD(VALUE(H48),100)-MOD(P48,100)))) | AD48: =LN(1+I48) | AE48: =IF(I48<2000000,1,0) | AF48: =IF(I48>50000000,1,0) | AG48: =IF(ISNUMBER(M48),N48/MAX(M48,1),0) | AH48: =IF(G48>=2021,1,0) | AI48: =S48 | AJ48: =T48 | AK48: =R48 | AL48: =U48 | AM48: =IF(ISNUMBER(SEARCH("CAPITAL FUNDING",D48)),1,0) | AN48: =IF(ISNUMBER(SEARCH("PNC",D48)),1,0) | AO48: =IF(ISNUMBER(SEARCH("WELLS FARGO",D48)),1,0) | AP48: =IF(ISNUMBER(SEARCH("DWIGHT",D48)),1,0) | AQ48: =IF(ISNUMBER(SEARCH("GREYSTONE",D48)),1,0) | AR48: =IF(OR(Q48="3896",Q48="3557"),1,0) | AS48: =V48*W48 | AT48: =V$4*(V48-V$3) | AU48: =W$4*(W48-W$3) | AV48: =X$4*(X48-X$3) | AW48: =Y$4*(Y48-Y$3) | AX48: =Z$4*(Z48-Z$3) | AY48: =AA$4*(AA48-AA$3) | AZ48: =AB$4*(AB48-AB$3) | BA48: =AC$4*(AC48-AC$3) | ... BQ48: =AS$4*(AS48-AS$3) | BR48: =SUM(AT48:BQ48) | BS48: =INTERCEPT_SCALED+BR48 | BT48: =1/(1+EXP(-BS48)) | BU48: =1-(1-BT48)^12 | BV48: =IFERROR(AT48/BR48*(BU48-BASELINE_CPR),0) | BW48: =IFERROR(AU48/BR48*(BU48-BASELINE_CPR),0) | BX48: =IFERROR(AV48/BR48*(BU48-BASELINE_CPR),0) | BY48: =IFERROR(AW48/BR48*(BU48-BASELINE_CPR),0) | BZ48: =IFERROR(AX48/BR48*(BU48-BASELINE_CPR),0) | CA48: =IFERROR(AY48/BR48*(BU48-BASELINE_CPR),0) | CB48: =IFERROR(AZ48/BR48*(BU48-BASELINE_CPR),0) | CC48: =IFERROR(BA48/BR48*(BU48-BASELINE_CPR),0) | CD48: =IFERROR(BB48/BR48*(BU48-BASELINE_CPR),0) | CE48: =IFERROR(BC48/BR48*(BU48-BASELINE_CPR),0) | CF48: =IFERROR(BD48/BR48*(BU48-BASELINE_CPR),0) | CG48: =IFERROR(BE48/BR48*(BU48-BASELINE_CPR),0) | CH48: =IFERROR(BF48/BR48*(BU48-BASELINE_CPR),0) | CI48: =IFERROR(BG48/BR48*(BU48-BASELINE_CPR),0) | CJ48: =IFERROR(BH48/BR48*(BU48-BASELINE_CPR),0) | CK48: =IFERROR(BI48/BR48*(BU48-BASELINE_CPR),0) | CL48: =IFERROR(BJ48/BR48*(BU48-BASELINE_CPR),0) | CM48: =IFERROR(BK48/BR48*(BU48-BASELINE_CPR),0) | CN48: =IFERROR(BL48/BR48*(BU48-BASELINE_CPR),0) | CO48: =IFERROR(BM48/BR48*(BU48-BASELINE_CPR),0) | CP48: =IFERROR(BN48/BR48*(BU48-BASELINE_CPR),0) | CQ48: =IFERROR(BO48/BR48*(BU48-BASELINE_CPR),0) | CR48: =IFERROR(BP48/BR48*(BU48-BASELINE_CPR),0) | CS48: =IFERROR(BQ48/BR48*(BU48-BASELINE_CPR),0) | CT48: =BASELINE_CPR+SUM(BV48:CS48)-BU48
A49: 3617AGRX1_000000007311922 | B49: BERKADIA_PRE21 | C49: 3617AGRX1 | D49: BERKADIA COMMERCIAL MORTGAGE, LLC | E49: 221d4 | F49: RP | G49: 2017 | H49: 202602 | I49: 137331.58 | J49: 4.25 | K49: 447 | L49: 3 | M49: 102 | N49: 36 | O49: 204712 | Q49: 4082 | R49: 0 | S49: 1 | T49: 0 | U49: 0 | V49: =J49*100-K49 | W49: =L49 | X49: =MIN(M49,36) | Y49: =MIN(MAX(M49-36,0),84) | Z49: =MAX(M49-120,0) | AA49: =IF(OR(O49="",NOT(ISNUMBER(O49))),360,MAX(0,MIN(480,(INT(O49/100)-INT(VALUE(H49)/100))*12+MOD(O49,100)-MOD(VALUE(H49),100)))) | AB49: =IF(AND(AA49>0,AA49<=24),1,0) | AC49: =IF(OR(P49="",NOT(ISNUMBER(P49))),0,MAX(0,MIN(24,(INT(VALUE(H49)/100)-INT(P49/100))*12+MOD(VALUE(H49),100)-MOD(P49,100)))) | AD49: =LN(1+I49) | AE49: =IF(I49<2000000,1,0) | AF49: =IF(I49>50000000,1,0) | AG49: =IF(ISNUMBER(M49),N49/MAX(M49,1),0) | AH49: =IF(G49>=2021,1,0) | AI49: =S49 | AJ49: =T49 | AK49: =R49 | AL49: =U49 | AM49: =IF(ISNUMBER(SEARCH("CAPITAL FUNDING",D49)),1,0) | AN49: =IF(ISNUMBER(SEARCH("PNC",D49)),1,0) | AO49: =IF(ISNUMBER(SEARCH("WELLS FARGO",D49)),1,0) | AP49: =IF(ISNUMBER(SEARCH("DWIGHT",D49)),1,0) | AQ49: =IF(ISNUMBER(SEARCH("GREYSTONE",D49)),1,0) | AR49: =IF(OR(Q49="3896",Q49="3557"),1,0) | AS49: =V49*W49 | AT49: =V$4*(V49-V$3) | AU49: =W$4*(W49-W$3) | AV49: =X$4*(X49-X$3) | AW49: =Y$4*(Y49-Y$3) | AX49: =Z$4*(Z49-Z$3) | AY49: =AA$4*(AA49-AA$3) | AZ49: =AB$4*(AB49-AB$3) | BA49: =AC$4*(AC49-AC$3) | ... BQ49: =AS$4*(AS49-AS$3) | BR49: =SUM(AT49:BQ49) | BS49: =INTERCEPT_SCALED+BR49 | BT49: =1/(1+EXP(-BS49)) | BU49: =1-(1-BT49)^12 | BV49: =IFERROR(AT49/BR49*(BU49-BASELINE_CPR),0) | BW49: =IFERROR(AU49/BR49*(BU49-BASELINE_CPR),0) | BX49: =IFERROR(AV49/BR49*(BU49-BASELINE_CPR),0) | BY49: =IFERROR(AW49/BR49*(BU49-BASELINE_CPR),0) | BZ49: =IFERROR(AX49/BR49*(BU49-BASELINE_CPR),0) | CA49: =IFERROR(AY49/BR49*(BU49-BASELINE_CPR),0) | CB49: =IFERROR(AZ49/BR49*(BU49-BASELINE_CPR),0) | CC49: =IFERROR(BA49/BR49*(BU49-BASELINE_CPR),0) | CD49: =IFERROR(BB49/BR49*(BU49-BASELINE_CPR),0) | CE49: =IFERROR(BC49/BR49*(BU49-BASELINE_CPR),0) | CF49: =IFERROR(BD49/BR49*(BU49-BASELINE_CPR),0) | CG49: =IFERROR(BE49/BR49*(BU49-BASELINE_CPR),0) | CH49: =IFERROR(BF49/BR49*(BU49-BASELINE_CPR),0) | CI49: =IFERROR(BG49/BR49*(BU49-BASELINE_CPR),0) | CJ49: =IFERROR(BH49/BR49*(BU49-BASELINE_CPR),0) | CK49: =IFERROR(BI49/BR49*(BU49-BASELINE_CPR),0) | CL49: =IFERROR(BJ49/BR49*(BU49-BASELINE_CPR),0) | CM49: =IFERROR(BK49/BR49*(BU49-BASELINE_CPR),0) | CN49: =IFERROR(BL49/BR49*(BU49-BASELINE_CPR),0) | CO49: =IFERROR(BM49/BR49*(BU49-BASELINE_CPR),0) | CP49: =IFERROR(BN49/BR49*(BU49-BASELINE_CPR),0) | CQ49: =IFERROR(BO49/BR49*(BU49-BASELINE_CPR),0) | CR49: =IFERROR(BP49/BR49*(BU49-BASELINE_CPR),0) | CS49: =IFERROR(BQ49/BR49*(BU49-BASELINE_CPR),0) | CT49: =BASELINE_CPR+SUM(BV49:CS49)-BU49
A50: 3617XJZZ6_000000011535902 | B50: BERKADIA_POST21 | C50: 3617XJZZ6 | D50: BERKADIA COMMERCIAL MORTGAGE, LLC | E50: 221d4 | F50: NC | G50: 2021 | H50: 202602 | I50: 45179300 | J50: 2.96 | K50: 447 | L50: 10 | M50: 50 | N50: 0 | O50: 206408 | Q50: 4082 | R50: 0 | S50: 0 | T50: 0 | U50: 1 | V50: =J50*100-K50 | W50: =L50 | X50: =MIN(M50,36) | Y50: =MIN(MAX(M50-36,0),84) | Z50: =MAX(M50-120,0) | AA50: =IF(OR(O50="",NOT(ISNUMBER(O50))),360,MAX(0,MIN(480,(INT(O50/100)-INT(VALUE(H50)/100))*12+MOD(O50,100)-MOD(VALUE(H50),100)))) | AB50: =IF(AND(AA50>0,AA50<=24),1,0) | AC50: =IF(OR(P50="",NOT(ISNUMBER(P50))),0,MAX(0,MIN(24,(INT(VALUE(H50)/100)-INT(P50/100))*12+MOD(VALUE(H50),100)-MOD(P50,100)))) | AD50: =LN(1+I50) | AE50: =IF(I50<2000000,1,0) | AF50: =IF(I50>50000000,1,0) | AG50: =IF(ISNUMBER(M50),N50/MAX(M50,1),0) | AH50: =IF(G50>=2021,1,0) | AI50: =S50 | AJ50: =T50 | AK50: =R50 | AL50: =U50 | AM50: =IF(ISNUMBER(SEARCH("CAPITAL FUNDING",D50)),1,0) | AN50: =IF(ISNUMBER(SEARCH("PNC",D50)),1,0) | AO50: =IF(ISNUMBER(SEARCH("WELLS FARGO",D50)),1,0) | AP50: =IF(ISNUMBER(SEARCH("DWIGHT",D50)),1,0) | AQ50: =IF(ISNUMBER(SEARCH("GREYSTONE",D50)),1,0) | AR50: =IF(OR(Q50="3896",Q50="3557"),1,0) | AS50: =V50*W50 | AT50: =V$4*(V50-V$3) | AU50: =W$4*(W50-W$3) | AV50: =X$4*(X50-X$3) | AW50: =Y$4*(Y50-Y$3) | AX50: =Z$4*(Z50-Z$3) | AY50: =AA$4*(AA50-AA$3) | AZ50: =AB$4*(AB50-AB$3) | BA50: =AC$4*(AC50-AC$3) | ... BQ50: =AS$4*(AS50-AS$3) | BR50: =SUM(AT50:BQ50) | BS50: =INTERCEPT_SCALED+BR50 | BT50: =1/(1+EXP(-BS50)) | BU50: =1-(1-BT50)^12 | BV50: =IFERROR(AT50/BR50*(BU50-BASELINE_CPR),0) | BW50: =IFERROR(AU50/BR50*(BU50-BASELINE_CPR),0) | BX50: =IFERROR(AV50/BR50*(BU50-BASELINE_CPR),0) | BY50: =IFERROR(AW50/BR50*(BU50-BASELINE_CPR),0) | BZ50: =IFERROR(AX50/BR50*(BU50-BASELINE_CPR),0) | CA50: =IFERROR(AY50/BR50*(BU50-BASELINE_CPR),0) | CB50: =IFERROR(AZ50/BR50*(BU50-BASELINE_CPR),0) | CC50: =IFERROR(BA50/BR50*(BU50-BASELINE_CPR),0) | CD50: =IFERROR(BB50/BR50*(BU50-BASELINE_CPR),0) | CE50: =IFERROR(BC50/BR50*(BU50-BASELINE_CPR),0) | CF50: =IFERROR(BD50/BR50*(BU50-BASELINE_CPR),0) | CG50: =IFERROR(BE50/BR50*(BU50-BASELINE_CPR),0) | CH50: =IFERROR(BF50/BR50*(BU50-BASELINE_CPR),0) | CI50: =IFERROR(BG50/BR50*(BU50-BASELINE_CPR),0) | CJ50: =IFERROR(BH50/BR50*(BU50-BASELINE_CPR),0) | CK50: =IFERROR(BI50/BR50*(BU50-BASELINE_CPR),0) | CL50: =IFERROR(BJ50/BR50*(BU50-BASELINE_CPR),0) | CM50: =IFERROR(BK50/BR50*(BU50-BASELINE_CPR),0) | CN50: =IFERROR(BL50/BR50*(BU50-BASELINE_CPR),0) | CO50: =IFERROR(BM50/BR50*(BU50-BASELINE_CPR),0) | CP50: =IFERROR(BN50/BR50*(BU50-BASELINE_CPR),0) | CQ50: =IFERROR(BO50/BR50*(BU50-BASELINE_CPR),0) | CR50: =IFERROR(BP50/BR50*(BU50-BASELINE_CPR),0) | CS50: =IFERROR(BQ50/BR50*(BU50-BASELINE_CPR),0) | CT50: =BASELINE_CPR+SUM(BV50:CS50)-BU50
A51: 3617BRLC8_000000005411156 | B51: BERKADIA_PRE21 | C51: 3617BRLC8 | D51: BERKADIA COMMERCIAL MORTGAGE, LLC | E51: 223f | F51: RP | G51: 2017 | H51: 202602 | I51: 3384137.4 | J51: 3.99 | K51: 447 | L51: 0 | M51: 99 | N51: 41 | O51: 204806 | Q51: 4082 | R51: 0 | S51: 0 | T51: 0 | U51: 0 | V51: =J51*100-K51 | W51: =L51 | X51: =MIN(M51,36) | Y51: =MIN(MAX(M51-36,0),84) | Z51: =MAX(M51-120,0) | AA51: =IF(OR(O51="",NOT(ISNUMBER(O51))),360,MAX(0,MIN(480,(INT(O51/100)-INT(VALUE(H51)/100))*12+MOD(O51,100)-MOD(VALUE(H51),100)))) | AB51: =IF(AND(AA51>0,AA51<=24),1,0) | AC51: =IF(OR(P51="",NOT(ISNUMBER(P51))),0,MAX(0,MIN(24,(INT(VALUE(H51)/100)-INT(P51/100))*12+MOD(VALUE(H51),100)-MOD(P51,100)))) | AD51: =LN(1+I51) | AE51: =IF(I51<2000000,1,0) | AF51: =IF(I51>50000000,1,0) | AG51: =IF(ISNUMBER(M51),N51/MAX(M51,1),0) | AH51: =IF(G51>=2021,1,0) | AI51: =S51 | AJ51: =T51 | AK51: =R51 | AL51: =U51 | AM51: =IF(ISNUMBER(SEARCH("CAPITAL FUNDING",D51)),1,0) | AN51: =IF(ISNUMBER(SEARCH("PNC",D51)),1,0) | AO51: =IF(ISNUMBER(SEARCH("WELLS FARGO",D51)),1,0) | AP51: =IF(ISNUMBER(SEARCH("DWIGHT",D51)),1,0) | AQ51: =IF(ISNUMBER(SEARCH("GREYSTONE",D51)),1,0) | AR51: =IF(OR(Q51="3896",Q51="3557"),1,0) | AS51: =V51*W51 | AT51: =V$4*(V51-V$3) | AU51: =W$4*(W51-W$3) | AV51: =X$4*(X51-X$3) | AW51: =Y$4*(Y51-Y$3) | AX51: =Z$4*(Z51-Z$3) | AY51: =AA$4*(AA51-AA$3) | AZ51: =AB$4*(AB51-AB$3) | BA51: =AC$4*(AC51-AC$3) | ... BQ51: =AS$4*(AS51-AS$3) | BR51: =SUM(AT51:BQ51) | BS51: =INTERCEPT_SCALED+BR51 | BT51: =1/(1+EXP(-BS51)) | BU51: =1-(1-BT51)^12 | BV51: =IFERROR(AT51/BR51*(BU51-BASELINE_CPR),0) | BW51: =IFERROR(AU51/BR51*(BU51-BASELINE_CPR),0) | BX51: =IFERROR(AV51/BR51*(BU51-BASELINE_CPR),0) | BY51: =IFERROR(AW51/BR51*(BU51-BASELINE_CPR),0) | BZ51: =IFERROR(AX51/BR51*(BU51-BASELINE_CPR),0) | CA51: =IFERROR(AY51/BR51*(BU51-BASELINE_CPR),0) | CB51: =IFERROR(AZ51/BR51*(BU51-BASELINE_CPR),0) | CC51: =IFERROR(BA51/BR51*(BU51-BASELINE_CPR),0) | CD51: =IFERROR(BB51/BR51*(BU51-BASELINE_CPR),0) | CE51: =IFERROR(BC51/BR51*(BU51-BASELINE_CPR),0) | CF51: =IFERROR(BD51/BR51*(BU51-BASELINE_CPR),0) | CG51: =IFERROR(BE51/BR51*(BU51-BASELINE_CPR),0) | CH51: =IFERROR(BF51/BR51*(BU51-BASELINE_CPR),0) | CI51: =IFERROR(BG51/BR51*(BU51-BASELINE_CPR),0) | CJ51: =IFERROR(BH51/BR51*(BU51-BASELINE_CPR),0) | CK51: =IFERROR(BI51/BR51*(BU51-BASELINE_CPR),0) | CL51: =IFERROR(BJ51/BR51*(BU51-BASELINE_CPR),0) | CM51: =IFERROR(BK51/BR51*(BU51-BASELINE_CPR),0) | CN51: =IFERROR(BL51/BR51*(BU51-BASELINE_CPR),0) | CO51: =IFERROR(BM51/BR51*(BU51-BASELINE_CPR),0) | CP51: =IFERROR(BN51/BR51*(BU51-BASELINE_CPR),0) | CQ51: =IFERROR(BO51/BR51*(BU51-BASELINE_CPR),0) | CR51: =IFERROR(BP51/BR51*(BU51-BASELINE_CPR),0) | CS51: =IFERROR(BQ51/BR51*(BU51-BASELINE_CPR),0) | CT51: =BASELINE_CPR+SUM(BV51:CS51)-BU51
A52: 3617XJ2D1_000000004711281 | B52: BERKADIA_POST21 | C52: 3617XJ2D1 | D52: BERKADIA COMMERCIAL MORTGAGE, LLC | E52: 223f | F52: RP | G52: 2021 | H52: 202602 | I52: 5205375.8 | J52: 2.49 | K52: 447 | L52: 8 | M52: 54 | N52: 0 | O52: 205604 | Q52: 4082 | R52: 0 | S52: 0 | T52: 0 | U52: 0 | V52: =J52*100-K52 | W52: =L52 | X52: =MIN(M52,36) | Y52: =MIN(MAX(M52-36,0),84) | Z52: =MAX(M52-120,0) | AA52: =IF(OR(O52="",NOT(ISNUMBER(O52))),360,MAX(0,MIN(480,(INT(O52/100)-INT(VALUE(H52)/100))*12+MOD(O52,100)-MOD(VALUE(H52),100)))) | AB52: =IF(AND(AA52>0,AA52<=24),1,0) | AC52: =IF(OR(P52="",NOT(ISNUMBER(P52))),0,MAX(0,MIN(24,(INT(VALUE(H52)/100)-INT(P52/100))*12+MOD(VALUE(H52),100)-MOD(P52,100)))) | AD52: =LN(1+I52) | AE52: =IF(I52<2000000,1,0) | AF52: =IF(I52>50000000,1,0) | AG52: =IF(ISNUMBER(M52),N52/MAX(M52,1),0) | AH52: =IF(G52>=2021,1,0) | AI52: =S52 | AJ52: =T52 | AK52: =R52 | AL52: =U52 | AM52: =IF(ISNUMBER(SEARCH("CAPITAL FUNDING",D52)),1,0) | AN52: =IF(ISNUMBER(SEARCH("PNC",D52)),1,0) | AO52: =IF(ISNUMBER(SEARCH("WELLS FARGO",D52)),1,0) | AP52: =IF(ISNUMBER(SEARCH("DWIGHT",D52)),1,0) | AQ52: =IF(ISNUMBER(SEARCH("GREYSTONE",D52)),1,0) | AR52: =IF(OR(Q52="3896",Q52="3557"),1,0) | AS52: =V52*W52 | AT52: =V$4*(V52-V$3) | AU52: =W$4*(W52-W$3) | AV52: =X$4*(X52-X$3) | AW52: =Y$4*(Y52-Y$3) | AX52: =Z$4*(Z52-Z$3) | AY52: =AA$4*(AA52-AA$3) | AZ52: =AB$4*(AB52-AB$3) | BA52: =AC$4*(AC52-AC$3) | ... BQ52: =AS$4*(AS52-AS$3) | BR52: =SUM(AT52:BQ52) | BS52: =INTERCEPT_SCALED+BR52 | BT52: =1/(1+EXP(-BS52)) | BU52: =1-(1-BT52)^12 | BV52: =IFERROR(AT52/BR52*(BU52-BASELINE_CPR),0) | BW52: =IFERROR(AU52/BR52*(BU52-BASELINE_CPR),0) | BX52: =IFERROR(AV52/BR52*(BU52-BASELINE_CPR),0) | BY52: =IFERROR(AW52/BR52*(BU52-BASELINE_CPR),0) | BZ52: =IFERROR(AX52/BR52*(BU52-BASELINE_CPR),0) | CA52: =IFERROR(AY52/BR52*(BU52-BASELINE_CPR),0) | CB52: =IFERROR(AZ52/BR52*(BU52-BASELINE_CPR),0) | CC52: =IFERROR(BA52/BR52*(BU52-BASELINE_CPR),0) | CD52: =IFERROR(BB52/BR52*(BU52-BASELINE_CPR),0) | CE52: =IFERROR(BC52/BR52*(BU52-BASELINE_CPR),0) | CF52: =IFERROR(BD52/BR52*(BU52-BASELINE_CPR),0) | CG52: =IFERROR(BE52/BR52*(BU52-BASELINE_CPR),0) | CH52: =IFERROR(BF52/BR52*(BU52-BASELINE_CPR),0) | CI52: =IFERROR(BG52/BR52*(BU52-BASELINE_CPR),0) | CJ52: =IFERROR(BH52/BR52*(BU52-BASELINE_CPR),0) | CK52: =IFERROR(BI52/BR52*(BU52-BASELINE_CPR),0) | CL52: =IFERROR(BJ52/BR52*(BU52-BASELINE_CPR),0) | CM52: =IFERROR(BK52/BR52*(BU52-BASELINE_CPR),0) | CN52: =IFERROR(BL52/BR52*(BU52-BASELINE_CPR),0) | CO52: =IFERROR(BM52/BR52*(BU52-BASELINE_CPR),0) | CP52: =IFERROR(BN52/BR52*(BU52-BASELINE_CPR),0) | CQ52: =IFERROR(BO52/BR52*(BU52-BASELINE_CPR),0) | CR52: =IFERROR(BP52/BR52*(BU52-BASELINE_CPR),0) | CS52: =IFERROR(BQ52/BR52*(BU52-BASELINE_CPR),0) | CT52: =BASELINE_CPR+SUM(BV52:CS52)-BU52
A53: 3617UNW83_000000005135817 | B53: BERKADIA_PRE21 | C53: 3617UNW83 | D53: BERKADIA COMMERCIAL MORTGAGE, LLC | E53: 221d4 | F53: RP | G53: 2020 | H53: 202602 | I53: 36370658 | J53: 2.3 | K53: 447 | L53: 7 | M53: 64 | N53: 12 | O53: 206103 | Q53: 4082 | R53: 0 | S53: 1 | T53: 0 | U53: 0 | V53: =J53*100-K53 | W53: =L53 | X53: =MIN(M53,36) | Y53: =MIN(MAX(M53-36,0),84) | Z53: =MAX(M53-120,0) | AA53: =IF(OR(O53="",NOT(ISNUMBER(O53))),360,MAX(0,MIN(480,(INT(O53/100)-INT(VALUE(H53)/100))*12+MOD(O53,100)-MOD(VALUE(H53),100)))) | AB53: =IF(AND(AA53>0,AA53<=24),1,0) | AC53: =IF(OR(P53="",NOT(ISNUMBER(P53))),0,MAX(0,MIN(24,(INT(VALUE(H53)/100)-INT(P53/100))*12+MOD(VALUE(H53),100)-MOD(P53,100)))) | AD53: =LN(1+I53) | AE53: =IF(I53<2000000,1,0) | AF53: =IF(I53>50000000,1,0) | AG53: =IF(ISNUMBER(M53),N53/MAX(M53,1),0) | AH53: =IF(G53>=2021,1,0) | AI53: =S53 | AJ53: =T53 | AK53: =R53 | AL53: =U53 | AM53: =IF(ISNUMBER(SEARCH("CAPITAL FUNDING",D53)),1,0) | AN53: =IF(ISNUMBER(SEARCH("PNC",D53)),1,0) | AO53: =IF(ISNUMBER(SEARCH("WELLS FARGO",D53)),1,0) | AP53: =IF(ISNUMBER(SEARCH("DWIGHT",D53)),1,0) | AQ53: =IF(ISNUMBER(SEARCH("GREYSTONE",D53)),1,0) | AR53: =IF(OR(Q53="3896",Q53="3557"),1,0) | AS53: =V53*W53 | AT53: =V$4*(V53-V$3) | AU53: =W$4*(W53-W$3) | AV53: =X$4*(X53-X$3) | AW53: =Y$4*(Y53-Y$3) | AX53: =Z$4*(Z53-Z$3) | AY53: =AA$4*(AA53-AA$3) | AZ53: =AB$4*(AB53-AB$3) | BA53: =AC$4*(AC53-AC$3) | ... BQ53: =AS$4*(AS53-AS$3) | BR53: =SUM(AT53:BQ53) | BS53: =INTERCEPT_SCALED+BR53 | BT53: =1/(1+EXP(-BS53)) | BU53: =1-(1-BT53)^12 | BV53: =IFERROR(AT53/BR53*(BU53-BASELINE_CPR),0) | BW53: =IFERROR(AU53/BR53*(BU53-BASELINE_CPR),0) | BX53: =IFERROR(AV53/BR53*(BU53-BASELINE_CPR),0) | BY53: =IFERROR(AW53/BR53*(BU53-BASELINE_CPR),0) | BZ53: =IFERROR(AX53/BR53*(BU53-BASELINE_CPR),0) | CA53: =IFERROR(AY53/BR53*(BU53-BASELINE_CPR),0) | CB53: =IFERROR(AZ53/BR53*(BU53-BASELINE_CPR),0) | CC53: =IFERROR(BA53/BR53*(BU53-BASELINE_CPR),0) | CD53: =IFERROR(BB53/BR53*(BU53-BASELINE_CPR),0) | CE53: =IFERROR(BC53/BR53*(BU53-BASELINE_CPR),0) | CF53: =IFERROR(BD53/BR53*(BU53-BASELINE_CPR),0) | CG53: =IFERROR(BE53/BR53*(BU53-BASELINE_CPR),0) | CH53: =IFERROR(BF53/BR53*(BU53-BASELINE_CPR),0) | CI53: =IFERROR(BG53/BR53*(BU53-BASELINE_CPR),0) | CJ53: =IFERROR(BH53/BR53*(BU53-BASELINE_CPR),0) | CK53: =IFERROR(BI53/BR53*(BU53-BASELINE_CPR),0) | CL53: =IFERROR(BJ53/BR53*(BU53-BASELINE_CPR),0) | CM53: =IFERROR(BK53/BR53*(BU53-BASELINE_CPR),0) | CN53: =IFERROR(BL53/BR53*(BU53-BASELINE_CPR),0) | CO53: =IFERROR(BM53/BR53*(BU53-BASELINE_CPR),0) | CP53: =IFERROR(BN53/BR53*(BU53-BASELINE_CPR),0) | CQ53: =IFERROR(BO53/BR53*(BU53-BASELINE_CPR),0) | CR53: =IFERROR(BP53/BR53*(BU53-BASELINE_CPR),0) | CS53: =IFERROR(BQ53/BR53*(BU53-BASELINE_CPR),0) | CT53: =BASELINE_CPR+SUM(BV53:CS53)-BU53
A54: 3617F6YH5_000000010511134 | B54: BERKADIA_POST21 | C54: 3617F6YH5 | D54: BERKADIA COMMERCIAL MORTGAGE, LLC | E54: 223f | F54: RP | G54: 2022 | H54: 202602 | I54: 40172298 | J54: 3.68 | K54: 447 | L54: 8 | M54: 46 | N54: 0 | O54: 205709 | Q54: 4082 | R54: 0 | S54: 0 | T54: 0 | U54: 0 | V54: =J54*100-K54 | W54: =L54 | X54: =MIN(M54,36) | Y54: =MIN(MAX(M54-36,0),84) | Z54: =MAX(M54-120,0) | AA54: =IF(OR(O54="",NOT(ISNUMBER(O54))),360,MAX(0,MIN(480,(INT(O54/100)-INT(VALUE(H54)/100))*12+MOD(O54,100)-MOD(VALUE(H54),100)))) | AB54: =IF(AND(AA54>0,AA54<=24),1,0) | AC54: =IF(OR(P54="",NOT(ISNUMBER(P54))),0,MAX(0,MIN(24,(INT(VALUE(H54)/100)-INT(P54/100))*12+MOD(VALUE(H54),100)-MOD(P54,100)))) | AD54: =LN(1+I54) | AE54: =IF(I54<2000000,1,0) | AF54: =IF(I54>50000000,1,0) | AG54: =IF(ISNUMBER(M54),N54/MAX(M54,1),0) | AH54: =IF(G54>=2021,1,0) | AI54: =S54 | AJ54: =T54 | AK54: =R54 | AL54: =U54 | AM54: =IF(ISNUMBER(SEARCH("CAPITAL FUNDING",D54)),1,0) | AN54: =IF(ISNUMBER(SEARCH("PNC",D54)),1,0) | AO54: =IF(ISNUMBER(SEARCH("WELLS FARGO",D54)),1,0) | AP54: =IF(ISNUMBER(SEARCH("DWIGHT",D54)),1,0) | AQ54: =IF(ISNUMBER(SEARCH("GREYSTONE",D54)),1,0) | AR54: =IF(OR(Q54="3896",Q54="3557"),1,0) | AS54: =V54*W54 | AT54: =V$4*(V54-V$3) | AU54: =W$4*(W54-W$3) | AV54: =X$4*(X54-X$3) | AW54: =Y$4*(Y54-Y$3) | AX54: =Z$4*(Z54-Z$3) | AY54: =AA$4*(AA54-AA$3) | AZ54: =AB$4*(AB54-AB$3) | BA54: =AC$4*(AC54-AC$3) | ... BQ54: =AS$4*(AS54-AS$3) | BR54: =SUM(AT54:BQ54) | BS54: =INTERCEPT_SCALED+BR54 | BT54: =1/(1+EXP(-BS54)) | BU54: =1-(1-BT54)^12 | BV54: =IFERROR(AT54/BR54*(BU54-BASELINE_CPR),0) | BW54: =IFERROR(AU54/BR54*(BU54-BASELINE_CPR),0) | BX54: =IFERROR(AV54/BR54*(BU54-BASELINE_CPR),0) | BY54: =IFERROR(AW54/BR54*(BU54-BASELINE_CPR),0) | BZ54: =IFERROR(AX54/BR54*(BU54-BASELINE_CPR),0) | CA54: =IFERROR(AY54/BR54*(BU54-BASELINE_CPR),0) | CB54: =IFERROR(AZ54/BR54*(BU54-BASELINE_CPR),0) | CC54: =IFERROR(BA54/BR54*(BU54-BASELINE_CPR),0) | CD54: =IFERROR(BB54/BR54*(BU54-BASELINE_CPR),0) | CE54: =IFERROR(BC54/BR54*(BU54-BASELINE_CPR),0) | CF54: =IFERROR(BD54/BR54*(BU54-BASELINE_CPR),0) | CG54: =IFERROR(BE54/BR54*(BU54-BASELINE_CPR),0) | CH54: =IFERROR(BF54/BR54*(BU54-BASELINE_CPR),0) | CI54: =IFERROR(BG54/BR54*(BU54-BASELINE_CPR),0) | CJ54: =IFERROR(BH54/BR54*(BU54-BASELINE_CPR),0) | CK54: =IFERROR(BI54/BR54*(BU54-BASELINE_CPR),0) | CL54: =IFERROR(BJ54/BR54*(BU54-BASELINE_CPR),0) | CM54: =IFERROR(BK54/BR54*(BU54-BASELINE_CPR),0) | CN54: =IFERROR(BL54/BR54*(BU54-BASELINE_CPR),0) | CO54: =IFERROR(BM54/BR54*(BU54-BASELINE_CPR),0) | CP54: =IFERROR(BN54/BR54*(BU54-BASELINE_CPR),0) | CQ54: =IFERROR(BO54/BR54*(BU54-BASELINE_CPR),0) | CR54: =IFERROR(BP54/BR54*(BU54-BASELINE_CPR),0) | CS54: =IFERROR(BQ54/BR54*(BU54-BASELINE_CPR),0) | CT54: =BASELINE_CPR+SUM(BV54:CS54)-BU54
... A65: 3617W0B92_000000003111141 | B65: BERKADIA_POST21 | C65: 3617W0B92 | D65: BERKADIA COMMERCIAL MORTGAGE, LLC | E65: 223f | F65: RP | G65: 2021 | H65: 202602 | I65: 23902483 | J65: 2.58 | K65: 447 | L65: 7 | M65: 58 | N65: 6 | O65: 205610 | Q65: 4082 | R65: 0 | S65: 0 | T65: 0 | U65: 0 | V65: =J65*100-K65 | W65: =L65 | X65: =MIN(M65,36) | Y65: =MIN(MAX(M65-36,0),84) | Z65: =MAX(M65-120,0) | AA65: =IF(OR(O65="",NOT(ISNUMBER(O65))),360,MAX(0,MIN(480,(INT(O65/100)-INT(VALUE(H65)/100))*12+MOD(O65,100)-MOD(VALUE(H65),100)))) | AB65: =IF(AND(AA65>0,AA65<=24),1,0) | AC65: =IF(OR(P65="",NOT(ISNUMBER(P65))),0,MAX(0,MIN(24,(INT(VALUE(H65)/100)-INT(P65/100))*12+MOD(VALUE(H65),100)-MOD(P65,100)))) | AD65: =LN(1+I65) | AE65: =IF(I65<2000000,1,0) | AF65: =IF(I65>50000000,1,0) | AG65: =IF(ISNUMBER(M65),N65/MAX(M65,1),0) | AH65: =IF(G65>=2021,1,0) | AI65: =S65 | AJ65: =T65 | AK65: =R65 | AL65: =U65 | AM65: =IF(ISNUMBER(SEARCH("CAPITAL FUNDING",D65)),1,0) | AN65: =IF(ISNUMBER(SEARCH("PNC",D65)),1,0) | AO65: =IF(ISNUMBER(SEARCH("WELLS FARGO",D65)),1,0) | AP65: =IF(ISNUMBER(SEARCH("DWIGHT",D65)),1,0) | AQ65: =IF(ISNUMBER(SEARCH("GREYSTONE",D65)),1,0) | AR65: =IF(OR(Q65="3896",Q65="3557"),1,0) | AS65: =V65*W65 | AT65: =V$4*(V65-V$3) | AU65: =W$4*(W65-W$3) | AV65: =X$4*(X65-X$3) | AW65: =Y$4*(Y65-Y$3) | AX65: =Z$4*(Z65-Z$3) | AY65: =AA$4*(AA65-AA$3) | AZ65: =AB$4*(AB65-AB$3) | BA65: =AC$4*(AC65-AC$3) | ... BQ65: =AS$4*(AS65-AS$3) | BR65: =SUM(AT65:BQ65) | BS65: =INTERCEPT_SCALED+BR65 | BT65: =1/(1+EXP(-BS65)) | BU65: =1-(1-BT65)^12 | BV65: =IFERROR(AT65/BR65*(BU65-BASELINE_CPR),0) | BW65: =IFERROR(AU65/BR65*(BU65-BASELINE_CPR),0) | BX65: =IFERROR(AV65/BR65*(BU65-BASELINE_CPR),0) | BY65: =IFERROR(AW65/BR65*(BU65-BASELINE_CPR),0) | BZ65: =IFERROR(AX65/BR65*(BU65-BASELINE_CPR),0) | CA65: =IFERROR(AY65/BR65*(BU65-BASELINE_CPR),0) | CB65: =IFERROR(AZ65/BR65*(BU65-BASELINE_CPR),0) | CC65: =IFERROR(BA65/BR65*(BU65-BASELINE_CPR),0) | CD65: =IFERROR(BB65/BR65*(BU65-BASELINE_CPR),0) | CE65: =IFERROR(BC65/BR65*(BU65-BASELINE_CPR),0) | CF65: =IFERROR(BD65/BR65*(BU65-BASELINE_CPR),0) | CG65: =IFERROR(BE65/BR65*(BU65-BASELINE_CPR),0) | CH65: =IFERROR(BF65/BR65*(BU65-BASELINE_CPR),0) | CI65: =IFERROR(BG65/BR65*(BU65-BASELINE_CPR),0) | CJ65: =IFERROR(BH65/BR65*(BU65-BASELINE_CPR),0) | CK65: =IFERROR(BI65/BR65*(BU65-BASELINE_CPR),0) | CL65: =IFERROR(BJ65/BR65*(BU65-BASELINE_CPR),0) | CM65: =IFERROR(BK65/BR65*(BU65-BASELINE_CPR),0) | CN65: =IFERROR(BL65/BR65*(BU65-BASELINE_CPR),0) | CO65: =IFERROR(BM65/BR65*(BU65-BASELINE_CPR),0) | CP65: =IFERROR(BN65/BR65*(BU65-BASELINE_CPR),0) | CQ65: =IFERROR(BO65/BR65*(BU65-BASELINE_CPR),0) | CR65: =IFERROR(BP65/BR65*(BU65-BASELINE_CPR),0) | CS65: =IFERROR(BQ65/BR65*(BU65-BASELINE_CPR),0) | CT65: =BASELINE_CPR+SUM(BV65:CS65)-BU65
A66: 36296MNL8_000000001410045 | B66: BERKADIA_PRE21 | C66: 36296MNL8 | D66: BERKADIA COMMERCIAL MORTGAGE, LLC | E66: 241 | F66: NC | G66: 2009 | H66: 202602 | I66: 662700.64 | J66: 6.2 | K66: 447 | L66: 0 | M66: 197 | N66: 86 | O66: 203811 | P66: 201205 | Q66: 4082 | R66: 0 | S66: 0 | T66: 0 | U66: 1 | V66: =J66*100-K66 | W66: =L66 | X66: =MIN(M66,36) | Y66: =MIN(MAX(M66-36,0),84) | Z66: =MAX(M66-120,0) | AA66: =IF(OR(O66="",NOT(ISNUMBER(O66))),360,MAX(0,MIN(480,(INT(O66/100)-INT(VALUE(H66)/100))*12+MOD(O66,100)-MOD(VALUE(H66),100)))) | AB66: =IF(AND(AA66>0,AA66<=24),1,0) | AC66: =IF(OR(P66="",NOT(ISNUMBER(P66))),0,MAX(0,MIN(24,(INT(VALUE(H66)/100)-INT(P66/100))*12+MOD(VALUE(H66),100)-MOD(P66,100)))) | AD66: =LN(1+I66) | AE66: =IF(I66<2000000,1,0) | AF66: =IF(I66>50000000,1,0) | AG66: =IF(ISNUMBER(M66),N66/MAX(M66,1),0) | AH66: =IF(G66>=2021,1,0) | AI66: =S66 | AJ66: =T66 | AK66: =R66 | AL66: =U66 | AM66: =IF(ISNUMBER(SEARCH("CAPITAL FUNDING",D66)),1,0) | AN66: =IF(ISNUMBER(SEARCH("PNC",D66)),1,0) | AO66: =IF(ISNUMBER(SEARCH("WELLS FARGO",D66)),1,0) | AP66: =IF(ISNUMBER(SEARCH("DWIGHT",D66)),1,0) | AQ66: =IF(ISNUMBER(SEARCH("GREYSTONE",D66)),1,0) | AR66: =IF(OR(Q66="3896",Q66="3557"),1,0) | AS66: =V66*W66 | AT66: =V$4*(V66-V$3) | AU66: =W$4*(W66-W$3) | AV66: =X$4*(X66-X$3) | AW66: =Y$4*(Y66-Y$3) | AX66: =Z$4*(Z66-Z$3) | AY66: =AA$4*(AA66-AA$3) | AZ66: =AB$4*(AB66-AB$3) | BA66: =AC$4*(AC66-AC$3) | ... BQ66: =AS$4*(AS66-AS$3) | BR66: =SUM(AT66:BQ66) | BS66: =INTERCEPT_SCALED+BR66 | BT66: =1/(1+EXP(-BS66)) | BU66: =1-(1-BT66)^12 | BV66: =IFERROR(AT66/BR66*(BU66-BASELINE_CPR),0) | BW66: =IFERROR(AU66/BR66*(BU66-BASELINE_CPR),0) | BX66: =IFERROR(AV66/BR66*(BU66-BASELINE_CPR),0) | BY66: =IFERROR(AW66/BR66*(BU66-BASELINE_CPR),0) | BZ66: =IFERROR(AX66/BR66*(BU66-BASELINE_CPR),0) | CA66: =IFERROR(AY66/BR66*(BU66-BASELINE_CPR),0) | CB66: =IFERROR(AZ66/BR66*(BU66-BASELINE_CPR),0) | CC66: =IFERROR(BA66/BR66*(BU66-BASELINE_CPR),0) | CD66: =IFERROR(BB66/BR66*(BU66-BASELINE_CPR),0) | CE66: =IFERROR(BC66/BR66*(BU66-BASELINE_CPR),0) | CF66: =IFERROR(BD66/BR66*(BU66-BASELINE_CPR),0) | CG66: =IFERROR(BE66/BR66*(BU66-BASELINE_CPR),0) | CH66: =IFERROR(BF66/BR66*(BU66-BASELINE_CPR),0) | CI66: =IFERROR(BG66/BR66*(BU66-BASELINE_CPR),0) | CJ66: =IFERROR(BH66/BR66*(BU66-BASELINE_CPR),0) | CK66: =IFERROR(BI66/BR66*(BU66-BASELINE_CPR),0) | CL66: =IFERROR(BJ66/BR66*(BU66-BASELINE_CPR),0) | CM66: =IFERROR(BK66/BR66*(BU66-BASELINE_CPR),0) | CN66: =IFERROR(BL66/BR66*(BU66-BASELINE_CPR),0) | CO66: =IFERROR(BM66/BR66*(BU66-BASELINE_CPR),0) | CP66: =IFERROR(BN66/BR66*(BU66-BASELINE_CPR),0) | CQ66: =IFERROR(BO66/BR66*(BU66-BASELINE_CPR),0) | CR66: =IFERROR(BP66/BR66*(BU66-BASELINE_CPR),0) | CS66: =IFERROR(BQ66/BR66*(BU66-BASELINE_CPR),0) | CT66: =BASELINE_CPR+SUM(BV66:CS66)-BU66
A67: 3618A9ZB4_000000009335146 | B67: BERKADIA_POST21 | C67: 3618A9ZB4 | D67: BERKADIA COMMERCIAL MORTGAGE, LLC | E67: 221d4 | F67: NC | G67: 2022 | H67: 202602 | I67: 9907257.3 | J67: 4.6 | K67: 447 | L67: 10 | M67: 41 | N67: 0 | O67: 206404 | Q67: 4082 | R67: 0 | S67: 0 | T67: 0 | U67: 1 | V67: =J67*100-K67 | W67: =L67 | X67: =MIN(M67,36) | Y67: =MIN(MAX(M67-36,0),84) | Z67: =MAX(M67-120,0) | AA67: =IF(OR(O67="",NOT(ISNUMBER(O67))),360,MAX(0,MIN(480,(INT(O67/100)-INT(VALUE(H67)/100))*12+MOD(O67,100)-MOD(VALUE(H67),100)))) | AB67: =IF(AND(AA67>0,AA67<=24),1,0) | AC67: =IF(OR(P67="",NOT(ISNUMBER(P67))),0,MAX(0,MIN(24,(INT(VALUE(H67)/100)-INT(P67/100))*12+MOD(VALUE(H67),100)-MOD(P67,100)))) | AD67: =LN(1+I67) | AE67: =IF(I67<2000000,1,0) | AF67: =IF(I67>50000000,1,0) | AG67: =IF(ISNUMBER(M67),N67/MAX(M67,1),0) | AH67: =IF(G67>=2021,1,0) | AI67: =S67 | AJ67: =T67 | AK67: =R67 | AL67: =U67 | AM67: =IF(ISNUMBER(SEARCH("CAPITAL FUNDING",D67)),1,0) | AN67: =IF(ISNUMBER(SEARCH("PNC",D67)),1,0) | AO67: =IF(ISNUMBER(SEARCH("WELLS FARGO",D67)),1,0) | AP67: =IF(ISNUMBER(SEARCH("DWIGHT",D67)),1,0) | AQ67: =IF(ISNUMBER(SEARCH("GREYSTONE",D67)),1,0) | AR67: =IF(OR(Q67="3896",Q67="3557"),1,0) | AS67: =V67*W67 | AT67: =V$4*(V67-V$3) | AU67: =W$4*(W67-W$3) | AV67: =X$4*(X67-X$3) | AW67: =Y$4*(Y67-Y$3) | AX67: =Z$4*(Z67-Z$3) | AY67: =AA$4*(AA67-AA$3) | AZ67: =AB$4*(AB67-AB$3) | BA67: =AC$4*(AC67-AC$3) | ... BQ67: =AS$4*(AS67-AS$3) | BR67: =SUM(AT67:BQ67) | BS67: =INTERCEPT_SCALED+BR67 | BT67: =1/(1+EXP(-BS67)) | BU67: =1-(1-BT67)^12 | BV67: =IFERROR(AT67/BR67*(BU67-BASELINE_CPR),0) | BW67: =IFERROR(AU67/BR67*(BU67-BASELINE_CPR),0) | BX67: =IFERROR(AV67/BR67*(BU67-BASELINE_CPR),0) | BY67: =IFERROR(AW67/BR67*(BU67-BASELINE_CPR),0) | BZ67: =IFERROR(AX67/BR67*(BU67-BASELINE_CPR),0) | CA67: =IFERROR(AY67/BR67*(BU67-BASELINE_CPR),0) | CB67: =IFERROR(AZ67/BR67*(BU67-BASELINE_CPR),0) | CC67: =IFERROR(BA67/BR67*(BU67-BASELINE_CPR),0) | CD67: =IFERROR(BB67/BR67*(BU67-BASELINE_CPR),0) | CE67: =IFERROR(BC67/BR67*(BU67-BASELINE_CPR),0) | CF67: =IFERROR(BD67/BR67*(BU67-BASELINE_CPR),0) | CG67: =IFERROR(BE67/BR67*(BU67-BASELINE_CPR),0) | CH67: =IFERROR(BF67/BR67*(BU67-BASELINE_CPR),0) | CI67: =IFERROR(BG67/BR67*(BU67-BASELINE_CPR),0) | CJ67: =IFERROR(BH67/BR67*(BU67-BASELINE_CPR),0) | CK67: =IFERROR(BI67/BR67*(BU67-BASELINE_CPR),0) | CL67: =IFERROR(BJ67/BR67*(BU67-BASELINE_CPR),0) | CM67: =IFERROR(BK67/BR67*(BU67-BASELINE_CPR),0) | CN67: =IFERROR(BL67/BR67*(BU67-BASELINE_CPR),0) | CO67: =IFERROR(BM67/BR67*(BU67-BASELINE_CPR),0) | CP67: =IFERROR(BN67/BR67*(BU67-BASELINE_CPR),0) | CQ67: =IFERROR(BO67/BR67*(BU67-BASELINE_CPR),0) | CR67: =IFERROR(BP67/BR67*(BU67-BASELINE_CPR),0) | CS67: =IFERROR(BQ67/BR67*(BU67-BASELINE_CPR),0) | CT67: =BASELINE_CPR+SUM(BV67:CS67)-BU67
A68: 36178VAE1_000000005111250 | B68: BERKADIA_PRE21 | C68: 36178VAE1 | D68: BERKADIA COMMERCIAL MORTGAGE, LLC | E68: 223a7 | F68: RP | G68: 2012 | H68: 202602 | I68: 17841211 | J68: 3.05 | K68: 447 | L68: 0 | M68: 160 | N68: 26 | O68: 204801 | P68: 201402 | Q68: 4082 | R68: 0 | S68: 1 | T68: 0 | U68: 0 | V68: =J68*100-K68 | W68: =L68 | X68: =MIN(M68,36) | Y68: =MIN(MAX(M68-36,0),84) | Z68: =MAX(M68-120,0) | AA68: =IF(OR(O68="",NOT(ISNUMBER(O68))),360,MAX(0,MIN(480,(INT(O68/100)-INT(VALUE(H68)/100))*12+MOD(O68,100)-MOD(VALUE(H68),100)))) | AB68: =IF(AND(AA68>0,AA68<=24),1,0) | AC68: =IF(OR(P68="",NOT(ISNUMBER(P68))),0,MAX(0,MIN(24,(INT(VALUE(H68)/100)-INT(P68/100))*12+MOD(VALUE(H68),100)-MOD(P68,100)))) | AD68: =LN(1+I68) | AE68: =IF(I68<2000000,1,0) | AF68: =IF(I68>50000000,1,0) | AG68: =IF(ISNUMBER(M68),N68/MAX(M68,1),0) | AH68: =IF(G68>=2021,1,0) | AI68: =S68 | AJ68: =T68 | AK68: =R68 | AL68: =U68 | AM68: =IF(ISNUMBER(SEARCH("CAPITAL FUNDING",D68)),1,0) | AN68: =IF(ISNUMBER(SEARCH("PNC",D68)),1,0) | AO68: =IF(ISNUMBER(SEARCH("WELLS FARGO",D68)),1,0) | AP68: =IF(ISNUMBER(SEARCH("DWIGHT",D68)),1,0) | AQ68: =IF(ISNUMBER(SEARCH("GREYSTONE",D68)),1,0) | AR68: =IF(OR(Q68="3896",Q68="3557"),1,0) | AS68: =V68*W68 | AT68: =V$4*(V68-V$3) | AU68: =W$4*(W68-W$3) | AV68: =X$4*(X68-X$3) | AW68: =Y$4*(Y68-Y$3) | AX68: =Z$4*(Z68-Z$3) | AY68: =AA$4*(AA68-AA$3) | AZ68: =AB$4*(AB68-AB$3) | BA68: =AC$4*(AC68-AC$3) | ... BQ68: =AS$4*(AS68-AS$3) | BR68: =SUM(AT68:BQ68) | BS68: =INTERCEPT_SCALED+BR68 | BT68: =1/(1+EXP(-BS68)) | BU68: =1-(1-BT68)^12 | BV68: =IFERROR(AT68/BR68*(BU68-BASELINE_CPR),0) | BW68: =IFERROR(AU68/BR68*(BU68-BASELINE_CPR),0) | BX68: =IFERROR(AV68/BR68*(BU68-BASELINE_CPR),0) | BY68: =IFERROR(AW68/BR68*(BU68-BASELINE_CPR),0) | BZ68: =IFERROR(AX68/BR68*(BU68-BASELINE_CPR),0) | CA68: =IFERROR(AY68/BR68*(BU68-BASELINE_CPR),0) | CB68: =IFERROR(AZ68/BR68*(BU68-BASELINE_CPR),0) | CC68: =IFERROR(BA68/BR68*(BU68-BASELINE_CPR),0) | CD68: =IFERROR(BB68/BR68*(BU68-BASELINE_CPR),0) | CE68: =IFERROR(BC68/BR68*(BU68-BASELINE_CPR),0) | CF68: =IFERROR(BD68/BR68*(BU68-BASELINE_CPR),0) | CG68: =IFERROR(BE68/BR68*(BU68-BASELINE_CPR),0) | CH68: =IFERROR(BF68/BR68*(BU68-BASELINE_CPR),0) | CI68: =IFERROR(BG68/BR68*(BU68-BASELINE_CPR),0) | CJ68: =IFERROR(BH68/BR68*(BU68-BASELINE_CPR),0) | CK68: =IFERROR(BI68/BR68*(BU68-BASELINE_CPR),0) | CL68: =IFERROR(BJ68/BR68*(BU68-BASELINE_CPR),0) | CM68: =IFERROR(BK68/BR68*(BU68-BASELINE_CPR),0) | CN68: =IFERROR(BL68/BR68*(BU68-BASELINE_CPR),0) | CO68: =IFERROR(BM68/BR68*(BU68-BASELINE_CPR),0) | CP68: =IFERROR(BN68/BR68*(BU68-BASELINE_CPR),0) | CQ68: =IFERROR(BO68/BR68*(BU68-BASELINE_CPR),0) | CR68: =IFERROR(BP68/BR68*(BU68-BASELINE_CPR),0) | CS68: =IFERROR(BQ68/BR68*(BU68-BASELINE_CPR),0) | CT68: =BASELINE_CPR+SUM(BV68:CS68)-BU68
A69: 3617M16P1_000000011422098 | B69: BERKADIA_PRE21 | C69: 3617M16P1 | D69: BERKADIA COMMERCIAL MORTGAGE, LLC | E69: 232 | F69: RP | G69: 2020 | H69: 202602 | I69: 6103063.3 | J69: 2.63 | K69: 447 | L69: 6 | M69: 71 | N69: 13 | O69: 205506 | Q69: 4082 | R69: 1 | S69: 0 | T69: 0 | U69: 0 | V69: =J69*100-K69 | W69: =L69 | X69: =MIN(M69,36) | Y69: =MIN(MAX(M69-36,0),84) | Z69: =MAX(M69-120,0) | AA69: =IF(OR(O69="",NOT(ISNUMBER(O69))),360,MAX(0,MIN(480,(INT(O69/100)-INT(VALUE(H69)/100))*12+MOD(O69,100)-MOD(VALUE(H69),100)))) | AB69: =IF(AND(AA69>0,AA69<=24),1,0) | AC69: =IF(OR(P69="",NOT(ISNUMBER(P69))),0,MAX(0,MIN(24,(INT(VALUE(H69)/100)-INT(P69/100))*12+MOD(VALUE(H69),100)-MOD(P69,100)))) | AD69: =LN(1+I69) | AE69: =IF(I69<2000000,1,0) | AF69: =IF(I69>50000000,1,0) | AG69: =IF(ISNUMBER(M69),N69/MAX(M69,1),0) | AH69: =IF(G69>=2021,1,0) | AI69: =S69 | AJ69: =T69 | AK69: =R69 | AL69: =U69 | AM69: =IF(ISNUMBER(SEARCH("CAPITAL FUNDING",D69)),1,0) | AN69: =IF(ISNUMBER(SEARCH("PNC",D69)),1,0) | AO69: =IF(ISNUMBER(SEARCH("WELLS FARGO",D69)),1,0) | AP69: =IF(ISNUMBER(SEARCH("DWIGHT",D69)),1,0) | AQ69: =IF(ISNUMBER(SEARCH("GREYSTONE",D69)),1,0) | AR69: =IF(OR(Q69="3896",Q69="3557"),1,0) | AS69: =V69*W69 | AT69: =V$4*(V69-V$3) | AU69: =W$4*(W69-W$3) | AV69: =X$4*(X69-X$3) | AW69: =Y$4*(Y69-Y$3) | AX69: =Z$4*(Z69-Z$3) | AY69: =AA$4*(AA69-AA$3) | AZ69: =AB$4*(AB69-AB$3) | BA69: =AC$4*(AC69-AC$3) | ... BQ69: =AS$4*(AS69-AS$3) | BR69: =SUM(AT69:BQ69) | BS69: =INTERCEPT_SCALED+BR69 | BT69: =1/(1+EXP(-BS69)) | BU69: =1-(1-BT69)^12 | BV69: =IFERROR(AT69/BR69*(BU69-BASELINE_CPR),0) | BW69: =IFERROR(AU69/BR69*(BU69-BASELINE_CPR),0) | BX69: =IFERROR(AV69/BR69*(BU69-BASELINE_CPR),0) | BY69: =IFERROR(AW69/BR69*(BU69-BASELINE_CPR),0) | BZ69: =IFERROR(AX69/BR69*(BU69-BASELINE_CPR),0) | CA69: =IFERROR(AY69/BR69*(BU69-BASELINE_CPR),0) | CB69: =IFERROR(AZ69/BR69*(BU69-BASELINE_CPR),0) | CC69: =IFERROR(BA69/BR69*(BU69-BASELINE_CPR),0) | CD69: =IFERROR(BB69/BR69*(BU69-BASELINE_CPR),0) | CE69: =IFERROR(BC69/BR69*(BU69-BASELINE_CPR),0) | CF69: =IFERROR(BD69/BR69*(BU69-BASELINE_CPR),0) | CG69: =IFERROR(BE69/BR69*(BU69-BASELINE_CPR),0) | CH69: =IFERROR(BF69/BR69*(BU69-BASELINE_CPR),0) | CI69: =IFERROR(BG69/BR69*(BU69-BASELINE_CPR),0) | CJ69: =IFERROR(BH69/BR69*(BU69-BASELINE_CPR),0) | CK69: =IFERROR(BI69/BR69*(BU69-BASELINE_CPR),0) | CL69: =IFERROR(BJ69/BR69*(BU69-BASELINE_CPR),0) | CM69: =IFERROR(BK69/BR69*(BU69-BASELINE_CPR),0) | CN69: =IFERROR(BL69/BR69*(BU69-BASELINE_CPR),0) | CO69: =IFERROR(BM69/BR69*(BU69-BASELINE_CPR),0) | CP69: =IFERROR(BN69/BR69*(BU69-BASELINE_CPR),0) | CQ69: =IFERROR(BO69/BR69*(BU69-BASELINE_CPR),0) | CR69: =IFERROR(BP69/BR69*(BU69-BASELINE_CPR),0) | CS69: =IFERROR(BQ69/BR69*(BU69-BASELINE_CPR),0) | CT69: =BASELINE_CPR+SUM(BV69:CS69)-BU69
A70: 36194RP61_000000007111200 | B70: WALKER_PRE21 | C70: 36194RP61 | D70: WALKER & DUNLOP, LLC | E70: 223f | F70: RP | G70: 2010 | H70: 202602 | I70: 3987517.4 | J70: 3.65 | K70: 447 | L70: 1 | M70: 188 | N70: 29 | O70: 204507 | Q70: 4080 | R70: 0 | S70: 0 | T70: 0 | U70: 0 | V70: =J70*100-K70 | W70: =L70 | X70: =MIN(M70,36) | Y70: =MIN(MAX(M70-36,0),84) | Z70: =MAX(M70-120,0) | AA70: =IF(OR(O70="",NOT(ISNUMBER(O70))),360,MAX(0,MIN(480,(INT(O70/100)-INT(VALUE(H70)/100))*12+MOD(O70,100)-MOD(VALUE(H70),100)))) | AB70: =IF(AND(AA70>0,AA70<=24),1,0) | AC70: =IF(OR(P70="",NOT(ISNUMBER(P70))),0,MAX(0,MIN(24,(INT(VALUE(H70)/100)-INT(P70/100))*12+MOD(VALUE(H70),100)-MOD(P70,100)))) | AD70: =LN(1+I70) | AE70: =IF(I70<2000000,1,0) | AF70: =IF(I70>50000000,1,0) | AG70: =IF(ISNUMBER(M70),N70/MAX(M70,1),0) | AH70: =IF(G70>=2021,1,0) | AI70: =S70 | AJ70: =T70 | AK70: =R70 | AL70: =U70 | AM70: =IF(ISNUMBER(SEARCH("CAPITAL FUNDING",D70)),1,0) | AN70: =IF(ISNUMBER(SEARCH("PNC",D70)),1,0) | AO70: =IF(ISNUMBER(SEARCH("WELLS FARGO",D70)),1,0) | AP70: =IF(ISNUMBER(SEARCH("DWIGHT",D70)),1,0) | AQ70: =IF(ISNUMBER(SEARCH("GREYSTONE",D70)),1,0) | AR70: =IF(OR(Q70="3896",Q70="3557"),1,0) | AS70: =V70*W70 | AT70: =V$4*(V70-V$3) | AU70: =W$4*(W70-W$3) | AV70: =X$4*(X70-X$3) | AW70: =Y$4*(Y70-Y$3) | AX70: =Z$4*(Z70-Z$3) | AY70: =AA$4*(AA70-AA$3) | AZ70: =AB$4*(AB70-AB$3) | BA70: =AC$4*(AC70-AC$3) | ... BQ70: =AS$4*(AS70-AS$3) | BR70: =SUM(AT70:BQ70) | BS70: =INTERCEPT_SCALED+BR70 | BT70: =1/(1+EXP(-BS70)) | BU70: =1-(1-BT70)^12 | BV70: =IFERROR(AT70/BR70*(BU70-BASELINE_CPR),0) | BW70: =IFERROR(AU70/BR70*(BU70-BASELINE_CPR),0) | BX70: =IFERROR(AV70/BR70*(BU70-BASELINE_CPR),0) | BY70: =IFERROR(AW70/BR70*(BU70-BASELINE_CPR),0) | BZ70: =IFERROR(AX70/BR70*(BU70-BASELINE_CPR),0) | CA70: =IFERROR(AY70/BR70*(BU70-BASELINE_CPR),0) | CB70: =IFERROR(AZ70/BR70*(BU70-BASELINE_CPR),0) | CC70: =IFERROR(BA70/BR70*(BU70-BASELINE_CPR),0) | CD70: =IFERROR(BB70/BR70*(BU70-BASELINE_CPR),0) | CE70: =IFERROR(BC70/BR70*(BU70-BASELINE_CPR),0) | CF70: =IFERROR(BD70/BR70*(BU70-BASELINE_CPR),0) | CG70: =IFERROR(BE70/BR70*(BU70-BASELINE_CPR),0) | CH70: =IFERROR(BF70/BR70*(BU70-BASELINE_CPR),0) | CI70: =IFERROR(BG70/BR70*(BU70-BASELINE_CPR),0) | CJ70: =IFERROR(BH70/BR70*(BU70-BASELINE_CPR),0) | CK70: =IFERROR(BI70/BR70*(BU70-BASELINE_CPR),0) | CL70: =IFERROR(BJ70/BR70*(BU70-BASELINE_CPR),0) | CM70: =IFERROR(BK70/BR70*(BU70-BASELINE_CPR),0) | CN70: =IFERROR(BL70/BR70*(BU70-BASELINE_CPR),0) | CO70: =IFERROR(BM70/BR70*(BU70-BASELINE_CPR),0) | CP70: =IFERROR(BN70/BR70*(BU70-BASELINE_CPR),0) | CQ70: =IFERROR(BO70/BR70*(BU70-BASELINE_CPR),0) | CR70: =IFERROR(BP70/BR70*(BU70-BASELINE_CPR),0) | CS70: =IFERROR(BQ70/BR70*(BU70-BASELINE_CPR),0) | CT70: =BASELINE_CPR+SUM(BV70:CS70)-BU70
A71: 3617X5EB2_000000011311435 | B71: WALKER_POST21 | C71: 3617X5EB2 | D71: WALKER & DUNLOP, LLC | E71: 223f | F71: RP | G71: 2021 | H71: 202602 | I71: 17646197 | J71: 2.33 | K71: 447 | L71: 6 | M71: 51 | N71: 0 | O71: 205612 | Q71: 4080 | R71: 0 | S71: 0 | T71: 0 | U71: 0 | V71: =J71*100-K71 | W71: =L71 | X71: =MIN(M71,36) | Y71: =MIN(MAX(M71-36,0),84) | Z71: =MAX(M71-120,0) | AA71: =IF(OR(O71="",NOT(ISNUMBER(O71))),360,MAX(0,MIN(480,(INT(O71/100)-INT(VALUE(H71)/100))*12+MOD(O71,100)-MOD(VALUE(H71),100)))) | AB71: =IF(AND(AA71>0,AA71<=24),1,0) | AC71: =IF(OR(P71="",NOT(ISNUMBER(P71))),0,MAX(0,MIN(24,(INT(VALUE(H71)/100)-INT(P71/100))*12+MOD(VALUE(H71),100)-MOD(P71,100)))) | AD71: =LN(1+I71) | AE71: =IF(I71<2000000,1,0) | AF71: =IF(I71>50000000,1,0) | AG71: =IF(ISNUMBER(M71),N71/MAX(M71,1),0) | AH71: =IF(G71>=2021,1,0) | AI71: =S71 | AJ71: =T71 | AK71: =R71 | AL71: =U71 | AM71: =IF(ISNUMBER(SEARCH("CAPITAL FUNDING",D71)),1,0) | AN71: =IF(ISNUMBER(SEARCH("PNC",D71)),1,0) | AO71: =IF(ISNUMBER(SEARCH("WELLS FARGO",D71)),1,0) | AP71: =IF(ISNUMBER(SEARCH("DWIGHT",D71)),1,0) | AQ71: =IF(ISNUMBER(SEARCH("GREYSTONE",D71)),1,0) | AR71: =IF(OR(Q71="3896",Q71="3557"),1,0) | AS71: =V71*W71 | AT71: =V$4*(V71-V$3) | AU71: =W$4*(W71-W$3) | AV71: =X$4*(X71-X$3) | AW71: =Y$4*(Y71-Y$3) | AX71: =Z$4*(Z71-Z$3) | AY71: =AA$4*(AA71-AA$3) | AZ71: =AB$4*(AB71-AB$3) | BA71: =AC$4*(AC71-AC$3) | ... BQ71: =AS$4*(AS71-AS$3) | BR71: =SUM(AT71:BQ71) | BS71: =INTERCEPT_SCALED+BR71 | BT71: =1/(1+EXP(-BS71)) | BU71: =1-(1-BT71)^12 | BV71: =IFERROR(AT71/BR71*(BU71-BASELINE_CPR),0) | BW71: =IFERROR(AU71/BR71*(BU71-BASELINE_CPR),0) | BX71: =IFERROR(AV71/BR71*(BU71-BASELINE_CPR),0) | BY71: =IFERROR(AW71/BR71*(BU71-BASELINE_CPR),0) | BZ71: =IFERROR(AX71/BR71*(BU71-BASELINE_CPR),0) | CA71: =IFERROR(AY71/BR71*(BU71-BASELINE_CPR),0) | CB71: =IFERROR(AZ71/BR71*(BU71-BASELINE_CPR),0) | CC71: =IFERROR(BA71/BR71*(BU71-BASELINE_CPR),0) | CD71: =IFERROR(BB71/BR71*(BU71-BASELINE_CPR),0) | CE71: =IFERROR(BC71/BR71*(BU71-BASELINE_CPR),0) | CF71: =IFERROR(BD71/BR71*(BU71-BASELINE_CPR),0) | CG71: =IFERROR(BE71/BR71*(BU71-BASELINE_CPR),0) | CH71: =IFERROR(BF71/BR71*(BU71-BASELINE_CPR),0) | CI71: =IFERROR(BG71/BR71*(BU71-BASELINE_CPR),0) | CJ71: =IFERROR(BH71/BR71*(BU71-BASELINE_CPR),0) | CK71: =IFERROR(BI71/BR71*(BU71-BASELINE_CPR),0) | CL71: =IFERROR(BJ71/BR71*(BU71-BASELINE_CPR),0) | CM71: =IFERROR(BK71/BR71*(BU71-BASELINE_CPR),0) | CN71: =IFERROR(BL71/BR71*(BU71-BASELINE_CPR),0) | CO71: =IFERROR(BM71/BR71*(BU71-BASELINE_CPR),0) | CP71: =IFERROR(BN71/BR71*(BU71-BASELINE_CPR),0) | CQ71: =IFERROR(BO71/BR71*(BU71-BASELINE_CPR),0) | CR71: =IFERROR(BP71/BR71*(BU71-BASELINE_CPR),0) | CS71: =IFERROR(BQ71/BR71*(BU71-BASELINE_CPR),0) | CT71: =BASELINE_CPR+SUM(BV71:CS71)-BU71
A72: 3617UQNP8_000000005111489 | B72: WALKER_POST21 | C72: 3617UQNP8 | D72: WALKER & DUNLOP, LLC | E72: 223a7 | F72: RP | G72: 2021 | H72: 202602 | I72: 5985368.1 | J72: 2.29 | K72: 447 | L72: 6 | M72: 60 | N72: 0 | O72: 205103 | Q72: 4080 | R72: 0 | S72: 1 | T72: 0 | U72: 0 | V72: =J72*100-K72 | W72: =L72 | X72: =MIN(M72,36) | Y72: =MIN(MAX(M72-36,0),84) | Z72: =MAX(M72-120,0) | AA72: =IF(OR(O72="",NOT(ISNUMBER(O72))),360,MAX(0,MIN(480,(INT(O72/100)-INT(VALUE(H72)/100))*12+MOD(O72,100)-MOD(VALUE(H72),100)))) | AB72: =IF(AND(AA72>0,AA72<=24),1,0) | AC72: =IF(OR(P72="",NOT(ISNUMBER(P72))),0,MAX(0,MIN(24,(INT(VALUE(H72)/100)-INT(P72/100))*12+MOD(VALUE(H72),100)-MOD(P72,100)))) | AD72: =LN(1+I72) | AE72: =IF(I72<2000000,1,0) | AF72: =IF(I72>50000000,1,0) | AG72: =IF(ISNUMBER(M72),N72/MAX(M72,1),0) | AH72: =IF(G72>=2021,1,0) | AI72: =S72 | AJ72: =T72 | AK72: =R72 | AL72: =U72 | AM72: =IF(ISNUMBER(SEARCH("CAPITAL FUNDING",D72)),1,0) | AN72: =IF(ISNUMBER(SEARCH("PNC",D72)),1,0) | AO72: =IF(ISNUMBER(SEARCH("WELLS FARGO",D72)),1,0) | AP72: =IF(ISNUMBER(SEARCH("DWIGHT",D72)),1,0) | AQ72: =IF(ISNUMBER(SEARCH("GREYSTONE",D72)),1,0) | AR72: =IF(OR(Q72="3896",Q72="3557"),1,0) | AS72: =V72*W72 | AT72: =V$4*(V72-V$3) | AU72: =W$4*(W72-W$3) | AV72: =X$4*(X72-X$3) | AW72: =Y$4*(Y72-Y$3) | AX72: =Z$4*(Z72-Z$3) | AY72: =AA$4*(AA72-AA$3) | AZ72: =AB$4*(AB72-AB$3) | BA72: =AC$4*(AC72-AC$3) | ... BQ72: =AS$4*(AS72-AS$3) | BR72: =SUM(AT72:BQ72) | BS72: =INTERCEPT_SCALED+BR72 | BT72: =1/(1+EXP(-BS72)) | BU72: =1-(1-BT72)^12 | BV72: =IFERROR(AT72/BR72*(BU72-BASELINE_CPR),0) | BW72: =IFERROR(AU72/BR72*(BU72-BASELINE_CPR),0) | BX72: =IFERROR(AV72/BR72*(BU72-BASELINE_CPR),0) | BY72: =IFERROR(AW72/BR72*(BU72-BASELINE_CPR),0) | BZ72: =IFERROR(AX72/BR72*(BU72-BASELINE_CPR),0) | CA72: =IFERROR(AY72/BR72*(BU72-BASELINE_CPR),0) | CB72: =IFERROR(AZ72/BR72*(BU72-BASELINE_CPR),0) | CC72: =IFERROR(BA72/BR72*(BU72-BASELINE_CPR),0) | CD72: =IFERROR(BB72/BR72*(BU72-BASELINE_CPR),0) | CE72: =IFERROR(BC72/BR72*(BU72-BASELINE_CPR),0) | CF72: =IFERROR(BD72/BR72*(BU72-BASELINE_CPR),0) | CG72: =IFERROR(BE72/BR72*(BU72-BASELINE_CPR),0) | CH72: =IFERROR(BF72/BR72*(BU72-BASELINE_CPR),0) | CI72: =IFERROR(BG72/BR72*(BU72-BASELINE_CPR),0) | CJ72: =IFERROR(BH72/BR72*(BU72-BASELINE_CPR),0) | CK72: =IFERROR(BI72/BR72*(BU72-BASELINE_CPR),0) | CL72: =IFERROR(BJ72/BR72*(BU72-BASELINE_CPR),0) | CM72: =IFERROR(BK72/BR72*(BU72-BASELINE_CPR),0) | CN72: =IFERROR(BL72/BR72*(BU72-BASELINE_CPR),0) | CO72: =IFERROR(BM72/BR72*(BU72-BASELINE_CPR),0) | CP72: =IFERROR(BN72/BR72*(BU72-BASELINE_CPR),0) | CQ72: =IFERROR(BO72/BR72*(BU72-BASELINE_CPR),0) | CR72: =IFERROR(BP72/BR72*(BU72-BASELINE_CPR),0) | CS72: =IFERROR(BQ72/BR72*(BU72-BASELINE_CPR),0) | CT72: =BASELINE_CPR+SUM(BV72:CS72)-BU72
A73: 3620ANPX2_000000004322064 | B73: WALKER_PRE21 | C73: 3620ANPX2 | D73: WALKER & DUNLOP, LLC | E73: 232 | F73: RP | G73: 2011 | H73: 202602 | I73: 4469240.9 | J73: 3.73 | K73: 447 | L73: 0 | M73: 172 | N73: 38 | O73: 204611 | P73: 201312 | Q73: 4080 | R73: 1 | S73: 0 | T73: 0 | U73: 0 | V73: =J73*100-K73 | W73: =L73 | X73: =MIN(M73,36) | Y73: =MIN(MAX(M73-36,0),84) | Z73: =MAX(M73-120,0) | AA73: =IF(OR(O73="",NOT(ISNUMBER(O73))),360,MAX(0,MIN(480,(INT(O73/100)-INT(VALUE(H73)/100))*12+MOD(O73,100)-MOD(VALUE(H73),100)))) | AB73: =IF(AND(AA73>0,AA73<=24),1,0) | AC73: =IF(OR(P73="",NOT(ISNUMBER(P73))),0,MAX(0,MIN(24,(INT(VALUE(H73)/100)-INT(P73/100))*12+MOD(VALUE(H73),100)-MOD(P73,100)))) | AD73: =LN(1+I73) | AE73: =IF(I73<2000000,1,0) | AF73: =IF(I73>50000000,1,0) | AG73: =IF(ISNUMBER(M73),N73/MAX(M73,1),0) | AH73: =IF(G73>=2021,1,0) | AI73: =S73 | AJ73: =T73 | AK73: =R73 | AL73: =U73 | AM73: =IF(ISNUMBER(SEARCH("CAPITAL FUNDING",D73)),1,0) | AN73: =IF(ISNUMBER(SEARCH("PNC",D73)),1,0) | AO73: =IF(ISNUMBER(SEARCH("WELLS FARGO",D73)),1,0) | AP73: =IF(ISNUMBER(SEARCH("DWIGHT",D73)),1,0) | AQ73: =IF(ISNUMBER(SEARCH("GREYSTONE",D73)),1,0) | AR73: =IF(OR(Q73="3896",Q73="3557"),1,0) | AS73: =V73*W73 | AT73: =V$4*(V73-V$3) | AU73: =W$4*(W73-W$3) | AV73: =X$4*(X73-X$3) | AW73: =Y$4*(Y73-Y$3) | AX73: =Z$4*(Z73-Z$3) | AY73: =AA$4*(AA73-AA$3) | AZ73: =AB$4*(AB73-AB$3) | BA73: =AC$4*(AC73-AC$3) | ... BQ73: =AS$4*(AS73-AS$3) | BR73: =SUM(AT73:BQ73) | BS73: =INTERCEPT_SCALED+BR73 | BT73: =1/(1+EXP(-BS73)) | BU73: =1-(1-BT73)^12 | BV73: =IFERROR(AT73/BR73*(BU73-BASELINE_CPR),0) | BW73: =IFERROR(AU73/BR73*(BU73-BASELINE_CPR),0) | BX73: =IFERROR(AV73/BR73*(BU73-BASELINE_CPR),0) | BY73: =IFERROR(AW73/BR73*(BU73-BASELINE_CPR),0) | BZ73: =IFERROR(AX73/BR73*(BU73-BASELINE_CPR),0) | CA73: =IFERROR(AY73/BR73*(BU73-BASELINE_CPR),0) | CB73: =IFERROR(AZ73/BR73*(BU73-BASELINE_CPR),0) | CC73: =IFERROR(BA73/BR73*(BU73-BASELINE_CPR),0) | CD73: =IFERROR(BB73/BR73*(BU73-BASELINE_CPR),0) | CE73: =IFERROR(BC73/BR73*(BU73-BASELINE_CPR),0) | CF73: =IFERROR(BD73/BR73*(BU73-BASELINE_CPR),0) | CG73: =IFERROR(BE73/BR73*(BU73-BASELINE_CPR),0) | CH73: =IFERROR(BF73/BR73*(BU73-BASELINE_CPR),0) | CI73: =IFERROR(BG73/BR73*(BU73-BASELINE_CPR),0) | CJ73: =IFERROR(BH73/BR73*(BU73-BASELINE_CPR),0) | CK73: =IFERROR(BI73/BR73*(BU73-BASELINE_CPR),0) | CL73: =IFERROR(BJ73/BR73*(BU73-BASELINE_CPR),0) | CM73: =IFERROR(BK73/BR73*(BU73-BASELINE_CPR),0) | CN73: =IFERROR(BL73/BR73*(BU73-BASELINE_CPR),0) | CO73: =IFERROR(BM73/BR73*(BU73-BASELINE_CPR),0) | CP73: =IFERROR(BN73/BR73*(BU73-BASELINE_CPR),0) | CQ73: =IFERROR(BO73/BR73*(BU73-BASELINE_CPR),0) | CR73: =IFERROR(BP73/BR73*(BU73-BASELINE_CPR),0) | CS73: =IFERROR(BQ73/BR73*(BU73-BASELINE_CPR),0) | CT73: =BASELINE_CPR+SUM(BV73:CS73)-BU73
A74: 36195LZX3_000000004722066 | B74: WALKER_PRE21 | C74: 36195LZX3 | D74: WALKER & DUNLOP, LLC | E74: 232 | F74: RP | G74: 2011 | H74: 202602 | I74: 1687095.6 | J74: 3.58 | K74: 447 | L74: 1 | M74: 176 | N74: 27 | O74: 204107 | Q74: 4080 | R74: 1 | S74: 0 | T74: 0 | U74: 0 | V74: =J74*100-K74 | W74: =L74 | X74: =MIN(M74,36) | Y74: =MIN(MAX(M74-36,0),84) | Z74: =MAX(M74-120,0) | AA74: =IF(OR(O74="",NOT(ISNUMBER(O74))),360,MAX(0,MIN(480,(INT(O74/100)-INT(VALUE(H74)/100))*12+MOD(O74,100)-MOD(VALUE(H74),100)))) | AB74: =IF(AND(AA74>0,AA74<=24),1,0) | AC74: =IF(OR(P74="",NOT(ISNUMBER(P74))),0,MAX(0,MIN(24,(INT(VALUE(H74)/100)-INT(P74/100))*12+MOD(VALUE(H74),100)-MOD(P74,100)))) | AD74: =LN(1+I74) | AE74: =IF(I74<2000000,1,0) | AF74: =IF(I74>50000000,1,0) | AG74: =IF(ISNUMBER(M74),N74/MAX(M74,1),0) | AH74: =IF(G74>=2021,1,0) | AI74: =S74 | AJ74: =T74 | AK74: =R74 | AL74: =U74 | AM74: =IF(ISNUMBER(SEARCH("CAPITAL FUNDING",D74)),1,0) | AN74: =IF(ISNUMBER(SEARCH("PNC",D74)),1,0) | AO74: =IF(ISNUMBER(SEARCH("WELLS FARGO",D74)),1,0) | AP74: =IF(ISNUMBER(SEARCH("DWIGHT",D74)),1,0) | AQ74: =IF(ISNUMBER(SEARCH("GREYSTONE",D74)),1,0) | AR74: =IF(OR(Q74="3896",Q74="3557"),1,0) | AS74: =V74*W74 | AT74: =V$4*(V74-V$3) | AU74: =W$4*(W74-W$3) | AV74: =X$4*(X74-X$3) | AW74: =Y$4*(Y74-Y$3) | AX74: =Z$4*(Z74-Z$3) | AY74: =AA$4*(AA74-AA$3) | AZ74: =AB$4*(AB74-AB$3) | BA74: =AC$4*(AC74-AC$3) | ... BQ74: =AS$4*(AS74-AS$3) | BR74: =SUM(AT74:BQ74) | BS74: =INTERCEPT_SCALED+BR74 | BT74: =1/(1+EXP(-BS74)) | BU74: =1-(1-BT74)^12 | BV74: =IFERROR(AT74/BR74*(BU74-BASELINE_CPR),0) | BW74: =IFERROR(AU74/BR74*(BU74-BASELINE_CPR),0) | BX74: =IFERROR(AV74/BR74*(BU74-BASELINE_CPR),0) | BY74: =IFERROR(AW74/BR74*(BU74-BASELINE_CPR),0) | BZ74: =IFERROR(AX74/BR74*(BU74-BASELINE_CPR),0) | CA74: =IFERROR(AY74/BR74*(BU74-BASELINE_CPR),0) | CB74: =IFERROR(AZ74/BR74*(BU74-BASELINE_CPR),0) | CC74: =IFERROR(BA74/BR74*(BU74-BASELINE_CPR),0) | CD74: =IFERROR(BB74/BR74*(BU74-BASELINE_CPR),0) | CE74: =IFERROR(BC74/BR74*(BU74-BASELINE_CPR),0) | CF74: =IFERROR(BD74/BR74*(BU74-BASELINE_CPR),0) | CG74: =IFERROR(BE74/BR74*(BU74-BASELINE_CPR),0) | CH74: =IFERROR(BF74/BR74*(BU74-BASELINE_CPR),0) | CI74: =IFERROR(BG74/BR74*(BU74-BASELINE_CPR),0) | CJ74: =IFERROR(BH74/BR74*(BU74-BASELINE_CPR),0) | CK74: =IFERROR(BI74/BR74*(BU74-BASELINE_CPR),0) | CL74: =IFERROR(BJ74/BR74*(BU74-BASELINE_CPR),0) | CM74: =IFERROR(BK74/BR74*(BU74-BASELINE_CPR),0) | CN74: =IFERROR(BL74/BR74*(BU74-BASELINE_CPR),0) | CO74: =IFERROR(BM74/BR74*(BU74-BASELINE_CPR),0) | CP74: =IFERROR(BN74/BR74*(BU74-BASELINE_CPR),0) | CQ74: =IFERROR(BO74/BR74*(BU74-BASELINE_CPR),0) | CR74: =IFERROR(BP74/BR74*(BU74-BASELINE_CPR),0) | CS74: =IFERROR(BQ74/BR74*(BU74-BASELINE_CPR),0) | CT74: =BASELINE_CPR+SUM(BV74:CS74)-BU74
A75: 3617NYVC9_000000002311566 | B75: WALKER_PRE21 | C75: 3617NYVC9 | D75: WALKER & DUNLOP, LLC | E75: 223f | F75: RP | G75: 2020 | H75: 202602 | I75: 13589484 | J75: 2.25 | K75: 447 | L75: 5 | M75: 65 | N75: 0 | O75: 205510 | Q75: 4080 | R75: 0 | S75: 0 | T75: 0 | U75: 0 | V75: =J75*100-K75 | W75: =L75 | X75: =MIN(M75,36) | Y75: =MIN(MAX(M75-36,0),84) | Z75: =MAX(M75-120,0) | AA75: =IF(OR(O75="",NOT(ISNUMBER(O75))),360,MAX(0,MIN(480,(INT(O75/100)-INT(VALUE(H75)/100))*12+MOD(O75,100)-MOD(VALUE(H75),100)))) | AB75: =IF(AND(AA75>0,AA75<=24),1,0) | AC75: =IF(OR(P75="",NOT(ISNUMBER(P75))),0,MAX(0,MIN(24,(INT(VALUE(H75)/100)-INT(P75/100))*12+MOD(VALUE(H75),100)-MOD(P75,100)))) | AD75: =LN(1+I75) | AE75: =IF(I75<2000000,1,0) | AF75: =IF(I75>50000000,1,0) | AG75: =IF(ISNUMBER(M75),N75/MAX(M75,1),0) | AH75: =IF(G75>=2021,1,0) | AI75: =S75 | AJ75: =T75 | AK75: =R75 | AL75: =U75 | AM75: =IF(ISNUMBER(SEARCH("CAPITAL FUNDING",D75)),1,0) | AN75: =IF(ISNUMBER(SEARCH("PNC",D75)),1,0) | AO75: =IF(ISNUMBER(SEARCH("WELLS FARGO",D75)),1,0) | AP75: =IF(ISNUMBER(SEARCH("DWIGHT",D75)),1,0) | AQ75: =IF(ISNUMBER(SEARCH("GREYSTONE",D75)),1,0) | AR75: =IF(OR(Q75="3896",Q75="3557"),1,0) | AS75: =V75*W75 | AT75: =V$4*(V75-V$3) | AU75: =W$4*(W75-W$3) | AV75: =X$4*(X75-X$3) | AW75: =Y$4*(Y75-Y$3) | AX75: =Z$4*(Z75-Z$3) | AY75: =AA$4*(AA75-AA$3) | AZ75: =AB$4*(AB75-AB$3) | BA75: =AC$4*(AC75-AC$3) | ... BQ75: =AS$4*(AS75-AS$3) | BR75: =SUM(AT75:BQ75) | BS75: =INTERCEPT_SCALED+BR75 | BT75: =1/(1+EXP(-BS75)) | BU75: =1-(1-BT75)^12 | BV75: =IFERROR(AT75/BR75*(BU75-BASELINE_CPR),0) | BW75: =IFERROR(AU75/BR75*(BU75-BASELINE_CPR),0) | BX75: =IFERROR(AV75/BR75*(BU75-BASELINE_CPR),0) | BY75: =IFERROR(AW75/BR75*(BU75-BASELINE_CPR),0) | BZ75: =IFERROR(AX75/BR75*(BU75-BASELINE_CPR),0) | CA75: =IFERROR(AY75/BR75*(BU75-BASELINE_CPR),0) | CB75: =IFERROR(AZ75/BR75*(BU75-BASELINE_CPR),0) | CC75: =IFERROR(BA75/BR75*(BU75-BASELINE_CPR),0) | CD75: =IFERROR(BB75/BR75*(BU75-BASELINE_CPR),0) | CE75: =IFERROR(BC75/BR75*(BU75-BASELINE_CPR),0) | CF75: =IFERROR(BD75/BR75*(BU75-BASELINE_CPR),0) | CG75: =IFERROR(BE75/BR75*(BU75-BASELINE_CPR),0) | CH75: =IFERROR(BF75/BR75*(BU75-BASELINE_CPR),0) | CI75: =IFERROR(BG75/BR75*(BU75-BASELINE_CPR),0) | CJ75: =IFERROR(BH75/BR75*(BU75-BASELINE_CPR),0) | CK75: =IFERROR(BI75/BR75*(BU75-BASELINE_CPR),0) | CL75: =IFERROR(BJ75/BR75*(BU75-BASELINE_CPR),0) | CM75: =IFERROR(BK75/BR75*(BU75-BASELINE_CPR),0) | CN75: =IFERROR(BL75/BR75*(BU75-BASELINE_CPR),0) | CO75: =IFERROR(BM75/BR75*(BU75-BASELINE_CPR),0) | CP75: =IFERROR(BN75/BR75*(BU75-BASELINE_CPR),0) | CQ75: =IFERROR(BO75/BR75*(BU75-BASELINE_CPR),0) | CR75: =IFERROR(BP75/BR75*(BU75-BASELINE_CPR),0) | CS75: =IFERROR(BQ75/BR75*(BU75-BASELINE_CPR),0) | CT75: =BASELINE_CPR+SUM(BV75:CS75)-BU75
A76: 3617N1EE6_000000004211125 | B76: WALKER_PRE21 | C76: 3617N1EE6 | D76: WALKER & DUNLOP, LLC | E76: 223f | F76: RP | G76: 2009 | H76: 202602 | I76: 2401815 | J76: 3.65 | K76: 447 | L76: 5 | M76: 203 | N76: 21 | O76: 204404 | Q76: 4080 | R76: 0 | S76: 0 | T76: 0 | U76: 0 | V76: =J76*100-K76 | W76: =L76 | X76: =MIN(M76,36) | Y76: =MIN(MAX(M76-36,0),84) | Z76: =MAX(M76-120,0) | AA76: =IF(OR(O76="",NOT(ISNUMBER(O76))),360,MAX(0,MIN(480,(INT(O76/100)-INT(VALUE(H76)/100))*12+MOD(O76,100)-MOD(VALUE(H76),100)))) | AB76: =IF(AND(AA76>0,AA76<=24),1,0) | AC76: =IF(OR(P76="",NOT(ISNUMBER(P76))),0,MAX(0,MIN(24,(INT(VALUE(H76)/100)-INT(P76/100))*12+MOD(VALUE(H76),100)-MOD(P76,100)))) | AD76: =LN(1+I76) | AE76: =IF(I76<2000000,1,0) | AF76: =IF(I76>50000000,1,0) | AG76: =IF(ISNUMBER(M76),N76/MAX(M76,1),0) | AH76: =IF(G76>=2021,1,0) | AI76: =S76 | AJ76: =T76 | AK76: =R76 | AL76: =U76 | AM76: =IF(ISNUMBER(SEARCH("CAPITAL FUNDING",D76)),1,0) | AN76: =IF(ISNUMBER(SEARCH("PNC",D76)),1,0) | AO76: =IF(ISNUMBER(SEARCH("WELLS FARGO",D76)),1,0) | AP76: =IF(ISNUMBER(SEARCH("DWIGHT",D76)),1,0) | AQ76: =IF(ISNUMBER(SEARCH("GREYSTONE",D76)),1,0) | AR76: =IF(OR(Q76="3896",Q76="3557"),1,0) | AS76: =V76*W76 | AT76: =V$4*(V76-V$3) | AU76: =W$4*(W76-W$3) | AV76: =X$4*(X76-X$3) | AW76: =Y$4*(Y76-Y$3) | AX76: =Z$4*(Z76-Z$3) | AY76: =AA$4*(AA76-AA$3) | AZ76: =AB$4*(AB76-AB$3) | BA76: =AC$4*(AC76-AC$3) | ... BQ76: =AS$4*(AS76-AS$3) | BR76: =SUM(AT76:BQ76) | BS76: =INTERCEPT_SCALED+BR76 | BT76: =1/(1+EXP(-BS76)) | BU76: =1-(1-BT76)^12 | BV76: =IFERROR(AT76/BR76*(BU76-BASELINE_CPR),0) | BW76: =IFERROR(AU76/BR76*(BU76-BASELINE_CPR),0) | BX76: =IFERROR(AV76/BR76*(BU76-BASELINE_CPR),0) | BY76: =IFERROR(AW76/BR76*(BU76-BASELINE_CPR),0) | BZ76: =IFERROR(AX76/BR76*(BU76-BASELINE_CPR),0) | CA76: =IFERROR(AY76/BR76*(BU76-BASELINE_CPR),0) | CB76: =IFERROR(AZ76/BR76*(BU76-BASELINE_CPR),0) | CC76: =IFERROR(BA76/BR76*(BU76-BASELINE_CPR),0) | CD76: =IFERROR(BB76/BR76*(BU76-BASELINE_CPR),0) | CE76: =IFERROR(BC76/BR76*(BU76-BASELINE_CPR),0) | CF76: =IFERROR(BD76/BR76*(BU76-BASELINE_CPR),0) | CG76: =IFERROR(BE76/BR76*(BU76-BASELINE_CPR),0) | CH76: =IFERROR(BF76/BR76*(BU76-BASELINE_CPR),0) | CI76: =IFERROR(BG76/BR76*(BU76-BASELINE_CPR),0) | CJ76: =IFERROR(BH76/BR76*(BU76-BASELINE_CPR),0) | CK76: =IFERROR(BI76/BR76*(BU76-BASELINE_CPR),0) | CL76: =IFERROR(BJ76/BR76*(BU76-BASELINE_CPR),0) | CM76: =IFERROR(BK76/BR76*(BU76-BASELINE_CPR),0) | CN76: =IFERROR(BL76/BR76*(BU76-BASELINE_CPR),0) | CO76: =IFERROR(BM76/BR76*(BU76-BASELINE_CPR),0) | CP76: =IFERROR(BN76/BR76*(BU76-BASELINE_CPR),0) | CQ76: =IFERROR(BO76/BR76*(BU76-BASELINE_CPR),0) | CR76: =IFERROR(BP76/BR76*(BU76-BASELINE_CPR),0) | CS76: =IFERROR(BQ76/BR76*(BU76-BASELINE_CPR),0) | CT76: =BASELINE_CPR+SUM(BV76:CS76)-BU76
A77: 3617UDKP0_000000007111196 | B77: WALKER_PRE21 | C77: 3617UDKP0 | D77: WALKER & DUNLOP, LLC | E77: 223f | F77: RP | G77: 2010 | H77: 202602 | I77: 3458376.6 | J77: 3.49 | K77: 447 | L77: 6 | M77: 190 | N77: 12 | O77: 204505 | Q77: 4080 | R77: 0 | S77: 0 | T77: 0 | U77: 0 | V77: =J77*100-K77 | W77: =L77 | X77: =MIN(M77,36) | Y77: =MIN(MAX(M77-36,0),84) | Z77: =MAX(M77-120,0) | AA77: =IF(OR(O77="",NOT(ISNUMBER(O77))),360,MAX(0,MIN(480,(INT(O77/100)-INT(VALUE(H77)/100))*12+MOD(O77,100)-MOD(VALUE(H77),100)))) | AB77: =IF(AND(AA77>0,AA77<=24),1,0) | AC77: =IF(OR(P77="",NOT(ISNUMBER(P77))),0,MAX(0,MIN(24,(INT(VALUE(H77)/100)-INT(P77/100))*12+MOD(VALUE(H77),100)-MOD(P77,100)))) | AD77: =LN(1+I77) | AE77: =IF(I77<2000000,1,0) | AF77: =IF(I77>50000000,1,0) | AG77: =IF(ISNUMBER(M77),N77/MAX(M77,1),0) | AH77: =IF(G77>=2021,1,0) | AI77: =S77 | AJ77: =T77 | AK77: =R77 | AL77: =U77 | AM77: =IF(ISNUMBER(SEARCH("CAPITAL FUNDING",D77)),1,0) | AN77: =IF(ISNUMBER(SEARCH("PNC",D77)),1,0) | AO77: =IF(ISNUMBER(SEARCH("WELLS FARGO",D77)),1,0) | AP77: =IF(ISNUMBER(SEARCH("DWIGHT",D77)),1,0) | AQ77: =IF(ISNUMBER(SEARCH("GREYSTONE",D77)),1,0) | AR77: =IF(OR(Q77="3896",Q77="3557"),1,0) | AS77: =V77*W77 | AT77: =V$4*(V77-V$3) | AU77: =W$4*(W77-W$3) | AV77: =X$4*(X77-X$3) | AW77: =Y$4*(Y77-Y$3) | AX77: =Z$4*(Z77-Z$3) | AY77: =AA$4*(AA77-AA$3) | AZ77: =AB$4*(AB77-AB$3) | BA77: =AC$4*(AC77-AC$3) | ... BQ77: =AS$4*(AS77-AS$3) | BR77: =SUM(AT77:BQ77) | BS77: =INTERCEPT_SCALED+BR77 | BT77: =1/(1+EXP(-BS77)) | BU77: =1-(1-BT77)^12 | BV77: =IFERROR(AT77/BR77*(BU77-BASELINE_CPR),0) | BW77: =IFERROR(AU77/BR77*(BU77-BASELINE_CPR),0) | BX77: =IFERROR(AV77/BR77*(BU77-BASELINE_CPR),0) | BY77: =IFERROR(AW77/BR77*(BU77-BASELINE_CPR),0) | BZ77: =IFERROR(AX77/BR77*(BU77-BASELINE_CPR),0) | CA77: =IFERROR(AY77/BR77*(BU77-BASELINE_CPR),0) | CB77: =IFERROR(AZ77/BR77*(BU77-BASELINE_CPR),0) | CC77: =IFERROR(BA77/BR77*(BU77-BASELINE_CPR),0) | CD77: =IFERROR(BB77/BR77*(BU77-BASELINE_CPR),0) | CE77: =IFERROR(BC77/BR77*(BU77-BASELINE_CPR),0) | CF77: =IFERROR(BD77/BR77*(BU77-BASELINE_CPR),0) | CG77: =IFERROR(BE77/BR77*(BU77-BASELINE_CPR),0) | CH77: =IFERROR(BF77/BR77*(BU77-BASELINE_CPR),0) | CI77: =IFERROR(BG77/BR77*(BU77-BASELINE_CPR),0) | CJ77: =IFERROR(BH77/BR77*(BU77-BASELINE_CPR),0) | CK77: =IFERROR(BI77/BR77*(BU77-BASELINE_CPR),0) | CL77: =IFERROR(BJ77/BR77*(BU77-BASELINE_CPR),0) | CM77: =IFERROR(BK77/BR77*(BU77-BASELINE_CPR),0) | CN77: =IFERROR(BL77/BR77*(BU77-BASELINE_CPR),0) | CO77: =IFERROR(BM77/BR77*(BU77-BASELINE_CPR),0) | CP77: =IFERROR(BN77/BR77*(BU77-BASELINE_CPR),0) | CQ77: =IFERROR(BO77/BR77*(BU77-BASELINE_CPR),0) | CR77: =IFERROR(BP77/BR77*(BU77-BASELINE_CPR),0) | CS77: =IFERROR(BQ77/BR77*(BU77-BASELINE_CPR),0) | CT77: =BASELINE_CPR+SUM(BV77:CS77)-BU77
A78: 36179ARA6_000000010222049 | B78: WALKER_PRE21 | C78: 36179ARA6 | D78: WALKER & DUNLOP, LLC | E78: 232 | F78: RP | G78: 2012 | H78: 202602 | I78: 9942041.3 | J78: 3.35 | K78: 447 | L78: 0 | M78: 158 | N78: 32 | O78: 204801 | P78: 201401 | Q78: 4080 | R78: 1 | S78: 0 | T78: 0 | U78: 0 | V78: =J78*100-K78 | W78: =L78 | X78: =MIN(M78,36) | Y78: =MIN(MAX(M78-36,0),84) | Z78: =MAX(M78-120,0) | AA78: =IF(OR(O78="",NOT(ISNUMBER(O78))),360,MAX(0,MIN(480,(INT(O78/100)-INT(VALUE(H78)/100))*12+MOD(O78,100)-MOD(VALUE(H78),100)))) | AB78: =IF(AND(AA78>0,AA78<=24),1,0) | AC78: =IF(OR(P78="",NOT(ISNUMBER(P78))),0,MAX(0,MIN(24,(INT(VALUE(H78)/100)-INT(P78/100))*12+MOD(VALUE(H78),100)-MOD(P78,100)))) | AD78: =LN(1+I78) | AE78: =IF(I78<2000000,1,0) | AF78: =IF(I78>50000000,1,0) | AG78: =IF(ISNUMBER(M78),N78/MAX(M78,1),0) | AH78: =IF(G78>=2021,1,0) | AI78: =S78 | AJ78: =T78 | AK78: =R78 | AL78: =U78 | AM78: =IF(ISNUMBER(SEARCH("CAPITAL FUNDING",D78)),1,0) | AN78: =IF(ISNUMBER(SEARCH("PNC",D78)),1,0) | AO78: =IF(ISNUMBER(SEARCH("WELLS FARGO",D78)),1,0) | AP78: =IF(ISNUMBER(SEARCH("DWIGHT",D78)),1,0) | AQ78: =IF(ISNUMBER(SEARCH("GREYSTONE",D78)),1,0) | AR78: =IF(OR(Q78="3896",Q78="3557"),1,0) | AS78: =V78*W78 | AT78: =V$4*(V78-V$3) | AU78: =W$4*(W78-W$3) | AV78: =X$4*(X78-X$3) | AW78: =Y$4*(Y78-Y$3) | AX78: =Z$4*(Z78-Z$3) | AY78: =AA$4*(AA78-AA$3) | AZ78: =AB$4*(AB78-AB$3) | BA78: =AC$4*(AC78-AC$3) | ... BQ78: =AS$4*(AS78-AS$3) | BR78: =SUM(AT78:BQ78) | BS78: =INTERCEPT_SCALED+BR78 | BT78: =1/(1+EXP(-BS78)) | BU78: =1-(1-BT78)^12 | BV78: =IFERROR(AT78/BR78*(BU78-BASELINE_CPR),0) | BW78: =IFERROR(AU78/BR78*(BU78-BASELINE_CPR),0) | BX78: =IFERROR(AV78/BR78*(BU78-BASELINE_CPR),0) | BY78: =IFERROR(AW78/BR78*(BU78-BASELINE_CPR),0) | BZ78: =IFERROR(AX78/BR78*(BU78-BASELINE_CPR),0) | CA78: =IFERROR(AY78/BR78*(BU78-BASELINE_CPR),0) | CB78: =IFERROR(AZ78/BR78*(BU78-BASELINE_CPR),0) | CC78: =IFERROR(BA78/BR78*(BU78-BASELINE_CPR),0) | CD78: =IFERROR(BB78/BR78*(BU78-BASELINE_CPR),0) | CE78: =IFERROR(BC78/BR78*(BU78-BASELINE_CPR),0) | CF78: =IFERROR(BD78/BR78*(BU78-BASELINE_CPR),0) | CG78: =IFERROR(BE78/BR78*(BU78-BASELINE_CPR),0) | CH78: =IFERROR(BF78/BR78*(BU78-BASELINE_CPR),0) | CI78: =IFERROR(BG78/BR78*(BU78-BASELINE_CPR),0) | CJ78: =IFERROR(BH78/BR78*(BU78-BASELINE_CPR),0) | CK78: =IFERROR(BI78/BR78*(BU78-BASELINE_CPR),0) | CL78: =IFERROR(BJ78/BR78*(BU78-BASELINE_CPR),0) | CM78: =IFERROR(BK78/BR78*(BU78-BASELINE_CPR),0) | CN78: =IFERROR(BL78/BR78*(BU78-BASELINE_CPR),0) | CO78: =IFERROR(BM78/BR78*(BU78-BASELINE_CPR),0) | CP78: =IFERROR(BN78/BR78*(BU78-BASELINE_CPR),0) | CQ78: =IFERROR(BO78/BR78*(BU78-BASELINE_CPR),0) | CR78: =IFERROR(BP78/BR78*(BU78-BASELINE_CPR),0) | CS78: =IFERROR(BQ78/BR78*(BU78-BASELINE_CPR),0) | CT78: =BASELINE_CPR+SUM(BV78:CS78)-BU78
A79: 36200EL25_000000001711151 | B79: WALKER_PRE21 | C79: 36200EL25 | D79: WALKER & DUNLOP, LLC | E79: 223f | F79: RP | G79: 2012 | H79: 202602 | I79: 1567346.2 | J79: 3.33 | K79: 447 | L79: 0 | M79: 167 | N79: 35 | O79: 204705 | P79: 201305 | Q79: 4080 | R79: 0 | S79: 0 | T79: 0 | U79: 0 | V79: =J79*100-K79 | W79: =L79 | X79: =MIN(M79,36) | Y79: =MIN(MAX(M79-36,0),84) | Z79: =MAX(M79-120,0) | AA79: =IF(OR(O79="",NOT(ISNUMBER(O79))),360,MAX(0,MIN(480,(INT(O79/100)-INT(VALUE(H79)/100))*12+MOD(O79,100)-MOD(VALUE(H79),100)))) | AB79: =IF(AND(AA79>0,AA79<=24),1,0) | AC79: =IF(OR(P79="",NOT(ISNUMBER(P79))),0,MAX(0,MIN(24,(INT(VALUE(H79)/100)-INT(P79/100))*12+MOD(VALUE(H79),100)-MOD(P79,100)))) | AD79: =LN(1+I79) | AE79: =IF(I79<2000000,1,0) | AF79: =IF(I79>50000000,1,0) | AG79: =IF(ISNUMBER(M79),N79/MAX(M79,1),0) | AH79: =IF(G79>=2021,1,0) | AI79: =S79 | AJ79: =T79 | AK79: =R79 | AL79: =U79 | AM79: =IF(ISNUMBER(SEARCH("CAPITAL FUNDING",D79)),1,0) | AN79: =IF(ISNUMBER(SEARCH("PNC",D79)),1,0) | AO79: =IF(ISNUMBER(SEARCH("WELLS FARGO",D79)),1,0) | AP79: =IF(ISNUMBER(SEARCH("DWIGHT",D79)),1,0) | AQ79: =IF(ISNUMBER(SEARCH("GREYSTONE",D79)),1,0) | AR79: =IF(OR(Q79="3896",Q79="3557"),1,0) | AS79: =V79*W79 | AT79: =V$4*(V79-V$3) | AU79: =W$4*(W79-W$3) | AV79: =X$4*(X79-X$3) | AW79: =Y$4*(Y79-Y$3) | AX79: =Z$4*(Z79-Z$3) | AY79: =AA$4*(AA79-AA$3) | AZ79: =AB$4*(AB79-AB$3) | BA79: =AC$4*(AC79-AC$3) | ... BQ79: =AS$4*(AS79-AS$3) | BR79: =SUM(AT79:BQ79) | BS79: =INTERCEPT_SCALED+BR79 | BT79: =1/(1+EXP(-BS79)) | BU79: =1-(1-BT79)^12 | BV79: =IFERROR(AT79/BR79*(BU79-BASELINE_CPR),0) | BW79: =IFERROR(AU79/BR79*(BU79-BASELINE_CPR),0) | BX79: =IFERROR(AV79/BR79*(BU79-BASELINE_CPR),0) | BY79: =IFERROR(AW79/BR79*(BU79-BASELINE_CPR),0) | BZ79: =IFERROR(AX79/BR79*(BU79-BASELINE_CPR),0) | CA79: =IFERROR(AY79/BR79*(BU79-BASELINE_CPR),0) | CB79: =IFERROR(AZ79/BR79*(BU79-BASELINE_CPR),0) | CC79: =IFERROR(BA79/BR79*(BU79-BASELINE_CPR),0) | CD79: =IFERROR(BB79/BR79*(BU79-BASELINE_CPR),0) | CE79: =IFERROR(BC79/BR79*(BU79-BASELINE_CPR),0) | CF79: =IFERROR(BD79/BR79*(BU79-BASELINE_CPR),0) | CG79: =IFERROR(BE79/BR79*(BU79-BASELINE_CPR),0) | CH79: =IFERROR(BF79/BR79*(BU79-BASELINE_CPR),0) | CI79: =IFERROR(BG79/BR79*(BU79-BASELINE_CPR),0) | CJ79: =IFERROR(BH79/BR79*(BU79-BASELINE_CPR),0) | CK79: =IFERROR(BI79/BR79*(BU79-BASELINE_CPR),0) | CL79: =IFERROR(BJ79/BR79*(BU79-BASELINE_CPR),0) | CM79: =IFERROR(BK79/BR79*(BU79-BASELINE_CPR),0) | CN79: =IFERROR(BL79/BR79*(BU79-BASELINE_CPR),0) | CO79: =IFERROR(BM79/BR79*(BU79-BASELINE_CPR),0) | CP79: =IFERROR(BN79/BR79*(BU79-BASELINE_CPR),0) | CQ79: =IFERROR(BO79/BR79*(BU79-BASELINE_CPR),0) | CR79: =IFERROR(BP79/BR79*(BU79-BASELINE_CPR),0) | CS79: =IFERROR(BQ79/BR79*(BU79-BASELINE_CPR),0) | CT79: =BASELINE_CPR+SUM(BV79:CS79)-BU79
A80: 36180GT83_000000012111176 | B80: WALKER_PRE21 | C80: 36180GT83 | D80: WALKER & DUNLOP, LLC | E80: 223f | F80: RP | G80: 2013 | H80: 202602 | I80: 4626699.6 | J80: 4.35 | K80: 447 | L80: 0 | M80: 146 | N80: 41 | O80: 204904 | P80: 201605 | Q80: 4080 | R80: 0 | S80: 0 | T80: 0 | U80: 0 | V80: =J80*100-K80 | W80: =L80 | X80: =MIN(M80,36) | Y80: =MIN(MAX(M80-36,0),84) | Z80: =MAX(M80-120,0) | AA80: =IF(OR(O80="",NOT(ISNUMBER(O80))),360,MAX(0,MIN(480,(INT(O80/100)-INT(VALUE(H80)/100))*12+MOD(O80,100)-MOD(VALUE(H80),100)))) | AB80: =IF(AND(AA80>0,AA80<=24),1,0) | AC80: =IF(OR(P80="",NOT(ISNUMBER(P80))),0,MAX(0,MIN(24,(INT(VALUE(H80)/100)-INT(P80/100))*12+MOD(VALUE(H80),100)-MOD(P80,100)))) | AD80: =LN(1+I80) | AE80: =IF(I80<2000000,1,0) | AF80: =IF(I80>50000000,1,0) | AG80: =IF(ISNUMBER(M80),N80/MAX(M80,1),0) | AH80: =IF(G80>=2021,1,0) | AI80: =S80 | AJ80: =T80 | AK80: =R80 | AL80: =U80 | AM80: =IF(ISNUMBER(SEARCH("CAPITAL FUNDING",D80)),1,0) | AN80: =IF(ISNUMBER(SEARCH("PNC",D80)),1,0) | AO80: =IF(ISNUMBER(SEARCH("WELLS FARGO",D80)),1,0) | AP80: =IF(ISNUMBER(SEARCH("DWIGHT",D80)),1,0) | AQ80: =IF(ISNUMBER(SEARCH("GREYSTONE",D80)),1,0) | AR80: =IF(OR(Q80="3896",Q80="3557"),1,0) | AS80: =V80*W80 | AT80: =V$4*(V80-V$3) | AU80: =W$4*(W80-W$3) | AV80: =X$4*(X80-X$3) | AW80: =Y$4*(Y80-Y$3) | AX80: =Z$4*(Z80-Z$3) | AY80: =AA$4*(AA80-AA$3) | AZ80: =AB$4*(AB80-AB$3) | BA80: =AC$4*(AC80-AC$3) | ... BQ80: =AS$4*(AS80-AS$3) | BR80: =SUM(AT80:BQ80) | BS80: =INTERCEPT_SCALED+BR80 | BT80: =1/(1+EXP(-BS80)) | BU80: =1-(1-BT80)^12 | BV80: =IFERROR(AT80/BR80*(BU80-BASELINE_CPR),0) | BW80: =IFERROR(AU80/BR80*(BU80-BASELINE_CPR),0) | BX80: =IFERROR(AV80/BR80*(BU80-BASELINE_CPR),0) | BY80: =IFERROR(AW80/BR80*(BU80-BASELINE_CPR),0) | BZ80: =IFERROR(AX80/BR80*(BU80-BASELINE_CPR),0) | CA80: =IFERROR(AY80/BR80*(BU80-BASELINE_CPR),0) | CB80: =IFERROR(AZ80/BR80*(BU80-BASELINE_CPR),0) | CC80: =IFERROR(BA80/BR80*(BU80-BASELINE_CPR),0) | CD80: =IFERROR(BB80/BR80*(BU80-BASELINE_CPR),0) | CE80: =IFERROR(BC80/BR80*(BU80-BASELINE_CPR),0) | CF80: =IFERROR(BD80/BR80*(BU80-BASELINE_CPR),0) | CG80: =IFERROR(BE80/BR80*(BU80-BASELINE_CPR),0) | CH80: =IFERROR(BF80/BR80*(BU80-BASELINE_CPR),0) | CI80: =IFERROR(BG80/BR80*(BU80-BASELINE_CPR),0) | CJ80: =IFERROR(BH80/BR80*(BU80-BASELINE_CPR),0) | CK80: =IFERROR(BI80/BR80*(BU80-BASELINE_CPR),0) | CL80: =IFERROR(BJ80/BR80*(BU80-BASELINE_CPR),0) | CM80: =IFERROR(BK80/BR80*(BU80-BASELINE_CPR),0) | CN80: =IFERROR(BL80/BR80*(BU80-BASELINE_CPR),0) | CO80: =IFERROR(BM80/BR80*(BU80-BASELINE_CPR),0) | CP80: =IFERROR(BN80/BR80*(BU80-BASELINE_CPR),0) | CQ80: =IFERROR(BO80/BR80*(BU80-BASELINE_CPR),0) | CR80: =IFERROR(BP80/BR80*(BU80-BASELINE_CPR),0) | CS80: =IFERROR(BQ80/BR80*(BU80-BASELINE_CPR),0) | CT80: =BASELINE_CPR+SUM(BV80:CS80)-BU80
A81: 36178FVA1_000000012722086 | B81: WALKER_PRE21 | C81: 36178FVA1 | D81: WALKER & DUNLOP, LLC | E81: 232 | F81: RP | G81: 2012 | H81: 202602 | I81: 2391566.6 | J81: 2.8 | K81: 447 | L81: 0 | M81: 164 | N81: 26 | O81: 203708 | P81: 201308 | Q81: 4080 | R81: 1 | S81: 1 | T81: 0 | U81: 0 | V81: =J81*100-K81 | W81: =L81 | X81: =MIN(M81,36) | Y81: =MIN(MAX(M81-36,0),84) | Z81: =MAX(M81-120,0) | AA81: =IF(OR(O81="",NOT(ISNUMBER(O81))),360,MAX(0,MIN(480,(INT(O81/100)-INT(VALUE(H81)/100))*12+MOD(O81,100)-MOD(VALUE(H81),100)))) | AB81: =IF(AND(AA81>0,AA81<=24),1,0) | AC81: =IF(OR(P81="",NOT(ISNUMBER(P81))),0,MAX(0,MIN(24,(INT(VALUE(H81)/100)-INT(P81/100))*12+MOD(VALUE(H81),100)-MOD(P81,100)))) | AD81: =LN(1+I81) | AE81: =IF(I81<2000000,1,0) | AF81: =IF(I81>50000000,1,0) | AG81: =IF(ISNUMBER(M81),N81/MAX(M81,1),0) | AH81: =IF(G81>=2021,1,0) | AI81: =S81 | AJ81: =T81 | AK81: =R81 | AL81: =U81 | AM81: =IF(ISNUMBER(SEARCH("CAPITAL FUNDING",D81)),1,0) | AN81: =IF(ISNUMBER(SEARCH("PNC",D81)),1,0) | AO81: =IF(ISNUMBER(SEARCH("WELLS FARGO",D81)),1,0) | AP81: =IF(ISNUMBER(SEARCH("DWIGHT",D81)),1,0) | AQ81: =IF(ISNUMBER(SEARCH("GREYSTONE",D81)),1,0) | AR81: =IF(OR(Q81="3896",Q81="3557"),1,0) | AS81: =V81*W81 | AT81: =V$4*(V81-V$3) | AU81: =W$4*(W81-W$3) | AV81: =X$4*(X81-X$3) | AW81: =Y$4*(Y81-Y$3) | AX81: =Z$4*(Z81-Z$3) | AY81: =AA$4*(AA81-AA$3) | AZ81: =AB$4*(AB81-AB$3) | BA81: =AC$4*(AC81-AC$3) | ... BQ81: =AS$4*(AS81-AS$3) | BR81: =SUM(AT81:BQ81) | BS81: =INTERCEPT_SCALED+BR81 | BT81: =1/(1+EXP(-BS81)) | BU81: =1-(1-BT81)^12 | BV81: =IFERROR(AT81/BR81*(BU81-BASELINE_CPR),0) | BW81: =IFERROR(AU81/BR81*(BU81-BASELINE_CPR),0) | BX81: =IFERROR(AV81/BR81*(BU81-BASELINE_CPR),0) | BY81: =IFERROR(AW81/BR81*(BU81-BASELINE_CPR),0) | BZ81: =IFERROR(AX81/BR81*(BU81-BASELINE_CPR),0) | CA81: =IFERROR(AY81/BR81*(BU81-BASELINE_CPR),0) | CB81: =IFERROR(AZ81/BR81*(BU81-BASELINE_CPR),0) | CC81: =IFERROR(BA81/BR81*(BU81-BASELINE_CPR),0) | CD81: =IFERROR(BB81/BR81*(BU81-BASELINE_CPR),0) | CE81: =IFERROR(BC81/BR81*(BU81-BASELINE_CPR),0) | CF81: =IFERROR(BD81/BR81*(BU81-BASELINE_CPR),0) | CG81: =IFERROR(BE81/BR81*(BU81-BASELINE_CPR),0) | CH81: =IFERROR(BF81/BR81*(BU81-BASELINE_CPR),0) | CI81: =IFERROR(BG81/BR81*(BU81-BASELINE_CPR),0) | CJ81: =IFERROR(BH81/BR81*(BU81-BASELINE_CPR),0) | CK81: =IFERROR(BI81/BR81*(BU81-BASELINE_CPR),0) | CL81: =IFERROR(BJ81/BR81*(BU81-BASELINE_CPR),0) | CM81: =IFERROR(BK81/BR81*(BU81-BASELINE_CPR),0) | CN81: =IFERROR(BL81/BR81*(BU81-BASELINE_CPR),0) | CO81: =IFERROR(BM81/BR81*(BU81-BASELINE_CPR),0) | CP81: =IFERROR(BN81/BR81*(BU81-BASELINE_CPR),0) | CQ81: =IFERROR(BO81/BR81*(BU81-BASELINE_CPR),0) | CR81: =IFERROR(BP81/BR81*(BU81-BASELINE_CPR),0) | CS81: =IFERROR(BQ81/BR81*(BU81-BASELINE_CPR),0) | CT81: =BASELINE_CPR+SUM(BV81:CS81)-BU81
A82: 3617N1EH9_000000002311546 | B82: WALKER_PRE21 | C82: 3617N1EH9 | D82: WALKER & DUNLOP, LLC | E82: 223f | F82: RP | G82: 2020 | H82: 202602 | I82: 5130860.1 | J82: 2.55 | K82: 447 | L82: 5 | M82: 68 | N82: 0 | O82: 205507 | Q82: 4080 | R82: 0 | S82: 0 | T82: 0 | U82: 0 | V82: =J82*100-K82 | W82: =L82 | X82: =MIN(M82,36) | Y82: =MIN(MAX(M82-36,0),84) | Z82: =MAX(M82-120,0) | AA82: =IF(OR(O82="",NOT(ISNUMBER(O82))),360,MAX(0,MIN(480,(INT(O82/100)-INT(VALUE(H82)/100))*12+MOD(O82,100)-MOD(VALUE(H82),100)))) | AB82: =IF(AND(AA82>0,AA82<=24),1,0) | AC82: =IF(OR(P82="",NOT(ISNUMBER(P82))),0,MAX(0,MIN(24,(INT(VALUE(H82)/100)-INT(P82/100))*12+MOD(VALUE(H82),100)-MOD(P82,100)))) | AD82: =LN(1+I82) | AE82: =IF(I82<2000000,1,0) | AF82: =IF(I82>50000000,1,0) | AG82: =IF(ISNUMBER(M82),N82/MAX(M82,1),0) | AH82: =IF(G82>=2021,1,0) | AI82: =S82 | AJ82: =T82 | AK82: =R82 | AL82: =U82 | AM82: =IF(ISNUMBER(SEARCH("CAPITAL FUNDING",D82)),1,0) | AN82: =IF(ISNUMBER(SEARCH("PNC",D82)),1,0) | AO82: =IF(ISNUMBER(SEARCH("WELLS FARGO",D82)),1,0) | AP82: =IF(ISNUMBER(SEARCH("DWIGHT",D82)),1,0) | AQ82: =IF(ISNUMBER(SEARCH("GREYSTONE",D82)),1,0) | AR82: =IF(OR(Q82="3896",Q82="3557"),1,0) | AS82: =V82*W82 | AT82: =V$4*(V82-V$3) | AU82: =W$4*(W82-W$3) | AV82: =X$4*(X82-X$3) | AW82: =Y$4*(Y82-Y$3) | AX82: =Z$4*(Z82-Z$3) | AY82: =AA$4*(AA82-AA$3) | AZ82: =AB$4*(AB82-AB$3) | BA82: =AC$4*(AC82-AC$3) | ... BQ82: =AS$4*(AS82-AS$3) | BR82: =SUM(AT82:BQ82) | BS82: =INTERCEPT_SCALED+BR82 | BT82: =1/(1+EXP(-BS82)) | BU82: =1-(1-BT82)^12 | BV82: =IFERROR(AT82/BR82*(BU82-BASELINE_CPR),0) | BW82: =IFERROR(AU82/BR82*(BU82-BASELINE_CPR),0) | BX82: =IFERROR(AV82/BR82*(BU82-BASELINE_CPR),0) | BY82: =IFERROR(AW82/BR82*(BU82-BASELINE_CPR),0) | BZ82: =IFERROR(AX82/BR82*(BU82-BASELINE_CPR),0) | CA82: =IFERROR(AY82/BR82*(BU82-BASELINE_CPR),0) | CB82: =IFERROR(AZ82/BR82*(BU82-BASELINE_CPR),0) | CC82: =IFERROR(BA82/BR82*(BU82-BASELINE_CPR),0) | CD82: =IFERROR(BB82/BR82*(BU82-BASELINE_CPR),0) | CE82: =IFERROR(BC82/BR82*(BU82-BASELINE_CPR),0) | CF82: =IFERROR(BD82/BR82*(BU82-BASELINE_CPR),0) | CG82: =IFERROR(BE82/BR82*(BU82-BASELINE_CPR),0) | CH82: =IFERROR(BF82/BR82*(BU82-BASELINE_CPR),0) | CI82: =IFERROR(BG82/BR82*(BU82-BASELINE_CPR),0) | CJ82: =IFERROR(BH82/BR82*(BU82-BASELINE_CPR),0) | CK82: =IFERROR(BI82/BR82*(BU82-BASELINE_CPR),0) | CL82: =IFERROR(BJ82/BR82*(BU82-BASELINE_CPR),0) | CM82: =IFERROR(BK82/BR82*(BU82-BASELINE_CPR),0) | CN82: =IFERROR(BL82/BR82*(BU82-BASELINE_CPR),0) | CO82: =IFERROR(BM82/BR82*(BU82-BASELINE_CPR),0) | CP82: =IFERROR(BN82/BR82*(BU82-BASELINE_CPR),0) | CQ82: =IFERROR(BO82/BR82*(BU82-BASELINE_CPR),0) | CR82: =IFERROR(BP82/BR82*(BU82-BASELINE_CPR),0) | CS82: =IFERROR(BQ82/BR82*(BU82-BASELINE_CPR),0) | CT82: =BASELINE_CPR+SUM(BV82:CS82)-BU82
A83: 36295SBS4_000000001711123 | B83: WALKER_PRE21 | C83: 36295SBS4 | D83: WALKER & DUNLOP, LLC | E83: 223f | F83: RP | G83: 2010 | H83: 202602 | I83: 1165207.3 | J83: 4.6 | K83: 447 | L83: 0 | M83: 189 | N83: 47 | O83: 204507 | P83: 201207 | Q83: 4080 | R83: 0 | S83: 0 | T83: 0 | U83: 0 | V83: =J83*100-K83 | W83: =L83 | X83: =MIN(M83,36) | Y83: =MIN(MAX(M83-36,0),84) | Z83: =MAX(M83-120,0) | AA83: =IF(OR(O83="",NOT(ISNUMBER(O83))),360,MAX(0,MIN(480,(INT(O83/100)-INT(VALUE(H83)/100))*12+MOD(O83,100)-MOD(VALUE(H83),100)))) | AB83: =IF(AND(AA83>0,AA83<=24),1,0) | AC83: =IF(OR(P83="",NOT(ISNUMBER(P83))),0,MAX(0,MIN(24,(INT(VALUE(H83)/100)-INT(P83/100))*12+MOD(VALUE(H83),100)-MOD(P83,100)))) | AD83: =LN(1+I83) | AE83: =IF(I83<2000000,1,0) | AF83: =IF(I83>50000000,1,0) | AG83: =IF(ISNUMBER(M83),N83/MAX(M83,1),0) | AH83: =IF(G83>=2021,1,0) | AI83: =S83 | AJ83: =T83 | AK83: =R83 | AL83: =U83 | AM83: =IF(ISNUMBER(SEARCH("CAPITAL FUNDING",D83)),1,0) | AN83: =IF(ISNUMBER(SEARCH("PNC",D83)),1,0) | AO83: =IF(ISNUMBER(SEARCH("WELLS FARGO",D83)),1,0) | AP83: =IF(ISNUMBER(SEARCH("DWIGHT",D83)),1,0) | AQ83: =IF(ISNUMBER(SEARCH("GREYSTONE",D83)),1,0) | AR83: =IF(OR(Q83="3896",Q83="3557"),1,0) | AS83: =V83*W83 | AT83: =V$4*(V83-V$3) | AU83: =W$4*(W83-W$3) | AV83: =X$4*(X83-X$3) | AW83: =Y$4*(Y83-Y$3) | AX83: =Z$4*(Z83-Z$3) | AY83: =AA$4*(AA83-AA$3) | AZ83: =AB$4*(AB83-AB$3) | BA83: =AC$4*(AC83-AC$3) | ... BQ83: =AS$4*(AS83-AS$3) | BR83: =SUM(AT83:BQ83) | BS83: =INTERCEPT_SCALED+BR83 | BT83: =1/(1+EXP(-BS83)) | BU83: =1-(1-BT83)^12 | BV83: =IFERROR(AT83/BR83*(BU83-BASELINE_CPR),0) | BW83: =IFERROR(AU83/BR83*(BU83-BASELINE_CPR),0) | BX83: =IFERROR(AV83/BR83*(BU83-BASELINE_CPR),0) | BY83: =IFERROR(AW83/BR83*(BU83-BASELINE_CPR),0) | BZ83: =IFERROR(AX83/BR83*(BU83-BASELINE_CPR),0) | CA83: =IFERROR(AY83/BR83*(BU83-BASELINE_CPR),0) | CB83: =IFERROR(AZ83/BR83*(BU83-BASELINE_CPR),0) | CC83: =IFERROR(BA83/BR83*(BU83-BASELINE_CPR),0) | CD83: =IFERROR(BB83/BR83*(BU83-BASELINE_CPR),0) | CE83: =IFERROR(BC83/BR83*(BU83-BASELINE_CPR),0) | CF83: =IFERROR(BD83/BR83*(BU83-BASELINE_CPR),0) | CG83: =IFERROR(BE83/BR83*(BU83-BASELINE_CPR),0) | CH83: =IFERROR(BF83/BR83*(BU83-BASELINE_CPR),0) | CI83: =IFERROR(BG83/BR83*(BU83-BASELINE_CPR),0) | CJ83: =IFERROR(BH83/BR83*(BU83-BASELINE_CPR),0) | CK83: =IFERROR(BI83/BR83*(BU83-BASELINE_CPR),0) | CL83: =IFERROR(BJ83/BR83*(BU83-BASELINE_CPR),0) | CM83: =IFERROR(BK83/BR83*(BU83-BASELINE_CPR),0) | CN83: =IFERROR(BL83/BR83*(BU83-BASELINE_CPR),0) | CO83: =IFERROR(BM83/BR83*(BU83-BASELINE_CPR),0) | CP83: =IFERROR(BN83/BR83*(BU83-BASELINE_CPR),0) | CQ83: =IFERROR(BO83/BR83*(BU83-BASELINE_CPR),0) | CR83: =IFERROR(BP83/BR83*(BU83-BASELINE_CPR),0) | CS83: =IFERROR(BQ83/BR83*(BU83-BASELINE_CPR),0) | CT83: =BASELINE_CPR+SUM(BV83:CS83)-BU83
A84: 36180M4N4_000000008111083 | B84: WALKER_PRE21 | C84: 36180M4N4 | D84: WALKER & DUNLOP, LLC | E84: 223f | F84: RP | G84: 2013 | H84: 202602 | I84: 696510.77 | J84: 2.97 | K84: 447 | L84: 0 | M84: 152 | N84: 27 | O84: 204307 | Q84: 4080 | R84: 0 | S84: 0 | T84: 0 | U84: 0 | V84: =J84*100-K84 | W84: =L84 | X84: =MIN(M84,36) | Y84: =MIN(MAX(M84-36,0),84) | Z84: =MAX(M84-120,0) | AA84: =IF(OR(O84="",NOT(ISNUMBER(O84))),360,MAX(0,MIN(480,(INT(O84/100)-INT(VALUE(H84)/100))*12+MOD(O84,100)-MOD(VALUE(H84),100)))) | AB84: =IF(AND(AA84>0,AA84<=24),1,0) | AC84: =IF(OR(P84="",NOT(ISNUMBER(P84))),0,MAX(0,MIN(24,(INT(VALUE(H84)/100)-INT(P84/100))*12+MOD(VALUE(H84),100)-MOD(P84,100)))) | AD84: =LN(1+I84) | AE84: =IF(I84<2000000,1,0) | AF84: =IF(I84>50000000,1,0) | AG84: =IF(ISNUMBER(M84),N84/MAX(M84,1),0) | AH84: =IF(G84>=2021,1,0) | AI84: =S84 | AJ84: =T84 | AK84: =R84 | AL84: =U84 | AM84: =IF(ISNUMBER(SEARCH("CAPITAL FUNDING",D84)),1,0) | AN84: =IF(ISNUMBER(SEARCH("PNC",D84)),1,0) | AO84: =IF(ISNUMBER(SEARCH("WELLS FARGO",D84)),1,0) | AP84: =IF(ISNUMBER(SEARCH("DWIGHT",D84)),1,0) | AQ84: =IF(ISNUMBER(SEARCH("GREYSTONE",D84)),1,0) | AR84: =IF(OR(Q84="3896",Q84="3557"),1,0) | AS84: =V84*W84 | AT84: =V$4*(V84-V$3) | AU84: =W$4*(W84-W$3) | AV84: =X$4*(X84-X$3) | AW84: =Y$4*(Y84-Y$3) | AX84: =Z$4*(Z84-Z$3) | AY84: =AA$4*(AA84-AA$3) | AZ84: =AB$4*(AB84-AB$3) | BA84: =AC$4*(AC84-AC$3) | ... BQ84: =AS$4*(AS84-AS$3) | BR84: =SUM(AT84:BQ84) | BS84: =INTERCEPT_SCALED+BR84 | BT84: =1/(1+EXP(-BS84)) | BU84: =1-(1-BT84)^12 | BV84: =IFERROR(AT84/BR84*(BU84-BASELINE_CPR),0) | BW84: =IFERROR(AU84/BR84*(BU84-BASELINE_CPR),0) | BX84: =IFERROR(AV84/BR84*(BU84-BASELINE_CPR),0) | BY84: =IFERROR(AW84/BR84*(BU84-BASELINE_CPR),0) | BZ84: =IFERROR(AX84/BR84*(BU84-BASELINE_CPR),0) | CA84: =IFERROR(AY84/BR84*(BU84-BASELINE_CPR),0) | CB84: =IFERROR(AZ84/BR84*(BU84-BASELINE_CPR),0) | CC84: =IFERROR(BA84/BR84*(BU84-BASELINE_CPR),0) | CD84: =IFERROR(BB84/BR84*(BU84-BASELINE_CPR),0) | CE84: =IFERROR(BC84/BR84*(BU84-BASELINE_CPR),0) | CF84: =IFERROR(BD84/BR84*(BU84-BASELINE_CPR),0) | CG84: =IFERROR(BE84/BR84*(BU84-BASELINE_CPR),0) | CH84: =IFERROR(BF84/BR84*(BU84-BASELINE_CPR),0) | CI84: =IFERROR(BG84/BR84*(BU84-BASELINE_CPR),0) | CJ84: =IFERROR(BH84/BR84*(BU84-BASELINE_CPR),0) | CK84: =IFERROR(BI84/BR84*(BU84-BASELINE_CPR),0) | CL84: =IFERROR(BJ84/BR84*(BU84-BASELINE_CPR),0) | CM84: =IFERROR(BK84/BR84*(BU84-BASELINE_CPR),0) | CN84: =IFERROR(BL84/BR84*(BU84-BASELINE_CPR),0) | CO84: =IFERROR(BM84/BR84*(BU84-BASELINE_CPR),0) | CP84: =IFERROR(BN84/BR84*(BU84-BASELINE_CPR),0) | CQ84: =IFERROR(BO84/BR84*(BU84-BASELINE_CPR),0) | CR84: =IFERROR(BP84/BR84*(BU84-BASELINE_CPR),0) | CS84: =IFERROR(BQ84/BR84*(BU84-BASELINE_CPR),0) | CT84: =BASELINE_CPR+SUM(BV84:CS84)-BU84
A85: 3617YC4K7_000000005138032 | B85: WALKER_POST21 | C85: 3617YC4K7 | D85: WALKER & DUNLOP, LLC | E85: OTHER | F85: OTHER | G85: 2022 | H85: 202602 | I85: 31181676 | J85: 3.15 | K85: 447 | L85: 9 | M85: 45 | N85: 0 | O85: 206406 | Q85: 4080 | R85: 0 | S85: 0 | T85: 0 | U85: 0 | V85: =J85*100-K85 | W85: =L85 | X85: =MIN(M85,36) | Y85: =MIN(MAX(M85-36,0),84) | Z85: =MAX(M85-120,0) | AA85: =IF(OR(O85="",NOT(ISNUMBER(O85))),360,MAX(0,MIN(480,(INT(O85/100)-INT(VALUE(H85)/100))*12+MOD(O85,100)-MOD(VALUE(H85),100)))) | AB85: =IF(AND(AA85>0,AA85<=24),1,0) | AC85: =IF(OR(P85="",NOT(ISNUMBER(P85))),0,MAX(0,MIN(24,(INT(VALUE(H85)/100)-INT(P85/100))*12+MOD(VALUE(H85),100)-MOD(P85,100)))) | AD85: =LN(1+I85) | AE85: =IF(I85<2000000,1,0) | AF85: =IF(I85>50000000,1,0) | AG85: =IF(ISNUMBER(M85),N85/MAX(M85,1),0) | AH85: =IF(G85>=2021,1,0) | AI85: =S85 | AJ85: =T85 | AK85: =R85 | AL85: =U85 | AM85: =IF(ISNUMBER(SEARCH("CAPITAL FUNDING",D85)),1,0) | AN85: =IF(ISNUMBER(SEARCH("PNC",D85)),1,0) | AO85: =IF(ISNUMBER(SEARCH("WELLS FARGO",D85)),1,0) | AP85: =IF(ISNUMBER(SEARCH("DWIGHT",D85)),1,0) | AQ85: =IF(ISNUMBER(SEARCH("GREYSTONE",D85)),1,0) | AR85: =IF(OR(Q85="3896",Q85="3557"),1,0) | AS85: =V85*W85 | AT85: =V$4*(V85-V$3) | AU85: =W$4*(W85-W$3) | AV85: =X$4*(X85-X$3) | AW85: =Y$4*(Y85-Y$3) | AX85: =Z$4*(Z85-Z$3) | AY85: =AA$4*(AA85-AA$3) | AZ85: =AB$4*(AB85-AB$3) | BA85: =AC$4*(AC85-AC$3) | ... BQ85: =AS$4*(AS85-AS$3) | BR85: =SUM(AT85:BQ85) | BS85: =INTERCEPT_SCALED+BR85 | BT85: =1/(1+EXP(-BS85)) | BU85: =1-(1-BT85)^12 | BV85: =IFERROR(AT85/BR85*(BU85-BASELINE_CPR),0) | BW85: =IFERROR(AU85/BR85*(BU85-BASELINE_CPR),0) | BX85: =IFERROR(AV85/BR85*(BU85-BASELINE_CPR),0) | BY85: =IFERROR(AW85/BR85*(BU85-BASELINE_CPR),0) | BZ85: =IFERROR(AX85/BR85*(BU85-BASELINE_CPR),0) | CA85: =IFERROR(AY85/BR85*(BU85-BASELINE_CPR),0) | CB85: =IFERROR(AZ85/BR85*(BU85-BASELINE_CPR),0) | CC85: =IFERROR(BA85/BR85*(BU85-BASELINE_CPR),0) | CD85: =IFERROR(BB85/BR85*(BU85-BASELINE_CPR),0) | CE85: =IFERROR(BC85/BR85*(BU85-BASELINE_CPR),0) | CF85: =IFERROR(BD85/BR85*(BU85-BASELINE_CPR),0) | CG85: =IFERROR(BE85/BR85*(BU85-BASELINE_CPR),0) | CH85: =IFERROR(BF85/BR85*(BU85-BASELINE_CPR),0) | CI85: =IFERROR(BG85/BR85*(BU85-BASELINE_CPR),0) | CJ85: =IFERROR(BH85/BR85*(BU85-BASELINE_CPR),0) | CK85: =IFERROR(BI85/BR85*(BU85-BASELINE_CPR),0) | CL85: =IFERROR(BJ85/BR85*(BU85-BASELINE_CPR),0) | CM85: =IFERROR(BK85/BR85*(BU85-BASELINE_CPR),0) | CN85: =IFERROR(BL85/BR85*(BU85-BASELINE_CPR),0) | CO85: =IFERROR(BM85/BR85*(BU85-BASELINE_CPR),0) | CP85: =IFERROR(BN85/BR85*(BU85-BASELINE_CPR),0) | CQ85: =IFERROR(BO85/BR85*(BU85-BASELINE_CPR),0) | CR85: =IFERROR(BP85/BR85*(BU85-BASELINE_CPR),0) | CS85: =IFERROR(BQ85/BR85*(BU85-BASELINE_CPR),0) | CT85: =BASELINE_CPR+SUM(BV85:CS85)-BU85
A86: 36177KSB3_000000012711174 | B86: WALKER_PRE21 | C86: 36177KSB3 | D86: WALKER & DUNLOP, LLC | E86: 223f | F86: RP | G86: 2012 | H86: 202602 | I86: 1897260.9 | J86: 3.35 | K86: 447 | L86: 0 | M86: 163 | N86: 33 | O86: 204708 | P86: 201409 | Q86: 4080 | R86: 0 | S86: 0 | T86: 0 | U86: 0 | V86: =J86*100-K86 | W86: =L86 | X86: =MIN(M86,36) | Y86: =MIN(MAX(M86-36,0),84) | Z86: =MAX(M86-120,0) | AA86: =IF(OR(O86="",NOT(ISNUMBER(O86))),360,MAX(0,MIN(480,(INT(O86/100)-INT(VALUE(H86)/100))*12+MOD(O86,100)-MOD(VALUE(H86),100)))) | AB86: =IF(AND(AA86>0,AA86<=24),1,0) | AC86: =IF(OR(P86="",NOT(ISNUMBER(P86))),0,MAX(0,MIN(24,(INT(VALUE(H86)/100)-INT(P86/100))*12+MOD(VALUE(H86),100)-MOD(P86,100)))) | AD86: =LN(1+I86) | AE86: =IF(I86<2000000,1,0) | AF86: =IF(I86>50000000,1,0) | AG86: =IF(ISNUMBER(M86),N86/MAX(M86,1),0) | AH86: =IF(G86>=2021,1,0) | AI86: =S86 | AJ86: =T86 | AK86: =R86 | AL86: =U86 | AM86: =IF(ISNUMBER(SEARCH("CAPITAL FUNDING",D86)),1,0) | AN86: =IF(ISNUMBER(SEARCH("PNC",D86)),1,0) | AO86: =IF(ISNUMBER(SEARCH("WELLS FARGO",D86)),1,0) | AP86: =IF(ISNUMBER(SEARCH("DWIGHT",D86)),1,0) | AQ86: =IF(ISNUMBER(SEARCH("GREYSTONE",D86)),1,0) | AR86: =IF(OR(Q86="3896",Q86="3557"),1,0) | AS86: =V86*W86 | AT86: =V$4*(V86-V$3) | AU86: =W$4*(W86-W$3) | AV86: =X$4*(X86-X$3) | AW86: =Y$4*(Y86-Y$3) | AX86: =Z$4*(Z86-Z$3) | AY86: =AA$4*(AA86-AA$3) | AZ86: =AB$4*(AB86-AB$3) | BA86: =AC$4*(AC86-AC$3) | ... BQ86: =AS$4*(AS86-AS$3) | BR86: =SUM(AT86:BQ86) | BS86: =INTERCEPT_SCALED+BR86 | BT86: =1/(1+EXP(-BS86)) | BU86: =1-(1-BT86)^12 | BV86: =IFERROR(AT86/BR86*(BU86-BASELINE_CPR),0) | BW86: =IFERROR(AU86/BR86*(BU86-BASELINE_CPR),0) | BX86: =IFERROR(AV86/BR86*(BU86-BASELINE_CPR),0) | BY86: =IFERROR(AW86/BR86*(BU86-BASELINE_CPR),0) | BZ86: =IFERROR(AX86/BR86*(BU86-BASELINE_CPR),0) | CA86: =IFERROR(AY86/BR86*(BU86-BASELINE_CPR),0) | CB86: =IFERROR(AZ86/BR86*(BU86-BASELINE_CPR),0) | CC86: =IFERROR(BA86/BR86*(BU86-BASELINE_CPR),0) | CD86: =IFERROR(BB86/BR86*(BU86-BASELINE_CPR),0) | CE86: =IFERROR(BC86/BR86*(BU86-BASELINE_CPR),0) | CF86: =IFERROR(BD86/BR86*(BU86-BASELINE_CPR),0) | CG86: =IFERROR(BE86/BR86*(BU86-BASELINE_CPR),0) | CH86: =IFERROR(BF86/BR86*(BU86-BASELINE_CPR),0) | CI86: =IFERROR(BG86/BR86*(BU86-BASELINE_CPR),0) | CJ86: =IFERROR(BH86/BR86*(BU86-BASELINE_CPR),0) | CK86: =IFERROR(BI86/BR86*(BU86-BASELINE_CPR),0) | CL86: =IFERROR(BJ86/BR86*(BU86-BASELINE_CPR),0) | CM86: =IFERROR(BK86/BR86*(BU86-BASELINE_CPR),0) | CN86: =IFERROR(BL86/BR86*(BU86-BASELINE_CPR),0) | CO86: =IFERROR(BM86/BR86*(BU86-BASELINE_CPR),0) | CP86: =IFERROR(BN86/BR86*(BU86-BASELINE_CPR),0) | CQ86: =IFERROR(BO86/BR86*(BU86-BASELINE_CPR),0) | CR86: =IFERROR(BP86/BR86*(BU86-BASELINE_CPR),0) | CS86: =IFERROR(BQ86/BR86*(BU86-BASELINE_CPR),0) | CT86: =BASELINE_CPR+SUM(BV86:CS86)-BU86
A87: 3617WNQG0_000000005143257 | B87: WALKER_POST21 | C87: 3617WNQG0 | D87: WALKER & DUNLOP, LLC | E87: 232 | F87: NC | G87: 2021 | H87: 202602 | I87: 20697800 | J87: 2.69 | K87: 447 | L87: 8 | M87: 50 | N87: 0 | O87: 206310 | Q87: 4080 | R87: 1 | S87: 0 | T87: 0 | U87: 1 | V87: =J87*100-K87 | W87: =L87 | X87: =MIN(M87,36) | Y87: =MIN(MAX(M87-36,0),84) | Z87: =MAX(M87-120,0) | AA87: =IF(OR(O87="",NOT(ISNUMBER(O87))),360,MAX(0,MIN(480,(INT(O87/100)-INT(VALUE(H87)/100))*12+MOD(O87,100)-MOD(VALUE(H87),100)))) | AB87: =IF(AND(AA87>0,AA87<=24),1,0) | AC87: =IF(OR(P87="",NOT(ISNUMBER(P87))),0,MAX(0,MIN(24,(INT(VALUE(H87)/100)-INT(P87/100))*12+MOD(VALUE(H87),100)-MOD(P87,100)))) | AD87: =LN(1+I87) | AE87: =IF(I87<2000000,1,0) | AF87: =IF(I87>50000000,1,0) | AG87: =IF(ISNUMBER(M87),N87/MAX(M87,1),0) | AH87: =IF(G87>=2021,1,0) | AI87: =S87 | AJ87: =T87 | AK87: =R87 | AL87: =U87 | AM87: =IF(ISNUMBER(SEARCH("CAPITAL FUNDING",D87)),1,0) | AN87: =IF(ISNUMBER(SEARCH("PNC",D87)),1,0) | AO87: =IF(ISNUMBER(SEARCH("WELLS FARGO",D87)),1,0) | AP87: =IF(ISNUMBER(SEARCH("DWIGHT",D87)),1,0) | AQ87: =IF(ISNUMBER(SEARCH("GREYSTONE",D87)),1,0) | AR87: =IF(OR(Q87="3896",Q87="3557"),1,0) | AS87: =V87*W87 | AT87: =V$4*(V87-V$3) | AU87: =W$4*(W87-W$3) | AV87: =X$4*(X87-X$3) | AW87: =Y$4*(Y87-Y$3) | AX87: =Z$4*(Z87-Z$3) | AY87: =AA$4*(AA87-AA$3) | AZ87: =AB$4*(AB87-AB$3) | BA87: =AC$4*(AC87-AC$3) | ... BQ87: =AS$4*(AS87-AS$3) | BR87: =SUM(AT87:BQ87) | BS87: =INTERCEPT_SCALED+BR87 | BT87: =1/(1+EXP(-BS87)) | BU87: =1-(1-BT87)^12 | BV87: =IFERROR(AT87/BR87*(BU87-BASELINE_CPR),0) | BW87: =IFERROR(AU87/BR87*(BU87-BASELINE_CPR),0) | BX87: =IFERROR(AV87/BR87*(BU87-BASELINE_CPR),0) | BY87: =IFERROR(AW87/BR87*(BU87-BASELINE_CPR),0) | BZ87: =IFERROR(AX87/BR87*(BU87-BASELINE_CPR),0) | CA87: =IFERROR(AY87/BR87*(BU87-BASELINE_CPR),0) | CB87: =IFERROR(AZ87/BR87*(BU87-BASELINE_CPR),0) | CC87: =IFERROR(BA87/BR87*(BU87-BASELINE_CPR),0) | CD87: =IFERROR(BB87/BR87*(BU87-BASELINE_CPR),0) | CE87: =IFERROR(BC87/BR87*(BU87-BASELINE_CPR),0) | CF87: =IFERROR(BD87/BR87*(BU87-BASELINE_CPR),0) | CG87: =IFERROR(BE87/BR87*(BU87-BASELINE_CPR),0) | CH87: =IFERROR(BF87/BR87*(BU87-BASELINE_CPR),0) | CI87: =IFERROR(BG87/BR87*(BU87-BASELINE_CPR),0) | CJ87: =IFERROR(BH87/BR87*(BU87-BASELINE_CPR),0) | CK87: =IFERROR(BI87/BR87*(BU87-BASELINE_CPR),0) | CL87: =IFERROR(BJ87/BR87*(BU87-BASELINE_CPR),0) | CM87: =IFERROR(BK87/BR87*(BU87-BASELINE_CPR),0) | CN87: =IFERROR(BL87/BR87*(BU87-BASELINE_CPR),0) | CO87: =IFERROR(BM87/BR87*(BU87-BASELINE_CPR),0) | CP87: =IFERROR(BN87/BR87*(BU87-BASELINE_CPR),0) | CQ87: =IFERROR(BO87/BR87*(BU87-BASELINE_CPR),0) | CR87: =IFERROR(BP87/BR87*(BU87-BASELINE_CPR),0) | CS87: =IFERROR(BQ87/BR87*(BU87-BASELINE_CPR),0) | CT87: =BASELINE_CPR+SUM(BV87:CS87)-BU87
A88: 3618KST93_000000012911145 | B88: WALKER_POST21 | C88: 3618KST93 | D88: WALKER & DUNLOP, LLC | E88: 223f | F88: RP | G88: 2025 | H88: 202602 | I88: 69885954 | J88: 5.95 | K88: 447 | L88: 10 | M88: 7 | N88: 1 | O88: 206008 | Q88: 4080 | R88: 0 | S88: 0 | T88: 0 | U88: 0 | V88: =J88*100-K88 | W88: =L88 | X88: =MIN(M88,36) | Y88: =MIN(MAX(M88-36,0),84) | Z88: =MAX(M88-120,0) | AA88: =IF(OR(O88="",NOT(ISNUMBER(O88))),360,MAX(0,MIN(480,(INT(O88/100)-INT(VALUE(H88)/100))*12+MOD(O88,100)-MOD(VALUE(H88),100)))) | AB88: =IF(AND(AA88>0,AA88<=24),1,0) | AC88: =IF(OR(P88="",NOT(ISNUMBER(P88))),0,MAX(0,MIN(24,(INT(VALUE(H88)/100)-INT(P88/100))*12+MOD(VALUE(H88),100)-MOD(P88,100)))) | AD88: =LN(1+I88) | AE88: =IF(I88<2000000,1,0) | AF88: =IF(I88>50000000,1,0) | AG88: =IF(ISNUMBER(M88),N88/MAX(M88,1),0) | AH88: =IF(G88>=2021,1,0) | AI88: =S88 | AJ88: =T88 | AK88: =R88 | AL88: =U88 | AM88: =IF(ISNUMBER(SEARCH("CAPITAL FUNDING",D88)),1,0) | AN88: =IF(ISNUMBER(SEARCH("PNC",D88)),1,0) | AO88: =IF(ISNUMBER(SEARCH("WELLS FARGO",D88)),1,0) | AP88: =IF(ISNUMBER(SEARCH("DWIGHT",D88)),1,0) | AQ88: =IF(ISNUMBER(SEARCH("GREYSTONE",D88)),1,0) | AR88: =IF(OR(Q88="3896",Q88="3557"),1,0) | AS88: =V88*W88 | AT88: =V$4*(V88-V$3) | AU88: =W$4*(W88-W$3) | AV88: =X$4*(X88-X$3) | AW88: =Y$4*(Y88-Y$3) | AX88: =Z$4*(Z88-Z$3) | AY88: =AA$4*(AA88-AA$3) | AZ88: =AB$4*(AB88-AB$3) | BA88: =AC$4*(AC88-AC$3) | ... BQ88: =AS$4*(AS88-AS$3) | BR88: =SUM(AT88:BQ88) | BS88: =INTERCEPT_SCALED+BR88 | BT88: =1/(1+EXP(-BS88)) | BU88: =1-(1-BT88)^12 | BV88: =IFERROR(AT88/BR88*(BU88-BASELINE_CPR),0) | BW88: =IFERROR(AU88/BR88*(BU88-BASELINE_CPR),0) | BX88: =IFERROR(AV88/BR88*(BU88-BASELINE_CPR),0) | BY88: =IFERROR(AW88/BR88*(BU88-BASELINE_CPR),0) | BZ88: =IFERROR(AX88/BR88*(BU88-BASELINE_CPR),0) | CA88: =IFERROR(AY88/BR88*(BU88-BASELINE_CPR),0) | CB88: =IFERROR(AZ88/BR88*(BU88-BASELINE_CPR),0) | CC88: =IFERROR(BA88/BR88*(BU88-BASELINE_CPR),0) | CD88: =IFERROR(BB88/BR88*(BU88-BASELINE_CPR),0) | CE88: =IFERROR(BC88/BR88*(BU88-BASELINE_CPR),0) | CF88: =IFERROR(BD88/BR88*(BU88-BASELINE_CPR),0) | CG88: =IFERROR(BE88/BR88*(BU88-BASELINE_CPR),0) | CH88: =IFERROR(BF88/BR88*(BU88-BASELINE_CPR),0) | CI88: =IFERROR(BG88/BR88*(BU88-BASELINE_CPR),0) | CJ88: =IFERROR(BH88/BR88*(BU88-BASELINE_CPR),0) | CK88: =IFERROR(BI88/BR88*(BU88-BASELINE_CPR),0) | CL88: =IFERROR(BJ88/BR88*(BU88-BASELINE_CPR),0) | CM88: =IFERROR(BK88/BR88*(BU88-BASELINE_CPR),0) | CN88: =IFERROR(BL88/BR88*(BU88-BASELINE_CPR),0) | CO88: =IFERROR(BM88/BR88*(BU88-BASELINE_CPR),0) | CP88: =IFERROR(BN88/BR88*(BU88-BASELINE_CPR),0) | CQ88: =IFERROR(BO88/BR88*(BU88-BASELINE_CPR),0) | CR88: =IFERROR(BP88/BR88*(BU88-BASELINE_CPR),0) | CS88: =IFERROR(BQ88/BR88*(BU88-BASELINE_CPR),0) | CT88: =BASELINE_CPR+SUM(BV88:CS88)-BU88
A89: 3620C25U4_000000007235671 | B89: WALKER_PRE21 | C89: 3620C25U4 | D89: WALKER & DUNLOP, LLC | E89: 221d4 | F89: RP | G89: 2010 | H89: 202602 | I89: 383060.16 | J89: 4.65 | K89: 447 | L89: 0 | M89: 187 | N89: 49 | O89: 203403 | P89: 201209 | Q89: 4080 | R89: 0 | S89: 1 | T89: 0 | U89: 0 | V89: =J89*100-K89 | W89: =L89 | X89: =MIN(M89,36) | Y89: =MIN(MAX(M89-36,0),84) | Z89: =MAX(M89-120,0) | AA89: =IF(OR(O89="",NOT(ISNUMBER(O89))),360,MAX(0,MIN(480,(INT(O89/100)-INT(VALUE(H89)/100))*12+MOD(O89,100)-MOD(VALUE(H89),100)))) | AB89: =IF(AND(AA89>0,AA89<=24),1,0) | AC89: =IF(OR(P89="",NOT(ISNUMBER(P89))),0,MAX(0,MIN(24,(INT(VALUE(H89)/100)-INT(P89/100))*12+MOD(VALUE(H89),100)-MOD(P89,100)))) | AD89: =LN(1+I89) | AE89: =IF(I89<2000000,1,0) | AF89: =IF(I89>50000000,1,0) | AG89: =IF(ISNUMBER(M89),N89/MAX(M89,1),0) | AH89: =IF(G89>=2021,1,0) | AI89: =S89 | AJ89: =T89 | AK89: =R89 | AL89: =U89 | AM89: =IF(ISNUMBER(SEARCH("CAPITAL FUNDING",D89)),1,0) | AN89: =IF(ISNUMBER(SEARCH("PNC",D89)),1,0) | AO89: =IF(ISNUMBER(SEARCH("WELLS FARGO",D89)),1,0) | AP89: =IF(ISNUMBER(SEARCH("DWIGHT",D89)),1,0) | AQ89: =IF(ISNUMBER(SEARCH("GREYSTONE",D89)),1,0) | AR89: =IF(OR(Q89="3896",Q89="3557"),1,0) | AS89: =V89*W89 | AT89: =V$4*(V89-V$3) | AU89: =W$4*(W89-W$3) | AV89: =X$4*(X89-X$3) | AW89: =Y$4*(Y89-Y$3) | AX89: =Z$4*(Z89-Z$3) | AY89: =AA$4*(AA89-AA$3) | AZ89: =AB$4*(AB89-AB$3) | BA89: =AC$4*(AC89-AC$3) | ... BQ89: =AS$4*(AS89-AS$3) | BR89: =SUM(AT89:BQ89) | BS89: =INTERCEPT_SCALED+BR89 | BT89: =1/(1+EXP(-BS89)) | BU89: =1-(1-BT89)^12 | BV89: =IFERROR(AT89/BR89*(BU89-BASELINE_CPR),0) | BW89: =IFERROR(AU89/BR89*(BU89-BASELINE_CPR),0) | BX89: =IFERROR(AV89/BR89*(BU89-BASELINE_CPR),0) | BY89: =IFERROR(AW89/BR89*(BU89-BASELINE_CPR),0) | BZ89: =IFERROR(AX89/BR89*(BU89-BASELINE_CPR),0) | CA89: =IFERROR(AY89/BR89*(BU89-BASELINE_CPR),0) | CB89: =IFERROR(AZ89/BR89*(BU89-BASELINE_CPR),0) | CC89: =IFERROR(BA89/BR89*(BU89-BASELINE_CPR),0) | CD89: =IFERROR(BB89/BR89*(BU89-BASELINE_CPR),0) | CE89: =IFERROR(BC89/BR89*(BU89-BASELINE_CPR),0) | CF89: =IFERROR(BD89/BR89*(BU89-BASELINE_CPR),0) | CG89: =IFERROR(BE89/BR89*(BU89-BASELINE_CPR),0) | CH89: =IFERROR(BF89/BR89*(BU89-BASELINE_CPR),0) | CI89: =IFERROR(BG89/BR89*(BU89-BASELINE_CPR),0) | CJ89: =IFERROR(BH89/BR89*(BU89-BASELINE_CPR),0) | CK89: =IFERROR(BI89/BR89*(BU89-BASELINE_CPR),0) | CL89: =IFERROR(BJ89/BR89*(BU89-BASELINE_CPR),0) | CM89: =IFERROR(BK89/BR89*(BU89-BASELINE_CPR),0) | CN89: =IFERROR(BL89/BR89*(BU89-BASELINE_CPR),0) | CO89: =IFERROR(BM89/BR89*(BU89-BASELINE_CPR),0) | CP89: =IFERROR(BN89/BR89*(BU89-BASELINE_CPR),0) | CQ89: =IFERROR(BO89/BR89*(BU89-BASELINE_CPR),0) | CR89: =IFERROR(BP89/BR89*(BU89-BASELINE_CPR),0) | CS89: =IFERROR(BQ89/BR89*(BU89-BASELINE_CPR),0) | CT89: =BASELINE_CPR+SUM(BV89:CS89)-BU89
A90: 3620C5WG8_000000012635300 | B90: WALKER_PRE21 | C90: 3620C5WG8 | D90: WALKER & DUNLOP, LLC | E90: OTHER | F90: OTHER | G90: 2011 | H90: 202602 | I90: 1739264.1 | J90: 6.25 | K90: 447 | L90: 0 | M90: 174 | N90: 86 | O90: 205304 | P90: 201405 | Q90: 4080 | R90: 0 | S90: 0 | T90: 0 | U90: 0 | V90: =J90*100-K90 | W90: =L90 | X90: =MIN(M90,36) | Y90: =MIN(MAX(M90-36,0),84) | Z90: =MAX(M90-120,0) | AA90: =IF(OR(O90="",NOT(ISNUMBER(O90))),360,MAX(0,MIN(480,(INT(O90/100)-INT(VALUE(H90)/100))*12+MOD(O90,100)-MOD(VALUE(H90),100)))) | AB90: =IF(AND(AA90>0,AA90<=24),1,0) | AC90: =IF(OR(P90="",NOT(ISNUMBER(P90))),0,MAX(0,MIN(24,(INT(VALUE(H90)/100)-INT(P90/100))*12+MOD(VALUE(H90),100)-MOD(P90,100)))) | AD90: =LN(1+I90) | AE90: =IF(I90<2000000,1,0) | AF90: =IF(I90>50000000,1,0) | AG90: =IF(ISNUMBER(M90),N90/MAX(M90,1),0) | AH90: =IF(G90>=2021,1,0) | AI90: =S90 | AJ90: =T90 | AK90: =R90 | AL90: =U90 | AM90: =IF(ISNUMBER(SEARCH("CAPITAL FUNDING",D90)),1,0) | AN90: =IF(ISNUMBER(SEARCH("PNC",D90)),1,0) | AO90: =IF(ISNUMBER(SEARCH("WELLS FARGO",D90)),1,0) | AP90: =IF(ISNUMBER(SEARCH("DWIGHT",D90)),1,0) | AQ90: =IF(ISNUMBER(SEARCH("GREYSTONE",D90)),1,0) | AR90: =IF(OR(Q90="3896",Q90="3557"),1,0) | AS90: =V90*W90 | AT90: =V$4*(V90-V$3) | AU90: =W$4*(W90-W$3) | AV90: =X$4*(X90-X$3) | AW90: =Y$4*(Y90-Y$3) | AX90: =Z$4*(Z90-Z$3) | AY90: =AA$4*(AA90-AA$3) | AZ90: =AB$4*(AB90-AB$3) | BA90: =AC$4*(AC90-AC$3) | ... BQ90: =AS$4*(AS90-AS$3) | BR90: =SUM(AT90:BQ90) | BS90: =INTERCEPT_SCALED+BR90 | BT90: =1/(1+EXP(-BS90)) | BU90: =1-(1-BT90)^12 | BV90: =IFERROR(AT90/BR90*(BU90-BASELINE_CPR),0) | BW90: =IFERROR(AU90/BR90*(BU90-BASELINE_CPR),0) | BX90: =IFERROR(AV90/BR90*(BU90-BASELINE_CPR),0) | BY90: =IFERROR(AW90/BR90*(BU90-BASELINE_CPR),0) | BZ90: =IFERROR(AX90/BR90*(BU90-BASELINE_CPR),0) | CA90: =IFERROR(AY90/BR90*(BU90-BASELINE_CPR),0) | CB90: =IFERROR(AZ90/BR90*(BU90-BASELINE_CPR),0) | CC90: =IFERROR(BA90/BR90*(BU90-BASELINE_CPR),0) | CD90: =IFERROR(BB90/BR90*(BU90-BASELINE_CPR),0) | CE90: =IFERROR(BC90/BR90*(BU90-BASELINE_CPR),0) | CF90: =IFERROR(BD90/BR90*(BU90-BASELINE_CPR),0) | CG90: =IFERROR(BE90/BR90*(BU90-BASELINE_CPR),0) | CH90: =IFERROR(BF90/BR90*(BU90-BASELINE_CPR),0) | CI90: =IFERROR(BG90/BR90*(BU90-BASELINE_CPR),0) | CJ90: =IFERROR(BH90/BR90*(BU90-BASELINE_CPR),0) | CK90: =IFERROR(BI90/BR90*(BU90-BASELINE_CPR),0) | CL90: =IFERROR(BJ90/BR90*(BU90-BASELINE_CPR),0) | CM90: =IFERROR(BK90/BR90*(BU90-BASELINE_CPR),0) | CN90: =IFERROR(BL90/BR90*(BU90-BASELINE_CPR),0) | CO90: =IFERROR(BM90/BR90*(BU90-BASELINE_CPR),0) | CP90: =IFERROR(BN90/BR90*(BU90-BASELINE_CPR),0) | CQ90: =IFERROR(BO90/BR90*(BU90-BASELINE_CPR),0) | CR90: =IFERROR(BP90/BR90*(BU90-BASELINE_CPR),0) | CS90: =IFERROR(BQ90/BR90*(BU90-BASELINE_CPR),0) | CT90: =BASELINE_CPR+SUM(BV90:CS90)-BU90
A91: 3617F7NC6_000000012311329 | B91: WALKER_POST21 | C91: 3617F7NC6 | D91: WALKER & DUNLOP, LLC | E91: 223f | F91: RP | G91: 2022 | H91: 202602 | I91: 64446670 | J91: 4.25 | K91: 447 | L91: 7 | M91: 42 | N91: 0 | O91: 205709 | Q91: 4080 | R91: 0 | S91: 0 | T91: 0 | U91: 0 | V91: =J91*100-K91 | W91: =L91 | X91: =MIN(M91,36) | Y91: =MIN(MAX(M91-36,0),84) | Z91: =MAX(M91-120,0) | AA91: =IF(OR(O91="",NOT(ISNUMBER(O91))),360,MAX(0,MIN(480,(INT(O91/100)-INT(VALUE(H91)/100))*12+MOD(O91,100)-MOD(VALUE(H91),100)))) | AB91: =IF(AND(AA91>0,AA91<=24),1,0) | AC91: =IF(OR(P91="",NOT(ISNUMBER(P91))),0,MAX(0,MIN(24,(INT(VALUE(H91)/100)-INT(P91/100))*12+MOD(VALUE(H91),100)-MOD(P91,100)))) | AD91: =LN(1+I91) | AE91: =IF(I91<2000000,1,0) | AF91: =IF(I91>50000000,1,0) | AG91: =IF(ISNUMBER(M91),N91/MAX(M91,1),0) | AH91: =IF(G91>=2021,1,0) | AI91: =S91 | AJ91: =T91 | AK91: =R91 | AL91: =U91 | AM91: =IF(ISNUMBER(SEARCH("CAPITAL FUNDING",D91)),1,0) | AN91: =IF(ISNUMBER(SEARCH("PNC",D91)),1,0) | AO91: =IF(ISNUMBER(SEARCH("WELLS FARGO",D91)),1,0) | AP91: =IF(ISNUMBER(SEARCH("DWIGHT",D91)),1,0) | AQ91: =IF(ISNUMBER(SEARCH("GREYSTONE",D91)),1,0) | AR91: =IF(OR(Q91="3896",Q91="3557"),1,0) | AS91: =V91*W91 | AT91: =V$4*(V91-V$3) | AU91: =W$4*(W91-W$3) | AV91: =X$4*(X91-X$3) | AW91: =Y$4*(Y91-Y$3) | AX91: =Z$4*(Z91-Z$3) | AY91: =AA$4*(AA91-AA$3) | AZ91: =AB$4*(AB91-AB$3) | BA91: =AC$4*(AC91-AC$3) | ... BQ91: =AS$4*(AS91-AS$3) | BR91: =SUM(AT91:BQ91) | BS91: =INTERCEPT_SCALED+BR91 | BT91: =1/(1+EXP(-BS91)) | BU91: =1-(1-BT91)^12 | BV91: =IFERROR(AT91/BR91*(BU91-BASELINE_CPR),0) | BW91: =IFERROR(AU91/BR91*(BU91-BASELINE_CPR),0) | BX91: =IFERROR(AV91/BR91*(BU91-BASELINE_CPR),0) | BY91: =IFERROR(AW91/BR91*(BU91-BASELINE_CPR),0) | BZ91: =IFERROR(AX91/BR91*(BU91-BASELINE_CPR),0) | CA91: =IFERROR(AY91/BR91*(BU91-BASELINE_CPR),0) | CB91: =IFERROR(AZ91/BR91*(BU91-BASELINE_CPR),0) | CC91: =IFERROR(BA91/BR91*(BU91-BASELINE_CPR),0) | CD91: =IFERROR(BB91/BR91*(BU91-BASELINE_CPR),0) | CE91: =IFERROR(BC91/BR91*(BU91-BASELINE_CPR),0) | CF91: =IFERROR(BD91/BR91*(BU91-BASELINE_CPR),0) | CG91: =IFERROR(BE91/BR91*(BU91-BASELINE_CPR),0) | CH91: =IFERROR(BF91/BR91*(BU91-BASELINE_CPR),0) | CI91: =IFERROR(BG91/BR91*(BU91-BASELINE_CPR),0) | CJ91: =IFERROR(BH91/BR91*(BU91-BASELINE_CPR),0) | CK91: =IFERROR(BI91/BR91*(BU91-BASELINE_CPR),0) | CL91: =IFERROR(BJ91/BR91*(BU91-BASELINE_CPR),0) | CM91: =IFERROR(BK91/BR91*(BU91-BASELINE_CPR),0) | CN91: =IFERROR(BL91/BR91*(BU91-BASELINE_CPR),0) | CO91: =IFERROR(BM91/BR91*(BU91-BASELINE_CPR),0) | CP91: =IFERROR(BN91/BR91*(BU91-BASELINE_CPR),0) | CQ91: =IFERROR(BO91/BR91*(BU91-BASELINE_CPR),0) | CR91: =IFERROR(BP91/BR91*(BU91-BASELINE_CPR),0) | CS91: =IFERROR(BQ91/BR91*(BU91-BASELINE_CPR),0) | CT91: =BASELINE_CPR+SUM(BV91:CS91)-BU91
A92: 3618AWG40_000000008711151 | B92: WALKER_POST21 | C92: 3618AWG40 | D92: WALKER & DUNLOP, LLC | E92: 223f | F92: RP | G92: 2023 | H92: 202602 | I92: 6005643.3 | J92: 6.19 | K92: 447 | L92: 8 | M92: 28 | N92: 7 | O92: 205811 | Q92: 4080 | R92: 0 | S92: 0 | T92: 0 | U92: 0 | V92: =J92*100-K92 | W92: =L92 | X92: =MIN(M92,36) | Y92: =MIN(MAX(M92-36,0),84) | Z92: =MAX(M92-120,0) | AA92: =IF(OR(O92="",NOT(ISNUMBER(O92))),360,MAX(0,MIN(480,(INT(O92/100)-INT(VALUE(H92)/100))*12+MOD(O92,100)-MOD(VALUE(H92),100)))) | AB92: =IF(AND(AA92>0,AA92<=24),1,0) | AC92: =IF(OR(P92="",NOT(ISNUMBER(P92))),0,MAX(0,MIN(24,(INT(VALUE(H92)/100)-INT(P92/100))*12+MOD(VALUE(H92),100)-MOD(P92,100)))) | AD92: =LN(1+I92) | AE92: =IF(I92<2000000,1,0) | AF92: =IF(I92>50000000,1,0) | AG92: =IF(ISNUMBER(M92),N92/MAX(M92,1),0) | AH92: =IF(G92>=2021,1,0) | AI92: =S92 | AJ92: =T92 | AK92: =R92 | AL92: =U92 | AM92: =IF(ISNUMBER(SEARCH("CAPITAL FUNDING",D92)),1,0) | AN92: =IF(ISNUMBER(SEARCH("PNC",D92)),1,0) | AO92: =IF(ISNUMBER(SEARCH("WELLS FARGO",D92)),1,0) | AP92: =IF(ISNUMBER(SEARCH("DWIGHT",D92)),1,0) | AQ92: =IF(ISNUMBER(SEARCH("GREYSTONE",D92)),1,0) | AR92: =IF(OR(Q92="3896",Q92="3557"),1,0) | AS92: =V92*W92 | AT92: =V$4*(V92-V$3) | AU92: =W$4*(W92-W$3) | AV92: =X$4*(X92-X$3) | AW92: =Y$4*(Y92-Y$3) | AX92: =Z$4*(Z92-Z$3) | AY92: =AA$4*(AA92-AA$3) | AZ92: =AB$4*(AB92-AB$3) | BA92: =AC$4*(AC92-AC$3) | ... BQ92: =AS$4*(AS92-AS$3) | BR92: =SUM(AT92:BQ92) | BS92: =INTERCEPT_SCALED+BR92 | BT92: =1/(1+EXP(-BS92)) | BU92: =1-(1-BT92)^12 | BV92: =IFERROR(AT92/BR92*(BU92-BASELINE_CPR),0) | BW92: =IFERROR(AU92/BR92*(BU92-BASELINE_CPR),0) | BX92: =IFERROR(AV92/BR92*(BU92-BASELINE_CPR),0) | BY92: =IFERROR(AW92/BR92*(BU92-BASELINE_CPR),0) | BZ92: =IFERROR(AX92/BR92*(BU92-BASELINE_CPR),0) | CA92: =IFERROR(AY92/BR92*(BU92-BASELINE_CPR),0) | CB92: =IFERROR(AZ92/BR92*(BU92-BASELINE_CPR),0) | CC92: =IFERROR(BA92/BR92*(BU92-BASELINE_CPR),0) | CD92: =IFERROR(BB92/BR92*(BU92-BASELINE_CPR),0) | CE92: =IFERROR(BC92/BR92*(BU92-BASELINE_CPR),0) | CF92: =IFERROR(BD92/BR92*(BU92-BASELINE_CPR),0) | CG92: =IFERROR(BE92/BR92*(BU92-BASELINE_CPR),0) | CH92: =IFERROR(BF92/BR92*(BU92-BASELINE_CPR),0) | CI92: =IFERROR(BG92/BR92*(BU92-BASELINE_CPR),0) | CJ92: =IFERROR(BH92/BR92*(BU92-BASELINE_CPR),0) | CK92: =IFERROR(BI92/BR92*(BU92-BASELINE_CPR),0) | CL92: =IFERROR(BJ92/BR92*(BU92-BASELINE_CPR),0) | CM92: =IFERROR(BK92/BR92*(BU92-BASELINE_CPR),0) | CN92: =IFERROR(BL92/BR92*(BU92-BASELINE_CPR),0) | CO92: =IFERROR(BM92/BR92*(BU92-BASELINE_CPR),0) | CP92: =IFERROR(BN92/BR92*(BU92-BASELINE_CPR),0) | CQ92: =IFERROR(BO92/BR92*(BU92-BASELINE_CPR),0) | CR92: =IFERROR(BP92/BR92*(BU92-BASELINE_CPR),0) | CS92: =IFERROR(BQ92/BR92*(BU92-BASELINE_CPR),0) | CT92: =BASELINE_CPR+SUM(BV92:CS92)-BU92
A93: 3617UQN29_000000014311196 | B93: WALKER_PRE21 | C93: 3617UQN29 | D93: WALKER & DUNLOP, LLC | E93: 223f | F93: RP | G93: 2018 | H93: 202602 | I93: 39007699 | J93: 3.38 | K93: 447 | L93: 7 | M93: 88 | N93: 9 | O93: 205311 | P93: 202204 | Q93: 4080 | R93: 0 | S93: 0 | T93: 0 | U93: 0 | V93: =J93*100-K93 | W93: =L93 | X93: =MIN(M93,36) | Y93: =MIN(MAX(M93-36,0),84) | Z93: =MAX(M93-120,0) | AA93: =IF(OR(O93="",NOT(ISNUMBER(O93))),360,MAX(0,MIN(480,(INT(O93/100)-INT(VALUE(H93)/100))*12+MOD(O93,100)-MOD(VALUE(H93),100)))) | AB93: =IF(AND(AA93>0,AA93<=24),1,0) | AC93: =IF(OR(P93="",NOT(ISNUMBER(P93))),0,MAX(0,MIN(24,(INT(VALUE(H93)/100)-INT(P93/100))*12+MOD(VALUE(H93),100)-MOD(P93,100)))) | AD93: =LN(1+I93) | AE93: =IF(I93<2000000,1,0) | AF93: =IF(I93>50000000,1,0) | AG93: =IF(ISNUMBER(M93),N93/MAX(M93,1),0) | AH93: =IF(G93>=2021,1,0) | AI93: =S93 | AJ93: =T93 | AK93: =R93 | AL93: =U93 | AM93: =IF(ISNUMBER(SEARCH("CAPITAL FUNDING",D93)),1,0) | AN93: =IF(ISNUMBER(SEARCH("PNC",D93)),1,0) | AO93: =IF(ISNUMBER(SEARCH("WELLS FARGO",D93)),1,0) | AP93: =IF(ISNUMBER(SEARCH("DWIGHT",D93)),1,0) | AQ93: =IF(ISNUMBER(SEARCH("GREYSTONE",D93)),1,0) | AR93: =IF(OR(Q93="3896",Q93="3557"),1,0) | AS93: =V93*W93 | AT93: =V$4*(V93-V$3) | AU93: =W$4*(W93-W$3) | AV93: =X$4*(X93-X$3) | AW93: =Y$4*(Y93-Y$3) | AX93: =Z$4*(Z93-Z$3) | AY93: =AA$4*(AA93-AA$3) | AZ93: =AB$4*(AB93-AB$3) | BA93: =AC$4*(AC93-AC$3) | ... BQ93: =AS$4*(AS93-AS$3) | BR93: =SUM(AT93:BQ93) | BS93: =INTERCEPT_SCALED+BR93 | BT93: =1/(1+EXP(-BS93)) | BU93: =1-(1-BT93)^12 | BV93: =IFERROR(AT93/BR93*(BU93-BASELINE_CPR),0) | BW93: =IFERROR(AU93/BR93*(BU93-BASELINE_CPR),0) | BX93: =IFERROR(AV93/BR93*(BU93-BASELINE_CPR),0) | BY93: =IFERROR(AW93/BR93*(BU93-BASELINE_CPR),0) | BZ93: =IFERROR(AX93/BR93*(BU93-BASELINE_CPR),0) | CA93: =IFERROR(AY93/BR93*(BU93-BASELINE_CPR),0) | CB93: =IFERROR(AZ93/BR93*(BU93-BASELINE_CPR),0) | CC93: =IFERROR(BA93/BR93*(BU93-BASELINE_CPR),0) | CD93: =IFERROR(BB93/BR93*(BU93-BASELINE_CPR),0) | CE93: =IFERROR(BC93/BR93*(BU93-BASELINE_CPR),0) | CF93: =IFERROR(BD93/BR93*(BU93-BASELINE_CPR),0) | CG93: =IFERROR(BE93/BR93*(BU93-BASELINE_CPR),0) | CH93: =IFERROR(BF93/BR93*(BU93-BASELINE_CPR),0) | CI93: =IFERROR(BG93/BR93*(BU93-BASELINE_CPR),0) | CJ93: =IFERROR(BH93/BR93*(BU93-BASELINE_CPR),0) | CK93: =IFERROR(BI93/BR93*(BU93-BASELINE_CPR),0) | CL93: =IFERROR(BJ93/BR93*(BU93-BASELINE_CPR),0) | CM93: =IFERROR(BK93/BR93*(BU93-BASELINE_CPR),0) | CN93: =IFERROR(BL93/BR93*(BU93-BASELINE_CPR),0) | CO93: =IFERROR(BM93/BR93*(BU93-BASELINE_CPR),0) | CP93: =IFERROR(BN93/BR93*(BU93-BASELINE_CPR),0) | CQ93: =IFERROR(BO93/BR93*(BU93-BASELINE_CPR),0) | CR93: =IFERROR(BP93/BR93*(BU93-BASELINE_CPR),0) | CS93: =IFERROR(BQ93/BR93*(BU93-BASELINE_CPR),0) | CT93: =BASELINE_CPR+SUM(BV93:CS93)-BU93
A94: 3618A7L72_000000010322077 | B94: WALKER_POST21 | C94: 3618A7L72 | D94: WALKER & DUNLOP, LLC | E94: 232 | F94: RP | G94: 2022 | H94: 202602 | I94: 7367100 | J94: 5.7 | K94: 447 | L94: 7 | M94: 39 | N94: 3 | O94: 205712 | Q94: 4080 | R94: 1 | S94: 0 | T94: 0 | U94: 0 | V94: =J94*100-K94 | W94: =L94 | X94: =MIN(M94,36) | Y94: =MIN(MAX(M94-36,0),84) | Z94: =MAX(M94-120,0) | AA94: =IF(OR(O94="",NOT(ISNUMBER(O94))),360,MAX(0,MIN(480,(INT(O94/100)-INT(VALUE(H94)/100))*12+MOD(O94,100)-MOD(VALUE(H94),100)))) | AB94: =IF(AND(AA94>0,AA94<=24),1,0) | AC94: =IF(OR(P94="",NOT(ISNUMBER(P94))),0,MAX(0,MIN(24,(INT(VALUE(H94)/100)-INT(P94/100))*12+MOD(VALUE(H94),100)-MOD(P94,100)))) | AD94: =LN(1+I94) | AE94: =IF(I94<2000000,1,0) | AF94: =IF(I94>50000000,1,0) | AG94: =IF(ISNUMBER(M94),N94/MAX(M94,1),0) | AH94: =IF(G94>=2021,1,0) | AI94: =S94 | AJ94: =T94 | AK94: =R94 | AL94: =U94 | AM94: =IF(ISNUMBER(SEARCH("CAPITAL FUNDING",D94)),1,0) | AN94: =IF(ISNUMBER(SEARCH("PNC",D94)),1,0) | AO94: =IF(ISNUMBER(SEARCH("WELLS FARGO",D94)),1,0) | AP94: =IF(ISNUMBER(SEARCH("DWIGHT",D94)),1,0) | AQ94: =IF(ISNUMBER(SEARCH("GREYSTONE",D94)),1,0) | AR94: =IF(OR(Q94="3896",Q94="3557"),1,0) | AS94: =V94*W94 | AT94: =V$4*(V94-V$3) | AU94: =W$4*(W94-W$3) | AV94: =X$4*(X94-X$3) | AW94: =Y$4*(Y94-Y$3) | AX94: =Z$4*(Z94-Z$3) | AY94: =AA$4*(AA94-AA$3) | AZ94: =AB$4*(AB94-AB$3) | BA94: =AC$4*(AC94-AC$3) | ... BQ94: =AS$4*(AS94-AS$3) | BR94: =SUM(AT94:BQ94) | BS94: =INTERCEPT_SCALED+BR94 | BT94: =1/(1+EXP(-BS94)) | BU94: =1-(1-BT94)^12 | BV94: =IFERROR(AT94/BR94*(BU94-BASELINE_CPR),0) | BW94: =IFERROR(AU94/BR94*(BU94-BASELINE_CPR),0) | BX94: =IFERROR(AV94/BR94*(BU94-BASELINE_CPR),0) | BY94: =IFERROR(AW94/BR94*(BU94-BASELINE_CPR),0) | BZ94: =IFERROR(AX94/BR94*(BU94-BASELINE_CPR),0) | CA94: =IFERROR(AY94/BR94*(BU94-BASELINE_CPR),0) | CB94: =IFERROR(AZ94/BR94*(BU94-BASELINE_CPR),0) | CC94: =IFERROR(BA94/BR94*(BU94-BASELINE_CPR),0) | CD94: =IFERROR(BB94/BR94*(BU94-BASELINE_CPR),0) | CE94: =IFERROR(BC94/BR94*(BU94-BASELINE_CPR),0) | CF94: =IFERROR(BD94/BR94*(BU94-BASELINE_CPR),0) | CG94: =IFERROR(BE94/BR94*(BU94-BASELINE_CPR),0) | CH94: =IFERROR(BF94/BR94*(BU94-BASELINE_CPR),0) | CI94: =IFERROR(BG94/BR94*(BU94-BASELINE_CPR),0) | CJ94: =IFERROR(BH94/BR94*(BU94-BASELINE_CPR),0) | CK94: =IFERROR(BI94/BR94*(BU94-BASELINE_CPR),0) | CL94: =IFERROR(BJ94/BR94*(BU94-BASELINE_CPR),0) | CM94: =IFERROR(BK94/BR94*(BU94-BASELINE_CPR),0) | CN94: =IFERROR(BL94/BR94*(BU94-BASELINE_CPR),0) | CO94: =IFERROR(BM94/BR94*(BU94-BASELINE_CPR),0) | CP94: =IFERROR(BN94/BR94*(BU94-BASELINE_CPR),0) | CQ94: =IFERROR(BO94/BR94*(BU94-BASELINE_CPR),0) | CR94: =IFERROR(BP94/BR94*(BU94-BASELINE_CPR),0) | CS94: =IFERROR(BQ94/BR94*(BU94-BASELINE_CPR),0) | CT94: =BASELINE_CPR+SUM(BV94:CS94)-BU94
A95: 3617YBQV1_000000004611202 | B95: GREYSTONE_POST21 | C95: 3617YBQV1 | D95: GREYSTONE FUNDING COMPANY LLC | E95: 223f | F95: RP | G95: 2022 | H95: 202602 | I95: 6334987 | J95: 2.9 | K95: 447 | L95: 0 | M95: 47 | N95: 0 | O95: 205704 | Q95: 4168 | R95: 0 | S95: 0 | T95: 0 | U95: 0 | V95: =J95*100-K95 | W95: =L95 | X95: =MIN(M95,36) | Y95: =MIN(MAX(M95-36,0),84) | Z95: =MAX(M95-120,0) | AA95: =IF(OR(O95="",NOT(ISNUMBER(O95))),360,MAX(0,MIN(480,(INT(O95/100)-INT(VALUE(H95)/100))*12+MOD(O95,100)-MOD(VALUE(H95),100)))) | AB95: =IF(AND(AA95>0,AA95<=24),1,0) | AC95: =IF(OR(P95="",NOT(ISNUMBER(P95))),0,MAX(0,MIN(24,(INT(VALUE(H95)/100)-INT(P95/100))*12+MOD(VALUE(H95),100)-MOD(P95,100)))) | AD95: =LN(1+I95) | AE95: =IF(I95<2000000,1,0) | AF95: =IF(I95>50000000,1,0) | AG95: =IF(ISNUMBER(M95),N95/MAX(M95,1),0) | AH95: =IF(G95>=2021,1,0) | AI95: =S95 | AJ95: =T95 | AK95: =R95 | AL95: =U95 | AM95: =IF(ISNUMBER(SEARCH("CAPITAL FUNDING",D95)),1,0) | AN95: =IF(ISNUMBER(SEARCH("PNC",D95)),1,0) | AO95: =IF(ISNUMBER(SEARCH("WELLS FARGO",D95)),1,0) | AP95: =IF(ISNUMBER(SEARCH("DWIGHT",D95)),1,0) | AQ95: =IF(ISNUMBER(SEARCH("GREYSTONE",D95)),1,0) | AR95: =IF(OR(Q95="3896",Q95="3557"),1,0) | AS95: =V95*W95 | AT95: =V$4*(V95-V$3) | AU95: =W$4*(W95-W$3) | AV95: =X$4*(X95-X$3) | AW95: =Y$4*(Y95-Y$3) | AX95: =Z$4*(Z95-Z$3) | AY95: =AA$4*(AA95-AA$3) | AZ95: =AB$4*(AB95-AB$3) | BA95: =AC$4*(AC95-AC$3) | ... BQ95: =AS$4*(AS95-AS$3) | BR95: =SUM(AT95:BQ95) | BS95: =INTERCEPT_SCALED+BR95 | BT95: =1/(1+EXP(-BS95)) | BU95: =1-(1-BT95)^12 | BV95: =IFERROR(AT95/BR95*(BU95-BASELINE_CPR),0) | BW95: =IFERROR(AU95/BR95*(BU95-BASELINE_CPR),0) | BX95: =IFERROR(AV95/BR95*(BU95-BASELINE_CPR),0) | BY95: =IFERROR(AW95/BR95*(BU95-BASELINE_CPR),0) | BZ95: =IFERROR(AX95/BR95*(BU95-BASELINE_CPR),0) | CA95: =IFERROR(AY95/BR95*(BU95-BASELINE_CPR),0) | CB95: =IFERROR(AZ95/BR95*(BU95-BASELINE_CPR),0) | CC95: =IFERROR(BA95/BR95*(BU95-BASELINE_CPR),0) | CD95: =IFERROR(BB95/BR95*(BU95-BASELINE_CPR),0) | CE95: =IFERROR(BC95/BR95*(BU95-BASELINE_CPR),0) | CF95: =IFERROR(BD95/BR95*(BU95-BASELINE_CPR),0) | CG95: =IFERROR(BE95/BR95*(BU95-BASELINE_CPR),0) | CH95: =IFERROR(BF95/BR95*(BU95-BASELINE_CPR),0) | CI95: =IFERROR(BG95/BR95*(BU95-BASELINE_CPR),0) | CJ95: =IFERROR(BH95/BR95*(BU95-BASELINE_CPR),0) | CK95: =IFERROR(BI95/BR95*(BU95-BASELINE_CPR),0) | CL95: =IFERROR(BJ95/BR95*(BU95-BASELINE_CPR),0) | CM95: =IFERROR(BK95/BR95*(BU95-BASELINE_CPR),0) | CN95: =IFERROR(BL95/BR95*(BU95-BASELINE_CPR),0) | CO95: =IFERROR(BM95/BR95*(BU95-BASELINE_CPR),0) | CP95: =IFERROR(BN95/BR95*(BU95-BASELINE_CPR),0) | CQ95: =IFERROR(BO95/BR95*(BU95-BASELINE_CPR),0) | CR95: =IFERROR(BP95/BR95*(BU95-BASELINE_CPR),0) | CS95: =IFERROR(BQ95/BR95*(BU95-BASELINE_CPR),0) | CT95: =BASELINE_CPR+SUM(BV95:CS95)-BU95
A96: 3618BKU31_000000004222412 | B96: GREYSTONE_POST21 | C96: 3618BKU31 | D96: GREYSTONE FUNDING COMPANY LLC | E96: 232 | F96: RP | G96: 2023 | H96: 202602 | I96: 8313205.9 | J96: 6.09 | K96: 447 | L96: 8 | M96: 29 | N96: 5 | O96: 205810 | Q96: 4168 | R96: 1 | S96: 0 | T96: 0 | U96: 0 | V96: =J96*100-K96 | W96: =L96 | X96: =MIN(M96,36) | Y96: =MIN(MAX(M96-36,0),84) | Z96: =MAX(M96-120,0) | AA96: =IF(OR(O96="",NOT(ISNUMBER(O96))),360,MAX(0,MIN(480,(INT(O96/100)-INT(VALUE(H96)/100))*12+MOD(O96,100)-MOD(VALUE(H96),100)))) | AB96: =IF(AND(AA96>0,AA96<=24),1,0) | AC96: =IF(OR(P96="",NOT(ISNUMBER(P96))),0,MAX(0,MIN(24,(INT(VALUE(H96)/100)-INT(P96/100))*12+MOD(VALUE(H96),100)-MOD(P96,100)))) | AD96: =LN(1+I96) | AE96: =IF(I96<2000000,1,0) | AF96: =IF(I96>50000000,1,0) | AG96: =IF(ISNUMBER(M96),N96/MAX(M96,1),0) | AH96: =IF(G96>=2021,1,0) | AI96: =S96 | AJ96: =T96 | AK96: =R96 | AL96: =U96 | AM96: =IF(ISNUMBER(SEARCH("CAPITAL FUNDING",D96)),1,0) | AN96: =IF(ISNUMBER(SEARCH("PNC",D96)),1,0) | AO96: =IF(ISNUMBER(SEARCH("WELLS FARGO",D96)),1,0) | AP96: =IF(ISNUMBER(SEARCH("DWIGHT",D96)),1,0) | AQ96: =IF(ISNUMBER(SEARCH("GREYSTONE",D96)),1,0) | AR96: =IF(OR(Q96="3896",Q96="3557"),1,0) | AS96: =V96*W96 | AT96: =V$4*(V96-V$3) | AU96: =W$4*(W96-W$3) | AV96: =X$4*(X96-X$3) | AW96: =Y$4*(Y96-Y$3) | AX96: =Z$4*(Z96-Z$3) | AY96: =AA$4*(AA96-AA$3) | AZ96: =AB$4*(AB96-AB$3) | BA96: =AC$4*(AC96-AC$3) | ... BQ96: =AS$4*(AS96-AS$3) | BR96: =SUM(AT96:BQ96) | BS96: =INTERCEPT_SCALED+BR96 | BT96: =1/(1+EXP(-BS96)) | BU96: =1-(1-BT96)^12 | BV96: =IFERROR(AT96/BR96*(BU96-BASELINE_CPR),0) | BW96: =IFERROR(AU96/BR96*(BU96-BASELINE_CPR),0) | BX96: =IFERROR(AV96/BR96*(BU96-BASELINE_CPR),0) | BY96: =IFERROR(AW96/BR96*(BU96-BASELINE_CPR),0) | BZ96: =IFERROR(AX96/BR96*(BU96-BASELINE_CPR),0) | CA96: =IFERROR(AY96/BR96*(BU96-BASELINE_CPR),0) | CB96: =IFERROR(AZ96/BR96*(BU96-BASELINE_CPR),0) | CC96: =IFERROR(BA96/BR96*(BU96-BASELINE_CPR),0) | CD96: =IFERROR(BB96/BR96*(BU96-BASELINE_CPR),0) | CE96: =IFERROR(BC96/BR96*(BU96-BASELINE_CPR),0) | CF96: =IFERROR(BD96/BR96*(BU96-BASELINE_CPR),0) | CG96: =IFERROR(BE96/BR96*(BU96-BASELINE_CPR),0) | CH96: =IFERROR(BF96/BR96*(BU96-BASELINE_CPR),0) | CI96: =IFERROR(BG96/BR96*(BU96-BASELINE_CPR),0) | CJ96: =IFERROR(BH96/BR96*(BU96-BASELINE_CPR),0) | CK96: =IFERROR(BI96/BR96*(BU96-BASELINE_CPR),0) | CL96: =IFERROR(BJ96/BR96*(BU96-BASELINE_CPR),0) | CM96: =IFERROR(BK96/BR96*(BU96-BASELINE_CPR),0) | CN96: =IFERROR(BL96/BR96*(BU96-BASELINE_CPR),0) | CO96: =IFERROR(BM96/BR96*(BU96-BASELINE_CPR),0) | CP96: =IFERROR(BN96/BR96*(BU96-BASELINE_CPR),0) | CQ96: =IFERROR(BO96/BR96*(BU96-BASELINE_CPR),0) | CR96: =IFERROR(BP96/BR96*(BU96-BASELINE_CPR),0) | CS96: =IFERROR(BQ96/BR96*(BU96-BASELINE_CPR),0) | CT96: =BASELINE_CPR+SUM(BV96:CS96)-BU96
A97: 3617QKDG7_000000012335554 | B97: GREYSTONE_PRE21 | C97: 3617QKDG7 | D97: GREYSTONE FUNDING COMPANY LLC | E97: 221d4 | F97: NC | G97: 2020 | H97: 202602 | I97: 28046988 | J97: 3.25 | K97: 447 | L97: 7 | M97: 65 | N97: 0 | O97: 206209 | Q97: 4168 | R97: 0 | S97: 0 | T97: 0 | U97: 1 | V97: =J97*100-K97 | W97: =L97 | X97: =MIN(M97,36) | Y97: =MIN(MAX(M97-36,0),84) | Z97: =MAX(M97-120,0) | AA97: =IF(OR(O97="",NOT(ISNUMBER(O97))),360,MAX(0,MIN(480,(INT(O97/100)-INT(VALUE(H97)/100))*12+MOD(O97,100)-MOD(VALUE(H97),100)))) | AB97: =IF(AND(AA97>0,AA97<=24),1,0) | AC97: =IF(OR(P97="",NOT(ISNUMBER(P97))),0,MAX(0,MIN(24,(INT(VALUE(H97)/100)-INT(P97/100))*12+MOD(VALUE(H97),100)-MOD(P97,100)))) | AD97: =LN(1+I97) | AE97: =IF(I97<2000000,1,0) | AF97: =IF(I97>50000000,1,0) | AG97: =IF(ISNUMBER(M97),N97/MAX(M97,1),0) | AH97: =IF(G97>=2021,1,0) | AI97: =S97 | AJ97: =T97 | AK97: =R97 | AL97: =U97 | AM97: =IF(ISNUMBER(SEARCH("CAPITAL FUNDING",D97)),1,0) | AN97: =IF(ISNUMBER(SEARCH("PNC",D97)),1,0) | AO97: =IF(ISNUMBER(SEARCH("WELLS FARGO",D97)),1,0) | AP97: =IF(ISNUMBER(SEARCH("DWIGHT",D97)),1,0) | AQ97: =IF(ISNUMBER(SEARCH("GREYSTONE",D97)),1,0) | AR97: =IF(OR(Q97="3896",Q97="3557"),1,0) | AS97: =V97*W97 | AT97: =V$4*(V97-V$3) | AU97: =W$4*(W97-W$3) | AV97: =X$4*(X97-X$3) | AW97: =Y$4*(Y97-Y$3) | AX97: =Z$4*(Z97-Z$3) | AY97: =AA$4*(AA97-AA$3) | AZ97: =AB$4*(AB97-AB$3) | BA97: =AC$4*(AC97-AC$3) | ... BQ97: =AS$4*(AS97-AS$3) | BR97: =SUM(AT97:BQ97) | BS97: =INTERCEPT_SCALED+BR97 | BT97: =1/(1+EXP(-BS97)) | BU97: =1-(1-BT97)^12 | BV97: =IFERROR(AT97/BR97*(BU97-BASELINE_CPR),0) | BW97: =IFERROR(AU97/BR97*(BU97-BASELINE_CPR),0) | BX97: =IFERROR(AV97/BR97*(BU97-BASELINE_CPR),0) | BY97: =IFERROR(AW97/BR97*(BU97-BASELINE_CPR),0) | BZ97: =IFERROR(AX97/BR97*(BU97-BASELINE_CPR),0) | CA97: =IFERROR(AY97/BR97*(BU97-BASELINE_CPR),0) | CB97: =IFERROR(AZ97/BR97*(BU97-BASELINE_CPR),0) | CC97: =IFERROR(BA97/BR97*(BU97-BASELINE_CPR),0) | CD97: =IFERROR(BB97/BR97*(BU97-BASELINE_CPR),0) | CE97: =IFERROR(BC97/BR97*(BU97-BASELINE_CPR),0) | CF97: =IFERROR(BD97/BR97*(BU97-BASELINE_CPR),0) | CG97: =IFERROR(BE97/BR97*(BU97-BASELINE_CPR),0) | CH97: =IFERROR(BF97/BR97*(BU97-BASELINE_CPR),0) | CI97: =IFERROR(BG97/BR97*(BU97-BASELINE_CPR),0) | CJ97: =IFERROR(BH97/BR97*(BU97-BASELINE_CPR),0) | CK97: =IFERROR(BI97/BR97*(BU97-BASELINE_CPR),0) | CL97: =IFERROR(BJ97/BR97*(BU97-BASELINE_CPR),0) | CM97: =IFERROR(BK97/BR97*(BU97-BASELINE_CPR),0) | CN97: =IFERROR(BL97/BR97*(BU97-BASELINE_CPR),0) | CO97: =IFERROR(BM97/BR97*(BU97-BASELINE_CPR),0) | CP97: =IFERROR(BN97/BR97*(BU97-BASELINE_CPR),0) | CQ97: =IFERROR(BO97/BR97*(BU97-BASELINE_CPR),0) | CR97: =IFERROR(BP97/BR97*(BU97-BASELINE_CPR),0) | CS97: =IFERROR(BQ97/BR97*(BU97-BASELINE_CPR),0) | CT97: =BASELINE_CPR+SUM(BV97:CS97)-BU97
