Workbook
Name V7_BASE_SMM: Multiplier_Params!$B$5
Name V7_SMM_CAP: Multiplier_Params!$B$6
Name V7_AGE_KNOT_Y_0: Multiplier_Params!$B$9
Name V7_AGE_KNOT_Y_1: Multiplier_Params!$B$10
Name V7_AGE_KNOT_Y_2: Multiplier_Params!$B$11
Name V7_AGE_KNOT_Y_3: Multiplier_Params!$B$12
Name V7_AGE_KNOT_Y_4: Multiplier_Params!$B$13
Name V7_AGE_KNOT_Y_5: Multiplier_Params!$B$14
Name V7_AGE_KNOT_X_0: Multiplier_Params!$B$16
Name V7_AGE_KNOT_X_1: Multiplier_Params!$B$17
Name V7_AGE_KNOT_X_2: Multiplier_Params!$B$18
Name V7_AGE_KNOT_X_3: Multiplier_Params!$B$19
Name V7_AGE_KNOT_X_4: Multiplier_Params!$B$20
Name V7_AGE_KNOT_X_5: Multiplier_Params!$B$21
Name V7_RATE_FLOOR: Multiplier_Params!$B$24
Name V7_RATE_ASYMPTOTE: Multiplier_Params!$B$25
Name V7_RATE_MID: Multiplier_Params!$B$26
Name V7_RATE_SLOPE: Multiplier_Params!$B$27
Name V7_SIZE_INTERCEPT: Multiplier_Params!$B$30
Name V7_SIZE_SLOPE: Multiplier_Params!$B$31
Name V7_SIZE_LOG_ANCHOR: Multiplier_Params!$B$32
Name V7_SIZE_LOW: Multiplier_Params!$B$33
Name V7_SIZE_HIGH: Multiplier_Params!$B$34
Name V7_PURPOSE_NC_BUMP: Multiplier_Params!$B$37
Name V7_PURPOSE_PEAK_AGE: Multiplier_Params!$B$38
Name V7_PURPOSE_WIDTH: Multiplier_Params!$B$39
Name V7_LOCKOUT_AMP: Multiplier_Params!$B$42
Name V7_LOCKOUT_TAU: Multiplier_Params!$B$43
Name V7_MTY_AMP: Multiplier_Params!$B$46
Name V7_MTY_CUTOFF: Multiplier_Params!$B$47
Name V7_BURN_FLOOR: Multiplier_Params!$B$50
Name V7_BURN_SLOPE: Multiplier_Params!$B$51
Name V7_USE_ISSUER: Multiplier_Params!$B$54
Name V7_TEST_AUC: Multiplier_Params!$B$57
Name V7_TEST_LL: Multiplier_Params!$B$58
Name V7_BASE_CPR: Multiplier_Params!$B$59
Name V7_PANEL_ACTUAL: Multiplier_Params!$B$60
Name V7_MAX_CPR: Multiplier_Params!$B$61
Name V7_PROGRAM_TABLE: Lookups!$A$5:$B$9
Name V7_PROGRAM_DEFAULT: Lookups!$B$9
Name V7_ISSUER_TABLE: Lookups!$E$5:$G$34

Sheet README
A1: V7 Voluntary Prepayment Calculator (multiplicative)
A3: Test AUC: 0.7788 Test log-loss: 0.04232 Free params: 27
A4: Training period: 201812 to 202602
A5: Training events: 7,686 prepays in 982,361 loan-months
A6: Max predicted CPR over full panel: 85.78% (SMM cap: 0.150)
A8: Architecture
A9: predicted_SMM = MIN(base_SMM × M_age × M_rate × M_size × M_program
A10: × M_purpose × M_lockout × M_maturity × M_burnout, smm_cap)
A11: M_rate input = net_refi_bps = gross_refi_bps - 12.5 × (ppp + 1) ← penalty bp-deductible
A12: predicted_CPR = 1 - (1 - predicted_SMM)^12
A14: Tabs
A15: Multiplier_Params - 9 multipliers + base_SMM + smm_cap, all parameters editable
... A32: base_CPR + SUM(attribution) - pred_CPR should be ≈ 0 (within rounding).

Sheet Multiplier_Params
A1: V7 Multiplier Parameters (edit at your own risk)
A2: Each cell is referenced by name from Loan_Snapshot formulas. Editing cascades through.
A4: Global
A5: base_SMM | B5: 0.0047133357
A6: smm_cap | B6: 0.15
A8: M_age (piecewise linear, 6 knots)
A9: knot 0: x = 0m → y | B9: 0.32039612
A10: knot 1: x = 12m → y | B10: 0.31570379
A11: knot 2: x = 36m → y | B11: 0.78253442
A12: knot 3: x = 96m → y | B12: 1.3960385
A13: knot 4: x = 180m → y | B13: 0.93148749
A14: knot 5: x = 360m → y | B14: 2.4223914
A15: (knot_x values, frozen)
A16: knot_x_0 | B16: 0
A17: knot_x_1 | B17: 12
A18: knot_x_2 | B18: 36
A19: knot_x_3 | B19: 96
A20: knot_x_4 | B20: 180
A21: knot_x_5 | B21: 360
A23: M_rate (sigmoid: floor + asymp/(1+exp(-(grf-mid)/slope)))
A24: floor | B24: 0.1615701
A25: asymptote | B25: 3.8774187
A26: mid (bp) | B26: 126.9326
A27: slope | B27: 95.706567
A29: M_size (smooth log on log_upb)
A30: intercept | B30: 0.64209336
A31: slope | B31: 0.44603609
A32: log_upb_anchor | B32: 14.508658
A33: low (clip) | B33: 0.39384537
A34: high (clip) | B34: 1.4178433
A36: M_purpose (NC triangular hump centered at peak_age)
A37: NC_bump | B37: 1.0454057
A38: peak_age | B38: 39.478259
A39: width | B39: 14.478228
A41: M_lockout (1 + amp*exp(-msle/tau) for msle ∈ (0,12])
A42: amplitude | B42: 4
A43: tau | B43: 1.7552982
A45: M_maturity (1 + amp*max(0, (cutoff-mtm)/cutoff))
A46: amplitude | B46: 8
A47: cutoff | B47: 12.309808
A49: M_burnout (max(floor, 1 - slope*burn_ratio))
A50: floor | B50: 0.5
A51: slope | B51: -4.0287037
A53: Issuer overlay toggle (0=off, 1=on)
A54: USE_ISSUER_OVERLAY | B54: 0
A56: Diagnostics (read-only)
A57: test_AUC | B57: 0.7787803
A58: test_log_loss | B58: 0.0423181
A59: base_CPR | B59: 0.055117
A60: panel_actual_CPR | B60: 0.089951
A61: max_pred_CPR (full panel) | B61: 0.8578

Sheet Lookups
A1: Categorical multiplier lookups
A3: M_program | E3: Issuer overlay (residual ratio)
A4: fha_pattern | B4: multiplier | E4: issuer_number | F4: issuer_name | G4: residual_ratio | H4: n
A5: 232 | B5: 0.90657311 | E5: 3896 | F5: RED MORTGAGE CAPITAL, LLC. | G5: 1.0443 | H5: 205895
A6: 538 | B6: 0.7081221 | E6: 4082 | F6: BERKADIA COMMERCIAL MORTGAGE, LLC | G6: 1.0002 | H6: 106649
A7: 223a7 | B7: 1.0737735 | E7: 4080 | F7: WALKER & DUNLOP, LLC | G7: 1.0311 | H7: 87217
A8: 223f | B8: 1.1183599 | E8: 4168 | F8: GREYSTONE FUNDING COMPANY LLC | G8: 1.5597 | H8: 59556
A9: default | B9: 0.95239057 | E9: 3487 | F9: MERCHANTS CAPITAL CORP. | G9: 0.8934 | H9: 59501
E10: 3998 | F10: WELLS FARGO MULTIFAMILY CAPITAL | G10: 0.8828 | H10: 53686
E11: 3976 | F11: PNC BANK, NA | G11: 0.6567 | H11: 44978
E12: 3866 | F12: CAPITAL FUNDING,LLC. | G12: 0.6435 | H12: 41909
E13: 3153 | F13: PRUDENTIAL HUNTOON PAIGE ASSOCIATES, LLC | G13: 0.9495 | H13: 38806
E14: 4398 | F14: DWIGHT CAPITAL LLC | G14: 1.4887 | H14: 38790
E15: 4012 | F15: BONNEVILLE MORTGAGE COMPANY | G15: 0.9212 | H15: 35248
E16: 4271 | F16: KEYBANK NATIONAL ASSOCIATION | G16: 1.1486 | H16: 32397
E17: 4067 | F17: BELLWETHER ENTERPRISE REAL ESTATE CAPITA | G17: 0.4723 | H17: 27200
E18: 3995 | F18: DOUGHERTY MORTGAGE, LLC | G18: 0.8276 | H18: 25918
E19: 2045 | F19: GERSHMAN INVESTMENT CORP. | G19: 1.7986 | H19: 24926
E20: 4065 | F20: JONES LANG LASALLE MULTIFAMILY LLC | G20: 1.3379 | H20: 24725
E21: 4300 | F21: MIDLAND STATES BANK | G21: 1.019 | H21: 23852
... E34: 2973 | F34: DAVIS-PENN MORTGAGE CO. | G34: 1.105 | H34: 9340

Sheet Loan_Snapshot
A1: Loan Identifiers | I1: Raw Inputs (editable) | T1: Derived inputs (formulas) | W1: V7 Multipliers (formulas) | AF1: Pred SMM/CPR | AI1: Per-multiplier attribution | AQ1: Check
A2: loan_id | B2: deal_id | C2: pool_cusip | D2: issuer_name | E2: fha_category | F2: loan_purpose | G2: vintage_year | H2: period | I2: upb | J2: loan_rate_pct | K2: plc_rate_bps | L2: prepay_penalty_points | M2: loan_age_months | N2: cum_itm | O2: loan_maturity_yyyymm | P2: lockout_end_yyyymm | Q2: issuer_number | R2: burn_ratio_in | S2: is_NC_in | T2: log_upb | U2: gross_refi_bps | V2: net_refi_bps | W2: M_age | X2: M_rate | Y2: M_size | Z2: M_program | AA2: M_purpose | AB2: M_lockout | AC2: M_maturity | AD2: M_burnout | AE2: M_issuer | AF2: product | AG2: capped_SMM | AH2: pred_CPR | AI2: attr_M_age | AJ2: attr_M_rate | AK2: attr_M_size | AL2: attr_M_program | AM2: attr_M_purpose | AN2: attr_M_lockout | AO2: attr_M_maturity | AP2: attr_M_burnout | AQ2: Sanity
A3: 3617UAX72_000000012211373 | B3: LUMENT_PRE21 | C3: 3617UAX72 | D3: LUMENT REAL ESTATE CAPITAL,LLC | E3: 223f | F3: RP | G3: 2015 | H3: 202602 | I3: 4746336.8 | J3: 2.96 | K3: 447 | L3: 5 | M3: 122 | N3: 1 | O3: 205101 | Q3: 3896 | R3: 0.0081967213 | S3: 0 | T3: =LN(1+I3) | U3: =J3*100-K3 | V3: =U3-12.5*(L3+1) | W3: =IF(M3<=V7_AGE_KNOT_X_0,V7_AGE_KNOT_Y_0,IF(M3>=V7_AGE_KNOT_X_5,V7_AGE_KNOT_Y_5,IF(M3<=V7_AGE_KNOT_X_1,V7_AGE_KNOT_Y_0+(M3-V7_AGE_KNOT_X_0)/(V7_AGE_KNOT_X_1-V7_AGE_KNOT_X_0)*(V7_AGE_KNOT_Y_1-V7_AGE_KNOT_Y_0),IF(M3<=V7_AGE_KNOT_X_2,V7_AGE_KNOT_Y_1+(M3-V7_AGE_KNOT_X_1)/(V7_AGE_KNOT_X_2-V7_AGE_KNOT_X_1)*(V7_AGE_KNOT_Y_2-V7_AGE_KNOT_Y_1),IF(M3<=V7_AGE_KNOT_X_3,V7_AGE_KNOT_Y_2+(M3-V7_AGE_KNOT_X_2)/(V7_AGE_KNOT_X_3-V7_AGE_KNOT_X_2)*(V7_AGE_KNOT_Y_3-V7_AGE_KNOT_Y_2),IF(M3<=V7_AGE_KNOT_X_4,V7_AGE_KNOT_Y_3+(M3-V7_AGE_KNOT_X_3)/(V7_AGE_KNOT_X_4-V7_AGE_KNOT_X_3)*(V7_AGE_KNOT_Y_4-V7_AGE_KNOT_Y_3),V7_AGE_KNOT_Y_4+(M3-V7_AGE_KNOT_X_4)/(V7_AGE_KNOT_X_5-V7_AGE_KNOT_X_4)*(V7_AGE_KNOT_Y_5-V7_AGE_KNOT_Y_4))))))) | X3: =V7_RATE_FLOOR+V7_RATE_ASYMPTOTE/(1+EXP(-(V3-V7_RATE_MID)/V7_RATE_SLOPE)) | Y3: =MAX(V7_SIZE_LOW,MIN(V7_SIZE_HIGH,V7_SIZE_INTERCEPT+V7_SIZE_SLOPE*(T3-V7_SIZE_LOG_ANCHOR))) | Z3: =IF(ISNUMBER(SEARCH("232",E3)),VLOOKUP("232",V7_PROGRAM_TABLE,2,FALSE),IF(ISNUMBER(SEARCH("538",E3)),VLOOKUP("538",V7_PROGRAM_TABLE,2,FALSE),IF(ISNUMBER(SEARCH("223a7",E3)),VLOOKUP("223a7",V7_PROGRAM_TABLE,2,FALSE),IF(ISNUMBER(SEARCH("223f",E3)),VLOOKUP("223f",V7_PROGRAM_TABLE,2,FALSE),V7_PROGRAM_DEFAULT)))) | AA3: =IF(S3=1,1+V7_PURPOSE_NC_BUMP*MAX(0,1-ABS(M3-V7_PURPOSE_PEAK_AGE)/V7_PURPOSE_WIDTH),1) | AB3: =IF(AND(IF(OR(P3="",NOT(ISNUMBER(P3))),0,MAX(0,MIN(24,(INT(VALUE(H3)/100)-INT(P3/100))*12+MOD(VALUE(H3),100)-MOD(P3,100))))>0,IF(OR(P3="",NOT(ISNUMBER(P3))),0,MAX(0,MIN(24,(INT(VALUE(H3)/100)-INT(P3/100))*12+MOD(VALUE(H3),100)-MOD(P3,100))))<=12),1+V7_LOCKOUT_AMP*EXP(-(IF(OR(P3="",NOT(ISNUMBER(P3))),0,MAX(0,MIN(24,(INT(VALUE(H3)/100)-INT(P3/100))*12+MOD(VALUE(H3),100)-MOD(P3,100)))))/V7_LOCKOUT_TAU),1) | AC3: =IF(IF(OR(O3="",NOT(ISNUMBER(O3))),360,MAX(0,MIN(480,(INT(O3/100)-INT(VALUE(H3)/100))*12+MOD(O3,100)-MOD(VALUE(H3),100))))>0,1+V7_MTY_AMP*MAX(0,(V7_MTY_CUTOFF-(IF(OR(O3="",NOT(ISNUMBER(O3))),360,MAX(0,MIN(480,(INT(O3/100)-INT(VALUE(H3)/100))*12+MOD(O3,100)-MOD(VALUE(H3),100))))))/V7_MTY_CUTOFF),1) | AD3: =MAX(V7_BURN_FLOOR,1-V7_BURN_SLOPE*MIN(1,MAX(0,R3))) | AE3: =IF(V7_USE_ISSUER=1,IFERROR(VLOOKUP(Q3,V7_ISSUER_TABLE,3,FALSE),1),1) | AF3: =PRODUCT(W3:AE3) | AG3: =MIN(V7_BASE_SMM*AF3,V7_SMM_CAP) | AH3: =1-(1-AG3)^12 | AI3: =IFERROR(LN(W3)/(LN(W3)+LN(X3)+LN(Y3)+LN(Z3)+LN(AA3)+LN(AB3)+LN(AC3)+LN(AD3))*(AH3-V7_BASE_CPR),0) | AJ3: =IFERROR(LN(X3)/(LN(W3)+LN(X3)+LN(Y3)+LN(Z3)+LN(AA3)+LN(AB3)+LN(AC3)+LN(AD3))*(AH3-V7_BASE_CPR),0) | AK3: =IFERROR(LN(Y3)/(LN(W3)+LN(X3)+LN(Y3)+LN(Z3)+LN(AA3)+LN(AB3)+LN(AC3)+LN(AD3))*(AH3-V7_BASE_CPR),0) | AL3: =IFERROR(LN(Z3)/(LN(W3)+LN(X3)+LN(Y3)+LN(Z3)+LN(AA3)+LN(AB3)+LN(AC3)+LN(AD3))*(AH3-V7_BASE_CPR),0) | AM3: =IFERROR(LN(AA3)/(LN(W3)+LN(X3)+LN(Y3)+LN(Z3)+LN(AA3)+LN(AB3)+LN(AC3)+LN(AD3))*(AH3-V7_BASE_CPR),0) | AN3: =IFERROR(LN(AB3)/(LN(W3)+LN(X3)+LN(Y3)+LN(Z3)+LN(AA3)+LN(AB3)+LN(AC3)+LN(AD3))*(AH3-V7_BASE_CPR),0) | AO3: =IFERROR(LN(AC3)/(LN(W3)+LN(X3)+LN(Y3)+LN(Z3)+LN(AA3)+LN(AB3)+LN(AC3)+LN(AD3))*(AH3-V7_BASE_CPR),0) | AP3: =IFERROR(LN(AD3)/(LN(W3)+LN(X3)+LN(Y3)+LN(Z3)+LN(AA3)+LN(AB3)+LN(AC3)+LN(AD3))*(AH3-V7_BASE_CPR),0) | AQ3: =V7_BASE_CPR+SUM(AI3:AP3)-AH3
A4: 3617H4UL3_000000012322093 | B4: LUMENT_PRE21 | C4: 3617H4UL3 | D4: LUMENT REAL ESTATE CAPITAL,LLC | E4: 232 | F4: RP | G4: 2018 | H4: 202602 | I4: 11482585 | J4: 4.35 | K4: 447 | L4: 0 | M4: 91 | N4: 35 | O4: 205308 | Q4: 3896 | R4: 0.38461538 | S4: 0 | T4: =LN(1+I4) | U4: =J4*100-K4 | V4: =U4-12.5*(L4+1) | W4: =IF(M4<=V7_AGE_KNOT_X_0,V7_AGE_KNOT_Y_0,IF(M4>=V7_AGE_KNOT_X_5,V7_AGE_KNOT_Y_5,IF(M4<=V7_AGE_KNOT_X_1,V7_AGE_KNOT_Y_0+(M4-V7_AGE_KNOT_X_0)/(V7_AGE_KNOT_X_1-V7_AGE_KNOT_X_0)*(V7_AGE_KNOT_Y_1-V7_AGE_KNOT_Y_0),IF(M4<=V7_AGE_KNOT_X_2,V7_AGE_KNOT_Y_1+(M4-V7_AGE_KNOT_X_1)/(V7_AGE_KNOT_X_2-V7_AGE_KNOT_X_1)*(V7_AGE_KNOT_Y_2-V7_AGE_KNOT_Y_1),IF(M4<=V7_AGE_KNOT_X_3,V7_AGE_KNOT_Y_2+(M4-V7_AGE_KNOT_X_2)/(V7_AGE_KNOT_X_3-V7_AGE_KNOT_X_2)*(V7_AGE_KNOT_Y_3-V7_AGE_KNOT_Y_2),IF(M4<=V7_AGE_KNOT_X_4,V7_AGE_KNOT_Y_3+(M4-V7_AGE_KNOT_X_3)/(V7_AGE_KNOT_X_4-V7_AGE_KNOT_X_3)*(V7_AGE_KNOT_Y_4-V7_AGE_KNOT_Y_3),V7_AGE_KNOT_Y_4+(M4-V7_AGE_KNOT_X_4)/(V7_AGE_KNOT_X_5-V7_AGE_KNOT_X_4)*(V7_AGE_KNOT_Y_5-V7_AGE_KNOT_Y_4))))))) | X4: =V7_RATE_FLOOR+V7_RATE_ASYMPTOTE/(1+EXP(-(V4-V7_RATE_MID)/V7_RATE_SLOPE)) | Y4: =MAX(V7_SIZE_LOW,MIN(V7_SIZE_HIGH,V7_SIZE_INTERCEPT+V7_SIZE_SLOPE*(T4-V7_SIZE_LOG_ANCHOR))) | Z4: =IF(ISNUMBER(SEARCH("232",E4)),VLOOKUP("232",V7_PROGRAM_TABLE,2,FALSE),IF(ISNUMBER(SEARCH("538",E4)),VLOOKUP("538",V7_PROGRAM_TABLE,2,FALSE),IF(ISNUMBER(SEARCH("223a7",E4)),VLOOKUP("223a7",V7_PROGRAM_TABLE,2,FALSE),IF(ISNUMBER(SEARCH("223f",E4)),VLOOKUP("223f",V7_PROGRAM_TABLE,2,FALSE),V7_PROGRAM_DEFAULT)))) | AA4: =IF(S4=1,1+V7_PURPOSE_NC_BUMP*MAX(0,1-ABS(M4-V7_PURPOSE_PEAK_AGE)/V7_PURPOSE_WIDTH),1) | AB4: =IF(AND(IF(OR(P4="",NOT(ISNUMBER(P4))),0,MAX(0,MIN(24,(INT(VALUE(H4)/100)-INT(P4/100))*12+MOD(VALUE(H4),100)-MOD(P4,100))))>0,IF(OR(P4="",NOT(ISNUMBER(P4))),0,MAX(0,MIN(24,(INT(VALUE(H4)/100)-INT(P4/100))*12+MOD(VALUE(H4),100)-MOD(P4,100))))<=12),1+V7_LOCKOUT_AMP*EXP(-(IF(OR(P4="",NOT(ISNUMBER(P4))),0,MAX(0,MIN(24,(INT(VALUE(H4)/100)-INT(P4/100))*12+MOD(VALUE(H4),100)-MOD(P4,100)))))/V7_LOCKOUT_TAU),1) | AC4: =IF(IF(OR(O4="",NOT(ISNUMBER(O4))),360,MAX(0,MIN(480,(INT(O4/100)-INT(VALUE(H4)/100))*12+MOD(O4,100)-MOD(VALUE(H4),100))))>0,1+V7_MTY_AMP*MAX(0,(V7_MTY_CUTOFF-(IF(OR(O4="",NOT(ISNUMBER(O4))),360,MAX(0,MIN(480,(INT(O4/100)-INT(VALUE(H4)/100))*12+MOD(O4,100)-MOD(VALUE(H4),100))))))/V7_MTY_CUTOFF),1) | AD4: =MAX(V7_BURN_FLOOR,1-V7_BURN_SLOPE*MIN(1,MAX(0,R4))) | AE4: =IF(V7_USE_ISSUER=1,IFERROR(VLOOKUP(Q4,V7_ISSUER_TABLE,3,FALSE),1),1) | AF4: =PRODUCT(W4:AE4) | AG4: =MIN(V7_BASE_SMM*AF4,V7_SMM_CAP) | AH4: =1-(1-AG4)^12 | AI4: =IFERROR(LN(W4)/(LN(W4)+LN(X4)+LN(Y4)+LN(Z4)+LN(AA4)+LN(AB4)+LN(AC4)+LN(AD4))*(AH4-V7_BASE_CPR),0) | AJ4: =IFERROR(LN(X4)/(LN(W4)+LN(X4)+LN(Y4)+LN(Z4)+LN(AA4)+LN(AB4)+LN(AC4)+LN(AD4))*(AH4-V7_BASE_CPR),0) | AK4: =IFERROR(LN(Y4)/(LN(W4)+LN(X4)+LN(Y4)+LN(Z4)+LN(AA4)+LN(AB4)+LN(AC4)+LN(AD4))*(AH4-V7_BASE_CPR),0) | AL4: =IFERROR(LN(Z4)/(LN(W4)+LN(X4)+LN(Y4)+LN(Z4)+LN(AA4)+LN(AB4)+LN(AC4)+LN(AD4))*(AH4-V7_BASE_CPR),0) | AM4: =IFERROR(LN(AA4)/(LN(W4)+LN(X4)+LN(Y4)+LN(Z4)+LN(AA4)+LN(AB4)+LN(AC4)+LN(AD4))*(AH4-V7_BASE_CPR),0) | AN4: =IFERROR(LN(AB4)/(LN(W4)+LN(X4)+LN(Y4)+LN(Z4)+LN(AA4)+LN(AB4)+LN(AC4)+LN(AD4))*(AH4-V7_BASE_CPR),0) | AO4: =IFERROR(LN(AC4)/(LN(W4)+LN(X4)+LN(Y4)+LN(Z4)+LN(AA4)+LN(AB4)+LN(AC4)+LN(AD4))*(AH4-V7_BASE_CPR),0) | AP4: =IFERROR(LN(AD4)/(LN(W4)+LN(X4)+LN(Y4)+LN(Z4)+LN(AA4)+LN(AB4)+LN(AC4)+LN(AD4))*(AH4-V7_BASE_CPR),0) | AQ4: =V7_BASE_CPR+SUM(AI4:AP4)-AH4
A5: 3617QRGV6_000000002311435 | B5: LUMENT_PRE21 | C5: 3617QRGV6 | D5: LUMENT REAL ESTATE CAPITAL,LLC | E5: 223f | F5: RP | G5: 2017 | H5: 202602 | I5: 13751711 | J5: 3.15 | K5: 447 | L5: 5 | M5: 106 | N5: 9 | O5: 205205 | Q5: 3896 | R5: 0.08490566 | S5: 0 | T5: =LN(1+I5) | U5: =J5*100-K5 | V5: =U5-12.5*(L5+1) | W5: =IF(M5<=V7_AGE_KNOT_X_0,V7_AGE_KNOT_Y_0,IF(M5>=V7_AGE_KNOT_X_5,V7_AGE_KNOT_Y_5,IF(M5<=V7_AGE_KNOT_X_1,V7_AGE_KNOT_Y_0+(M5-V7_AGE_KNOT_X_0)/(V7_AGE_KNOT_X_1-V7_AGE_KNOT_X_0)*(V7_AGE_KNOT_Y_1-V7_AGE_KNOT_Y_0),IF(M5<=V7_AGE_KNOT_X_2,V7_AGE_KNOT_Y_1+(M5-V7_AGE_KNOT_X_1)/(V7_AGE_KNOT_X_2-V7_AGE_KNOT_X_1)*(V7_AGE_KNOT_Y_2-V7_AGE_KNOT_Y_1),IF(M5<=V7_AGE_KNOT_X_3,V7_AGE_KNOT_Y_2+(M5-V7_AGE_KNOT_X_2)/(V7_AGE_KNOT_X_3-V7_AGE_KNOT_X_2)*(V7_AGE_KNOT_Y_3-V7_AGE_KNOT_Y_2),IF(M5<=V7_AGE_KNOT_X_4,V7_AGE_KNOT_Y_3+(M5-V7_AGE_KNOT_X_3)/(V7_AGE_KNOT_X_4-V7_AGE_KNOT_X_3)*(V7_AGE_KNOT_Y_4-V7_AGE_KNOT_Y_3),V7_AGE_KNOT_Y_4+(M5-V7_AGE_KNOT_X_4)/(V7_AGE_KNOT_X_5-V7_AGE_KNOT_X_4)*(V7_AGE_KNOT_Y_5-V7_AGE_KNOT_Y_4))))))) | X5: =V7_RATE_FLOOR+V7_RATE_ASYMPTOTE/(1+EXP(-(V5-V7_RATE_MID)/V7_RATE_SLOPE)) | Y5: =MAX(V7_SIZE_LOW,MIN(V7_SIZE_HIGH,V7_SIZE_INTERCEPT+V7_SIZE_SLOPE*(T5-V7_SIZE_LOG_ANCHOR))) | Z5: =IF(ISNUMBER(SEARCH("232",E5)),VLOOKUP("232",V7_PROGRAM_TABLE,2,FALSE),IF(ISNUMBER(SEARCH("538",E5)),VLOOKUP("538",V7_PROGRAM_TABLE,2,FALSE),IF(ISNUMBER(SEARCH("223a7",E5)),VLOOKUP("223a7",V7_PROGRAM_TABLE,2,FALSE),IF(ISNUMBER(SEARCH("223f",E5)),VLOOKUP("223f",V7_PROGRAM_TABLE,2,FALSE),V7_PROGRAM_DEFAULT)))) | AA5: =IF(S5=1,1+V7_PURPOSE_NC_BUMP*MAX(0,1-ABS(M5-V7_PURPOSE_PEAK_AGE)/V7_PURPOSE_WIDTH),1) | AB5: =IF(AND(IF(OR(P5="",NOT(ISNUMBER(P5))),0,MAX(0,MIN(24,(INT(VALUE(H5)/100)-INT(P5/100))*12+MOD(VALUE(H5),100)-MOD(P5,100))))>0,IF(OR(P5="",NOT(ISNUMBER(P5))),0,MAX(0,MIN(24,(INT(VALUE(H5)/100)-INT(P5/100))*12+MOD(VALUE(H5),100)-MOD(P5,100))))<=12),1+V7_LOCKOUT_AMP*EXP(-(IF(OR(P5="",NOT(ISNUMBER(P5))),0,MAX(0,MIN(24,(INT(VALUE(H5)/100)-INT(P5/100))*12+MOD(VALUE(H5),100)-MOD(P5,100)))))/V7_LOCKOUT_TAU),1) | AC5: =IF(IF(OR(O5="",NOT(ISNUMBER(O5))),360,MAX(0,MIN(480,(INT(O5/100)-INT(VALUE(H5)/100))*12+MOD(O5,100)-MOD(VALUE(H5),100))))>0,1+V7_MTY_AMP*MAX(0,(V7_MTY_CUTOFF-(IF(OR(O5="",NOT(ISNUMBER(O5))),360,MAX(0,MIN(480,(INT(O5/100)-INT(VALUE(H5)/100))*12+MOD(O5,100)-MOD(VALUE(H5),100))))))/V7_MTY_CUTOFF),1) | AD5: =MAX(V7_BURN_FLOOR,1-V7_BURN_SLOPE*MIN(1,MAX(0,R5))) | AE5: =IF(V7_USE_ISSUER=1,IFERROR(VLOOKUP(Q5,V7_ISSUER_TABLE,3,FALSE),1),1) | AF5: =PRODUCT(W5:AE5) | AG5: =MIN(V7_BASE_SMM*AF5,V7_SMM_CAP) | AH5: =1-(1-AG5)^12 | AI5: =IFERROR(LN(W5)/(LN(W5)+LN(X5)+LN(Y5)+LN(Z5)+LN(AA5)+LN(AB5)+LN(AC5)+LN(AD5))*(AH5-V7_BASE_CPR),0) | AJ5: =IFERROR(LN(X5)/(LN(W5)+LN(X5)+LN(Y5)+LN(Z5)+LN(AA5)+LN(AB5)+LN(AC5)+LN(AD5))*(AH5-V7_BASE_CPR),0) | AK5: =IFERROR(LN(Y5)/(LN(W5)+LN(X5)+LN(Y5)+LN(Z5)+LN(AA5)+LN(AB5)+LN(AC5)+LN(AD5))*(AH5-V7_BASE_CPR),0) | AL5: =IFERROR(LN(Z5)/(LN(W5)+LN(X5)+LN(Y5)+LN(Z5)+LN(AA5)+LN(AB5)+LN(AC5)+LN(AD5))*(AH5-V7_BASE_CPR),0) | AM5: =IFERROR(LN(AA5)/(LN(W5)+LN(X5)+LN(Y5)+LN(Z5)+LN(AA5)+LN(AB5)+LN(AC5)+LN(AD5))*(AH5-V7_BASE_CPR),0) | AN5: =IFERROR(LN(AB5)/(LN(W5)+LN(X5)+LN(Y5)+LN(Z5)+LN(AA5)+LN(AB5)+LN(AC5)+LN(AD5))*(AH5-V7_BASE_CPR),0) | AO5: =IFERROR(LN(AC5)/(LN(W5)+LN(X5)+LN(Y5)+LN(Z5)+LN(AA5)+LN(AB5)+LN(AC5)+LN(AD5))*(AH5-V7_BASE_CPR),0) | AP5: =IFERROR(LN(AD5)/(LN(W5)+LN(X5)+LN(Y5)+LN(Z5)+LN(AA5)+LN(AB5)+LN(AC5)+LN(AD5))*(AH5-V7_BASE_CPR),0) | AQ5: =V7_BASE_CPR+SUM(AI5:AP5)-AH5
A6: 3617GAE46_000000007122391 | B6: LUMENT_PRE21 | C6: 3617GAE46 | D6: LUMENT REAL ESTATE CAPITAL,LLC | E6: 232 | F6: RP | G6: 2018 | H6: 202602 | I6: 9767084.7 | J6: 3.58 | K6: 447 | L6: 4 | M6: 95 | N6: 27 | O6: 205304 | Q6: 3896 | R6: 0.28421053 | S6: 0 | T6: =LN(1+I6) | U6: =J6*100-K6 | V6: =U6-12.5*(L6+1) | W6: =IF(M6<=V7_AGE_KNOT_X_0,V7_AGE_KNOT_Y_0,IF(M6>=V7_AGE_KNOT_X_5,V7_AGE_KNOT_Y_5,IF(M6<=V7_AGE_KNOT_X_1,V7_AGE_KNOT_Y_0+(M6-V7_AGE_KNOT_X_0)/(V7_AGE_KNOT_X_1-V7_AGE_KNOT_X_0)*(V7_AGE_KNOT_Y_1-V7_AGE_KNOT_Y_0),IF(M6<=V7_AGE_KNOT_X_2,V7_AGE_KNOT_Y_1+(M6-V7_AGE_KNOT_X_1)/(V7_AGE_KNOT_X_2-V7_AGE_KNOT_X_1)*(V7_AGE_KNOT_Y_2-V7_AGE_KNOT_Y_1),IF(M6<=V7_AGE_KNOT_X_3,V7_AGE_KNOT_Y_2+(M6-V7_AGE_KNOT_X_2)/(V7_AGE_KNOT_X_3-V7_AGE_KNOT_X_2)*(V7_AGE_KNOT_Y_3-V7_AGE_KNOT_Y_2),IF(M6<=V7_AGE_KNOT_X_4,V7_AGE_KNOT_Y_3+(M6-V7_AGE_KNOT_X_3)/(V7_AGE_KNOT_X_4-V7_AGE_KNOT_X_3)*(V7_AGE_KNOT_Y_4-V7_AGE_KNOT_Y_3),V7_AGE_KNOT_Y_4+(M6-V7_AGE_KNOT_X_4)/(V7_AGE_KNOT_X_5-V7_AGE_KNOT_X_4)*(V7_AGE_KNOT_Y_5-V7_AGE_KNOT_Y_4))))))) | X6: =V7_RATE_FLOOR+V7_RATE_ASYMPTOTE/(1+EXP(-(V6-V7_RATE_MID)/V7_RATE_SLOPE)) | Y6: =MAX(V7_SIZE_LOW,MIN(V7_SIZE_HIGH,V7_SIZE_INTERCEPT+V7_SIZE_SLOPE*(T6-V7_SIZE_LOG_ANCHOR))) | Z6: =IF(ISNUMBER(SEARCH("232",E6)),VLOOKUP("232",V7_PROGRAM_TABLE,2,FALSE),IF(ISNUMBER(SEARCH("538",E6)),VLOOKUP("538",V7_PROGRAM_TABLE,2,FALSE),IF(ISNUMBER(SEARCH("223a7",E6)),VLOOKUP("223a7",V7_PROGRAM_TABLE,2,FALSE),IF(ISNUMBER(SEARCH("223f",E6)),VLOOKUP("223f",V7_PROGRAM_TABLE,2,FALSE),V7_PROGRAM_DEFAULT)))) | AA6: =IF(S6=1,1+V7_PURPOSE_NC_BUMP*MAX(0,1-ABS(M6-V7_PURPOSE_PEAK_AGE)/V7_PURPOSE_WIDTH),1) | AB6: =IF(AND(IF(OR(P6="",NOT(ISNUMBER(P6))),0,MAX(0,MIN(24,(INT(VALUE(H6)/100)-INT(P6/100))*12+MOD(VALUE(H6),100)-MOD(P6,100))))>0,IF(OR(P6="",NOT(ISNUMBER(P6))),0,MAX(0,MIN(24,(INT(VALUE(H6)/100)-INT(P6/100))*12+MOD(VALUE(H6),100)-MOD(P6,100))))<=12),1+V7_LOCKOUT_AMP*EXP(-(IF(OR(P6="",NOT(ISNUMBER(P6))),0,MAX(0,MIN(24,(INT(VALUE(H6)/100)-INT(P6/100))*12+MOD(VALUE(H6),100)-MOD(P6,100)))))/V7_LOCKOUT_TAU),1) | AC6: =IF(IF(OR(O6="",NOT(ISNUMBER(O6))),360,MAX(0,MIN(480,(INT(O6/100)-INT(VALUE(H6)/100))*12+MOD(O6,100)-MOD(VALUE(H6),100))))>0,1+V7_MTY_AMP*MAX(0,(V7_MTY_CUTOFF-(IF(OR(O6="",NOT(ISNUMBER(O6))),360,MAX(0,MIN(480,(INT(O6/100)-INT(VALUE(H6)/100))*12+MOD(O6,100)-MOD(VALUE(H6),100))))))/V7_MTY_CUTOFF),1) | AD6: =MAX(V7_BURN_FLOOR,1-V7_BURN_SLOPE*MIN(1,MAX(0,R6))) | AE6: =IF(V7_USE_ISSUER=1,IFERROR(VLOOKUP(Q6,V7_ISSUER_TABLE,3,FALSE),1),1) | AF6: =PRODUCT(W6:AE6) | AG6: =MIN(V7_BASE_SMM*AF6,V7_SMM_CAP) | AH6: =1-(1-AG6)^12 | AI6: =IFERROR(LN(W6)/(LN(W6)+LN(X6)+LN(Y6)+LN(Z6)+LN(AA6)+LN(AB6)+LN(AC6)+LN(AD6))*(AH6-V7_BASE_CPR),0) | AJ6: =IFERROR(LN(X6)/(LN(W6)+LN(X6)+LN(Y6)+LN(Z6)+LN(AA6)+LN(AB6)+LN(AC6)+LN(AD6))*(AH6-V7_BASE_CPR),0) | AK6: =IFERROR(LN(Y6)/(LN(W6)+LN(X6)+LN(Y6)+LN(Z6)+LN(AA6)+LN(AB6)+LN(AC6)+LN(AD6))*(AH6-V7_BASE_CPR),0) | AL6: =IFERROR(LN(Z6)/(LN(W6)+LN(X6)+LN(Y6)+LN(Z6)+LN(AA6)+LN(AB6)+LN(AC6)+LN(AD6))*(AH6-V7_BASE_CPR),0) | AM6: =IFERROR(LN(AA6)/(LN(W6)+LN(X6)+LN(Y6)+LN(Z6)+LN(AA6)+LN(AB6)+LN(AC6)+LN(AD6))*(AH6-V7_BASE_CPR),0) | AN6: =IFERROR(LN(AB6)/(LN(W6)+LN(X6)+LN(Y6)+LN(Z6)+LN(AA6)+LN(AB6)+LN(AC6)+LN(AD6))*(AH6-V7_BASE_CPR),0) | AO6: =IFERROR(LN(AC6)/(LN(W6)+LN(X6)+LN(Y6)+LN(Z6)+LN(AA6)+LN(AB6)+LN(AC6)+LN(AD6))*(AH6-V7_BASE_CPR),0) | AP6: =IFERROR(LN(AD6)/(LN(W6)+LN(X6)+LN(Y6)+LN(Z6)+LN(AA6)+LN(AB6)+LN(AC6)+LN(AD6))*(AH6-V7_BASE_CPR),0) | AQ6: =V7_BASE_CPR+SUM(AI6:AP6)-AH6
A7: 3617X72J4_000000003422052 | B7: LUMENT_PRE21 | C7: 3617X72J4 | D7: LUMENT REAL ESTATE CAPITAL,LLC | E7: 232 | F7: RP | G7: 2011 | H7: 202602 | I7: 5069016.5 | J7: 3.05 | K7: 447 | L7: 6 | M7: 176 | N7: 0 | O7: 204607 | Q7: 3896 | R7: 0 | S7: 0 | T7: =LN(1+I7) | U7: =J7*100-K7 | V7: =U7-12.5*(L7+1) | W7: =IF(M7<=V7_AGE_KNOT_X_0,V7_AGE_KNOT_Y_0,IF(M7>=V7_AGE_KNOT_X_5,V7_AGE_KNOT_Y_5,IF(M7<=V7_AGE_KNOT_X_1,V7_AGE_KNOT_Y_0+(M7-V7_AGE_KNOT_X_0)/(V7_AGE_KNOT_X_1-V7_AGE_KNOT_X_0)*(V7_AGE_KNOT_Y_1-V7_AGE_KNOT_Y_0),IF(M7<=V7_AGE_KNOT_X_2,V7_AGE_KNOT_Y_1+(M7-V7_AGE_KNOT_X_1)/(V7_AGE_KNOT_X_2-V7_AGE_KNOT_X_1)*(V7_AGE_KNOT_Y_2-V7_AGE_KNOT_Y_1),IF(M7<=V7_AGE_KNOT_X_3,V7_AGE_KNOT_Y_2+(M7-V7_AGE_KNOT_X_2)/(V7_AGE_KNOT_X_3-V7_AGE_KNOT_X_2)*(V7_AGE_KNOT_Y_3-V7_AGE_KNOT_Y_2),IF(M7<=V7_AGE_KNOT_X_4,V7_AGE_KNOT_Y_3+(M7-V7_AGE_KNOT_X_3)/(V7_AGE_KNOT_X_4-V7_AGE_KNOT_X_3)*(V7_AGE_KNOT_Y_4-V7_AGE_KNOT_Y_3),V7_AGE_KNOT_Y_4+(M7-V7_AGE_KNOT_X_4)/(V7_AGE_KNOT_X_5-V7_AGE_KNOT_X_4)*(V7_AGE_KNOT_Y_5-V7_AGE_KNOT_Y_4))))))) | X7: =V7_RATE_FLOOR+V7_RATE_ASYMPTOTE/(1+EXP(-(V7-V7_RATE_MID)/V7_RATE_SLOPE)) | Y7: =MAX(V7_SIZE_LOW,MIN(V7_SIZE_HIGH,V7_SIZE_INTERCEPT+V7_SIZE_SLOPE*(T7-V7_SIZE_LOG_ANCHOR))) | Z7: =IF(ISNUMBER(SEARCH("232",E7)),VLOOKUP("232",V7_PROGRAM_TABLE,2,FALSE),IF(ISNUMBER(SEARCH("538",E7)),VLOOKUP("538",V7_PROGRAM_TABLE,2,FALSE),IF(ISNUMBER(SEARCH("223a7",E7)),VLOOKUP("223a7",V7_PROGRAM_TABLE,2,FALSE),IF(ISNUMBER(SEARCH("223f",E7)),VLOOKUP("223f",V7_PROGRAM_TABLE,2,FALSE),V7_PROGRAM_DEFAULT)))) | AA7: =IF(S7=1,1+V7_PURPOSE_NC_BUMP*MAX(0,1-ABS(M7-V7_PURPOSE_PEAK_AGE)/V7_PURPOSE_WIDTH),1) | AB7: =IF(AND(IF(OR(P7="",NOT(ISNUMBER(P7))),0,MAX(0,MIN(24,(INT(VALUE(H7)/100)-INT(P7/100))*12+MOD(VALUE(H7),100)-MOD(P7,100))))>0,IF(OR(P7="",NOT(ISNUMBER(P7))),0,MAX(0,MIN(24,(INT(VALUE(H7)/100)-INT(P7/100))*12+MOD(VALUE(H7),100)-MOD(P7,100))))<=12),1+V7_LOCKOUT_AMP*EXP(-(IF(OR(P7="",NOT(ISNUMBER(P7))),0,MAX(0,MIN(24,(INT(VALUE(H7)/100)-INT(P7/100))*12+MOD(VALUE(H7),100)-MOD(P7,100)))))/V7_LOCKOUT_TAU),1) | AC7: =IF(IF(OR(O7="",NOT(ISNUMBER(O7))),360,MAX(0,MIN(480,(INT(O7/100)-INT(VALUE(H7)/100))*12+MOD(O7,100)-MOD(VALUE(H7),100))))>0,1+V7_MTY_AMP*MAX(0,(V7_MTY_CUTOFF-(IF(OR(O7="",NOT(ISNUMBER(O7))),360,MAX(0,MIN(480,(INT(O7/100)-INT(VALUE(H7)/100))*12+MOD(O7,100)-MOD(VALUE(H7),100))))))/V7_MTY_CUTOFF),1) | AD7: =MAX(V7_BURN_FLOOR,1-V7_BURN_SLOPE*MIN(1,MAX(0,R7))) | AE7: =IF(V7_USE_ISSUER=1,IFERROR(VLOOKUP(Q7,V7_ISSUER_TABLE,3,FALSE),1),1) | AF7: =PRODUCT(W7:AE7) | AG7: =MIN(V7_BASE_SMM*AF7,V7_SMM_CAP) | AH7: =1-(1-AG7)^12 | AI7: =IFERROR(LN(W7)/(LN(W7)+LN(X7)+LN(Y7)+LN(Z7)+LN(AA7)+LN(AB7)+LN(AC7)+LN(AD7))*(AH7-V7_BASE_CPR),0) | AJ7: =IFERROR(LN(X7)/(LN(W7)+LN(X7)+LN(Y7)+LN(Z7)+LN(AA7)+LN(AB7)+LN(AC7)+LN(AD7))*(AH7-V7_BASE_CPR),0) | AK7: =IFERROR(LN(Y7)/(LN(W7)+LN(X7)+LN(Y7)+LN(Z7)+LN(AA7)+LN(AB7)+LN(AC7)+LN(AD7))*(AH7-V7_BASE_CPR),0) | AL7: =IFERROR(LN(Z7)/(LN(W7)+LN(X7)+LN(Y7)+LN(Z7)+LN(AA7)+LN(AB7)+LN(AC7)+LN(AD7))*(AH7-V7_BASE_CPR),0) | AM7: =IFERROR(LN(AA7)/(LN(W7)+LN(X7)+LN(Y7)+LN(Z7)+LN(AA7)+LN(AB7)+LN(AC7)+LN(AD7))*(AH7-V7_BASE_CPR),0) | AN7: =IFERROR(LN(AB7)/(LN(W7)+LN(X7)+LN(Y7)+LN(Z7)+LN(AA7)+LN(AB7)+LN(AC7)+LN(AD7))*(AH7-V7_BASE_CPR),0) | AO7: =IFERROR(LN(AC7)/(LN(W7)+LN(X7)+LN(Y7)+LN(Z7)+LN(AA7)+LN(AB7)+LN(AC7)+LN(AD7))*(AH7-V7_BASE_CPR),0) | AP7: =IFERROR(LN(AD7)/(LN(W7)+LN(X7)+LN(Y7)+LN(Z7)+LN(AA7)+LN(AB7)+LN(AC7)+LN(AD7))*(AH7-V7_BASE_CPR),0) | AQ7: =V7_BASE_CPR+SUM(AI7:AP7)-AH7
A8: 3617X74P8_000000007343145 | B8: LUMENT_PRE21 | C8: 3617X74P8 | D8: LUMENT REAL ESTATE CAPITAL,LLC | E8: 232 | F8: RP | G8: 2013 | H8: 202602 | I8: 11587614 | J8: 3.42 | K8: 447 | L8: 6 | M8: 148 | N8: 1 | O8: 205108 | Q8: 3896 | R8: 0.0067567568 | S8: 0 | T8: =LN(1+I8) | U8: =J8*100-K8 | V8: =U8-12.5*(L8+1) | W8: =IF(M8<=V7_AGE_KNOT_X_0,V7_AGE_KNOT_Y_0,IF(M8>=V7_AGE_KNOT_X_5,V7_AGE_KNOT_Y_5,IF(M8<=V7_AGE_KNOT_X_1,V7_AGE_KNOT_Y_0+(M8-V7_AGE_KNOT_X_0)/(V7_AGE_KNOT_X_1-V7_AGE_KNOT_X_0)*(V7_AGE_KNOT_Y_1-V7_AGE_KNOT_Y_0),IF(M8<=V7_AGE_KNOT_X_2,V7_AGE_KNOT_Y_1+(M8-V7_AGE_KNOT_X_1)/(V7_AGE_KNOT_X_2-V7_AGE_KNOT_X_1)*(V7_AGE_KNOT_Y_2-V7_AGE_KNOT_Y_1),IF(M8<=V7_AGE_KNOT_X_3,V7_AGE_KNOT_Y_2+(M8-V7_AGE_KNOT_X_2)/(V7_AGE_KNOT_X_3-V7_AGE_KNOT_X_2)*(V7_AGE_KNOT_Y_3-V7_AGE_KNOT_Y_2),IF(M8<=V7_AGE_KNOT_X_4,V7_AGE_KNOT_Y_3+(M8-V7_AGE_KNOT_X_3)/(V7_AGE_KNOT_X_4-V7_AGE_KNOT_X_3)*(V7_AGE_KNOT_Y_4-V7_AGE_KNOT_Y_3),V7_AGE_KNOT_Y_4+(M8-V7_AGE_KNOT_X_4)/(V7_AGE_KNOT_X_5-V7_AGE_KNOT_X_4)*(V7_AGE_KNOT_Y_5-V7_AGE_KNOT_Y_4))))))) | X8: =V7_RATE_FLOOR+V7_RATE_ASYMPTOTE/(1+EXP(-(V8-V7_RATE_MID)/V7_RATE_SLOPE)) | Y8: =MAX(V7_SIZE_LOW,MIN(V7_SIZE_HIGH,V7_SIZE_INTERCEPT+V7_SIZE_SLOPE*(T8-V7_SIZE_LOG_ANCHOR))) | Z8: =IF(ISNUMBER(SEARCH("232",E8)),VLOOKUP("232",V7_PROGRAM_TABLE,2,FALSE),IF(ISNUMBER(SEARCH("538",E8)),VLOOKUP("538",V7_PROGRAM_TABLE,2,FALSE),IF(ISNUMBER(SEARCH("223a7",E8)),VLOOKUP("223a7",V7_PROGRAM_TABLE,2,FALSE),IF(ISNUMBER(SEARCH("223f",E8)),VLOOKUP("223f",V7_PROGRAM_TABLE,2,FALSE),V7_PROGRAM_DEFAULT)))) | AA8: =IF(S8=1,1+V7_PURPOSE_NC_BUMP*MAX(0,1-ABS(M8-V7_PURPOSE_PEAK_AGE)/V7_PURPOSE_WIDTH),1) | AB8: =IF(AND(IF(OR(P8="",NOT(ISNUMBER(P8))),0,MAX(0,MIN(24,(INT(VALUE(H8)/100)-INT(P8/100))*12+MOD(VALUE(H8),100)-MOD(P8,100))))>0,IF(OR(P8="",NOT(ISNUMBER(P8))),0,MAX(0,MIN(24,(INT(VALUE(H8)/100)-INT(P8/100))*12+MOD(VALUE(H8),100)-MOD(P8,100))))<=12),1+V7_LOCKOUT_AMP*EXP(-(IF(OR(P8="",NOT(ISNUMBER(P8))),0,MAX(0,MIN(24,(INT(VALUE(H8)/100)-INT(P8/100))*12+MOD(VALUE(H8),100)-MOD(P8,100)))))/V7_LOCKOUT_TAU),1) | AC8: =IF(IF(OR(O8="",NOT(ISNUMBER(O8))),360,MAX(0,MIN(480,(INT(O8/100)-INT(VALUE(H8)/100))*12+MOD(O8,100)-MOD(VALUE(H8),100))))>0,1+V7_MTY_AMP*MAX(0,(V7_MTY_CUTOFF-(IF(OR(O8="",NOT(ISNUMBER(O8))),360,MAX(0,MIN(480,(INT(O8/100)-INT(VALUE(H8)/100))*12+MOD(O8,100)-MOD(VALUE(H8),100))))))/V7_MTY_CUTOFF),1) | AD8: =MAX(V7_BURN_FLOOR,1-V7_BURN_SLOPE*MIN(1,MAX(0,R8))) | AE8: =IF(V7_USE_ISSUER=1,IFERROR(VLOOKUP(Q8,V7_ISSUER_TABLE,3,FALSE),1),1) | AF8: =PRODUCT(W8:AE8) | AG8: =MIN(V7_BASE_SMM*AF8,V7_SMM_CAP) | AH8: =1-(1-AG8)^12 | AI8: =IFERROR(LN(W8)/(LN(W8)+LN(X8)+LN(Y8)+LN(Z8)+LN(AA8)+LN(AB8)+LN(AC8)+LN(AD8))*(AH8-V7_BASE_CPR),0) | AJ8: =IFERROR(LN(X8)/(LN(W8)+LN(X8)+LN(Y8)+LN(Z8)+LN(AA8)+LN(AB8)+LN(AC8)+LN(AD8))*(AH8-V7_BASE_CPR),0) | AK8: =IFERROR(LN(Y8)/(LN(W8)+LN(X8)+LN(Y8)+LN(Z8)+LN(AA8)+LN(AB8)+LN(AC8)+LN(AD8))*(AH8-V7_BASE_CPR),0) | AL8: =IFERROR(LN(Z8)/(LN(W8)+LN(X8)+LN(Y8)+LN(Z8)+LN(AA8)+LN(AB8)+LN(AC8)+LN(AD8))*(AH8-V7_BASE_CPR),0) | AM8: =IFERROR(LN(AA8)/(LN(W8)+LN(X8)+LN(Y8)+LN(Z8)+LN(AA8)+LN(AB8)+LN(AC8)+LN(AD8))*(AH8-V7_BASE_CPR),0) | AN8: =IFERROR(LN(AB8)/(LN(W8)+LN(X8)+LN(Y8)+LN(Z8)+LN(AA8)+LN(AB8)+LN(AC8)+LN(AD8))*(AH8-V7_BASE_CPR),0) | AO8: =IFERROR(LN(AC8)/(LN(W8)+LN(X8)+LN(Y8)+LN(Z8)+LN(AA8)+LN(AB8)+LN(AC8)+LN(AD8))*(AH8-V7_BASE_CPR),0) | AP8: =IFERROR(LN(AD8)/(LN(W8)+LN(X8)+LN(Y8)+LN(Z8)+LN(AA8)+LN(AB8)+LN(AC8)+LN(AD8))*(AH8-V7_BASE_CPR),0) | AQ8: =V7_BASE_CPR+SUM(AI8:AP8)-AH8
A9: 3620AEYZ7_000000010535179 | B9: LUMENT_PRE21 | C9: 3620AEYZ7 | D9: LUMENT REAL ESTATE CAPITAL,LLC | E9: OTHER | F9: OTHER | G9: 2010 | H9: 202602 | I9: 7782165.9 | J9: 3.38 | K9: 447 | L9: 0 | M9: 182 | N9: 36 | O9: 205206 | Q9: 3896 | R9: 0.1978022 | S9: 0 | T9: =LN(1+I9) | U9: =J9*100-K9 | V9: =U9-12.5*(L9+1) | W9: =IF(M9<=V7_AGE_KNOT_X_0,V7_AGE_KNOT_Y_0,IF(M9>=V7_AGE_KNOT_X_5,V7_AGE_KNOT_Y_5,IF(M9<=V7_AGE_KNOT_X_1,V7_AGE_KNOT_Y_0+(M9-V7_AGE_KNOT_X_0)/(V7_AGE_KNOT_X_1-V7_AGE_KNOT_X_0)*(V7_AGE_KNOT_Y_1-V7_AGE_KNOT_Y_0),IF(M9<=V7_AGE_KNOT_X_2,V7_AGE_KNOT_Y_1+(M9-V7_AGE_KNOT_X_1)/(V7_AGE_KNOT_X_2-V7_AGE_KNOT_X_1)*(V7_AGE_KNOT_Y_2-V7_AGE_KNOT_Y_1),IF(M9<=V7_AGE_KNOT_X_3,V7_AGE_KNOT_Y_2+(M9-V7_AGE_KNOT_X_2)/(V7_AGE_KNOT_X_3-V7_AGE_KNOT_X_2)*(V7_AGE_KNOT_Y_3-V7_AGE_KNOT_Y_2),IF(M9<=V7_AGE_KNOT_X_4,V7_AGE_KNOT_Y_3+(M9-V7_AGE_KNOT_X_3)/(V7_AGE_KNOT_X_4-V7_AGE_KNOT_X_3)*(V7_AGE_KNOT_Y_4-V7_AGE_KNOT_Y_3),V7_AGE_KNOT_Y_4+(M9-V7_AGE_KNOT_X_4)/(V7_AGE_KNOT_X_5-V7_AGE_KNOT_X_4)*(V7_AGE_KNOT_Y_5-V7_AGE_KNOT_Y_4))))))) | X9: =V7_RATE_FLOOR+V7_RATE_ASYMPTOTE/(1+EXP(-(V9-V7_RATE_MID)/V7_RATE_SLOPE)) | Y9: =MAX(V7_SIZE_LOW,MIN(V7_SIZE_HIGH,V7_SIZE_INTERCEPT+V7_SIZE_SLOPE*(T9-V7_SIZE_LOG_ANCHOR))) | Z9: =IF(ISNUMBER(SEARCH("232",E9)),VLOOKUP("232",V7_PROGRAM_TABLE,2,FALSE),IF(ISNUMBER(SEARCH("538",E9)),VLOOKUP("538",V7_PROGRAM_TABLE,2,FALSE),IF(ISNUMBER(SEARCH("223a7",E9)),VLOOKUP("223a7",V7_PROGRAM_TABLE,2,FALSE),IF(ISNUMBER(SEARCH("223f",E9)),VLOOKUP("223f",V7_PROGRAM_TABLE,2,FALSE),V7_PROGRAM_DEFAULT)))) | AA9: =IF(S9=1,1+V7_PURPOSE_NC_BUMP*MAX(0,1-ABS(M9-V7_PURPOSE_PEAK_AGE)/V7_PURPOSE_WIDTH),1) | AB9: =IF(AND(IF(OR(P9="",NOT(ISNUMBER(P9))),0,MAX(0,MIN(24,(INT(VALUE(H9)/100)-INT(P9/100))*12+MOD(VALUE(H9),100)-MOD(P9,100))))>0,IF(OR(P9="",NOT(ISNUMBER(P9))),0,MAX(0,MIN(24,(INT(VALUE(H9)/100)-INT(P9/100))*12+MOD(VALUE(H9),100)-MOD(P9,100))))<=12),1+V7_LOCKOUT_AMP*EXP(-(IF(OR(P9="",NOT(ISNUMBER(P9))),0,MAX(0,MIN(24,(INT(VALUE(H9)/100)-INT(P9/100))*12+MOD(VALUE(H9),100)-MOD(P9,100)))))/V7_LOCKOUT_TAU),1) | AC9: =IF(IF(OR(O9="",NOT(ISNUMBER(O9))),360,MAX(0,MIN(480,(INT(O9/100)-INT(VALUE(H9)/100))*12+MOD(O9,100)-MOD(VALUE(H9),100))))>0,1+V7_MTY_AMP*MAX(0,(V7_MTY_CUTOFF-(IF(OR(O9="",NOT(ISNUMBER(O9))),360,MAX(0,MIN(480,(INT(O9/100)-INT(VALUE(H9)/100))*12+MOD(O9,100)-MOD(VALUE(H9),100))))))/V7_MTY_CUTOFF),1) | AD9: =MAX(V7_BURN_FLOOR,1-V7_BURN_SLOPE*MIN(1,MAX(0,R9))) | AE9: =IF(V7_USE_ISSUER=1,IFERROR(VLOOKUP(Q9,V7_ISSUER_TABLE,3,FALSE),1),1) | AF9: =PRODUCT(W9:AE9) | AG9: =MIN(V7_BASE_SMM*AF9,V7_SMM_CAP) | AH9: =1-(1-AG9)^12 | AI9: =IFERROR(LN(W9)/(LN(W9)+LN(X9)+LN(Y9)+LN(Z9)+LN(AA9)+LN(AB9)+LN(AC9)+LN(AD9))*(AH9-V7_BASE_CPR),0) | AJ9: =IFERROR(LN(X9)/(LN(W9)+LN(X9)+LN(Y9)+LN(Z9)+LN(AA9)+LN(AB9)+LN(AC9)+LN(AD9))*(AH9-V7_BASE_CPR),0) | AK9: =IFERROR(LN(Y9)/(LN(W9)+LN(X9)+LN(Y9)+LN(Z9)+LN(AA9)+LN(AB9)+LN(AC9)+LN(AD9))*(AH9-V7_BASE_CPR),0) | AL9: =IFERROR(LN(Z9)/(LN(W9)+LN(X9)+LN(Y9)+LN(Z9)+LN(AA9)+LN(AB9)+LN(AC9)+LN(AD9))*(AH9-V7_BASE_CPR),0) | AM9: =IFERROR(LN(AA9)/(LN(W9)+LN(X9)+LN(Y9)+LN(Z9)+LN(AA9)+LN(AB9)+LN(AC9)+LN(AD9))*(AH9-V7_BASE_CPR),0) | AN9: =IFERROR(LN(AB9)/(LN(W9)+LN(X9)+LN(Y9)+LN(Z9)+LN(AA9)+LN(AB9)+LN(AC9)+LN(AD9))*(AH9-V7_BASE_CPR),0) | AO9: =IFERROR(LN(AC9)/(LN(W9)+LN(X9)+LN(Y9)+LN(Z9)+LN(AA9)+LN(AB9)+LN(AC9)+LN(AD9))*(AH9-V7_BASE_CPR),0) | AP9: =IFERROR(LN(AD9)/(LN(W9)+LN(X9)+LN(Y9)+LN(Z9)+LN(AA9)+LN(AB9)+LN(AC9)+LN(AD9))*(AH9-V7_BASE_CPR),0) | AQ9: =V7_BASE_CPR+SUM(AI9:AP9)-AH9
A10: 3618BNC43_000000001211581 | B10: LUMENT_POST21 | C10: 3618BNC43 | D10: LUMENT REAL ESTATE CAPITAL,LLC | E10: 223f | F10: RP | G10: 2023 | H10: 202602 | I10: 30791262 | J10: 5.36 | K10: 447 | L10: 8 | M10: 32 | N10: 0 | O10: 205707 | Q10: 3896 | R10: 0 | S10: 0 | T10: =LN(1+I10) | U10: =J10*100-K10 | V10: =U10-12.5*(L10+1) | W10: =IF(M10<=V7_AGE_KNOT_X_0,V7_AGE_KNOT_Y_0,IF(M10>=V7_AGE_KNOT_X_5,V7_AGE_KNOT_Y_5,IF(M10<=V7_AGE_KNOT_X_1,V7_AGE_KNOT_Y_0+(M10-V7_AGE_KNOT_X_0)/(V7_AGE_KNOT_X_1-V7_AGE_KNOT_X_0)*(V7_AGE_KNOT_Y_1-V7_AGE_KNOT_Y_0),IF(M10<=V7_AGE_KNOT_X_2,V7_AGE_KNOT_Y_1+(M10-V7_AGE_KNOT_X_1)/(V7_AGE_KNOT_X_2-V7_AGE_KNOT_X_1)*(V7_AGE_KNOT_Y_2-V7_AGE_KNOT_Y_1),IF(M10<=V7_AGE_KNOT_X_3,V7_AGE_KNOT_Y_2+(M10-V7_AGE_KNOT_X_2)/(V7_AGE_KNOT_X_3-V7_AGE_KNOT_X_2)*(V7_AGE_KNOT_Y_3-V7_AGE_KNOT_Y_2),IF(M10<=V7_AGE_KNOT_X_4,V7_AGE_KNOT_Y_3+(M10-V7_AGE_KNOT_X_3)/(V7_AGE_KNOT_X_4-V7_AGE_KNOT_X_3)*(V7_AGE_KNOT_Y_4-V7_AGE_KNOT_Y_3),V7_AGE_KNOT_Y_4+(M10-V7_AGE_KNOT_X_4)/(V7_AGE_KNOT_X_5-V7_AGE_KNOT_X_4)*(V7_AGE_KNOT_Y_5-V7_AGE_KNOT_Y_4))))))) | X10: =V7_RATE_FLOOR+V7_RATE_ASYMPTOTE/(1+EXP(-(V10-V7_RATE_MID)/V7_RATE_SLOPE)) | Y10: =MAX(V7_SIZE_LOW,MIN(V7_SIZE_HIGH,V7_SIZE_INTERCEPT+V7_SIZE_SLOPE*(T10-V7_SIZE_LOG_ANCHOR))) | Z10: =IF(ISNUMBER(SEARCH("232",E10)),VLOOKUP("232",V7_PROGRAM_TABLE,2,FALSE),IF(ISNUMBER(SEARCH("538",E10)),VLOOKUP("538",V7_PROGRAM_TABLE,2,FALSE),IF(ISNUMBER(SEARCH("223a7",E10)),VLOOKUP("223a7",V7_PROGRAM_TABLE,2,FALSE),IF(ISNUMBER(SEARCH("223f",E10)),VLOOKUP("223f",V7_PROGRAM_TABLE,2,FALSE),V7_PROGRAM_DEFAULT)))) | AA10: =IF(S10=1,1+V7_PURPOSE_NC_BUMP*MAX(0,1-ABS(M10-V7_PURPOSE_PEAK_AGE)/V7_PURPOSE_WIDTH),1) | AB10: =IF(AND(IF(OR(P10="",NOT(ISNUMBER(P10))),0,MAX(0,MIN(24,(INT(VALUE(H10)/100)-INT(P10/100))*12+MOD(VALUE(H10),100)-MOD(P10,100))))>0,IF(OR(P10="",NOT(ISNUMBER(P10))),0,MAX(0,MIN(24,(INT(VALUE(H10)/100)-INT(P10/100))*12+MOD(VALUE(H10),100)-MOD(P10,100))))<=12),1+V7_LOCKOUT_AMP*EXP(-(IF(OR(P10="",NOT(ISNUMBER(P10))),0,MAX(0,MIN(24,(INT(VALUE(H10)/100)-INT(P10/100))*12+MOD(VALUE(H10),100)-MOD(P10,100)))))/V7_LOCKOUT_TAU),1) | AC10: =IF(IF(OR(O10="",NOT(ISNUMBER(O10))),360,MAX(0,MIN(480,(INT(O10/100)-INT(VALUE(H10)/100))*12+MOD(O10,100)-MOD(VALUE(H10),100))))>0,1+V7_MTY_AMP*MAX(0,(V7_MTY_CUTOFF-(IF(OR(O10="",NOT(ISNUMBER(O10))),360,MAX(0,MIN(480,(INT(O10/100)-INT(VALUE(H10)/100))*12+MOD(O10,100)-MOD(VALUE(H10),100))))))/V7_MTY_CUTOFF),1) | AD10: =MAX(V7_BURN_FLOOR,1-V7_BURN_SLOPE*MIN(1,MAX(0,R10))) | AE10: =IF(V7_USE_ISSUER=1,IFERROR(VLOOKUP(Q10,V7_ISSUER_TABLE,3,FALSE),1),1) | AF10: =PRODUCT(W10:AE10) | AG10: =MIN(V7_BASE_SMM*AF10,V7_SMM_CAP) | AH10: =1-(1-AG10)^12 | AI10: =IFERROR(LN(W10)/(LN(W10)+LN(X10)+LN(Y10)+LN(Z10)+LN(AA10)+LN(AB10)+LN(AC10)+LN(AD10))*(AH10-V7_BASE_CPR),0) | AJ10: =IFERROR(LN(X10)/(LN(W10)+LN(X10)+LN(Y10)+LN(Z10)+LN(AA10)+LN(AB10)+LN(AC10)+LN(AD10))*(AH10-V7_BASE_CPR),0) | AK10: =IFERROR(LN(Y10)/(LN(W10)+LN(X10)+LN(Y10)+LN(Z10)+LN(AA10)+LN(AB10)+LN(AC10)+LN(AD10))*(AH10-V7_BASE_CPR),0) | AL10: =IFERROR(LN(Z10)/(LN(W10)+LN(X10)+LN(Y10)+LN(Z10)+LN(AA10)+LN(AB10)+LN(AC10)+LN(AD10))*(AH10-V7_BASE_CPR),0) | AM10: =IFERROR(LN(AA10)/(LN(W10)+LN(X10)+LN(Y10)+LN(Z10)+LN(AA10)+LN(AB10)+LN(AC10)+LN(AD10))*(AH10-V7_BASE_CPR),0) | AN10: =IFERROR(LN(AB10)/(LN(W10)+LN(X10)+LN(Y10)+LN(Z10)+LN(AA10)+LN(AB10)+LN(AC10)+LN(AD10))*(AH10-V7_BASE_CPR),0) | AO10: =IFERROR(LN(AC10)/(LN(W10)+LN(X10)+LN(Y10)+LN(Z10)+LN(AA10)+LN(AB10)+LN(AC10)+LN(AD10))*(AH10-V7_BASE_CPR),0) | AP10: =IFERROR(LN(AD10)/(LN(W10)+LN(X10)+LN(Y10)+LN(Z10)+LN(AA10)+LN(AB10)+LN(AC10)+LN(AD10))*(AH10-V7_BASE_CPR),0) | AQ10: =V7_BASE_CPR+SUM(AI10:AP10)-AH10
A11: 3618KLMG9_000000001211630 | B11: LUMENT_POST21 | C11: 3618KLMG9 | D11: LUMENT REAL ESTATE CAPITAL,LLC | E11: 223f | F11: RP | G11: 2025 | H11: 202602 | I11: 59508580 | J11: 5.65 | K11: 447 | L11: 10 | M11: 4 | N11: 0 | O11: 206011 | Q11: 3896 | R11: 0 | S11: 0 | T11: =LN(1+I11) | U11: =J11*100-K11 | V11: =U11-12.5*(L11+1) | W11: =IF(M11<=V7_AGE_KNOT_X_0,V7_AGE_KNOT_Y_0,IF(M11>=V7_AGE_KNOT_X_5,V7_AGE_KNOT_Y_5,IF(M11<=V7_AGE_KNOT_X_1,V7_AGE_KNOT_Y_0+(M11-V7_AGE_KNOT_X_0)/(V7_AGE_KNOT_X_1-V7_AGE_KNOT_X_0)*(V7_AGE_KNOT_Y_1-V7_AGE_KNOT_Y_0),IF(M11<=V7_AGE_KNOT_X_2,V7_AGE_KNOT_Y_1+(M11-V7_AGE_KNOT_X_1)/(V7_AGE_KNOT_X_2-V7_AGE_KNOT_X_1)*(V7_AGE_KNOT_Y_2-V7_AGE_KNOT_Y_1),IF(M11<=V7_AGE_KNOT_X_3,V7_AGE_KNOT_Y_2+(M11-V7_AGE_KNOT_X_2)/(V7_AGE_KNOT_X_3-V7_AGE_KNOT_X_2)*(V7_AGE_KNOT_Y_3-V7_AGE_KNOT_Y_2),IF(M11<=V7_AGE_KNOT_X_4,V7_AGE_KNOT_Y_3+(M11-V7_AGE_KNOT_X_3)/(V7_AGE_KNOT_X_4-V7_AGE_KNOT_X_3)*(V7_AGE_KNOT_Y_4-V7_AGE_KNOT_Y_3),V7_AGE_KNOT_Y_4+(M11-V7_AGE_KNOT_X_4)/(V7_AGE_KNOT_X_5-V7_AGE_KNOT_X_4)*(V7_AGE_KNOT_Y_5-V7_AGE_KNOT_Y_4))))))) | X11: =V7_RATE_FLOOR+V7_RATE_ASYMPTOTE/(1+EXP(-(V11-V7_RATE_MID)/V7_RATE_SLOPE)) | Y11: =MAX(V7_SIZE_LOW,MIN(V7_SIZE_HIGH,V7_SIZE_INTERCEPT+V7_SIZE_SLOPE*(T11-V7_SIZE_LOG_ANCHOR))) | Z11: =IF(ISNUMBER(SEARCH("232",E11)),VLOOKUP("232",V7_PROGRAM_TABLE,2,FALSE),IF(ISNUMBER(SEARCH("538",E11)),VLOOKUP("538",V7_PROGRAM_TABLE,2,FALSE),IF(ISNUMBER(SEARCH("223a7",E11)),VLOOKUP("223a7",V7_PROGRAM_TABLE,2,FALSE),IF(ISNUMBER(SEARCH("223f",E11)),VLOOKUP("223f",V7_PROGRAM_TABLE,2,FALSE),V7_PROGRAM_DEFAULT)))) | AA11: =IF(S11=1,1+V7_PURPOSE_NC_BUMP*MAX(0,1-ABS(M11-V7_PURPOSE_PEAK_AGE)/V7_PURPOSE_WIDTH),1) | AB11: =IF(AND(IF(OR(P11="",NOT(ISNUMBER(P11))),0,MAX(0,MIN(24,(INT(VALUE(H11)/100)-INT(P11/100))*12+MOD(VALUE(H11),100)-MOD(P11,100))))>0,IF(OR(P11="",NOT(ISNUMBER(P11))),0,MAX(0,MIN(24,(INT(VALUE(H11)/100)-INT(P11/100))*12+MOD(VALUE(H11),100)-MOD(P11,100))))<=12),1+V7_LOCKOUT_AMP*EXP(-(IF(OR(P11="",NOT(ISNUMBER(P11))),0,MAX(0,MIN(24,(INT(VALUE(H11)/100)-INT(P11/100))*12+MOD(VALUE(H11),100)-MOD(P11,100)))))/V7_LOCKOUT_TAU),1) | AC11: =IF(IF(OR(O11="",NOT(ISNUMBER(O11))),360,MAX(0,MIN(480,(INT(O11/100)-INT(VALUE(H11)/100))*12+MOD(O11,100)-MOD(VALUE(H11),100))))>0,1+V7_MTY_AMP*MAX(0,(V7_MTY_CUTOFF-(IF(OR(O11="",NOT(ISNUMBER(O11))),360,MAX(0,MIN(480,(INT(O11/100)-INT(VALUE(H11)/100))*12+MOD(O11,100)-MOD(VALUE(H11),100))))))/V7_MTY_CUTOFF),1) | AD11: =MAX(V7_BURN_FLOOR,1-V7_BURN_SLOPE*MIN(1,MAX(0,R11))) | AE11: =IF(V7_USE_ISSUER=1,IFERROR(VLOOKUP(Q11,V7_ISSUER_TABLE,3,FALSE),1),1) | AF11: =PRODUCT(W11:AE11) | AG11: =MIN(V7_BASE_SMM*AF11,V7_SMM_CAP) | AH11: =1-(1-AG11)^12 | AI11: =IFERROR(LN(W11)/(LN(W11)+LN(X11)+LN(Y11)+LN(Z11)+LN(AA11)+LN(AB11)+LN(AC11)+LN(AD11))*(AH11-V7_BASE_CPR),0) | AJ11: =IFERROR(LN(X11)/(LN(W11)+LN(X11)+LN(Y11)+LN(Z11)+LN(AA11)+LN(AB11)+LN(AC11)+LN(AD11))*(AH11-V7_BASE_CPR),0) | AK11: =IFERROR(LN(Y11)/(LN(W11)+LN(X11)+LN(Y11)+LN(Z11)+LN(AA11)+LN(AB11)+LN(AC11)+LN(AD11))*(AH11-V7_BASE_CPR),0) | AL11: =IFERROR(LN(Z11)/(LN(W11)+LN(X11)+LN(Y11)+LN(Z11)+LN(AA11)+LN(AB11)+LN(AC11)+LN(AD11))*(AH11-V7_BASE_CPR),0) | AM11: =IFERROR(LN(AA11)/(LN(W11)+LN(X11)+LN(Y11)+LN(Z11)+LN(AA11)+LN(AB11)+LN(AC11)+LN(AD11))*(AH11-V7_BASE_CPR),0) | AN11: =IFERROR(LN(AB11)/(LN(W11)+LN(X11)+LN(Y11)+LN(Z11)+LN(AA11)+LN(AB11)+LN(AC11)+LN(AD11))*(AH11-V7_BASE_CPR),0) | AO11: =IFERROR(LN(AC11)/(LN(W11)+LN(X11)+LN(Y11)+LN(Z11)+LN(AA11)+LN(AB11)+LN(AC11)+LN(AD11))*(AH11-V7_BASE_CPR),0) | AP11: =IFERROR(LN(AD11)/(LN(W11)+LN(X11)+LN(Y11)+LN(Z11)+LN(AA11)+LN(AB11)+LN(AC11)+LN(AD11))*(AH11-V7_BASE_CPR),0) | AQ11: =V7_BASE_CPR+SUM(AI11:AP11)-AH11
A12: 36297HB49_000000010222024 | B12: LUMENT_PRE21 | C12: 36297HB49 | D12: LUMENT REAL ESTATE CAPITAL,LLC | E12: 232 | F12: RP | G12: 2009 | H12: 202602 | I12: 2318598.5 | J12: 5.65 | K12: 447 | L12: 0 | M12: 200 | N12: 84 | O12: 203907 | P12: 201108 | Q12: 3896 | R12: 0.42 | S12: 0 | T12: =LN(1+I12) | U12: =J12*100-K12 | V12: =U12-12.5*(L12+1) | W12: =IF(M12<=V7_AGE_KNOT_X_0,V7_AGE_KNOT_Y_0,IF(M12>=V7_AGE_KNOT_X_5,V7_AGE_KNOT_Y_5,IF(M12<=V7_AGE_KNOT_X_1,V7_AGE_KNOT_Y_0+(M12-V7_AGE_KNOT_X_0)/(V7_AGE_KNOT_X_1-V7_AGE_KNOT_X_0)*(V7_AGE_KNOT_Y_1-V7_AGE_KNOT_Y_0),IF(M12<=V7_AGE_KNOT_X_2,V7_AGE_KNOT_Y_1+(M12-V7_AGE_KNOT_X_1)/(V7_AGE_KNOT_X_2-V7_AGE_KNOT_X_1)*(V7_AGE_KNOT_Y_2-V7_AGE_KNOT_Y_1),IF(M12<=V7_AGE_KNOT_X_3,V7_AGE_KNOT_Y_2+(M12-V7_AGE_KNOT_X_2)/(V7_AGE_KNOT_X_3-V7_AGE_KNOT_X_2)*(V7_AGE_KNOT_Y_3-V7_AGE_KNOT_Y_2),IF(M12<=V7_AGE_KNOT_X_4,V7_AGE_KNOT_Y_3+(M12-V7_AGE_KNOT_X_3)/(V7_AGE_KNOT_X_4-V7_AGE_KNOT_X_3)*(V7_AGE_KNOT_Y_4-V7_AGE_KNOT_Y_3),V7_AGE_KNOT_Y_4+(M12-V7_AGE_KNOT_X_4)/(V7_AGE_KNOT_X_5-V7_AGE_KNOT_X_4)*(V7_AGE_KNOT_Y_5-V7_AGE_KNOT_Y_4))))))) | X12: =V7_RATE_FLOOR+V7_RATE_ASYMPTOTE/(1+EXP(-(V12-V7_RATE_MID)/V7_RATE_SLOPE)) | Y12: =MAX(V7_SIZE_LOW,MIN(V7_SIZE_HIGH,V7_SIZE_INTERCEPT+V7_SIZE_SLOPE*(T12-V7_SIZE_LOG_ANCHOR))) | Z12: =IF(ISNUMBER(SEARCH("232",E12)),VLOOKUP("232",V7_PROGRAM_TABLE,2,FALSE),IF(ISNUMBER(SEARCH("538",E12)),VLOOKUP("538",V7_PROGRAM_TABLE,2,FALSE),IF(ISNUMBER(SEARCH("223a7",E12)),VLOOKUP("223a7",V7_PROGRAM_TABLE,2,FALSE),IF(ISNUMBER(SEARCH("223f",E12)),VLOOKUP("223f",V7_PROGRAM_TABLE,2,FALSE),V7_PROGRAM_DEFAULT)))) | AA12: =IF(S12=1,1+V7_PURPOSE_NC_BUMP*MAX(0,1-ABS(M12-V7_PURPOSE_PEAK_AGE)/V7_PURPOSE_WIDTH),1) | AB12: =IF(AND(IF(OR(P12="",NOT(ISNUMBER(P12))),0,MAX(0,MIN(24,(INT(VALUE(H12)/100)-INT(P12/100))*12+MOD(VALUE(H12),100)-MOD(P12,100))))>0,IF(OR(P12="",NOT(ISNUMBER(P12))),0,MAX(0,MIN(24,(INT(VALUE(H12)/100)-INT(P12/100))*12+MOD(VALUE(H12),100)-MOD(P12,100))))<=12),1+V7_LOCKOUT_AMP*EXP(-(IF(OR(P12="",NOT(ISNUMBER(P12))),0,MAX(0,MIN(24,(INT(VALUE(H12)/100)-INT(P12/100))*12+MOD(VALUE(H12),100)-MOD(P12,100)))))/V7_LOCKOUT_TAU),1) | AC12: =IF(IF(OR(O12="",NOT(ISNUMBER(O12))),360,MAX(0,MIN(480,(INT(O12/100)-INT(VALUE(H12)/100))*12+MOD(O12,100)-MOD(VALUE(H12),100))))>0,1+V7_MTY_AMP*MAX(0,(V7_MTY_CUTOFF-(IF(OR(O12="",NOT(ISNUMBER(O12))),360,MAX(0,MIN(480,(INT(O12/100)-INT(VALUE(H12)/100))*12+MOD(O12,100)-MOD(VALUE(H12),100))))))/V7_MTY_CUTOFF),1) | AD12: =MAX(V7_BURN_FLOOR,1-V7_BURN_SLOPE*MIN(1,MAX(0,R12))) | AE12: =IF(V7_USE_ISSUER=1,IFERROR(VLOOKUP(Q12,V7_ISSUER_TABLE,3,FALSE),1),1) | AF12: =PRODUCT(W12:AE12) | AG12: =MIN(V7_BASE_SMM*AF12,V7_SMM_CAP) | AH12: =1-(1-AG12)^12 | AI12: =IFERROR(LN(W12)/(LN(W12)+LN(X12)+LN(Y12)+LN(Z12)+LN(AA12)+LN(AB12)+LN(AC12)+LN(AD12))*(AH12-V7_BASE_CPR),0) | AJ12: =IFERROR(LN(X12)/(LN(W12)+LN(X12)+LN(Y12)+LN(Z12)+LN(AA12)+LN(AB12)+LN(AC12)+LN(AD12))*(AH12-V7_BASE_CPR),0) | AK12: =IFERROR(LN(Y12)/(LN(W12)+LN(X12)+LN(Y12)+LN(Z12)+LN(AA12)+LN(AB12)+LN(AC12)+LN(AD12))*(AH12-V7_BASE_CPR),0) | AL12: =IFERROR(LN(Z12)/(LN(W12)+LN(X12)+LN(Y12)+LN(Z12)+LN(AA12)+LN(AB12)+LN(AC12)+LN(AD12))*(AH12-V7_BASE_CPR),0) | AM12: =IFERROR(LN(AA12)/(LN(W12)+LN(X12)+LN(Y12)+LN(Z12)+LN(AA12)+LN(AB12)+LN(AC12)+LN(AD12))*(AH12-V7_BASE_CPR),0) | AN12: =IFERROR(LN(AB12)/(LN(W12)+LN(X12)+LN(Y12)+LN(Z12)+LN(AA12)+LN(AB12)+LN(AC12)+LN(AD12))*(AH12-V7_BASE_CPR),0) | AO12: =IFERROR(LN(AC12)/(LN(W12)+LN(X12)+LN(Y12)+LN(Z12)+LN(AA12)+LN(AB12)+LN(AC12)+LN(AD12))*(AH12-V7_BASE_CPR),0) | AP12: =IFERROR(LN(AD12)/(LN(W12)+LN(X12)+LN(Y12)+LN(Z12)+LN(AA12)+LN(AB12)+LN(AC12)+LN(AD12))*(AH12-V7_BASE_CPR),0) | AQ12: =V7_BASE_CPR+SUM(AI12:AP12)-AH12
A13: 3618HNAN7_000000006122229 | B13: LUMENT_POST21 | C13: 3618HNAN7 | D13: LUMENT REAL ESTATE CAPITAL,LLC | E13: 232 | F13: RP | G13: 2024 | H13: 202602 | I13: 10649283 | J13: 5.35 | K13: 447 | L13: 9 | M13: 14 | N13: 0 | O13: 206001 | Q13: 3896 | R13: 0 | S13: 0 | T13: =LN(1+I13) | U13: =J13*100-K13 | V13: =U13-12.5*(L13+1) | W13: =IF(M13<=V7_AGE_KNOT_X_0,V7_AGE_KNOT_Y_0,IF(M13>=V7_AGE_KNOT_X_5,V7_AGE_KNOT_Y_5,IF(M13<=V7_AGE_KNOT_X_1,V7_AGE_KNOT_Y_0+(M13-V7_AGE_KNOT_X_0)/(V7_AGE_KNOT_X_1-V7_AGE_KNOT_X_0)*(V7_AGE_KNOT_Y_1-V7_AGE_KNOT_Y_0),IF(M13<=V7_AGE_KNOT_X_2,V7_AGE_KNOT_Y_1+(M13-V7_AGE_KNOT_X_1)/(V7_AGE_KNOT_X_2-V7_AGE_KNOT_X_1)*(V7_AGE_KNOT_Y_2-V7_AGE_KNOT_Y_1),IF(M13<=V7_AGE_KNOT_X_3,V7_AGE_KNOT_Y_2+(M13-V7_AGE_KNOT_X_2)/(V7_AGE_KNOT_X_3-V7_AGE_KNOT_X_2)*(V7_AGE_KNOT_Y_3-V7_AGE_KNOT_Y_2),IF(M13<=V7_AGE_KNOT_X_4,V7_AGE_KNOT_Y_3+(M13-V7_AGE_KNOT_X_3)/(V7_AGE_KNOT_X_4-V7_AGE_KNOT_X_3)*(V7_AGE_KNOT_Y_4-V7_AGE_KNOT_Y_3),V7_AGE_KNOT_Y_4+(M13-V7_AGE_KNOT_X_4)/(V7_AGE_KNOT_X_5-V7_AGE_KNOT_X_4)*(V7_AGE_KNOT_Y_5-V7_AGE_KNOT_Y_4))))))) | X13: =V7_RATE_FLOOR+V7_RATE_ASYMPTOTE/(1+EXP(-(V13-V7_RATE_MID)/V7_RATE_SLOPE)) | Y13: =MAX(V7_SIZE_LOW,MIN(V7_SIZE_HIGH,V7_SIZE_INTERCEPT+V7_SIZE_SLOPE*(T13-V7_SIZE_LOG_ANCHOR))) | Z13: =IF(ISNUMBER(SEARCH("232",E13)),VLOOKUP("232",V7_PROGRAM_TABLE,2,FALSE),IF(ISNUMBER(SEARCH("538",E13)),VLOOKUP("538",V7_PROGRAM_TABLE,2,FALSE),IF(ISNUMBER(SEARCH("223a7",E13)),VLOOKUP("223a7",V7_PROGRAM_TABLE,2,FALSE),IF(ISNUMBER(SEARCH("223f",E13)),VLOOKUP("223f",V7_PROGRAM_TABLE,2,FALSE),V7_PROGRAM_DEFAULT)))) | AA13: =IF(S13=1,1+V7_PURPOSE_NC_BUMP*MAX(0,1-ABS(M13-V7_PURPOSE_PEAK_AGE)/V7_PURPOSE_WIDTH),1) | AB13: =IF(AND(IF(OR(P13="",NOT(ISNUMBER(P13))),0,MAX(0,MIN(24,(INT(VALUE(H13)/100)-INT(P13/100))*12+MOD(VALUE(H13),100)-MOD(P13,100))))>0,IF(OR(P13="",NOT(ISNUMBER(P13))),0,MAX(0,MIN(24,(INT(VALUE(H13)/100)-INT(P13/100))*12+MOD(VALUE(H13),100)-MOD(P13,100))))<=12),1+V7_LOCKOUT_AMP*EXP(-(IF(OR(P13="",NOT(ISNUMBER(P13))),0,MAX(0,MIN(24,(INT(VALUE(H13)/100)-INT(P13/100))*12+MOD(VALUE(H13),100)-MOD(P13,100)))))/V7_LOCKOUT_TAU),1) | AC13: =IF(IF(OR(O13="",NOT(ISNUMBER(O13))),360,MAX(0,MIN(480,(INT(O13/100)-INT(VALUE(H13)/100))*12+MOD(O13,100)-MOD(VALUE(H13),100))))>0,1+V7_MTY_AMP*MAX(0,(V7_MTY_CUTOFF-(IF(OR(O13="",NOT(ISNUMBER(O13))),360,MAX(0,MIN(480,(INT(O13/100)-INT(VALUE(H13)/100))*12+MOD(O13,100)-MOD(VALUE(H13),100))))))/V7_MTY_CUTOFF),1) | AD13: =MAX(V7_BURN_FLOOR,1-V7_BURN_SLOPE*MIN(1,MAX(0,R13))) | AE13: =IF(V7_USE_ISSUER=1,IFERROR(VLOOKUP(Q13,V7_ISSUER_TABLE,3,FALSE),1),1) | AF13: =PRODUCT(W13:AE13) | AG13: =MIN(V7_BASE_SMM*AF13,V7_SMM_CAP) | AH13: =1-(1-AG13)^12 | AI13: =IFERROR(LN(W13)/(LN(W13)+LN(X13)+LN(Y13)+LN(Z13)+LN(AA13)+LN(AB13)+LN(AC13)+LN(AD13))*(AH13-V7_BASE_CPR),0) | AJ13: =IFERROR(LN(X13)/(LN(W13)+LN(X13)+LN(Y13)+LN(Z13)+LN(AA13)+LN(AB13)+LN(AC13)+LN(AD13))*(AH13-V7_BASE_CPR),0) | AK13: =IFERROR(LN(Y13)/(LN(W13)+LN(X13)+LN(Y13)+LN(Z13)+LN(AA13)+LN(AB13)+LN(AC13)+LN(AD13))*(AH13-V7_BASE_CPR),0) | AL13: =IFERROR(LN(Z13)/(LN(W13)+LN(X13)+LN(Y13)+LN(Z13)+LN(AA13)+LN(AB13)+LN(AC13)+LN(AD13))*(AH13-V7_BASE_CPR),0) | AM13: =IFERROR(LN(AA13)/(LN(W13)+LN(X13)+LN(Y13)+LN(Z13)+LN(AA13)+LN(AB13)+LN(AC13)+LN(AD13))*(AH13-V7_BASE_CPR),0) | AN13: =IFERROR(LN(AB13)/(LN(W13)+LN(X13)+LN(Y13)+LN(Z13)+LN(AA13)+LN(AB13)+LN(AC13)+LN(AD13))*(AH13-V7_BASE_CPR),0) | AO13: =IFERROR(LN(AC13)/(LN(W13)+LN(X13)+LN(Y13)+LN(Z13)+LN(AA13)+LN(AB13)+LN(AC13)+LN(AD13))*(AH13-V7_BASE_CPR),0) | AP13: =IFERROR(LN(AD13)/(LN(W13)+LN(X13)+LN(Y13)+LN(Z13)+LN(AA13)+LN(AB13)+LN(AC13)+LN(AD13))*(AH13-V7_BASE_CPR),0) | AQ13: =V7_BASE_CPR+SUM(AI13:AP13)-AH13
A14: 3617LC5T1_000000004611186 | B14: LUMENT_PRE21 | C14: 3617LC5T1 | D14: LUMENT REAL ESTATE CAPITAL,LLC | E14: 223f | F14: RP | G14: 2019 | H14: 202602 | I14: 14083196 | J14: 2.95 | K14: 447 | L14: 4 | M14: 75 | N14: 7 | O14: 205412 | Q14: 3896 | R14: 0.093333333 | S14: 0 | T14: =LN(1+I14) | U14: =J14*100-K14 | V14: =U14-12.5*(L14+1) | W14: =IF(M14<=V7_AGE_KNOT_X_0,V7_AGE_KNOT_Y_0,IF(M14>=V7_AGE_KNOT_X_5,V7_AGE_KNOT_Y_5,IF(M14<=V7_AGE_KNOT_X_1,V7_AGE_KNOT_Y_0+(M14-V7_AGE_KNOT_X_0)/(V7_AGE_KNOT_X_1-V7_AGE_KNOT_X_0)*(V7_AGE_KNOT_Y_1-V7_AGE_KNOT_Y_0),IF(M14<=V7_AGE_KNOT_X_2,V7_AGE_KNOT_Y_1+(M14-V7_AGE_KNOT_X_1)/(V7_AGE_KNOT_X_2-V7_AGE_KNOT_X_1)*(V7_AGE_KNOT_Y_2-V7_AGE_KNOT_Y_1),IF(M14<=V7_AGE_KNOT_X_3,V7_AGE_KNOT_Y_2+(M14-V7_AGE_KNOT_X_2)/(V7_AGE_KNOT_X_3-V7_AGE_KNOT_X_2)*(V7_AGE_KNOT_Y_3-V7_AGE_KNOT_Y_2),IF(M14<=V7_AGE_KNOT_X_4,V7_AGE_KNOT_Y_3+(M14-V7_AGE_KNOT_X_3)/(V7_AGE_KNOT_X_4-V7_AGE_KNOT_X_3)*(V7_AGE_KNOT_Y_4-V7_AGE_KNOT_Y_3),V7_AGE_KNOT_Y_4+(M14-V7_AGE_KNOT_X_4)/(V7_AGE_KNOT_X_5-V7_AGE_KNOT_X_4)*(V7_AGE_KNOT_Y_5-V7_AGE_KNOT_Y_4))))))) | X14: =V7_RATE_FLOOR+V7_RATE_ASYMPTOTE/(1+EXP(-(V14-V7_RATE_MID)/V7_RATE_SLOPE)) | Y14: =MAX(V7_SIZE_LOW,MIN(V7_SIZE_HIGH,V7_SIZE_INTERCEPT+V7_SIZE_SLOPE*(T14-V7_SIZE_LOG_ANCHOR))) | Z14: =IF(ISNUMBER(SEARCH("232",E14)),VLOOKUP("232",V7_PROGRAM_TABLE,2,FALSE),IF(ISNUMBER(SEARCH("538",E14)),VLOOKUP("538",V7_PROGRAM_TABLE,2,FALSE),IF(ISNUMBER(SEARCH("223a7",E14)),VLOOKUP("223a7",V7_PROGRAM_TABLE,2,FALSE),IF(ISNUMBER(SEARCH("223f",E14)),VLOOKUP("223f",V7_PROGRAM_TABLE,2,FALSE),V7_PROGRAM_DEFAULT)))) | AA14: =IF(S14=1,1+V7_PURPOSE_NC_BUMP*MAX(0,1-ABS(M14-V7_PURPOSE_PEAK_AGE)/V7_PURPOSE_WIDTH),1) | AB14: =IF(AND(IF(OR(P14="",NOT(ISNUMBER(P14))),0,MAX(0,MIN(24,(INT(VALUE(H14)/100)-INT(P14/100))*12+MOD(VALUE(H14),100)-MOD(P14,100))))>0,IF(OR(P14="",NOT(ISNUMBER(P14))),0,MAX(0,MIN(24,(INT(VALUE(H14)/100)-INT(P14/100))*12+MOD(VALUE(H14),100)-MOD(P14,100))))<=12),1+V7_LOCKOUT_AMP*EXP(-(IF(OR(P14="",NOT(ISNUMBER(P14))),0,MAX(0,MIN(24,(INT(VALUE(H14)/100)-INT(P14/100))*12+MOD(VALUE(H14),100)-MOD(P14,100)))))/V7_LOCKOUT_TAU),1) | AC14: =IF(IF(OR(O14="",NOT(ISNUMBER(O14))),360,MAX(0,MIN(480,(INT(O14/100)-INT(VALUE(H14)/100))*12+MOD(O14,100)-MOD(VALUE(H14),100))))>0,1+V7_MTY_AMP*MAX(0,(V7_MTY_CUTOFF-(IF(OR(O14="",NOT(ISNUMBER(O14))),360,MAX(0,MIN(480,(INT(O14/100)-INT(VALUE(H14)/100))*12+MOD(O14,100)-MOD(VALUE(H14),100))))))/V7_MTY_CUTOFF),1) | AD14: =MAX(V7_BURN_FLOOR,1-V7_BURN_SLOPE*MIN(1,MAX(0,R14))) | AE14: =IF(V7_USE_ISSUER=1,IFERROR(VLOOKUP(Q14,V7_ISSUER_TABLE,3,FALSE),1),1) | AF14: =PRODUCT(W14:AE14) | AG14: =MIN(V7_BASE_SMM*AF14,V7_SMM_CAP) | AH14: =1-(1-AG14)^12 | AI14: =IFERROR(LN(W14)/(LN(W14)+LN(X14)+LN(Y14)+LN(Z14)+LN(AA14)+LN(AB14)+LN(AC14)+LN(AD14))*(AH14-V7_BASE_CPR),0) | AJ14: =IFERROR(LN(X14)/(LN(W14)+LN(X14)+LN(Y14)+LN(Z14)+LN(AA14)+LN(AB14)+LN(AC14)+LN(AD14))*(AH14-V7_BASE_CPR),0) | AK14: =IFERROR(LN(Y14)/(LN(W14)+LN(X14)+LN(Y14)+LN(Z14)+LN(AA14)+LN(AB14)+LN(AC14)+LN(AD14))*(AH14-V7_BASE_CPR),0) | AL14: =IFERROR(LN(Z14)/(LN(W14)+LN(X14)+LN(Y14)+LN(Z14)+LN(AA14)+LN(AB14)+LN(AC14)+LN(AD14))*(AH14-V7_BASE_CPR),0) | AM14: =IFERROR(LN(AA14)/(LN(W14)+LN(X14)+LN(Y14)+LN(Z14)+LN(AA14)+LN(AB14)+LN(AC14)+LN(AD14))*(AH14-V7_BASE_CPR),0) | AN14: =IFERROR(LN(AB14)/(LN(W14)+LN(X14)+LN(Y14)+LN(Z14)+LN(AA14)+LN(AB14)+LN(AC14)+LN(AD14))*(AH14-V7_BASE_CPR),0) | AO14: =IFERROR(LN(AC14)/(LN(W14)+LN(X14)+LN(Y14)+LN(Z14)+LN(AA14)+LN(AB14)+LN(AC14)+LN(AD14))*(AH14-V7_BASE_CPR),0) | AP14: =IFERROR(LN(AD14)/(LN(W14)+LN(X14)+LN(Y14)+LN(Z14)+LN(AA14)+LN(AB14)+LN(AC14)+LN(AD14))*(AH14-V7_BASE_CPR),0) | AQ14: =V7_BASE_CPR+SUM(AI14:AP14)-AH14
A15: 3617J9LY2_000000001411271 | B15: LUMENT_PRE21 | C15: 3617J9LY2 | D15: LUMENT REAL ESTATE CAPITAL,LLC | E15: 223f | F15: RP | G15: 2019 | H15: 202602 | I15: 6145581.9 | J15: 4.3 | K15: 447 | L15: 4 | M15: 82 | N15: 35 | O15: 205405 | Q15: 3896 | R15: 0.42682927 | S15: 0 | T15: =LN(1+I15) | U15: =J15*100-K15 | V15: =U15-12.5*(L15+1) | W15: =IF(M15<=V7_AGE_KNOT_X_0,V7_AGE_KNOT_Y_0,IF(M15>=V7_AGE_KNOT_X_5,V7_AGE_KNOT_Y_5,IF(M15<=V7_AGE_KNOT_X_1,V7_AGE_KNOT_Y_0+(M15-V7_AGE_KNOT_X_0)/(V7_AGE_KNOT_X_1-V7_AGE_KNOT_X_0)*(V7_AGE_KNOT_Y_1-V7_AGE_KNOT_Y_0),IF(M15<=V7_AGE_KNOT_X_2,V7_AGE_KNOT_Y_1+(M15-V7_AGE_KNOT_X_1)/(V7_AGE_KNOT_X_2-V7_AGE_KNOT_X_1)*(V7_AGE_KNOT_Y_2-V7_AGE_KNOT_Y_1),IF(M15<=V7_AGE_KNOT_X_3,V7_AGE_KNOT_Y_2+(M15-V7_AGE_KNOT_X_2)/(V7_AGE_KNOT_X_3-V7_AGE_KNOT_X_2)*(V7_AGE_KNOT_Y_3-V7_AGE_KNOT_Y_2),IF(M15<=V7_AGE_KNOT_X_4,V7_AGE_KNOT_Y_3+(M15-V7_AGE_KNOT_X_3)/(V7_AGE_KNOT_X_4-V7_AGE_KNOT_X_3)*(V7_AGE_KNOT_Y_4-V7_AGE_KNOT_Y_3),V7_AGE_KNOT_Y_4+(M15-V7_AGE_KNOT_X_4)/(V7_AGE_KNOT_X_5-V7_AGE_KNOT_X_4)*(V7_AGE_KNOT_Y_5-V7_AGE_KNOT_Y_4))))))) | X15: =V7_RATE_FLOOR+V7_RATE_ASYMPTOTE/(1+EXP(-(V15-V7_RATE_MID)/V7_RATE_SLOPE)) | Y15: =MAX(V7_SIZE_LOW,MIN(V7_SIZE_HIGH,V7_SIZE_INTERCEPT+V7_SIZE_SLOPE*(T15-V7_SIZE_LOG_ANCHOR))) | Z15: =IF(ISNUMBER(SEARCH("232",E15)),VLOOKUP("232",V7_PROGRAM_TABLE,2,FALSE),IF(ISNUMBER(SEARCH("538",E15)),VLOOKUP("538",V7_PROGRAM_TABLE,2,FALSE),IF(ISNUMBER(SEARCH("223a7",E15)),VLOOKUP("223a7",V7_PROGRAM_TABLE,2,FALSE),IF(ISNUMBER(SEARCH("223f",E15)),VLOOKUP("223f",V7_PROGRAM_TABLE,2,FALSE),V7_PROGRAM_DEFAULT)))) | AA15: =IF(S15=1,1+V7_PURPOSE_NC_BUMP*MAX(0,1-ABS(M15-V7_PURPOSE_PEAK_AGE)/V7_PURPOSE_WIDTH),1) | AB15: =IF(AND(IF(OR(P15="",NOT(ISNUMBER(P15))),0,MAX(0,MIN(24,(INT(VALUE(H15)/100)-INT(P15/100))*12+MOD(VALUE(H15),100)-MOD(P15,100))))>0,IF(OR(P15="",NOT(ISNUMBER(P15))),0,MAX(0,MIN(24,(INT(VALUE(H15)/100)-INT(P15/100))*12+MOD(VALUE(H15),100)-MOD(P15,100))))<=12),1+V7_LOCKOUT_AMP*EXP(-(IF(OR(P15="",NOT(ISNUMBER(P15))),0,MAX(0,MIN(24,(INT(VALUE(H15)/100)-INT(P15/100))*12+MOD(VALUE(H15),100)-MOD(P15,100)))))/V7_LOCKOUT_TAU),1) | AC15: =IF(IF(OR(O15="",NOT(ISNUMBER(O15))),360,MAX(0,MIN(480,(INT(O15/100)-INT(VALUE(H15)/100))*12+MOD(O15,100)-MOD(VALUE(H15),100))))>0,1+V7_MTY_AMP*MAX(0,(V7_MTY_CUTOFF-(IF(OR(O15="",NOT(ISNUMBER(O15))),360,MAX(0,MIN(480,(INT(O15/100)-INT(VALUE(H15)/100))*12+MOD(O15,100)-MOD(VALUE(H15),100))))))/V7_MTY_CUTOFF),1) | AD15: =MAX(V7_BURN_FLOOR,1-V7_BURN_SLOPE*MIN(1,MAX(0,R15))) | AE15: =IF(V7_USE_ISSUER=1,IFERROR(VLOOKUP(Q15,V7_ISSUER_TABLE,3,FALSE),1),1) | AF15: =PRODUCT(W15:AE15) | AG15: =MIN(V7_BASE_SMM*AF15,V7_SMM_CAP) | AH15: =1-(1-AG15)^12 | AI15: =IFERROR(LN(W15)/(LN(W15)+LN(X15)+LN(Y15)+LN(Z15)+LN(AA15)+LN(AB15)+LN(AC15)+LN(AD15))*(AH15-V7_BASE_CPR),0) | AJ15: =IFERROR(LN(X15)/(LN(W15)+LN(X15)+LN(Y15)+LN(Z15)+LN(AA15)+LN(AB15)+LN(AC15)+LN(AD15))*(AH15-V7_BASE_CPR),0) | AK15: =IFERROR(LN(Y15)/(LN(W15)+LN(X15)+LN(Y15)+LN(Z15)+LN(AA15)+LN(AB15)+LN(AC15)+LN(AD15))*(AH15-V7_BASE_CPR),0) | AL15: =IFERROR(LN(Z15)/(LN(W15)+LN(X15)+LN(Y15)+LN(Z15)+LN(AA15)+LN(AB15)+LN(AC15)+LN(AD15))*(AH15-V7_BASE_CPR),0) | AM15: =IFERROR(LN(AA15)/(LN(W15)+LN(X15)+LN(Y15)+LN(Z15)+LN(AA15)+LN(AB15)+LN(AC15)+LN(AD15))*(AH15-V7_BASE_CPR),0) | AN15: =IFERROR(LN(AB15)/(LN(W15)+LN(X15)+LN(Y15)+LN(Z15)+LN(AA15)+LN(AB15)+LN(AC15)+LN(AD15))*(AH15-V7_BASE_CPR),0) | AO15: =IFERROR(LN(AC15)/(LN(W15)+LN(X15)+LN(Y15)+LN(Z15)+LN(AA15)+LN(AB15)+LN(AC15)+LN(AD15))*(AH15-V7_BASE_CPR),0) | AP15: =IFERROR(LN(AD15)/(LN(W15)+LN(X15)+LN(Y15)+LN(Z15)+LN(AA15)+LN(AB15)+LN(AC15)+LN(AD15))*(AH15-V7_BASE_CPR),0) | AQ15: =V7_BASE_CPR+SUM(AI15:AP15)-AH15
A16: 3617FTDM7_000000008311235 | B16: LUMENT_POST21 | C16: 3617FTDM7 | D16: LUMENT REAL ESTATE CAPITAL,LLC | E16: 223f | F16: RP | G16: 2023 | H16: 202602 | I16: 15752462 | J16: 5.1 | K16: 447 | L16: 8 | M16: 34 | N16: 0 | O16: 205805 | Q16: 3896 | R16: 0 | S16: 0 | T16: =LN(1+I16) | U16: =J16*100-K16 | V16: =U16-12.5*(L16+1) | W16: =IF(M16<=V7_AGE_KNOT_X_0,V7_AGE_KNOT_Y_0,IF(M16>=V7_AGE_KNOT_X_5,V7_AGE_KNOT_Y_5,IF(M16<=V7_AGE_KNOT_X_1,V7_AGE_KNOT_Y_0+(M16-V7_AGE_KNOT_X_0)/(V7_AGE_KNOT_X_1-V7_AGE_KNOT_X_0)*(V7_AGE_KNOT_Y_1-V7_AGE_KNOT_Y_0),IF(M16<=V7_AGE_KNOT_X_2,V7_AGE_KNOT_Y_1+(M16-V7_AGE_KNOT_X_1)/(V7_AGE_KNOT_X_2-V7_AGE_KNOT_X_1)*(V7_AGE_KNOT_Y_2-V7_AGE_KNOT_Y_1),IF(M16<=V7_AGE_KNOT_X_3,V7_AGE_KNOT_Y_2+(M16-V7_AGE_KNOT_X_2)/(V7_AGE_KNOT_X_3-V7_AGE_KNOT_X_2)*(V7_AGE_KNOT_Y_3-V7_AGE_KNOT_Y_2),IF(M16<=V7_AGE_KNOT_X_4,V7_AGE_KNOT_Y_3+(M16-V7_AGE_KNOT_X_3)/(V7_AGE_KNOT_X_4-V7_AGE_KNOT_X_3)*(V7_AGE_KNOT_Y_4-V7_AGE_KNOT_Y_3),V7_AGE_KNOT_Y_4+(M16-V7_AGE_KNOT_X_4)/(V7_AGE_KNOT_X_5-V7_AGE_KNOT_X_4)*(V7_AGE_KNOT_Y_5-V7_AGE_KNOT_Y_4))))))) | X16: =V7_RATE_FLOOR+V7_RATE_ASYMPTOTE/(1+EXP(-(V16-V7_RATE_MID)/V7_RATE_SLOPE)) | Y16: =MAX(V7_SIZE_LOW,MIN(V7_SIZE_HIGH,V7_SIZE_INTERCEPT+V7_SIZE_SLOPE*(T16-V7_SIZE_LOG_ANCHOR))) | Z16: =IF(ISNUMBER(SEARCH("232",E16)),VLOOKUP("232",V7_PROGRAM_TABLE,2,FALSE),IF(ISNUMBER(SEARCH("538",E16)),VLOOKUP("538",V7_PROGRAM_TABLE,2,FALSE),IF(ISNUMBER(SEARCH("223a7",E16)),VLOOKUP("223a7",V7_PROGRAM_TABLE,2,FALSE),IF(ISNUMBER(SEARCH("223f",E16)),VLOOKUP("223f",V7_PROGRAM_TABLE,2,FALSE),V7_PROGRAM_DEFAULT)))) | AA16: =IF(S16=1,1+V7_PURPOSE_NC_BUMP*MAX(0,1-ABS(M16-V7_PURPOSE_PEAK_AGE)/V7_PURPOSE_WIDTH),1) | AB16: =IF(AND(IF(OR(P16="",NOT(ISNUMBER(P16))),0,MAX(0,MIN(24,(INT(VALUE(H16)/100)-INT(P16/100))*12+MOD(VALUE(H16),100)-MOD(P16,100))))>0,IF(OR(P16="",NOT(ISNUMBER(P16))),0,MAX(0,MIN(24,(INT(VALUE(H16)/100)-INT(P16/100))*12+MOD(VALUE(H16),100)-MOD(P16,100))))<=12),1+V7_LOCKOUT_AMP*EXP(-(IF(OR(P16="",NOT(ISNUMBER(P16))),0,MAX(0,MIN(24,(INT(VALUE(H16)/100)-INT(P16/100))*12+MOD(VALUE(H16),100)-MOD(P16,100)))))/V7_LOCKOUT_TAU),1) | AC16: =IF(IF(OR(O16="",NOT(ISNUMBER(O16))),360,MAX(0,MIN(480,(INT(O16/100)-INT(VALUE(H16)/100))*12+MOD(O16,100)-MOD(VALUE(H16),100))))>0,1+V7_MTY_AMP*MAX(0,(V7_MTY_CUTOFF-(IF(OR(O16="",NOT(ISNUMBER(O16))),360,MAX(0,MIN(480,(INT(O16/100)-INT(VALUE(H16)/100))*12+MOD(O16,100)-MOD(VALUE(H16),100))))))/V7_MTY_CUTOFF),1) | AD16: =MAX(V7_BURN_FLOOR,1-V7_BURN_SLOPE*MIN(1,MAX(0,R16))) | AE16: =IF(V7_USE_ISSUER=1,IFERROR(VLOOKUP(Q16,V7_ISSUER_TABLE,3,FALSE),1),1) | AF16: =PRODUCT(W16:AE16) | AG16: =MIN(V7_BASE_SMM*AF16,V7_SMM_CAP) | AH16: =1-(1-AG16)^12 | AI16: =IFERROR(LN(W16)/(LN(W16)+LN(X16)+LN(Y16)+LN(Z16)+LN(AA16)+LN(AB16)+LN(AC16)+LN(AD16))*(AH16-V7_BASE_CPR),0) | AJ16: =IFERROR(LN(X16)/(LN(W16)+LN(X16)+LN(Y16)+LN(Z16)+LN(AA16)+LN(AB16)+LN(AC16)+LN(AD16))*(AH16-V7_BASE_CPR),0) | AK16: =IFERROR(LN(Y16)/(LN(W16)+LN(X16)+LN(Y16)+LN(Z16)+LN(AA16)+LN(AB16)+LN(AC16)+LN(AD16))*(AH16-V7_BASE_CPR),0) | AL16: =IFERROR(LN(Z16)/(LN(W16)+LN(X16)+LN(Y16)+LN(Z16)+LN(AA16)+LN(AB16)+LN(AC16)+LN(AD16))*(AH16-V7_BASE_CPR),0) | AM16: =IFERROR(LN(AA16)/(LN(W16)+LN(X16)+LN(Y16)+LN(Z16)+LN(AA16)+LN(AB16)+LN(AC16)+LN(AD16))*(AH16-V7_BASE_CPR),0) | AN16: =IFERROR(LN(AB16)/(LN(W16)+LN(X16)+LN(Y16)+LN(Z16)+LN(AA16)+LN(AB16)+LN(AC16)+LN(AD16))*(AH16-V7_BASE_CPR),0) | AO16: =IFERROR(LN(AC16)/(LN(W16)+LN(X16)+LN(Y16)+LN(Z16)+LN(AA16)+LN(AB16)+LN(AC16)+LN(AD16))*(AH16-V7_BASE_CPR),0) | AP16: =IFERROR(LN(AD16)/(LN(W16)+LN(X16)+LN(Y16)+LN(Z16)+LN(AA16)+LN(AB16)+LN(AC16)+LN(AD16))*(AH16-V7_BASE_CPR),0) | AQ16: =V7_BASE_CPR+SUM(AI16:AP16)-AH16
A17: 36187SCA3_000000001411159 | B17: LUMENT_PRE21 | C17: 36187SCA3 | D17: LUMENT REAL ESTATE CAPITAL,LLC | E17: 223f | F17: RP | G17: 2009 | H17: 202602 | I17: 1334344.3 | J17: 4.29 | K17: 447 | L17: 0 | M17: 205 | N17: 38 | O17: 204403 | Q17: 3896 | R17: 0.18536585 | S17: 0 | T17: =LN(1+I17) | U17: =J17*100-K17 | V17: =U17-12.5*(L17+1) | W17: =IF(M17<=V7_AGE_KNOT_X_0,V7_AGE_KNOT_Y_0,IF(M17>=V7_AGE_KNOT_X_5,V7_AGE_KNOT_Y_5,IF(M17<=V7_AGE_KNOT_X_1,V7_AGE_KNOT_Y_0+(M17-V7_AGE_KNOT_X_0)/(V7_AGE_KNOT_X_1-V7_AGE_KNOT_X_0)*(V7_AGE_KNOT_Y_1-V7_AGE_KNOT_Y_0),IF(M17<=V7_AGE_KNOT_X_2,V7_AGE_KNOT_Y_1+(M17-V7_AGE_KNOT_X_1)/(V7_AGE_KNOT_X_2-V7_AGE_KNOT_X_1)*(V7_AGE_KNOT_Y_2-V7_AGE_KNOT_Y_1),IF(M17<=V7_AGE_KNOT_X_3,V7_AGE_KNOT_Y_2+(M17-V7_AGE_KNOT_X_2)/(V7_AGE_KNOT_X_3-V7_AGE_KNOT_X_2)*(V7_AGE_KNOT_Y_3-V7_AGE_KNOT_Y_2),IF(M17<=V7_AGE_KNOT_X_4,V7_AGE_KNOT_Y_3+(M17-V7_AGE_KNOT_X_3)/(V7_AGE_KNOT_X_4-V7_AGE_KNOT_X_3)*(V7_AGE_KNOT_Y_4-V7_AGE_KNOT_Y_3),V7_AGE_KNOT_Y_4+(M17-V7_AGE_KNOT_X_4)/(V7_AGE_KNOT_X_5-V7_AGE_KNOT_X_4)*(V7_AGE_KNOT_Y_5-V7_AGE_KNOT_Y_4))))))) | X17: =V7_RATE_FLOOR+V7_RATE_ASYMPTOTE/(1+EXP(-(V17-V7_RATE_MID)/V7_RATE_SLOPE)) | Y17: =MAX(V7_SIZE_LOW,MIN(V7_SIZE_HIGH,V7_SIZE_INTERCEPT+V7_SIZE_SLOPE*(T17-V7_SIZE_LOG_ANCHOR))) | Z17: =IF(ISNUMBER(SEARCH("232",E17)),VLOOKUP("232",V7_PROGRAM_TABLE,2,FALSE),IF(ISNUMBER(SEARCH("538",E17)),VLOOKUP("538",V7_PROGRAM_TABLE,2,FALSE),IF(ISNUMBER(SEARCH("223a7",E17)),VLOOKUP("223a7",V7_PROGRAM_TABLE,2,FALSE),IF(ISNUMBER(SEARCH("223f",E17)),VLOOKUP("223f",V7_PROGRAM_TABLE,2,FALSE),V7_PROGRAM_DEFAULT)))) | AA17: =IF(S17=1,1+V7_PURPOSE_NC_BUMP*MAX(0,1-ABS(M17-V7_PURPOSE_PEAK_AGE)/V7_PURPOSE_WIDTH),1) | AB17: =IF(AND(IF(OR(P17="",NOT(ISNUMBER(P17))),0,MAX(0,MIN(24,(INT(VALUE(H17)/100)-INT(P17/100))*12+MOD(VALUE(H17),100)-MOD(P17,100))))>0,IF(OR(P17="",NOT(ISNUMBER(P17))),0,MAX(0,MIN(24,(INT(VALUE(H17)/100)-INT(P17/100))*12+MOD(VALUE(H17),100)-MOD(P17,100))))<=12),1+V7_LOCKOUT_AMP*EXP(-(IF(OR(P17="",NOT(ISNUMBER(P17))),0,MAX(0,MIN(24,(INT(VALUE(H17)/100)-INT(P17/100))*12+MOD(VALUE(H17),100)-MOD(P17,100)))))/V7_LOCKOUT_TAU),1) | AC17: =IF(IF(OR(O17="",NOT(ISNUMBER(O17))),360,MAX(0,MIN(480,(INT(O17/100)-INT(VALUE(H17)/100))*12+MOD(O17,100)-MOD(VALUE(H17),100))))>0,1+V7_MTY_AMP*MAX(0,(V7_MTY_CUTOFF-(IF(OR(O17="",NOT(ISNUMBER(O17))),360,MAX(0,MIN(480,(INT(O17/100)-INT(VALUE(H17)/100))*12+MOD(O17,100)-MOD(VALUE(H17),100))))))/V7_MTY_CUTOFF),1) | AD17: =MAX(V7_BURN_FLOOR,1-V7_BURN_SLOPE*MIN(1,MAX(0,R17))) | AE17: =IF(V7_USE_ISSUER=1,IFERROR(VLOOKUP(Q17,V7_ISSUER_TABLE,3,FALSE),1),1) | AF17: =PRODUCT(W17:AE17) | AG17: =MIN(V7_BASE_SMM*AF17,V7_SMM_CAP) | AH17: =1-(1-AG17)^12 | AI17: =IFERROR(LN(W17)/(LN(W17)+LN(X17)+LN(Y17)+LN(Z17)+LN(AA17)+LN(AB17)+LN(AC17)+LN(AD17))*(AH17-V7_BASE_CPR),0) | AJ17: =IFERROR(LN(X17)/(LN(W17)+LN(X17)+LN(Y17)+LN(Z17)+LN(AA17)+LN(AB17)+LN(AC17)+LN(AD17))*(AH17-V7_BASE_CPR),0) | AK17: =IFERROR(LN(Y17)/(LN(W17)+LN(X17)+LN(Y17)+LN(Z17)+LN(AA17)+LN(AB17)+LN(AC17)+LN(AD17))*(AH17-V7_BASE_CPR),0) | AL17: =IFERROR(LN(Z17)/(LN(W17)+LN(X17)+LN(Y17)+LN(Z17)+LN(AA17)+LN(AB17)+LN(AC17)+LN(AD17))*(AH17-V7_BASE_CPR),0) | AM17: =IFERROR(LN(AA17)/(LN(W17)+LN(X17)+LN(Y17)+LN(Z17)+LN(AA17)+LN(AB17)+LN(AC17)+LN(AD17))*(AH17-V7_BASE_CPR),0) | AN17: =IFERROR(LN(AB17)/(LN(W17)+LN(X17)+LN(Y17)+LN(Z17)+LN(AA17)+LN(AB17)+LN(AC17)+LN(AD17))*(AH17-V7_BASE_CPR),0) | AO17: =IFERROR(LN(AC17)/(LN(W17)+LN(X17)+LN(Y17)+LN(Z17)+LN(AA17)+LN(AB17)+LN(AC17)+LN(AD17))*(AH17-V7_BASE_CPR),0) | AP17: =IFERROR(LN(AD17)/(LN(W17)+LN(X17)+LN(Y17)+LN(Z17)+LN(AA17)+LN(AB17)+LN(AC17)+LN(AD17))*(AH17-V7_BASE_CPR),0) | AQ17: =V7_BASE_CPR+SUM(AI17:AP17)-AH17
A18: 3617AVUR7_049031028004210 | B18: LUMENT_PRE21 | C18: 3617AVUR7 | D18: LUMENT REAL ESTATE CAPITAL,LLC | E18: 538 | F18: 538 | G18: 2017 | H18: 202602 | I18: 1419192.9 | J18: 3.89 | K18: 447 | L18: 3 | M18: 103 | N18: 31 | O18: 204708 | Q18: 3896 | R18: 0.30097087 | S18: 0 | T18: =LN(1+I18) | U18: =J18*100-K18 | V18: =U18-12.5*(L18+1) | W18: =IF(M18<=V7_AGE_KNOT_X_0,V7_AGE_KNOT_Y_0,IF(M18>=V7_AGE_KNOT_X_5,V7_AGE_KNOT_Y_5,IF(M18<=V7_AGE_KNOT_X_1,V7_AGE_KNOT_Y_0+(M18-V7_AGE_KNOT_X_0)/(V7_AGE_KNOT_X_1-V7_AGE_KNOT_X_0)*(V7_AGE_KNOT_Y_1-V7_AGE_KNOT_Y_0),IF(M18<=V7_AGE_KNOT_X_2,V7_AGE_KNOT_Y_1+(M18-V7_AGE_KNOT_X_1)/(V7_AGE_KNOT_X_2-V7_AGE_KNOT_X_1)*(V7_AGE_KNOT_Y_2-V7_AGE_KNOT_Y_1),IF(M18<=V7_AGE_KNOT_X_3,V7_AGE_KNOT_Y_2+(M18-V7_AGE_KNOT_X_2)/(V7_AGE_KNOT_X_3-V7_AGE_KNOT_X_2)*(V7_AGE_KNOT_Y_3-V7_AGE_KNOT_Y_2),IF(M18<=V7_AGE_KNOT_X_4,V7_AGE_KNOT_Y_3+(M18-V7_AGE_KNOT_X_3)/(V7_AGE_KNOT_X_4-V7_AGE_KNOT_X_3)*(V7_AGE_KNOT_Y_4-V7_AGE_KNOT_Y_3),V7_AGE_KNOT_Y_4+(M18-V7_AGE_KNOT_X_4)/(V7_AGE_KNOT_X_5-V7_AGE_KNOT_X_4)*(V7_AGE_KNOT_Y_5-V7_AGE_KNOT_Y_4))))))) | X18: =V7_RATE_FLOOR+V7_RATE_ASYMPTOTE/(1+EXP(-(V18-V7_RATE_MID)/V7_RATE_SLOPE)) | Y18: =MAX(V7_SIZE_LOW,MIN(V7_SIZE_HIGH,V7_SIZE_INTERCEPT+V7_SIZE_SLOPE*(T18-V7_SIZE_LOG_ANCHOR))) | Z18: =IF(ISNUMBER(SEARCH("232",E18)),VLOOKUP("232",V7_PROGRAM_TABLE,2,FALSE),IF(ISNUMBER(SEARCH("538",E18)),VLOOKUP("538",V7_PROGRAM_TABLE,2,FALSE),IF(ISNUMBER(SEARCH("223a7",E18)),VLOOKUP("223a7",V7_PROGRAM_TABLE,2,FALSE),IF(ISNUMBER(SEARCH("223f",E18)),VLOOKUP("223f",V7_PROGRAM_TABLE,2,FALSE),V7_PROGRAM_DEFAULT)))) | AA18: =IF(S18=1,1+V7_PURPOSE_NC_BUMP*MAX(0,1-ABS(M18-V7_PURPOSE_PEAK_AGE)/V7_PURPOSE_WIDTH),1) | AB18: =IF(AND(IF(OR(P18="",NOT(ISNUMBER(P18))),0,MAX(0,MIN(24,(INT(VALUE(H18)/100)-INT(P18/100))*12+MOD(VALUE(H18),100)-MOD(P18,100))))>0,IF(OR(P18="",NOT(ISNUMBER(P18))),0,MAX(0,MIN(24,(INT(VALUE(H18)/100)-INT(P18/100))*12+MOD(VALUE(H18),100)-MOD(P18,100))))<=12),1+V7_LOCKOUT_AMP*EXP(-(IF(OR(P18="",NOT(ISNUMBER(P18))),0,MAX(0,MIN(24,(INT(VALUE(H18)/100)-INT(P18/100))*12+MOD(VALUE(H18),100)-MOD(P18,100)))))/V7_LOCKOUT_TAU),1) | AC18: =IF(IF(OR(O18="",NOT(ISNUMBER(O18))),360,MAX(0,MIN(480,(INT(O18/100)-INT(VALUE(H18)/100))*12+MOD(O18,100)-MOD(VALUE(H18),100))))>0,1+V7_MTY_AMP*MAX(0,(V7_MTY_CUTOFF-(IF(OR(O18="",NOT(ISNUMBER(O18))),360,MAX(0,MIN(480,(INT(O18/100)-INT(VALUE(H18)/100))*12+MOD(O18,100)-MOD(VALUE(H18),100))))))/V7_MTY_CUTOFF),1) | AD18: =MAX(V7_BURN_FLOOR,1-V7_BURN_SLOPE*MIN(1,MAX(0,R18))) | AE18: =IF(V7_USE_ISSUER=1,IFERROR(VLOOKUP(Q18,V7_ISSUER_TABLE,3,FALSE),1),1) | AF18: =PRODUCT(W18:AE18) | AG18: =MIN(V7_BASE_SMM*AF18,V7_SMM_CAP) | AH18: =1-(1-AG18)^12 | AI18: =IFERROR(LN(W18)/(LN(W18)+LN(X18)+LN(Y18)+LN(Z18)+LN(AA18)+LN(AB18)+LN(AC18)+LN(AD18))*(AH18-V7_BASE_CPR),0) | AJ18: =IFERROR(LN(X18)/(LN(W18)+LN(X18)+LN(Y18)+LN(Z18)+LN(AA18)+LN(AB18)+LN(AC18)+LN(AD18))*(AH18-V7_BASE_CPR),0) | AK18: =IFERROR(LN(Y18)/(LN(W18)+LN(X18)+LN(Y18)+LN(Z18)+LN(AA18)+LN(AB18)+LN(AC18)+LN(AD18))*(AH18-V7_BASE_CPR),0) | AL18: =IFERROR(LN(Z18)/(LN(W18)+LN(X18)+LN(Y18)+LN(Z18)+LN(AA18)+LN(AB18)+LN(AC18)+LN(AD18))*(AH18-V7_BASE_CPR),0) | AM18: =IFERROR(LN(AA18)/(LN(W18)+LN(X18)+LN(Y18)+LN(Z18)+LN(AA18)+LN(AB18)+LN(AC18)+LN(AD18))*(AH18-V7_BASE_CPR),0) | AN18: =IFERROR(LN(AB18)/(LN(W18)+LN(X18)+LN(Y18)+LN(Z18)+LN(AA18)+LN(AB18)+LN(AC18)+LN(AD18))*(AH18-V7_BASE_CPR),0) | AO18: =IFERROR(LN(AC18)/(LN(W18)+LN(X18)+LN(Y18)+LN(Z18)+LN(AA18)+LN(AB18)+LN(AC18)+LN(AD18))*(AH18-V7_BASE_CPR),0) | AP18: =IFERROR(LN(AD18)/(LN(W18)+LN(X18)+LN(Y18)+LN(Z18)+LN(AA18)+LN(AB18)+LN(AC18)+LN(AD18))*(AH18-V7_BASE_CPR),0) | AQ18: =V7_BASE_CPR+SUM(AI18:AP18)-AH18
A19: 3617GKP67_000000002411077 | B19: LUMENT_PRE21 | C19: 3617GKP67 | D19: LUMENT REAL ESTATE CAPITAL,LLC | E19: 223f | F19: RP | G19: 2018 | H19: 202602 | I19: 5685256.4 | J19: 4.02 | K19: 447 | L19: 3 | M19: 93 | N19: 32 | O19: 205306 | Q19: 3896 | R19: 0.34408602 | S19: 0 | T19: =LN(1+I19) | U19: =J19*100-K19 | V19: =U19-12.5*(L19+1) | W19: =IF(M19<=V7_AGE_KNOT_X_0,V7_AGE_KNOT_Y_0,IF(M19>=V7_AGE_KNOT_X_5,V7_AGE_KNOT_Y_5,IF(M19<=V7_AGE_KNOT_X_1,V7_AGE_KNOT_Y_0+(M19-V7_AGE_KNOT_X_0)/(V7_AGE_KNOT_X_1-V7_AGE_KNOT_X_0)*(V7_AGE_KNOT_Y_1-V7_AGE_KNOT_Y_0),IF(M19<=V7_AGE_KNOT_X_2,V7_AGE_KNOT_Y_1+(M19-V7_AGE_KNOT_X_1)/(V7_AGE_KNOT_X_2-V7_AGE_KNOT_X_1)*(V7_AGE_KNOT_Y_2-V7_AGE_KNOT_Y_1),IF(M19<=V7_AGE_KNOT_X_3,V7_AGE_KNOT_Y_2+(M19-V7_AGE_KNOT_X_2)/(V7_AGE_KNOT_X_3-V7_AGE_KNOT_X_2)*(V7_AGE_KNOT_Y_3-V7_AGE_KNOT_Y_2),IF(M19<=V7_AGE_KNOT_X_4,V7_AGE_KNOT_Y_3+(M19-V7_AGE_KNOT_X_3)/(V7_AGE_KNOT_X_4-V7_AGE_KNOT_X_3)*(V7_AGE_KNOT_Y_4-V7_AGE_KNOT_Y_3),V7_AGE_KNOT_Y_4+(M19-V7_AGE_KNOT_X_4)/(V7_AGE_KNOT_X_5-V7_AGE_KNOT_X_4)*(V7_AGE_KNOT_Y_5-V7_AGE_KNOT_Y_4))))))) | X19: =V7_RATE_FLOOR+V7_RATE_ASYMPTOTE/(1+EXP(-(V19-V7_RATE_MID)/V7_RATE_SLOPE)) | Y19: =MAX(V7_SIZE_LOW,MIN(V7_SIZE_HIGH,V7_SIZE_INTERCEPT+V7_SIZE_SLOPE*(T19-V7_SIZE_LOG_ANCHOR))) | Z19: =IF(ISNUMBER(SEARCH("232",E19)),VLOOKUP("232",V7_PROGRAM_TABLE,2,FALSE),IF(ISNUMBER(SEARCH("538",E19)),VLOOKUP("538",V7_PROGRAM_TABLE,2,FALSE),IF(ISNUMBER(SEARCH("223a7",E19)),VLOOKUP("223a7",V7_PROGRAM_TABLE,2,FALSE),IF(ISNUMBER(SEARCH("223f",E19)),VLOOKUP("223f",V7_PROGRAM_TABLE,2,FALSE),V7_PROGRAM_DEFAULT)))) | AA19: =IF(S19=1,1+V7_PURPOSE_NC_BUMP*MAX(0,1-ABS(M19-V7_PURPOSE_PEAK_AGE)/V7_PURPOSE_WIDTH),1) | AB19: =IF(AND(IF(OR(P19="",NOT(ISNUMBER(P19))),0,MAX(0,MIN(24,(INT(VALUE(H19)/100)-INT(P19/100))*12+MOD(VALUE(H19),100)-MOD(P19,100))))>0,IF(OR(P19="",NOT(ISNUMBER(P19))),0,MAX(0,MIN(24,(INT(VALUE(H19)/100)-INT(P19/100))*12+MOD(VALUE(H19),100)-MOD(P19,100))))<=12),1+V7_LOCKOUT_AMP*EXP(-(IF(OR(P19="",NOT(ISNUMBER(P19))),0,MAX(0,MIN(24,(INT(VALUE(H19)/100)-INT(P19/100))*12+MOD(VALUE(H19),100)-MOD(P19,100)))))/V7_LOCKOUT_TAU),1) | AC19: =IF(IF(OR(O19="",NOT(ISNUMBER(O19))),360,MAX(0,MIN(480,(INT(O19/100)-INT(VALUE(H19)/100))*12+MOD(O19,100)-MOD(VALUE(H19),100))))>0,1+V7_MTY_AMP*MAX(0,(V7_MTY_CUTOFF-(IF(OR(O19="",NOT(ISNUMBER(O19))),360,MAX(0,MIN(480,(INT(O19/100)-INT(VALUE(H19)/100))*12+MOD(O19,100)-MOD(VALUE(H19),100))))))/V7_MTY_CUTOFF),1) | AD19: =MAX(V7_BURN_FLOOR,1-V7_BURN_SLOPE*MIN(1,MAX(0,R19))) | AE19: =IF(V7_USE_ISSUER=1,IFERROR(VLOOKUP(Q19,V7_ISSUER_TABLE,3,FALSE),1),1) | AF19: =PRODUCT(W19:AE19) | AG19: =MIN(V7_BASE_SMM*AF19,V7_SMM_CAP) | AH19: =1-(1-AG19)^12 | AI19: =IFERROR(LN(W19)/(LN(W19)+LN(X19)+LN(Y19)+LN(Z19)+LN(AA19)+LN(AB19)+LN(AC19)+LN(AD19))*(AH19-V7_BASE_CPR),0) | AJ19: =IFERROR(LN(X19)/(LN(W19)+LN(X19)+LN(Y19)+LN(Z19)+LN(AA19)+LN(AB19)+LN(AC19)+LN(AD19))*(AH19-V7_BASE_CPR),0) | AK19: =IFERROR(LN(Y19)/(LN(W19)+LN(X19)+LN(Y19)+LN(Z19)+LN(AA19)+LN(AB19)+LN(AC19)+LN(AD19))*(AH19-V7_BASE_CPR),0) | AL19: =IFERROR(LN(Z19)/(LN(W19)+LN(X19)+LN(Y19)+LN(Z19)+LN(AA19)+LN(AB19)+LN(AC19)+LN(AD19))*(AH19-V7_BASE_CPR),0) | AM19: =IFERROR(LN(AA19)/(LN(W19)+LN(X19)+LN(Y19)+LN(Z19)+LN(AA19)+LN(AB19)+LN(AC19)+LN(AD19))*(AH19-V7_BASE_CPR),0) | AN19: =IFERROR(LN(AB19)/(LN(W19)+LN(X19)+LN(Y19)+LN(Z19)+LN(AA19)+LN(AB19)+LN(AC19)+LN(AD19))*(AH19-V7_BASE_CPR),0) | AO19: =IFERROR(LN(AC19)/(LN(W19)+LN(X19)+LN(Y19)+LN(Z19)+LN(AA19)+LN(AB19)+LN(AC19)+LN(AD19))*(AH19-V7_BASE_CPR),0) | AP19: =IFERROR(LN(AD19)/(LN(W19)+LN(X19)+LN(Y19)+LN(Z19)+LN(AA19)+LN(AB19)+LN(AC19)+LN(AD19))*(AH19-V7_BASE_CPR),0) | AQ19: =V7_BASE_CPR+SUM(AI19:AP19)-AH19
A20: 36180QCV8_000000010535250 | B20: LUMENT_PRE21 | C20: 36180QCV8 | D20: LUMENT REAL ESTATE CAPITAL,LLC | E20: 221d4 | F20: NC | G20: 2015 | H20: 202602 | I20: 2808410.9 | J20: 3.35 | K20: 447 | L20: 1 | M20: 128 | N20: 27 | O20: 205604 | Q20: 3896 | R20: 0.2109375 | S20: 1 | T20: =LN(1+I20) | U20: =J20*100-K20 | V20: =U20-12.5*(L20+1) | W20: =IF(M20<=V7_AGE_KNOT_X_0,V7_AGE_KNOT_Y_0,IF(M20>=V7_AGE_KNOT_X_5,V7_AGE_KNOT_Y_5,IF(M20<=V7_AGE_KNOT_X_1,V7_AGE_KNOT_Y_0+(M20-V7_AGE_KNOT_X_0)/(V7_AGE_KNOT_X_1-V7_AGE_KNOT_X_0)*(V7_AGE_KNOT_Y_1-V7_AGE_KNOT_Y_0),IF(M20<=V7_AGE_KNOT_X_2,V7_AGE_KNOT_Y_1+(M20-V7_AGE_KNOT_X_1)/(V7_AGE_KNOT_X_2-V7_AGE_KNOT_X_1)*(V7_AGE_KNOT_Y_2-V7_AGE_KNOT_Y_1),IF(M20<=V7_AGE_KNOT_X_3,V7_AGE_KNOT_Y_2+(M20-V7_AGE_KNOT_X_2)/(V7_AGE_KNOT_X_3-V7_AGE_KNOT_X_2)*(V7_AGE_KNOT_Y_3-V7_AGE_KNOT_Y_2),IF(M20<=V7_AGE_KNOT_X_4,V7_AGE_KNOT_Y_3+(M20-V7_AGE_KNOT_X_3)/(V7_AGE_KNOT_X_4-V7_AGE_KNOT_X_3)*(V7_AGE_KNOT_Y_4-V7_AGE_KNOT_Y_3),V7_AGE_KNOT_Y_4+(M20-V7_AGE_KNOT_X_4)/(V7_AGE_KNOT_X_5-V7_AGE_KNOT_X_4)*(V7_AGE_KNOT_Y_5-V7_AGE_KNOT_Y_4))))))) | X20: =V7_RATE_FLOOR+V7_RATE_ASYMPTOTE/(1+EXP(-(V20-V7_RATE_MID)/V7_RATE_SLOPE)) | Y20: =MAX(V7_SIZE_LOW,MIN(V7_SIZE_HIGH,V7_SIZE_INTERCEPT+V7_SIZE_SLOPE*(T20-V7_SIZE_LOG_ANCHOR))) | Z20: =IF(ISNUMBER(SEARCH("232",E20)),VLOOKUP("232",V7_PROGRAM_TABLE,2,FALSE),IF(ISNUMBER(SEARCH("538",E20)),VLOOKUP("538",V7_PROGRAM_TABLE,2,FALSE),IF(ISNUMBER(SEARCH("223a7",E20)),VLOOKUP("223a7",V7_PROGRAM_TABLE,2,FALSE),IF(ISNUMBER(SEARCH("223f",E20)),VLOOKUP("223f",V7_PROGRAM_TABLE,2,FALSE),V7_PROGRAM_DEFAULT)))) | AA20: =IF(S20=1,1+V7_PURPOSE_NC_BUMP*MAX(0,1-ABS(M20-V7_PURPOSE_PEAK_AGE)/V7_PURPOSE_WIDTH),1) | AB20: =IF(AND(IF(OR(P20="",NOT(ISNUMBER(P20))),0,MAX(0,MIN(24,(INT(VALUE(H20)/100)-INT(P20/100))*12+MOD(VALUE(H20),100)-MOD(P20,100))))>0,IF(OR(P20="",NOT(ISNUMBER(P20))),0,MAX(0,MIN(24,(INT(VALUE(H20)/100)-INT(P20/100))*12+MOD(VALUE(H20),100)-MOD(P20,100))))<=12),1+V7_LOCKOUT_AMP*EXP(-(IF(OR(P20="",NOT(ISNUMBER(P20))),0,MAX(0,MIN(24,(INT(VALUE(H20)/100)-INT(P20/100))*12+MOD(VALUE(H20),100)-MOD(P20,100)))))/V7_LOCKOUT_TAU),1) | AC20: =IF(IF(OR(O20="",NOT(ISNUMBER(O20))),360,MAX(0,MIN(480,(INT(O20/100)-INT(VALUE(H20)/100))*12+MOD(O20,100)-MOD(VALUE(H20),100))))>0,1+V7_MTY_AMP*MAX(0,(V7_MTY_CUTOFF-(IF(OR(O20="",NOT(ISNUMBER(O20))),360,MAX(0,MIN(480,(INT(O20/100)-INT(VALUE(H20)/100))*12+MOD(O20,100)-MOD(VALUE(H20),100))))))/V7_MTY_CUTOFF),1) | AD20: =MAX(V7_BURN_FLOOR,1-V7_BURN_SLOPE*MIN(1,MAX(0,R20))) | AE20: =IF(V7_USE_ISSUER=1,IFERROR(VLOOKUP(Q20,V7_ISSUER_TABLE,3,FALSE),1),1) | AF20: =PRODUCT(W20:AE20) | AG20: =MIN(V7_BASE_SMM*AF20,V7_SMM_CAP) | AH20: =1-(1-AG20)^12 | AI20: =IFERROR(LN(W20)/(LN(W20)+LN(X20)+LN(Y20)+LN(Z20)+LN(AA20)+LN(AB20)+LN(AC20)+LN(AD20))*(AH20-V7_BASE_CPR),0) | AJ20: =IFERROR(LN(X20)/(LN(W20)+LN(X20)+LN(Y20)+LN(Z20)+LN(AA20)+LN(AB20)+LN(AC20)+LN(AD20))*(AH20-V7_BASE_CPR),0) | AK20: =IFERROR(LN(Y20)/(LN(W20)+LN(X20)+LN(Y20)+LN(Z20)+LN(AA20)+LN(AB20)+LN(AC20)+LN(AD20))*(AH20-V7_BASE_CPR),0) | AL20: =IFERROR(LN(Z20)/(LN(W20)+LN(X20)+LN(Y20)+LN(Z20)+LN(AA20)+LN(AB20)+LN(AC20)+LN(AD20))*(AH20-V7_BASE_CPR),0) | AM20: =IFERROR(LN(AA20)/(LN(W20)+LN(X20)+LN(Y20)+LN(Z20)+LN(AA20)+LN(AB20)+LN(AC20)+LN(AD20))*(AH20-V7_BASE_CPR),0) | AN20: =IFERROR(LN(AB20)/(LN(W20)+LN(X20)+LN(Y20)+LN(Z20)+LN(AA20)+LN(AB20)+LN(AC20)+LN(AD20))*(AH20-V7_BASE_CPR),0) | AO20: =IFERROR(LN(AC20)/(LN(W20)+LN(X20)+LN(Y20)+LN(Z20)+LN(AA20)+LN(AB20)+LN(AC20)+LN(AD20))*(AH20-V7_BASE_CPR),0) | AP20: =IFERROR(LN(AD20)/(LN(W20)+LN(X20)+LN(Y20)+LN(Z20)+LN(AA20)+LN(AB20)+LN(AC20)+LN(AD20))*(AH20-V7_BASE_CPR),0) | AQ20: =V7_BASE_CPR+SUM(AI20:AP20)-AH20
A21: 3617X76V3_000000012211483 | B21: LUMENT_POST21 | C21: 3617X76V3 | D21: LUMENT REAL ESTATE CAPITAL,LLC | E21: 223f | F21: RP | G21: 2022 | H21: 202602 | I21: 11152291 | J21: 2.6 | K21: 447 | L21: 7 | M21: 47 | N21: 0 | O21: 205704 | Q21: 3896 | R21: 0 | S21: 0 | T21: =LN(1+I21) | U21: =J21*100-K21 | V21: =U21-12.5*(L21+1) | W21: =IF(M21<=V7_AGE_KNOT_X_0,V7_AGE_KNOT_Y_0,IF(M21>=V7_AGE_KNOT_X_5,V7_AGE_KNOT_Y_5,IF(M21<=V7_AGE_KNOT_X_1,V7_AGE_KNOT_Y_0+(M21-V7_AGE_KNOT_X_0)/(V7_AGE_KNOT_X_1-V7_AGE_KNOT_X_0)*(V7_AGE_KNOT_Y_1-V7_AGE_KNOT_Y_0),IF(M21<=V7_AGE_KNOT_X_2,V7_AGE_KNOT_Y_1+(M21-V7_AGE_KNOT_X_1)/(V7_AGE_KNOT_X_2-V7_AGE_KNOT_X_1)*(V7_AGE_KNOT_Y_2-V7_AGE_KNOT_Y_1),IF(M21<=V7_AGE_KNOT_X_3,V7_AGE_KNOT_Y_2+(M21-V7_AGE_KNOT_X_2)/(V7_AGE_KNOT_X_3-V7_AGE_KNOT_X_2)*(V7_AGE_KNOT_Y_3-V7_AGE_KNOT_Y_2),IF(M21<=V7_AGE_KNOT_X_4,V7_AGE_KNOT_Y_3+(M21-V7_AGE_KNOT_X_3)/(V7_AGE_KNOT_X_4-V7_AGE_KNOT_X_3)*(V7_AGE_KNOT_Y_4-V7_AGE_KNOT_Y_3),V7_AGE_KNOT_Y_4+(M21-V7_AGE_KNOT_X_4)/(V7_AGE_KNOT_X_5-V7_AGE_KNOT_X_4)*(V7_AGE_KNOT_Y_5-V7_AGE_KNOT_Y_4))))))) | X21: =V7_RATE_FLOOR+V7_RATE_ASYMPTOTE/(1+EXP(-(V21-V7_RATE_MID)/V7_RATE_SLOPE)) | Y21: =MAX(V7_SIZE_LOW,MIN(V7_SIZE_HIGH,V7_SIZE_INTERCEPT+V7_SIZE_SLOPE*(T21-V7_SIZE_LOG_ANCHOR))) | Z21: =IF(ISNUMBER(SEARCH("232",E21)),VLOOKUP("232",V7_PROGRAM_TABLE,2,FALSE),IF(ISNUMBER(SEARCH("538",E21)),VLOOKUP("538",V7_PROGRAM_TABLE,2,FALSE),IF(ISNUMBER(SEARCH("223a7",E21)),VLOOKUP("223a7",V7_PROGRAM_TABLE,2,FALSE),IF(ISNUMBER(SEARCH("223f",E21)),VLOOKUP("223f",V7_PROGRAM_TABLE,2,FALSE),V7_PROGRAM_DEFAULT)))) | AA21: =IF(S21=1,1+V7_PURPOSE_NC_BUMP*MAX(0,1-ABS(M21-V7_PURPOSE_PEAK_AGE)/V7_PURPOSE_WIDTH),1) | AB21: =IF(AND(IF(OR(P21="",NOT(ISNUMBER(P21))),0,MAX(0,MIN(24,(INT(VALUE(H21)/100)-INT(P21/100))*12+MOD(VALUE(H21),100)-MOD(P21,100))))>0,IF(OR(P21="",NOT(ISNUMBER(P21))),0,MAX(0,MIN(24,(INT(VALUE(H21)/100)-INT(P21/100))*12+MOD(VALUE(H21),100)-MOD(P21,100))))<=12),1+V7_LOCKOUT_AMP*EXP(-(IF(OR(P21="",NOT(ISNUMBER(P21))),0,MAX(0,MIN(24,(INT(VALUE(H21)/100)-INT(P21/100))*12+MOD(VALUE(H21),100)-MOD(P21,100)))))/V7_LOCKOUT_TAU),1) | AC21: =IF(IF(OR(O21="",NOT(ISNUMBER(O21))),360,MAX(0,MIN(480,(INT(O21/100)-INT(VALUE(H21)/100))*12+MOD(O21,100)-MOD(VALUE(H21),100))))>0,1+V7_MTY_AMP*MAX(0,(V7_MTY_CUTOFF-(IF(OR(O21="",NOT(ISNUMBER(O21))),360,MAX(0,MIN(480,(INT(O21/100)-INT(VALUE(H21)/100))*12+MOD(O21,100)-MOD(VALUE(H21),100))))))/V7_MTY_CUTOFF),1) | AD21: =MAX(V7_BURN_FLOOR,1-V7_BURN_SLOPE*MIN(1,MAX(0,R21))) | AE21: =IF(V7_USE_ISSUER=1,IFERROR(VLOOKUP(Q21,V7_ISSUER_TABLE,3,FALSE),1),1) | AF21: =PRODUCT(W21:AE21) | AG21: =MIN(V7_BASE_SMM*AF21,V7_SMM_CAP) | AH21: =1-(1-AG21)^12 | AI21: =IFERROR(LN(W21)/(LN(W21)+LN(X21)+LN(Y21)+LN(Z21)+LN(AA21)+LN(AB21)+LN(AC21)+LN(AD21))*(AH21-V7_BASE_CPR),0) | AJ21: =IFERROR(LN(X21)/(LN(W21)+LN(X21)+LN(Y21)+LN(Z21)+LN(AA21)+LN(AB21)+LN(AC21)+LN(AD21))*(AH21-V7_BASE_CPR),0) | AK21: =IFERROR(LN(Y21)/(LN(W21)+LN(X21)+LN(Y21)+LN(Z21)+LN(AA21)+LN(AB21)+LN(AC21)+LN(AD21))*(AH21-V7_BASE_CPR),0) | AL21: =IFERROR(LN(Z21)/(LN(W21)+LN(X21)+LN(Y21)+LN(Z21)+LN(AA21)+LN(AB21)+LN(AC21)+LN(AD21))*(AH21-V7_BASE_CPR),0) | AM21: =IFERROR(LN(AA21)/(LN(W21)+LN(X21)+LN(Y21)+LN(Z21)+LN(AA21)+LN(AB21)+LN(AC21)+LN(AD21))*(AH21-V7_BASE_CPR),0) | AN21: =IFERROR(LN(AB21)/(LN(W21)+LN(X21)+LN(Y21)+LN(Z21)+LN(AA21)+LN(AB21)+LN(AC21)+LN(AD21))*(AH21-V7_BASE_CPR),0) | AO21: =IFERROR(LN(AC21)/(LN(W21)+LN(X21)+LN(Y21)+LN(Z21)+LN(AA21)+LN(AB21)+LN(AC21)+LN(AD21))*(AH21-V7_BASE_CPR),0) | AP21: =IFERROR(LN(AD21)/(LN(W21)+LN(X21)+LN(Y21)+LN(Z21)+LN(AA21)+LN(AB21)+LN(AC21)+LN(AD21))*(AH21-V7_BASE_CPR),0) | AQ21: =V7_BASE_CPR+SUM(AI21:AP21)-AH21
A22: 3617W8NP6_000000011335648 | B22: LUMENT_PRE21 | C22: 3617W8NP6 | D22: LUMENT REAL ESTATE CAPITAL,LLC | E22: 221d4 | F22: NC | G22: 2016 | H22: 202602 | I22: 17567640 | J22: 2.65 | K22: 447 | L22: 6 | M22: 114 | N22: 0 | O22: 205802 | Q22: 3896 | R22: 0 | S22: 1 | T22: =LN(1+I22) | U22: =J22*100-K22 | V22: =U22-12.5*(L22+1) | W22: =IF(M22<=V7_AGE_KNOT_X_0,V7_AGE_KNOT_Y_0,IF(M22>=V7_AGE_KNOT_X_5,V7_AGE_KNOT_Y_5,IF(M22<=V7_AGE_KNOT_X_1,V7_AGE_KNOT_Y_0+(M22-V7_AGE_KNOT_X_0)/(V7_AGE_KNOT_X_1-V7_AGE_KNOT_X_0)*(V7_AGE_KNOT_Y_1-V7_AGE_KNOT_Y_0),IF(M22<=V7_AGE_KNOT_X_2,V7_AGE_KNOT_Y_1+(M22-V7_AGE_KNOT_X_1)/(V7_AGE_KNOT_X_2-V7_AGE_KNOT_X_1)*(V7_AGE_KNOT_Y_2-V7_AGE_KNOT_Y_1),IF(M22<=V7_AGE_KNOT_X_3,V7_AGE_KNOT_Y_2+(M22-V7_AGE_KNOT_X_2)/(V7_AGE_KNOT_X_3-V7_AGE_KNOT_X_2)*(V7_AGE_KNOT_Y_3-V7_AGE_KNOT_Y_2),IF(M22<=V7_AGE_KNOT_X_4,V7_AGE_KNOT_Y_3+(M22-V7_AGE_KNOT_X_3)/(V7_AGE_KNOT_X_4-V7_AGE_KNOT_X_3)*(V7_AGE_KNOT_Y_4-V7_AGE_KNOT_Y_3),V7_AGE_KNOT_Y_4+(M22-V7_AGE_KNOT_X_4)/(V7_AGE_KNOT_X_5-V7_AGE_KNOT_X_4)*(V7_AGE_KNOT_Y_5-V7_AGE_KNOT_Y_4))))))) | X22: =V7_RATE_FLOOR+V7_RATE_ASYMPTOTE/(1+EXP(-(V22-V7_RATE_MID)/V7_RATE_SLOPE)) | Y22: =MAX(V7_SIZE_LOW,MIN(V7_SIZE_HIGH,V7_SIZE_INTERCEPT+V7_SIZE_SLOPE*(T22-V7_SIZE_LOG_ANCHOR))) | Z22: =IF(ISNUMBER(SEARCH("232",E22)),VLOOKUP("232",V7_PROGRAM_TABLE,2,FALSE),IF(ISNUMBER(SEARCH("538",E22)),VLOOKUP("538",V7_PROGRAM_TABLE,2,FALSE),IF(ISNUMBER(SEARCH("223a7",E22)),VLOOKUP("223a7",V7_PROGRAM_TABLE,2,FALSE),IF(ISNUMBER(SEARCH("223f",E22)),VLOOKUP("223f",V7_PROGRAM_TABLE,2,FALSE),V7_PROGRAM_DEFAULT)))) | AA22: =IF(S22=1,1+V7_PURPOSE_NC_BUMP*MAX(0,1-ABS(M22-V7_PURPOSE_PEAK_AGE)/V7_PURPOSE_WIDTH),1) | AB22: =IF(AND(IF(OR(P22="",NOT(ISNUMBER(P22))),0,MAX(0,MIN(24,(INT(VALUE(H22)/100)-INT(P22/100))*12+MOD(VALUE(H22),100)-MOD(P22,100))))>0,IF(OR(P22="",NOT(ISNUMBER(P22))),0,MAX(0,MIN(24,(INT(VALUE(H22)/100)-INT(P22/100))*12+MOD(VALUE(H22),100)-MOD(P22,100))))<=12),1+V7_LOCKOUT_AMP*EXP(-(IF(OR(P22="",NOT(ISNUMBER(P22))),0,MAX(0,MIN(24,(INT(VALUE(H22)/100)-INT(P22/100))*12+MOD(VALUE(H22),100)-MOD(P22,100)))))/V7_LOCKOUT_TAU),1) | AC22: =IF(IF(OR(O22="",NOT(ISNUMBER(O22))),360,MAX(0,MIN(480,(INT(O22/100)-INT(VALUE(H22)/100))*12+MOD(O22,100)-MOD(VALUE(H22),100))))>0,1+V7_MTY_AMP*MAX(0,(V7_MTY_CUTOFF-(IF(OR(O22="",NOT(ISNUMBER(O22))),360,MAX(0,MIN(480,(INT(O22/100)-INT(VALUE(H22)/100))*12+MOD(O22,100)-MOD(VALUE(H22),100))))))/V7_MTY_CUTOFF),1) | AD22: =MAX(V7_BURN_FLOOR,1-V7_BURN_SLOPE*MIN(1,MAX(0,R22))) | AE22: =IF(V7_USE_ISSUER=1,IFERROR(VLOOKUP(Q22,V7_ISSUER_TABLE,3,FALSE),1),1) | AF22: =PRODUCT(W22:AE22) | AG22: =MIN(V7_BASE_SMM*AF22,V7_SMM_CAP) | AH22: =1-(1-AG22)^12 | AI22: =IFERROR(LN(W22)/(LN(W22)+LN(X22)+LN(Y22)+LN(Z22)+LN(AA22)+LN(AB22)+LN(AC22)+LN(AD22))*(AH22-V7_BASE_CPR),0) | AJ22: =IFERROR(LN(X22)/(LN(W22)+LN(X22)+LN(Y22)+LN(Z22)+LN(AA22)+LN(AB22)+LN(AC22)+LN(AD22))*(AH22-V7_BASE_CPR),0) | AK22: =IFERROR(LN(Y22)/(LN(W22)+LN(X22)+LN(Y22)+LN(Z22)+LN(AA22)+LN(AB22)+LN(AC22)+LN(AD22))*(AH22-V7_BASE_CPR),0) | AL22: =IFERROR(LN(Z22)/(LN(W22)+LN(X22)+LN(Y22)+LN(Z22)+LN(AA22)+LN(AB22)+LN(AC22)+LN(AD22))*(AH22-V7_BASE_CPR),0) | AM22: =IFERROR(LN(AA22)/(LN(W22)+LN(X22)+LN(Y22)+LN(Z22)+LN(AA22)+LN(AB22)+LN(AC22)+LN(AD22))*(AH22-V7_BASE_CPR),0) | AN22: =IFERROR(LN(AB22)/(LN(W22)+LN(X22)+LN(Y22)+LN(Z22)+LN(AA22)+LN(AB22)+LN(AC22)+LN(AD22))*(AH22-V7_BASE_CPR),0) | AO22: =IFERROR(LN(AC22)/(LN(W22)+LN(X22)+LN(Y22)+LN(Z22)+LN(AA22)+LN(AB22)+LN(AC22)+LN(AD22))*(AH22-V7_BASE_CPR),0) | AP22: =IFERROR(LN(AD22)/(LN(W22)+LN(X22)+LN(Y22)+LN(Z22)+LN(AA22)+LN(AB22)+LN(AC22)+LN(AD22))*(AH22-V7_BASE_CPR),0) | AQ22: =V7_BASE_CPR+SUM(AI22:AP22)-AH22
A23: 3617AVU89_000000003222025 | B23: LUMENT_PRE21 | C23: 3617AVU89 | D23: LUMENT REAL ESTATE CAPITAL,LLC | E23: 232 | F23: RP | G23: 2017 | H23: 202602 | I23: 18702496 | J23: 3.48 | K23: 447 | L23: 3 | M23: 101 | N23: 25 | O23: 205210 | Q23: 3896 | R23: 0.24752475 | S23: 0 | T23: =LN(1+I23) | U23: =J23*100-K23 | V23: =U23-12.5*(L23+1) | W23: =IF(M23<=V7_AGE_KNOT_X_0,V7_AGE_KNOT_Y_0,IF(M23>=V7_AGE_KNOT_X_5,V7_AGE_KNOT_Y_5,IF(M23<=V7_AGE_KNOT_X_1,V7_AGE_KNOT_Y_0+(M23-V7_AGE_KNOT_X_0)/(V7_AGE_KNOT_X_1-V7_AGE_KNOT_X_0)*(V7_AGE_KNOT_Y_1-V7_AGE_KNOT_Y_0),IF(M23<=V7_AGE_KNOT_X_2,V7_AGE_KNOT_Y_1+(M23-V7_AGE_KNOT_X_1)/(V7_AGE_KNOT_X_2-V7_AGE_KNOT_X_1)*(V7_AGE_KNOT_Y_2-V7_AGE_KNOT_Y_1),IF(M23<=V7_AGE_KNOT_X_3,V7_AGE_KNOT_Y_2+(M23-V7_AGE_KNOT_X_2)/(V7_AGE_KNOT_X_3-V7_AGE_KNOT_X_2)*(V7_AGE_KNOT_Y_3-V7_AGE_KNOT_Y_2),IF(M23<=V7_AGE_KNOT_X_4,V7_AGE_KNOT_Y_3+(M23-V7_AGE_KNOT_X_3)/(V7_AGE_KNOT_X_4-V7_AGE_KNOT_X_3)*(V7_AGE_KNOT_Y_4-V7_AGE_KNOT_Y_3),V7_AGE_KNOT_Y_4+(M23-V7_AGE_KNOT_X_4)/(V7_AGE_KNOT_X_5-V7_AGE_KNOT_X_4)*(V7_AGE_KNOT_Y_5-V7_AGE_KNOT_Y_4))))))) | X23: =V7_RATE_FLOOR+V7_RATE_ASYMPTOTE/(1+EXP(-(V23-V7_RATE_MID)/V7_RATE_SLOPE)) | Y23: =MAX(V7_SIZE_LOW,MIN(V7_SIZE_HIGH,V7_SIZE_INTERCEPT+V7_SIZE_SLOPE*(T23-V7_SIZE_LOG_ANCHOR))) | Z23: =IF(ISNUMBER(SEARCH("232",E23)),VLOOKUP("232",V7_PROGRAM_TABLE,2,FALSE),IF(ISNUMBER(SEARCH("538",E23)),VLOOKUP("538",V7_PROGRAM_TABLE,2,FALSE),IF(ISNUMBER(SEARCH("223a7",E23)),VLOOKUP("223a7",V7_PROGRAM_TABLE,2,FALSE),IF(ISNUMBER(SEARCH("223f",E23)),VLOOKUP("223f",V7_PROGRAM_TABLE,2,FALSE),V7_PROGRAM_DEFAULT)))) | AA23: =IF(S23=1,1+V7_PURPOSE_NC_BUMP*MAX(0,1-ABS(M23-V7_PURPOSE_PEAK_AGE)/V7_PURPOSE_WIDTH),1) | AB23: =IF(AND(IF(OR(P23="",NOT(ISNUMBER(P23))),0,MAX(0,MIN(24,(INT(VALUE(H23)/100)-INT(P23/100))*12+MOD(VALUE(H23),100)-MOD(P23,100))))>0,IF(OR(P23="",NOT(ISNUMBER(P23))),0,MAX(0,MIN(24,(INT(VALUE(H23)/100)-INT(P23/100))*12+MOD(VALUE(H23),100)-MOD(P23,100))))<=12),1+V7_LOCKOUT_AMP*EXP(-(IF(OR(P23="",NOT(ISNUMBER(P23))),0,MAX(0,MIN(24,(INT(VALUE(H23)/100)-INT(P23/100))*12+MOD(VALUE(H23),100)-MOD(P23,100)))))/V7_LOCKOUT_TAU),1) | AC23: =IF(IF(OR(O23="",NOT(ISNUMBER(O23))),360,MAX(0,MIN(480,(INT(O23/100)-INT(VALUE(H23)/100))*12+MOD(O23,100)-MOD(VALUE(H23),100))))>0,1+V7_MTY_AMP*MAX(0,(V7_MTY_CUTOFF-(IF(OR(O23="",NOT(ISNUMBER(O23))),360,MAX(0,MIN(480,(INT(O23/100)-INT(VALUE(H23)/100))*12+MOD(O23,100)-MOD(VALUE(H23),100))))))/V7_MTY_CUTOFF),1) | AD23: =MAX(V7_BURN_FLOOR,1-V7_BURN_SLOPE*MIN(1,MAX(0,R23))) | AE23: =IF(V7_USE_ISSUER=1,IFERROR(VLOOKUP(Q23,V7_ISSUER_TABLE,3,FALSE),1),1) | AF23: =PRODUCT(W23:AE23) | AG23: =MIN(V7_BASE_SMM*AF23,V7_SMM_CAP) | AH23: =1-(1-AG23)^12 | AI23: =IFERROR(LN(W23)/(LN(W23)+LN(X23)+LN(Y23)+LN(Z23)+LN(AA23)+LN(AB23)+LN(AC23)+LN(AD23))*(AH23-V7_BASE_CPR),0) | AJ23: =IFERROR(LN(X23)/(LN(W23)+LN(X23)+LN(Y23)+LN(Z23)+LN(AA23)+LN(AB23)+LN(AC23)+LN(AD23))*(AH23-V7_BASE_CPR),0) | AK23: =IFERROR(LN(Y23)/(LN(W23)+LN(X23)+LN(Y23)+LN(Z23)+LN(AA23)+LN(AB23)+LN(AC23)+LN(AD23))*(AH23-V7_BASE_CPR),0) | AL23: =IFERROR(LN(Z23)/(LN(W23)+LN(X23)+LN(Y23)+LN(Z23)+LN(AA23)+LN(AB23)+LN(AC23)+LN(AD23))*(AH23-V7_BASE_CPR),0) | AM23: =IFERROR(LN(AA23)/(LN(W23)+LN(X23)+LN(Y23)+LN(Z23)+LN(AA23)+LN(AB23)+LN(AC23)+LN(AD23))*(AH23-V7_BASE_CPR),0) | AN23: =IFERROR(LN(AB23)/(LN(W23)+LN(X23)+LN(Y23)+LN(Z23)+LN(AA23)+LN(AB23)+LN(AC23)+LN(AD23))*(AH23-V7_BASE_CPR),0) | AO23: =IFERROR(LN(AC23)/(LN(W23)+LN(X23)+LN(Y23)+LN(Z23)+LN(AA23)+LN(AB23)+LN(AC23)+LN(AD23))*(AH23-V7_BASE_CPR),0) | AP23: =IFERROR(LN(AD23)/(LN(W23)+LN(X23)+LN(Y23)+LN(Z23)+LN(AA23)+LN(AB23)+LN(AC23)+LN(AD23))*(AH23-V7_BASE_CPR),0) | AQ23: =V7_BASE_CPR+SUM(AI23:AP23)-AH23
A24: 3617UAXY3_000000010522063 | B24: LUMENT_PRE21 | C24: 3617UAXY3 | D24: LUMENT REAL ESTATE CAPITAL,LLC | E24: 232 | F24: RP | G24: 2015 | H24: 202602 | I24: 8582540 | J24: 2.8 | K24: 447 | L24: 10 | M24: 124 | N24: 0 | O24: 205011 | Q24: 3896 | R24: 0 | S24: 0 | T24: =LN(1+I24) | U24: =J24*100-K24 | V24: =U24-12.5*(L24+1) | W24: =IF(M24<=V7_AGE_KNOT_X_0,V7_AGE_KNOT_Y_0,IF(M24>=V7_AGE_KNOT_X_5,V7_AGE_KNOT_Y_5,IF(M24<=V7_AGE_KNOT_X_1,V7_AGE_KNOT_Y_0+(M24-V7_AGE_KNOT_X_0)/(V7_AGE_KNOT_X_1-V7_AGE_KNOT_X_0)*(V7_AGE_KNOT_Y_1-V7_AGE_KNOT_Y_0),IF(M24<=V7_AGE_KNOT_X_2,V7_AGE_KNOT_Y_1+(M24-V7_AGE_KNOT_X_1)/(V7_AGE_KNOT_X_2-V7_AGE_KNOT_X_1)*(V7_AGE_KNOT_Y_2-V7_AGE_KNOT_Y_1),IF(M24<=V7_AGE_KNOT_X_3,V7_AGE_KNOT_Y_2+(M24-V7_AGE_KNOT_X_2)/(V7_AGE_KNOT_X_3-V7_AGE_KNOT_X_2)*(V7_AGE_KNOT_Y_3-V7_AGE_KNOT_Y_2),IF(M24<=V7_AGE_KNOT_X_4,V7_AGE_KNOT_Y_3+(M24-V7_AGE_KNOT_X_3)/(V7_AGE_KNOT_X_4-V7_AGE_KNOT_X_3)*(V7_AGE_KNOT_Y_4-V7_AGE_KNOT_Y_3),V7_AGE_KNOT_Y_4+(M24-V7_AGE_KNOT_X_4)/(V7_AGE_KNOT_X_5-V7_AGE_KNOT_X_4)*(V7_AGE_KNOT_Y_5-V7_AGE_KNOT_Y_4))))))) | X24: =V7_RATE_FLOOR+V7_RATE_ASYMPTOTE/(1+EXP(-(V24-V7_RATE_MID)/V7_RATE_SLOPE)) | Y24: =MAX(V7_SIZE_LOW,MIN(V7_SIZE_HIGH,V7_SIZE_INTERCEPT+V7_SIZE_SLOPE*(T24-V7_SIZE_LOG_ANCHOR))) | Z24: =IF(ISNUMBER(SEARCH("232",E24)),VLOOKUP("232",V7_PROGRAM_TABLE,2,FALSE),IF(ISNUMBER(SEARCH("538",E24)),VLOOKUP("538",V7_PROGRAM_TABLE,2,FALSE),IF(ISNUMBER(SEARCH("223a7",E24)),VLOOKUP("223a7",V7_PROGRAM_TABLE,2,FALSE),IF(ISNUMBER(SEARCH("223f",E24)),VLOOKUP("223f",V7_PROGRAM_TABLE,2,FALSE),V7_PROGRAM_DEFAULT)))) | AA24: =IF(S24=1,1+V7_PURPOSE_NC_BUMP*MAX(0,1-ABS(M24-V7_PURPOSE_PEAK_AGE)/V7_PURPOSE_WIDTH),1) | AB24: =IF(AND(IF(OR(P24="",NOT(ISNUMBER(P24))),0,MAX(0,MIN(24,(INT(VALUE(H24)/100)-INT(P24/100))*12+MOD(VALUE(H24),100)-MOD(P24,100))))>0,IF(OR(P24="",NOT(ISNUMBER(P24))),0,MAX(0,MIN(24,(INT(VALUE(H24)/100)-INT(P24/100))*12+MOD(VALUE(H24),100)-MOD(P24,100))))<=12),1+V7_LOCKOUT_AMP*EXP(-(IF(OR(P24="",NOT(ISNUMBER(P24))),0,MAX(0,MIN(24,(INT(VALUE(H24)/100)-INT(P24/100))*12+MOD(VALUE(H24),100)-MOD(P24,100)))))/V7_LOCKOUT_TAU),1) | AC24: =IF(IF(OR(O24="",NOT(ISNUMBER(O24))),360,MAX(0,MIN(480,(INT(O24/100)-INT(VALUE(H24)/100))*12+MOD(O24,100)-MOD(VALUE(H24),100))))>0,1+V7_MTY_AMP*MAX(0,(V7_MTY_CUTOFF-(IF(OR(O24="",NOT(ISNUMBER(O24))),360,MAX(0,MIN(480,(INT(O24/100)-INT(VALUE(H24)/100))*12+MOD(O24,100)-MOD(VALUE(H24),100))))))/V7_MTY_CUTOFF),1) | AD24: =MAX(V7_BURN_FLOOR,1-V7_BURN_SLOPE*MIN(1,MAX(0,R24))) | AE24: =IF(V7_USE_ISSUER=1,IFERROR(VLOOKUP(Q24,V7_ISSUER_TABLE,3,FALSE),1),1) | AF24: =PRODUCT(W24:AE24) | AG24: =MIN(V7_BASE_SMM*AF24,V7_SMM_CAP) | AH24: =1-(1-AG24)^12 | AI24: =IFERROR(LN(W24)/(LN(W24)+LN(X24)+LN(Y24)+LN(Z24)+LN(AA24)+LN(AB24)+LN(AC24)+LN(AD24))*(AH24-V7_BASE_CPR),0) | AJ24: =IFERROR(LN(X24)/(LN(W24)+LN(X24)+LN(Y24)+LN(Z24)+LN(AA24)+LN(AB24)+LN(AC24)+LN(AD24))*(AH24-V7_BASE_CPR),0) | AK24: =IFERROR(LN(Y24)/(LN(W24)+LN(X24)+LN(Y24)+LN(Z24)+LN(AA24)+LN(AB24)+LN(AC24)+LN(AD24))*(AH24-V7_BASE_CPR),0) | AL24: =IFERROR(LN(Z24)/(LN(W24)+LN(X24)+LN(Y24)+LN(Z24)+LN(AA24)+LN(AB24)+LN(AC24)+LN(AD24))*(AH24-V7_BASE_CPR),0) | AM24: =IFERROR(LN(AA24)/(LN(W24)+LN(X24)+LN(Y24)+LN(Z24)+LN(AA24)+LN(AB24)+LN(AC24)+LN(AD24))*(AH24-V7_BASE_CPR),0) | AN24: =IFERROR(LN(AB24)/(LN(W24)+LN(X24)+LN(Y24)+LN(Z24)+LN(AA24)+LN(AB24)+LN(AC24)+LN(AD24))*(AH24-V7_BASE_CPR),0) | AO24: =IFERROR(LN(AC24)/(LN(W24)+LN(X24)+LN(Y24)+LN(Z24)+LN(AA24)+LN(AB24)+LN(AC24)+LN(AD24))*(AH24-V7_BASE_CPR),0) | AP24: =IFERROR(LN(AD24)/(LN(W24)+LN(X24)+LN(Y24)+LN(Z24)+LN(AA24)+LN(AB24)+LN(AC24)+LN(AD24))*(AH24-V7_BASE_CPR),0) | AQ24: =V7_BASE_CPR+SUM(AI24:AP24)-AH24
... A39: 36189MGT9_000000007111384 | B39: BERKADIA_PRE21 | C39: 36189MGT9 | D39: BERKADIA COMMERCIAL MORTGAGE, LLC | E39: 223f | F39: RP | G39: 2015 | H39: 202602 | I39: 3434607.5 | J39: 3.25 | K39: 447 | L39: 0 | M39: 125 | N39: 25 | O39: 205101 | Q39: 4082 | R39: 0.2 | S39: 0 | T39: =LN(1+I39) | U39: =J39*100-K39 | V39: =U39-12.5*(L39+1) | W39: =IF(M39<=V7_AGE_KNOT_X_0,V7_AGE_KNOT_Y_0,IF(M39>=V7_AGE_KNOT_X_5,V7_AGE_KNOT_Y_5,IF(M39<=V7_AGE_KNOT_X_1,V7_AGE_KNOT_Y_0+(M39-V7_AGE_KNOT_X_0)/(V7_AGE_KNOT_X_1-V7_AGE_KNOT_X_0)*(V7_AGE_KNOT_Y_1-V7_AGE_KNOT_Y_0),IF(M39<=V7_AGE_KNOT_X_2,V7_AGE_KNOT_Y_1+(M39-V7_AGE_KNOT_X_1)/(V7_AGE_KNOT_X_2-V7_AGE_KNOT_X_1)*(V7_AGE_KNOT_Y_2-V7_AGE_KNOT_Y_1),IF(M39<=V7_AGE_KNOT_X_3,V7_AGE_KNOT_Y_2+(M39-V7_AGE_KNOT_X_2)/(V7_AGE_KNOT_X_3-V7_AGE_KNOT_X_2)*(V7_AGE_KNOT_Y_3-V7_AGE_KNOT_Y_2),IF(M39<=V7_AGE_KNOT_X_4,V7_AGE_KNOT_Y_3+(M39-V7_AGE_KNOT_X_3)/(V7_AGE_KNOT_X_4-V7_AGE_KNOT_X_3)*(V7_AGE_KNOT_Y_4-V7_AGE_KNOT_Y_3),V7_AGE_KNOT_Y_4+(M39-V7_AGE_KNOT_X_4)/(V7_AGE_KNOT_X_5-V7_AGE_KNOT_X_4)*(V7_AGE_KNOT_Y_5-V7_AGE_KNOT_Y_4))))))) | X39: =V7_RATE_FLOOR+V7_RATE_ASYMPTOTE/(1+EXP(-(V39-V7_RATE_MID)/V7_RATE_SLOPE)) | Y39: =MAX(V7_SIZE_LOW,MIN(V7_SIZE_HIGH,V7_SIZE_INTERCEPT+V7_SIZE_SLOPE*(T39-V7_SIZE_LOG_ANCHOR))) | Z39: =IF(ISNUMBER(SEARCH("232",E39)),VLOOKUP("232",V7_PROGRAM_TABLE,2,FALSE),IF(ISNUMBER(SEARCH("538",E39)),VLOOKUP("538",V7_PROGRAM_TABLE,2,FALSE),IF(ISNUMBER(SEARCH("223a7",E39)),VLOOKUP("223a7",V7_PROGRAM_TABLE,2,FALSE),IF(ISNUMBER(SEARCH("223f",E39)),VLOOKUP("223f",V7_PROGRAM_TABLE,2,FALSE),V7_PROGRAM_DEFAULT)))) | AA39: =IF(S39=1,1+V7_PURPOSE_NC_BUMP*MAX(0,1-ABS(M39-V7_PURPOSE_PEAK_AGE)/V7_PURPOSE_WIDTH),1) | AB39: =IF(AND(IF(OR(P39="",NOT(ISNUMBER(P39))),0,MAX(0,MIN(24,(INT(VALUE(H39)/100)-INT(P39/100))*12+MOD(VALUE(H39),100)-MOD(P39,100))))>0,IF(OR(P39="",NOT(ISNUMBER(P39))),0,MAX(0,MIN(24,(INT(VALUE(H39)/100)-INT(P39/100))*12+MOD(VALUE(H39),100)-MOD(P39,100))))<=12),1+V7_LOCKOUT_AMP*EXP(-(IF(OR(P39="",NOT(ISNUMBER(P39))),0,MAX(0,MIN(24,(INT(VALUE(H39)/100)-INT(P39/100))*12+MOD(VALUE(H39),100)-MOD(P39,100)))))/V7_LOCKOUT_TAU),1) | AC39: =IF(IF(OR(O39="",NOT(ISNUMBER(O39))),360,MAX(0,MIN(480,(INT(O39/100)-INT(VALUE(H39)/100))*12+MOD(O39,100)-MOD(VALUE(H39),100))))>0,1+V7_MTY_AMP*MAX(0,(V7_MTY_CUTOFF-(IF(OR(O39="",NOT(ISNUMBER(O39))),360,MAX(0,MIN(480,(INT(O39/100)-INT(VALUE(H39)/100))*12+MOD(O39,100)-MOD(VALUE(H39),100))))))/V7_MTY_CUTOFF),1) | AD39: =MAX(V7_BURN_FLOOR,1-V7_BURN_SLOPE*MIN(1,MAX(0,R39))) | AE39: =IF(V7_USE_ISSUER=1,IFERROR(VLOOKUP(Q39,V7_ISSUER_TABLE,3,FALSE),1),1) | AF39: =PRODUCT(W39:AE39) | AG39: =MIN(V7_BASE_SMM*AF39,V7_SMM_CAP) | AH39: =1-(1-AG39)^12 | AI39: =IFERROR(LN(W39)/(LN(W39)+LN(X39)+LN(Y39)+LN(Z39)+LN(AA39)+LN(AB39)+LN(AC39)+LN(AD39))*(AH39-V7_BASE_CPR),0) | AJ39: =IFERROR(LN(X39)/(LN(W39)+LN(X39)+LN(Y39)+LN(Z39)+LN(AA39)+LN(AB39)+LN(AC39)+LN(AD39))*(AH39-V7_BASE_CPR),0) | AK39: =IFERROR(LN(Y39)/(LN(W39)+LN(X39)+LN(Y39)+LN(Z39)+LN(AA39)+LN(AB39)+LN(AC39)+LN(AD39))*(AH39-V7_BASE_CPR),0) | AL39: =IFERROR(LN(Z39)/(LN(W39)+LN(X39)+LN(Y39)+LN(Z39)+LN(AA39)+LN(AB39)+LN(AC39)+LN(AD39))*(AH39-V7_BASE_CPR),0) | AM39: =IFERROR(LN(AA39)/(LN(W39)+LN(X39)+LN(Y39)+LN(Z39)+LN(AA39)+LN(AB39)+LN(AC39)+LN(AD39))*(AH39-V7_BASE_CPR),0) | AN39: =IFERROR(LN(AB39)/(LN(W39)+LN(X39)+LN(Y39)+LN(Z39)+LN(AA39)+LN(AB39)+LN(AC39)+LN(AD39))*(AH39-V7_BASE_CPR),0) | AO39: =IFERROR(LN(AC39)/(LN(W39)+LN(X39)+LN(Y39)+LN(Z39)+LN(AA39)+LN(AB39)+LN(AC39)+LN(AD39))*(AH39-V7_BASE_CPR),0) | AP39: =IFERROR(LN(AD39)/(LN(W39)+LN(X39)+LN(Y39)+LN(Z39)+LN(AA39)+LN(AB39)+LN(AC39)+LN(AD39))*(AH39-V7_BASE_CPR),0) | AQ39: =V7_BASE_CPR+SUM(AI39:AP39)-AH39
A40: 36177YET9_000000006311078 | B40: BERKADIA_PRE21 | C40: 36177YET9 | D40: BERKADIA COMMERCIAL MORTGAGE, LLC | E40: 223f | F40: RP | G40: 2012 | H40: 202602 | I40: 8184805 | J40: 3.2 | K40: 447 | L40: 0 | M40: 167 | N40: 30 | O40: 204708 | P40: 201409 | Q40: 4082 | R40: 0.17964072 | S40: 0 | T40: =LN(1+I40) | U40: =J40*100-K40 | V40: =U40-12.5*(L40+1) | W40: =IF(M40<=V7_AGE_KNOT_X_0,V7_AGE_KNOT_Y_0,IF(M40>=V7_AGE_KNOT_X_5,V7_AGE_KNOT_Y_5,IF(M40<=V7_AGE_KNOT_X_1,V7_AGE_KNOT_Y_0+(M40-V7_AGE_KNOT_X_0)/(V7_AGE_KNOT_X_1-V7_AGE_KNOT_X_0)*(V7_AGE_KNOT_Y_1-V7_AGE_KNOT_Y_0),IF(M40<=V7_AGE_KNOT_X_2,V7_AGE_KNOT_Y_1+(M40-V7_AGE_KNOT_X_1)/(V7_AGE_KNOT_X_2-V7_AGE_KNOT_X_1)*(V7_AGE_KNOT_Y_2-V7_AGE_KNOT_Y_1),IF(M40<=V7_AGE_KNOT_X_3,V7_AGE_KNOT_Y_2+(M40-V7_AGE_KNOT_X_2)/(V7_AGE_KNOT_X_3-V7_AGE_KNOT_X_2)*(V7_AGE_KNOT_Y_3-V7_AGE_KNOT_Y_2),IF(M40<=V7_AGE_KNOT_X_4,V7_AGE_KNOT_Y_3+(M40-V7_AGE_KNOT_X_3)/(V7_AGE_KNOT_X_4-V7_AGE_KNOT_X_3)*(V7_AGE_KNOT_Y_4-V7_AGE_KNOT_Y_3),V7_AGE_KNOT_Y_4+(M40-V7_AGE_KNOT_X_4)/(V7_AGE_KNOT_X_5-V7_AGE_KNOT_X_4)*(V7_AGE_KNOT_Y_5-V7_AGE_KNOT_Y_4))))))) | X40: =V7_RATE_FLOOR+V7_RATE_ASYMPTOTE/(1+EXP(-(V40-V7_RATE_MID)/V7_RATE_SLOPE)) | Y40: =MAX(V7_SIZE_LOW,MIN(V7_SIZE_HIGH,V7_SIZE_INTERCEPT+V7_SIZE_SLOPE*(T40-V7_SIZE_LOG_ANCHOR))) | Z40: =IF(ISNUMBER(SEARCH("232",E40)),VLOOKUP("232",V7_PROGRAM_TABLE,2,FALSE),IF(ISNUMBER(SEARCH("538",E40)),VLOOKUP("538",V7_PROGRAM_TABLE,2,FALSE),IF(ISNUMBER(SEARCH("223a7",E40)),VLOOKUP("223a7",V7_PROGRAM_TABLE,2,FALSE),IF(ISNUMBER(SEARCH("223f",E40)),VLOOKUP("223f",V7_PROGRAM_TABLE,2,FALSE),V7_PROGRAM_DEFAULT)))) | AA40: =IF(S40=1,1+V7_PURPOSE_NC_BUMP*MAX(0,1-ABS(M40-V7_PURPOSE_PEAK_AGE)/V7_PURPOSE_WIDTH),1) | AB40: =IF(AND(IF(OR(P40="",NOT(ISNUMBER(P40))),0,MAX(0,MIN(24,(INT(VALUE(H40)/100)-INT(P40/100))*12+MOD(VALUE(H40),100)-MOD(P40,100))))>0,IF(OR(P40="",NOT(ISNUMBER(P40))),0,MAX(0,MIN(24,(INT(VALUE(H40)/100)-INT(P40/100))*12+MOD(VALUE(H40),100)-MOD(P40,100))))<=12),1+V7_LOCKOUT_AMP*EXP(-(IF(OR(P40="",NOT(ISNUMBER(P40))),0,MAX(0,MIN(24,(INT(VALUE(H40)/100)-INT(P40/100))*12+MOD(VALUE(H40),100)-MOD(P40,100)))))/V7_LOCKOUT_TAU),1) | AC40: =IF(IF(OR(O40="",NOT(ISNUMBER(O40))),360,MAX(0,MIN(480,(INT(O40/100)-INT(VALUE(H40)/100))*12+MOD(O40,100)-MOD(VALUE(H40),100))))>0,1+V7_MTY_AMP*MAX(0,(V7_MTY_CUTOFF-(IF(OR(O40="",NOT(ISNUMBER(O40))),360,MAX(0,MIN(480,(INT(O40/100)-INT(VALUE(H40)/100))*12+MOD(O40,100)-MOD(VALUE(H40),100))))))/V7_MTY_CUTOFF),1) | AD40: =MAX(V7_BURN_FLOOR,1-V7_BURN_SLOPE*MIN(1,MAX(0,R40))) | AE40: =IF(V7_USE_ISSUER=1,IFERROR(VLOOKUP(Q40,V7_ISSUER_TABLE,3,FALSE),1),1) | AF40: =PRODUCT(W40:AE40) | AG40: =MIN(V7_BASE_SMM*AF40,V7_SMM_CAP) | AH40: =1-(1-AG40)^12 | AI40: =IFERROR(LN(W40)/(LN(W40)+LN(X40)+LN(Y40)+LN(Z40)+LN(AA40)+LN(AB40)+LN(AC40)+LN(AD40))*(AH40-V7_BASE_CPR),0) | AJ40: =IFERROR(LN(X40)/(LN(W40)+LN(X40)+LN(Y40)+LN(Z40)+LN(AA40)+LN(AB40)+LN(AC40)+LN(AD40))*(AH40-V7_BASE_CPR),0) | AK40: =IFERROR(LN(Y40)/(LN(W40)+LN(X40)+LN(Y40)+LN(Z40)+LN(AA40)+LN(AB40)+LN(AC40)+LN(AD40))*(AH40-V7_BASE_CPR),0) | AL40: =IFERROR(LN(Z40)/(LN(W40)+LN(X40)+LN(Y40)+LN(Z40)+LN(AA40)+LN(AB40)+LN(AC40)+LN(AD40))*(AH40-V7_BASE_CPR),0) | AM40: =IFERROR(LN(AA40)/(LN(W40)+LN(X40)+LN(Y40)+LN(Z40)+LN(AA40)+LN(AB40)+LN(AC40)+LN(AD40))*(AH40-V7_BASE_CPR),0) | AN40: =IFERROR(LN(AB40)/(LN(W40)+LN(X40)+LN(Y40)+LN(Z40)+LN(AA40)+LN(AB40)+LN(AC40)+LN(AD40))*(AH40-V7_BASE_CPR),0) | AO40: =IFERROR(LN(AC40)/(LN(W40)+LN(X40)+LN(Y40)+LN(Z40)+LN(AA40)+LN(AB40)+LN(AC40)+LN(AD40))*(AH40-V7_BASE_CPR),0) | AP40: =IFERROR(LN(AD40)/(LN(W40)+LN(X40)+LN(Y40)+LN(Z40)+LN(AA40)+LN(AB40)+LN(AC40)+LN(AD40))*(AH40-V7_BASE_CPR),0) | AQ40: =V7_BASE_CPR+SUM(AI40:AP40)-AH40
A41: 3617F6YS1_000000005111525 | B41: BERKADIA_POST21 | C41: 3617F6YS1 | D41: BERKADIA COMMERCIAL MORTGAGE, LLC | E41: 223f | F41: RP | G41: 2022 | H41: 202602 | I41: 19717396 | J41: 4.45 | K41: 447 | L41: 8 | M41: 43 | N41: 1 | O41: 205711 | Q41: 4082 | R41: 0.023255814 | S41: 0 | T41: =LN(1+I41) | U41: =J41*100-K41 | V41: =U41-12.5*(L41+1) | W41: =IF(M41<=V7_AGE_KNOT_X_0,V7_AGE_KNOT_Y_0,IF(M41>=V7_AGE_KNOT_X_5,V7_AGE_KNOT_Y_5,IF(M41<=V7_AGE_KNOT_X_1,V7_AGE_KNOT_Y_0+(M41-V7_AGE_KNOT_X_0)/(V7_AGE_KNOT_X_1-V7_AGE_KNOT_X_0)*(V7_AGE_KNOT_Y_1-V7_AGE_KNOT_Y_0),IF(M41<=V7_AGE_KNOT_X_2,V7_AGE_KNOT_Y_1+(M41-V7_AGE_KNOT_X_1)/(V7_AGE_KNOT_X_2-V7_AGE_KNOT_X_1)*(V7_AGE_KNOT_Y_2-V7_AGE_KNOT_Y_1),IF(M41<=V7_AGE_KNOT_X_3,V7_AGE_KNOT_Y_2+(M41-V7_AGE_KNOT_X_2)/(V7_AGE_KNOT_X_3-V7_AGE_KNOT_X_2)*(V7_AGE_KNOT_Y_3-V7_AGE_KNOT_Y_2),IF(M41<=V7_AGE_KNOT_X_4,V7_AGE_KNOT_Y_3+(M41-V7_AGE_KNOT_X_3)/(V7_AGE_KNOT_X_4-V7_AGE_KNOT_X_3)*(V7_AGE_KNOT_Y_4-V7_AGE_KNOT_Y_3),V7_AGE_KNOT_Y_4+(M41-V7_AGE_KNOT_X_4)/(V7_AGE_KNOT_X_5-V7_AGE_KNOT_X_4)*(V7_AGE_KNOT_Y_5-V7_AGE_KNOT_Y_4))))))) | X41: =V7_RATE_FLOOR+V7_RATE_ASYMPTOTE/(1+EXP(-(V41-V7_RATE_MID)/V7_RATE_SLOPE)) | Y41: =MAX(V7_SIZE_LOW,MIN(V7_SIZE_HIGH,V7_SIZE_INTERCEPT+V7_SIZE_SLOPE*(T41-V7_SIZE_LOG_ANCHOR))) | Z41: =IF(ISNUMBER(SEARCH("232",E41)),VLOOKUP("232",V7_PROGRAM_TABLE,2,FALSE),IF(ISNUMBER(SEARCH("538",E41)),VLOOKUP("538",V7_PROGRAM_TABLE,2,FALSE),IF(ISNUMBER(SEARCH("223a7",E41)),VLOOKUP("223a7",V7_PROGRAM_TABLE,2,FALSE),IF(ISNUMBER(SEARCH("223f",E41)),VLOOKUP("223f",V7_PROGRAM_TABLE,2,FALSE),V7_PROGRAM_DEFAULT)))) | AA41: =IF(S41=1,1+V7_PURPOSE_NC_BUMP*MAX(0,1-ABS(M41-V7_PURPOSE_PEAK_AGE)/V7_PURPOSE_WIDTH),1) | AB41: =IF(AND(IF(OR(P41="",NOT(ISNUMBER(P41))),0,MAX(0,MIN(24,(INT(VALUE(H41)/100)-INT(P41/100))*12+MOD(VALUE(H41),100)-MOD(P41,100))))>0,IF(OR(P41="",NOT(ISNUMBER(P41))),0,MAX(0,MIN(24,(INT(VALUE(H41)/100)-INT(P41/100))*12+MOD(VALUE(H41),100)-MOD(P41,100))))<=12),1+V7_LOCKOUT_AMP*EXP(-(IF(OR(P41="",NOT(ISNUMBER(P41))),0,MAX(0,MIN(24,(INT(VALUE(H41)/100)-INT(P41/100))*12+MOD(VALUE(H41),100)-MOD(P41,100)))))/V7_LOCKOUT_TAU),1) | AC41: =IF(IF(OR(O41="",NOT(ISNUMBER(O41))),360,MAX(0,MIN(480,(INT(O41/100)-INT(VALUE(H41)/100))*12+MOD(O41,100)-MOD(VALUE(H41),100))))>0,1+V7_MTY_AMP*MAX(0,(V7_MTY_CUTOFF-(IF(OR(O41="",NOT(ISNUMBER(O41))),360,MAX(0,MIN(480,(INT(O41/100)-INT(VALUE(H41)/100))*12+MOD(O41,100)-MOD(VALUE(H41),100))))))/V7_MTY_CUTOFF),1) | AD41: =MAX(V7_BURN_FLOOR,1-V7_BURN_SLOPE*MIN(1,MAX(0,R41))) | AE41: =IF(V7_USE_ISSUER=1,IFERROR(VLOOKUP(Q41,V7_ISSUER_TABLE,3,FALSE),1),1) | AF41: =PRODUCT(W41:AE41) | AG41: =MIN(V7_BASE_SMM*AF41,V7_SMM_CAP) | AH41: =1-(1-AG41)^12 | AI41: =IFERROR(LN(W41)/(LN(W41)+LN(X41)+LN(Y41)+LN(Z41)+LN(AA41)+LN(AB41)+LN(AC41)+LN(AD41))*(AH41-V7_BASE_CPR),0) | AJ41: =IFERROR(LN(X41)/(LN(W41)+LN(X41)+LN(Y41)+LN(Z41)+LN(AA41)+LN(AB41)+LN(AC41)+LN(AD41))*(AH41-V7_BASE_CPR),0) | AK41: =IFERROR(LN(Y41)/(LN(W41)+LN(X41)+LN(Y41)+LN(Z41)+LN(AA41)+LN(AB41)+LN(AC41)+LN(AD41))*(AH41-V7_BASE_CPR),0) | AL41: =IFERROR(LN(Z41)/(LN(W41)+LN(X41)+LN(Y41)+LN(Z41)+LN(AA41)+LN(AB41)+LN(AC41)+LN(AD41))*(AH41-V7_BASE_CPR),0) | AM41: =IFERROR(LN(AA41)/(LN(W41)+LN(X41)+LN(Y41)+LN(Z41)+LN(AA41)+LN(AB41)+LN(AC41)+LN(AD41))*(AH41-V7_BASE_CPR),0) | AN41: =IFERROR(LN(AB41)/(LN(W41)+LN(X41)+LN(Y41)+LN(Z41)+LN(AA41)+LN(AB41)+LN(AC41)+LN(AD41))*(AH41-V7_BASE_CPR),0) | AO41: =IFERROR(LN(AC41)/(LN(W41)+LN(X41)+LN(Y41)+LN(Z41)+LN(AA41)+LN(AB41)+LN(AC41)+LN(AD41))*(AH41-V7_BASE_CPR),0) | AP41: =IFERROR(LN(AD41)/(LN(W41)+LN(X41)+LN(Y41)+LN(Z41)+LN(AA41)+LN(AB41)+LN(AC41)+LN(AD41))*(AH41-V7_BASE_CPR),0) | AQ41: =V7_BASE_CPR+SUM(AI41:AP41)-AH41
A42: 3617VFMT4_000000004711152 | B42: BERKADIA_PRE21 | C42: 3617VFMT4 | D42: BERKADIA COMMERCIAL MORTGAGE, LLC | E42: 223f | F42: RP | G42: 2013 | H42: 202602 | I42: 345445.31 | J42: 2.9 | K42: 447 | L42: 7 | M42: 149 | N42: 9 | O42: 203401 | Q42: 4082 | R42: 0.060402685 | S42: 0 | T42: =LN(1+I42) | U42: =J42*100-K42 | V42: =U42-12.5*(L42+1) | W42: =IF(M42<=V7_AGE_KNOT_X_0,V7_AGE_KNOT_Y_0,IF(M42>=V7_AGE_KNOT_X_5,V7_AGE_KNOT_Y_5,IF(M42<=V7_AGE_KNOT_X_1,V7_AGE_KNOT_Y_0+(M42-V7_AGE_KNOT_X_0)/(V7_AGE_KNOT_X_1-V7_AGE_KNOT_X_0)*(V7_AGE_KNOT_Y_1-V7_AGE_KNOT_Y_0),IF(M42<=V7_AGE_KNOT_X_2,V7_AGE_KNOT_Y_1+(M42-V7_AGE_KNOT_X_1)/(V7_AGE_KNOT_X_2-V7_AGE_KNOT_X_1)*(V7_AGE_KNOT_Y_2-V7_AGE_KNOT_Y_1),IF(M42<=V7_AGE_KNOT_X_3,V7_AGE_KNOT_Y_2+(M42-V7_AGE_KNOT_X_2)/(V7_AGE_KNOT_X_3-V7_AGE_KNOT_X_2)*(V7_AGE_KNOT_Y_3-V7_AGE_KNOT_Y_2),IF(M42<=V7_AGE_KNOT_X_4,V7_AGE_KNOT_Y_3+(M42-V7_AGE_KNOT_X_3)/(V7_AGE_KNOT_X_4-V7_AGE_KNOT_X_3)*(V7_AGE_KNOT_Y_4-V7_AGE_KNOT_Y_3),V7_AGE_KNOT_Y_4+(M42-V7_AGE_KNOT_X_4)/(V7_AGE_KNOT_X_5-V7_AGE_KNOT_X_4)*(V7_AGE_KNOT_Y_5-V7_AGE_KNOT_Y_4))))))) | X42: =V7_RATE_FLOOR+V7_RATE_ASYMPTOTE/(1+EXP(-(V42-V7_RATE_MID)/V7_RATE_SLOPE)) | Y42: =MAX(V7_SIZE_LOW,MIN(V7_SIZE_HIGH,V7_SIZE_INTERCEPT+V7_SIZE_SLOPE*(T42-V7_SIZE_LOG_ANCHOR))) | Z42: =IF(ISNUMBER(SEARCH("232",E42)),VLOOKUP("232",V7_PROGRAM_TABLE,2,FALSE),IF(ISNUMBER(SEARCH("538",E42)),VLOOKUP("538",V7_PROGRAM_TABLE,2,FALSE),IF(ISNUMBER(SEARCH("223a7",E42)),VLOOKUP("223a7",V7_PROGRAM_TABLE,2,FALSE),IF(ISNUMBER(SEARCH("223f",E42)),VLOOKUP("223f",V7_PROGRAM_TABLE,2,FALSE),V7_PROGRAM_DEFAULT)))) | AA42: =IF(S42=1,1+V7_PURPOSE_NC_BUMP*MAX(0,1-ABS(M42-V7_PURPOSE_PEAK_AGE)/V7_PURPOSE_WIDTH),1) | AB42: =IF(AND(IF(OR(P42="",NOT(ISNUMBER(P42))),0,MAX(0,MIN(24,(INT(VALUE(H42)/100)-INT(P42/100))*12+MOD(VALUE(H42),100)-MOD(P42,100))))>0,IF(OR(P42="",NOT(ISNUMBER(P42))),0,MAX(0,MIN(24,(INT(VALUE(H42)/100)-INT(P42/100))*12+MOD(VALUE(H42),100)-MOD(P42,100))))<=12),1+V7_LOCKOUT_AMP*EXP(-(IF(OR(P42="",NOT(ISNUMBER(P42))),0,MAX(0,MIN(24,(INT(VALUE(H42)/100)-INT(P42/100))*12+MOD(VALUE(H42),100)-MOD(P42,100)))))/V7_LOCKOUT_TAU),1) | AC42: =IF(IF(OR(O42="",NOT(ISNUMBER(O42))),360,MAX(0,MIN(480,(INT(O42/100)-INT(VALUE(H42)/100))*12+MOD(O42,100)-MOD(VALUE(H42),100))))>0,1+V7_MTY_AMP*MAX(0,(V7_MTY_CUTOFF-(IF(OR(O42="",NOT(ISNUMBER(O42))),360,MAX(0,MIN(480,(INT(O42/100)-INT(VALUE(H42)/100))*12+MOD(O42,100)-MOD(VALUE(H42),100))))))/V7_MTY_CUTOFF),1) | AD42: =MAX(V7_BURN_FLOOR,1-V7_BURN_SLOPE*MIN(1,MAX(0,R42))) | AE42: =IF(V7_USE_ISSUER=1,IFERROR(VLOOKUP(Q42,V7_ISSUER_TABLE,3,FALSE),1),1) | AF42: =PRODUCT(W42:AE42) | AG42: =MIN(V7_BASE_SMM*AF42,V7_SMM_CAP) | AH42: =1-(1-AG42)^12 | AI42: =IFERROR(LN(W42)/(LN(W42)+LN(X42)+LN(Y42)+LN(Z42)+LN(AA42)+LN(AB42)+LN(AC42)+LN(AD42))*(AH42-V7_BASE_CPR),0) | AJ42: =IFERROR(LN(X42)/(LN(W42)+LN(X42)+LN(Y42)+LN(Z42)+LN(AA42)+LN(AB42)+LN(AC42)+LN(AD42))*(AH42-V7_BASE_CPR),0) | AK42: =IFERROR(LN(Y42)/(LN(W42)+LN(X42)+LN(Y42)+LN(Z42)+LN(AA42)+LN(AB42)+LN(AC42)+LN(AD42))*(AH42-V7_BASE_CPR),0) | AL42: =IFERROR(LN(Z42)/(LN(W42)+LN(X42)+LN(Y42)+LN(Z42)+LN(AA42)+LN(AB42)+LN(AC42)+LN(AD42))*(AH42-V7_BASE_CPR),0) | AM42: =IFERROR(LN(AA42)/(LN(W42)+LN(X42)+LN(Y42)+LN(Z42)+LN(AA42)+LN(AB42)+LN(AC42)+LN(AD42))*(AH42-V7_BASE_CPR),0) | AN42: =IFERROR(LN(AB42)/(LN(W42)+LN(X42)+LN(Y42)+LN(Z42)+LN(AA42)+LN(AB42)+LN(AC42)+LN(AD42))*(AH42-V7_BASE_CPR),0) | AO42: =IFERROR(LN(AC42)/(LN(W42)+LN(X42)+LN(Y42)+LN(Z42)+LN(AA42)+LN(AB42)+LN(AC42)+LN(AD42))*(AH42-V7_BASE_CPR),0) | AP42: =IFERROR(LN(AD42)/(LN(W42)+LN(X42)+LN(Y42)+LN(Z42)+LN(AA42)+LN(AB42)+LN(AC42)+LN(AD42))*(AH42-V7_BASE_CPR),0) | AQ42: =V7_BASE_CPR+SUM(AI42:AP42)-AH42
A43: 3617XJ2A7_000000004811084 | B43: BERKADIA_POST21 | C43: 3617XJ2A7 | D43: BERKADIA COMMERCIAL MORTGAGE, LLC | E43: 223f | F43: RP | G43: 2021 | H43: 202602 | I43: 6267503.1 | J43: 2.15 | K43: 447 | L43: 8 | M43: 51 | N43: 0 | O43: 205703 | Q43: 4082 | R43: 0 | S43: 0 | T43: =LN(1+I43) | U43: =J43*100-K43 | V43: =U43-12.5*(L43+1) | W43: =IF(M43<=V7_AGE_KNOT_X_0,V7_AGE_KNOT_Y_0,IF(M43>=V7_AGE_KNOT_X_5,V7_AGE_KNOT_Y_5,IF(M43<=V7_AGE_KNOT_X_1,V7_AGE_KNOT_Y_0+(M43-V7_AGE_KNOT_X_0)/(V7_AGE_KNOT_X_1-V7_AGE_KNOT_X_0)*(V7_AGE_KNOT_Y_1-V7_AGE_KNOT_Y_0),IF(M43<=V7_AGE_KNOT_X_2,V7_AGE_KNOT_Y_1+(M43-V7_AGE_KNOT_X_1)/(V7_AGE_KNOT_X_2-V7_AGE_KNOT_X_1)*(V7_AGE_KNOT_Y_2-V7_AGE_KNOT_Y_1),IF(M43<=V7_AGE_KNOT_X_3,V7_AGE_KNOT_Y_2+(M43-V7_AGE_KNOT_X_2)/(V7_AGE_KNOT_X_3-V7_AGE_KNOT_X_2)*(V7_AGE_KNOT_Y_3-V7_AGE_KNOT_Y_2),IF(M43<=V7_AGE_KNOT_X_4,V7_AGE_KNOT_Y_3+(M43-V7_AGE_KNOT_X_3)/(V7_AGE_KNOT_X_4-V7_AGE_KNOT_X_3)*(V7_AGE_KNOT_Y_4-V7_AGE_KNOT_Y_3),V7_AGE_KNOT_Y_4+(M43-V7_AGE_KNOT_X_4)/(V7_AGE_KNOT_X_5-V7_AGE_KNOT_X_4)*(V7_AGE_KNOT_Y_5-V7_AGE_KNOT_Y_4))))))) | X43: =V7_RATE_FLOOR+V7_RATE_ASYMPTOTE/(1+EXP(-(V43-V7_RATE_MID)/V7_RATE_SLOPE)) | Y43: =MAX(V7_SIZE_LOW,MIN(V7_SIZE_HIGH,V7_SIZE_INTERCEPT+V7_SIZE_SLOPE*(T43-V7_SIZE_LOG_ANCHOR))) | Z43: =IF(ISNUMBER(SEARCH("232",E43)),VLOOKUP("232",V7_PROGRAM_TABLE,2,FALSE),IF(ISNUMBER(SEARCH("538",E43)),VLOOKUP("538",V7_PROGRAM_TABLE,2,FALSE),IF(ISNUMBER(SEARCH("223a7",E43)),VLOOKUP("223a7",V7_PROGRAM_TABLE,2,FALSE),IF(ISNUMBER(SEARCH("223f",E43)),VLOOKUP("223f",V7_PROGRAM_TABLE,2,FALSE),V7_PROGRAM_DEFAULT)))) | AA43: =IF(S43=1,1+V7_PURPOSE_NC_BUMP*MAX(0,1-ABS(M43-V7_PURPOSE_PEAK_AGE)/V7_PURPOSE_WIDTH),1) | AB43: =IF(AND(IF(OR(P43="",NOT(ISNUMBER(P43))),0,MAX(0,MIN(24,(INT(VALUE(H43)/100)-INT(P43/100))*12+MOD(VALUE(H43),100)-MOD(P43,100))))>0,IF(OR(P43="",NOT(ISNUMBER(P43))),0,MAX(0,MIN(24,(INT(VALUE(H43)/100)-INT(P43/100))*12+MOD(VALUE(H43),100)-MOD(P43,100))))<=12),1+V7_LOCKOUT_AMP*EXP(-(IF(OR(P43="",NOT(ISNUMBER(P43))),0,MAX(0,MIN(24,(INT(VALUE(H43)/100)-INT(P43/100))*12+MOD(VALUE(H43),100)-MOD(P43,100)))))/V7_LOCKOUT_TAU),1) | AC43: =IF(IF(OR(O43="",NOT(ISNUMBER(O43))),360,MAX(0,MIN(480,(INT(O43/100)-INT(VALUE(H43)/100))*12+MOD(O43,100)-MOD(VALUE(H43),100))))>0,1+V7_MTY_AMP*MAX(0,(V7_MTY_CUTOFF-(IF(OR(O43="",NOT(ISNUMBER(O43))),360,MAX(0,MIN(480,(INT(O43/100)-INT(VALUE(H43)/100))*12+MOD(O43,100)-MOD(VALUE(H43),100))))))/V7_MTY_CUTOFF),1) | AD43: =MAX(V7_BURN_FLOOR,1-V7_BURN_SLOPE*MIN(1,MAX(0,R43))) | AE43: =IF(V7_USE_ISSUER=1,IFERROR(VLOOKUP(Q43,V7_ISSUER_TABLE,3,FALSE),1),1) | AF43: =PRODUCT(W43:AE43) | AG43: =MIN(V7_BASE_SMM*AF43,V7_SMM_CAP) | AH43: =1-(1-AG43)^12 | AI43: =IFERROR(LN(W43)/(LN(W43)+LN(X43)+LN(Y43)+LN(Z43)+LN(AA43)+LN(AB43)+LN(AC43)+LN(AD43))*(AH43-V7_BASE_CPR),0) | AJ43: =IFERROR(LN(X43)/(LN(W43)+LN(X43)+LN(Y43)+LN(Z43)+LN(AA43)+LN(AB43)+LN(AC43)+LN(AD43))*(AH43-V7_BASE_CPR),0) | AK43: =IFERROR(LN(Y43)/(LN(W43)+LN(X43)+LN(Y43)+LN(Z43)+LN(AA43)+LN(AB43)+LN(AC43)+LN(AD43))*(AH43-V7_BASE_CPR),0) | AL43: =IFERROR(LN(Z43)/(LN(W43)+LN(X43)+LN(Y43)+LN(Z43)+LN(AA43)+LN(AB43)+LN(AC43)+LN(AD43))*(AH43-V7_BASE_CPR),0) | AM43: =IFERROR(LN(AA43)/(LN(W43)+LN(X43)+LN(Y43)+LN(Z43)+LN(AA43)+LN(AB43)+LN(AC43)+LN(AD43))*(AH43-V7_BASE_CPR),0) | AN43: =IFERROR(LN(AB43)/(LN(W43)+LN(X43)+LN(Y43)+LN(Z43)+LN(AA43)+LN(AB43)+LN(AC43)+LN(AD43))*(AH43-V7_BASE_CPR),0) | AO43: =IFERROR(LN(AC43)/(LN(W43)+LN(X43)+LN(Y43)+LN(Z43)+LN(AA43)+LN(AB43)+LN(AC43)+LN(AD43))*(AH43-V7_BASE_CPR),0) | AP43: =IFERROR(LN(AD43)/(LN(W43)+LN(X43)+LN(Y43)+LN(Z43)+LN(AA43)+LN(AB43)+LN(AC43)+LN(AD43))*(AH43-V7_BASE_CPR),0) | AQ43: =V7_BASE_CPR+SUM(AI43:AP43)-AH43
A44: 3617NEBN1_000000006722139 | B44: BERKADIA_PRE21 | C44: 3617NEBN1 | D44: BERKADIA COMMERCIAL MORTGAGE, LLC | E44: 232 | F44: RP | G44: 2013 | H44: 202602 | I44: 8404084.8 | J44: 2.95 | K44: 447 | L44: 6 | M44: 148 | N44: 14 | O44: 204508 | Q44: 4082 | R44: 0.094594595 | S44: 0 | T44: =LN(1+I44) | U44: =J44*100-K44 | V44: =U44-12.5*(L44+1) | W44: =IF(M44<=V7_AGE_KNOT_X_0,V7_AGE_KNOT_Y_0,IF(M44>=V7_AGE_KNOT_X_5,V7_AGE_KNOT_Y_5,IF(M44<=V7_AGE_KNOT_X_1,V7_AGE_KNOT_Y_0+(M44-V7_AGE_KNOT_X_0)/(V7_AGE_KNOT_X_1-V7_AGE_KNOT_X_0)*(V7_AGE_KNOT_Y_1-V7_AGE_KNOT_Y_0),IF(M44<=V7_AGE_KNOT_X_2,V7_AGE_KNOT_Y_1+(M44-V7_AGE_KNOT_X_1)/(V7_AGE_KNOT_X_2-V7_AGE_KNOT_X_1)*(V7_AGE_KNOT_Y_2-V7_AGE_KNOT_Y_1),IF(M44<=V7_AGE_KNOT_X_3,V7_AGE_KNOT_Y_2+(M44-V7_AGE_KNOT_X_2)/(V7_AGE_KNOT_X_3-V7_AGE_KNOT_X_2)*(V7_AGE_KNOT_Y_3-V7_AGE_KNOT_Y_2),IF(M44<=V7_AGE_KNOT_X_4,V7_AGE_KNOT_Y_3+(M44-V7_AGE_KNOT_X_3)/(V7_AGE_KNOT_X_4-V7_AGE_KNOT_X_3)*(V7_AGE_KNOT_Y_4-V7_AGE_KNOT_Y_3),V7_AGE_KNOT_Y_4+(M44-V7_AGE_KNOT_X_4)/(V7_AGE_KNOT_X_5-V7_AGE_KNOT_X_4)*(V7_AGE_KNOT_Y_5-V7_AGE_KNOT_Y_4))))))) | X44: =V7_RATE_FLOOR+V7_RATE_ASYMPTOTE/(1+EXP(-(V44-V7_RATE_MID)/V7_RATE_SLOPE)) | Y44: =MAX(V7_SIZE_LOW,MIN(V7_SIZE_HIGH,V7_SIZE_INTERCEPT+V7_SIZE_SLOPE*(T44-V7_SIZE_LOG_ANCHOR))) | Z44: =IF(ISNUMBER(SEARCH("232",E44)),VLOOKUP("232",V7_PROGRAM_TABLE,2,FALSE),IF(ISNUMBER(SEARCH("538",E44)),VLOOKUP("538",V7_PROGRAM_TABLE,2,FALSE),IF(ISNUMBER(SEARCH("223a7",E44)),VLOOKUP("223a7",V7_PROGRAM_TABLE,2,FALSE),IF(ISNUMBER(SEARCH("223f",E44)),VLOOKUP("223f",V7_PROGRAM_TABLE,2,FALSE),V7_PROGRAM_DEFAULT)))) | AA44: =IF(S44=1,1+V7_PURPOSE_NC_BUMP*MAX(0,1-ABS(M44-V7_PURPOSE_PEAK_AGE)/V7_PURPOSE_WIDTH),1) | AB44: =IF(AND(IF(OR(P44="",NOT(ISNUMBER(P44))),0,MAX(0,MIN(24,(INT(VALUE(H44)/100)-INT(P44/100))*12+MOD(VALUE(H44),100)-MOD(P44,100))))>0,IF(OR(P44="",NOT(ISNUMBER(P44))),0,MAX(0,MIN(24,(INT(VALUE(H44)/100)-INT(P44/100))*12+MOD(VALUE(H44),100)-MOD(P44,100))))<=12),1+V7_LOCKOUT_AMP*EXP(-(IF(OR(P44="",NOT(ISNUMBER(P44))),0,MAX(0,MIN(24,(INT(VALUE(H44)/100)-INT(P44/100))*12+MOD(VALUE(H44),100)-MOD(P44,100)))))/V7_LOCKOUT_TAU),1) | AC44: =IF(IF(OR(O44="",NOT(ISNUMBER(O44))),360,MAX(0,MIN(480,(INT(O44/100)-INT(VALUE(H44)/100))*12+MOD(O44,100)-MOD(VALUE(H44),100))))>0,1+V7_MTY_AMP*MAX(0,(V7_MTY_CUTOFF-(IF(OR(O44="",NOT(ISNUMBER(O44))),360,MAX(0,MIN(480,(INT(O44/100)-INT(VALUE(H44)/100))*12+MOD(O44,100)-MOD(VALUE(H44),100))))))/V7_MTY_CUTOFF),1) | AD44: =MAX(V7_BURN_FLOOR,1-V7_BURN_SLOPE*MIN(1,MAX(0,R44))) | AE44: =IF(V7_USE_ISSUER=1,IFERROR(VLOOKUP(Q44,V7_ISSUER_TABLE,3,FALSE),1),1) | AF44: =PRODUCT(W44:AE44) | AG44: =MIN(V7_BASE_SMM*AF44,V7_SMM_CAP) | AH44: =1-(1-AG44)^12 | AI44: =IFERROR(LN(W44)/(LN(W44)+LN(X44)+LN(Y44)+LN(Z44)+LN(AA44)+LN(AB44)+LN(AC44)+LN(AD44))*(AH44-V7_BASE_CPR),0) | AJ44: =IFERROR(LN(X44)/(LN(W44)+LN(X44)+LN(Y44)+LN(Z44)+LN(AA44)+LN(AB44)+LN(AC44)+LN(AD44))*(AH44-V7_BASE_CPR),0) | AK44: =IFERROR(LN(Y44)/(LN(W44)+LN(X44)+LN(Y44)+LN(Z44)+LN(AA44)+LN(AB44)+LN(AC44)+LN(AD44))*(AH44-V7_BASE_CPR),0) | AL44: =IFERROR(LN(Z44)/(LN(W44)+LN(X44)+LN(Y44)+LN(Z44)+LN(AA44)+LN(AB44)+LN(AC44)+LN(AD44))*(AH44-V7_BASE_CPR),0) | AM44: =IFERROR(LN(AA44)/(LN(W44)+LN(X44)+LN(Y44)+LN(Z44)+LN(AA44)+LN(AB44)+LN(AC44)+LN(AD44))*(AH44-V7_BASE_CPR),0) | AN44: =IFERROR(LN(AB44)/(LN(W44)+LN(X44)+LN(Y44)+LN(Z44)+LN(AA44)+LN(AB44)+LN(AC44)+LN(AD44))*(AH44-V7_BASE_CPR),0) | AO44: =IFERROR(LN(AC44)/(LN(W44)+LN(X44)+LN(Y44)+LN(Z44)+LN(AA44)+LN(AB44)+LN(AC44)+LN(AD44))*(AH44-V7_BASE_CPR),0) | AP44: =IFERROR(LN(AD44)/(LN(W44)+LN(X44)+LN(Y44)+LN(Z44)+LN(AA44)+LN(AB44)+LN(AC44)+LN(AD44))*(AH44-V7_BASE_CPR),0) | AQ44: =V7_BASE_CPR+SUM(AI44:AP44)-AH44
A45: 3617XJY61_000000012122239 | B45: BERKADIA_POST21 | C45: 3617XJY61 | D45: BERKADIA COMMERCIAL MORTGAGE, LLC | E45: 232 | F45: RP | G45: 2021 | H45: 202602 | I45: 4130019.2 | J45: 2.58 | K45: 447 | L45: 8 | M45: 53 | N45: 0 | O45: 204206 | Q45: 4082 | R45: 0 | S45: 0 | T45: =LN(1+I45) | U45: =J45*100-K45 | V45: =U45-12.5*(L45+1) | W45: =IF(M45<=V7_AGE_KNOT_X_0,V7_AGE_KNOT_Y_0,IF(M45>=V7_AGE_KNOT_X_5,V7_AGE_KNOT_Y_5,IF(M45<=V7_AGE_KNOT_X_1,V7_AGE_KNOT_Y_0+(M45-V7_AGE_KNOT_X_0)/(V7_AGE_KNOT_X_1-V7_AGE_KNOT_X_0)*(V7_AGE_KNOT_Y_1-V7_AGE_KNOT_Y_0),IF(M45<=V7_AGE_KNOT_X_2,V7_AGE_KNOT_Y_1+(M45-V7_AGE_KNOT_X_1)/(V7_AGE_KNOT_X_2-V7_AGE_KNOT_X_1)*(V7_AGE_KNOT_Y_2-V7_AGE_KNOT_Y_1),IF(M45<=V7_AGE_KNOT_X_3,V7_AGE_KNOT_Y_2+(M45-V7_AGE_KNOT_X_2)/(V7_AGE_KNOT_X_3-V7_AGE_KNOT_X_2)*(V7_AGE_KNOT_Y_3-V7_AGE_KNOT_Y_2),IF(M45<=V7_AGE_KNOT_X_4,V7_AGE_KNOT_Y_3+(M45-V7_AGE_KNOT_X_3)/(V7_AGE_KNOT_X_4-V7_AGE_KNOT_X_3)*(V7_AGE_KNOT_Y_4-V7_AGE_KNOT_Y_3),V7_AGE_KNOT_Y_4+(M45-V7_AGE_KNOT_X_4)/(V7_AGE_KNOT_X_5-V7_AGE_KNOT_X_4)*(V7_AGE_KNOT_Y_5-V7_AGE_KNOT_Y_4))))))) | X45: =V7_RATE_FLOOR+V7_RATE_ASYMPTOTE/(1+EXP(-(V45-V7_RATE_MID)/V7_RATE_SLOPE)) | Y45: =MAX(V7_SIZE_LOW,MIN(V7_SIZE_HIGH,V7_SIZE_INTERCEPT+V7_SIZE_SLOPE*(T45-V7_SIZE_LOG_ANCHOR))) | Z45: =IF(ISNUMBER(SEARCH("232",E45)),VLOOKUP("232",V7_PROGRAM_TABLE,2,FALSE),IF(ISNUMBER(SEARCH("538",E45)),VLOOKUP("538",V7_PROGRAM_TABLE,2,FALSE),IF(ISNUMBER(SEARCH("223a7",E45)),VLOOKUP("223a7",V7_PROGRAM_TABLE,2,FALSE),IF(ISNUMBER(SEARCH("223f",E45)),VLOOKUP("223f",V7_PROGRAM_TABLE,2,FALSE),V7_PROGRAM_DEFAULT)))) | AA45: =IF(S45=1,1+V7_PURPOSE_NC_BUMP*MAX(0,1-ABS(M45-V7_PURPOSE_PEAK_AGE)/V7_PURPOSE_WIDTH),1) | AB45: =IF(AND(IF(OR(P45="",NOT(ISNUMBER(P45))),0,MAX(0,MIN(24,(INT(VALUE(H45)/100)-INT(P45/100))*12+MOD(VALUE(H45),100)-MOD(P45,100))))>0,IF(OR(P45="",NOT(ISNUMBER(P45))),0,MAX(0,MIN(24,(INT(VALUE(H45)/100)-INT(P45/100))*12+MOD(VALUE(H45),100)-MOD(P45,100))))<=12),1+V7_LOCKOUT_AMP*EXP(-(IF(OR(P45="",NOT(ISNUMBER(P45))),0,MAX(0,MIN(24,(INT(VALUE(H45)/100)-INT(P45/100))*12+MOD(VALUE(H45),100)-MOD(P45,100)))))/V7_LOCKOUT_TAU),1) | AC45: =IF(IF(OR(O45="",NOT(ISNUMBER(O45))),360,MAX(0,MIN(480,(INT(O45/100)-INT(VALUE(H45)/100))*12+MOD(O45,100)-MOD(VALUE(H45),100))))>0,1+V7_MTY_AMP*MAX(0,(V7_MTY_CUTOFF-(IF(OR(O45="",NOT(ISNUMBER(O45))),360,MAX(0,MIN(480,(INT(O45/100)-INT(VALUE(H45)/100))*12+MOD(O45,100)-MOD(VALUE(H45),100))))))/V7_MTY_CUTOFF),1) | AD45: =MAX(V7_BURN_FLOOR,1-V7_BURN_SLOPE*MIN(1,MAX(0,R45))) | AE45: =IF(V7_USE_ISSUER=1,IFERROR(VLOOKUP(Q45,V7_ISSUER_TABLE,3,FALSE),1),1) | AF45: =PRODUCT(W45:AE45) | AG45: =MIN(V7_BASE_SMM*AF45,V7_SMM_CAP) | AH45: =1-(1-AG45)^12 | AI45: =IFERROR(LN(W45)/(LN(W45)+LN(X45)+LN(Y45)+LN(Z45)+LN(AA45)+LN(AB45)+LN(AC45)+LN(AD45))*(AH45-V7_BASE_CPR),0) | AJ45: =IFERROR(LN(X45)/(LN(W45)+LN(X45)+LN(Y45)+LN(Z45)+LN(AA45)+LN(AB45)+LN(AC45)+LN(AD45))*(AH45-V7_BASE_CPR),0) | AK45: =IFERROR(LN(Y45)/(LN(W45)+LN(X45)+LN(Y45)+LN(Z45)+LN(AA45)+LN(AB45)+LN(AC45)+LN(AD45))*(AH45-V7_BASE_CPR),0) | AL45: =IFERROR(LN(Z45)/(LN(W45)+LN(X45)+LN(Y45)+LN(Z45)+LN(AA45)+LN(AB45)+LN(AC45)+LN(AD45))*(AH45-V7_BASE_CPR),0) | AM45: =IFERROR(LN(AA45)/(LN(W45)+LN(X45)+LN(Y45)+LN(Z45)+LN(AA45)+LN(AB45)+LN(AC45)+LN(AD45))*(AH45-V7_BASE_CPR),0) | AN45: =IFERROR(LN(AB45)/(LN(W45)+LN(X45)+LN(Y45)+LN(Z45)+LN(AA45)+LN(AB45)+LN(AC45)+LN(AD45))*(AH45-V7_BASE_CPR),0) | AO45: =IFERROR(LN(AC45)/(LN(W45)+LN(X45)+LN(Y45)+LN(Z45)+LN(AA45)+LN(AB45)+LN(AC45)+LN(AD45))*(AH45-V7_BASE_CPR),0) | AP45: =IFERROR(LN(AD45)/(LN(W45)+LN(X45)+LN(Y45)+LN(Z45)+LN(AA45)+LN(AB45)+LN(AC45)+LN(AD45))*(AH45-V7_BASE_CPR),0) | AQ45: =V7_BASE_CPR+SUM(AI45:AP45)-AH45
A46: 3617BRKN5_000000005111395 | B46: BERKADIA_PRE21 | C46: 3617BRKN5 | D46: BERKADIA COMMERCIAL MORTGAGE, LLC | E46: 223f | F46: RP | G46: 2017 | H46: 202602 | I46: 6113588.5 | J46: 3.13 | K46: 447 | L46: 4 | M46: 98 | N46: 19 | O46: 205303 | Q46: 4082 | R46: 0.19387755 | S46: 0 | T46: =LN(1+I46) | U46: =J46*100-K46 | V46: =U46-12.5*(L46+1) | W46: =IF(M46<=V7_AGE_KNOT_X_0,V7_AGE_KNOT_Y_0,IF(M46>=V7_AGE_KNOT_X_5,V7_AGE_KNOT_Y_5,IF(M46<=V7_AGE_KNOT_X_1,V7_AGE_KNOT_Y_0+(M46-V7_AGE_KNOT_X_0)/(V7_AGE_KNOT_X_1-V7_AGE_KNOT_X_0)*(V7_AGE_KNOT_Y_1-V7_AGE_KNOT_Y_0),IF(M46<=V7_AGE_KNOT_X_2,V7_AGE_KNOT_Y_1+(M46-V7_AGE_KNOT_X_1)/(V7_AGE_KNOT_X_2-V7_AGE_KNOT_X_1)*(V7_AGE_KNOT_Y_2-V7_AGE_KNOT_Y_1),IF(M46<=V7_AGE_KNOT_X_3,V7_AGE_KNOT_Y_2+(M46-V7_AGE_KNOT_X_2)/(V7_AGE_KNOT_X_3-V7_AGE_KNOT_X_2)*(V7_AGE_KNOT_Y_3-V7_AGE_KNOT_Y_2),IF(M46<=V7_AGE_KNOT_X_4,V7_AGE_KNOT_Y_3+(M46-V7_AGE_KNOT_X_3)/(V7_AGE_KNOT_X_4-V7_AGE_KNOT_X_3)*(V7_AGE_KNOT_Y_4-V7_AGE_KNOT_Y_3),V7_AGE_KNOT_Y_4+(M46-V7_AGE_KNOT_X_4)/(V7_AGE_KNOT_X_5-V7_AGE_KNOT_X_4)*(V7_AGE_KNOT_Y_5-V7_AGE_KNOT_Y_4))))))) | X46: =V7_RATE_FLOOR+V7_RATE_ASYMPTOTE/(1+EXP(-(V46-V7_RATE_MID)/V7_RATE_SLOPE)) | Y46: =MAX(V7_SIZE_LOW,MIN(V7_SIZE_HIGH,V7_SIZE_INTERCEPT+V7_SIZE_SLOPE*(T46-V7_SIZE_LOG_ANCHOR))) | Z46: =IF(ISNUMBER(SEARCH("232",E46)),VLOOKUP("232",V7_PROGRAM_TABLE,2,FALSE),IF(ISNUMBER(SEARCH("538",E46)),VLOOKUP("538",V7_PROGRAM_TABLE,2,FALSE),IF(ISNUMBER(SEARCH("223a7",E46)),VLOOKUP("223a7",V7_PROGRAM_TABLE,2,FALSE),IF(ISNUMBER(SEARCH("223f",E46)),VLOOKUP("223f",V7_PROGRAM_TABLE,2,FALSE),V7_PROGRAM_DEFAULT)))) | AA46: =IF(S46=1,1+V7_PURPOSE_NC_BUMP*MAX(0,1-ABS(M46-V7_PURPOSE_PEAK_AGE)/V7_PURPOSE_WIDTH),1) | AB46: =IF(AND(IF(OR(P46="",NOT(ISNUMBER(P46))),0,MAX(0,MIN(24,(INT(VALUE(H46)/100)-INT(P46/100))*12+MOD(VALUE(H46),100)-MOD(P46,100))))>0,IF(OR(P46="",NOT(ISNUMBER(P46))),0,MAX(0,MIN(24,(INT(VALUE(H46)/100)-INT(P46/100))*12+MOD(VALUE(H46),100)-MOD(P46,100))))<=12),1+V7_LOCKOUT_AMP*EXP(-(IF(OR(P46="",NOT(ISNUMBER(P46))),0,MAX(0,MIN(24,(INT(VALUE(H46)/100)-INT(P46/100))*12+MOD(VALUE(H46),100)-MOD(P46,100)))))/V7_LOCKOUT_TAU),1) | AC46: =IF(IF(OR(O46="",NOT(ISNUMBER(O46))),360,MAX(0,MIN(480,(INT(O46/100)-INT(VALUE(H46)/100))*12+MOD(O46,100)-MOD(VALUE(H46),100))))>0,1+V7_MTY_AMP*MAX(0,(V7_MTY_CUTOFF-(IF(OR(O46="",NOT(ISNUMBER(O46))),360,MAX(0,MIN(480,(INT(O46/100)-INT(VALUE(H46)/100))*12+MOD(O46,100)-MOD(VALUE(H46),100))))))/V7_MTY_CUTOFF),1) | AD46: =MAX(V7_BURN_FLOOR,1-V7_BURN_SLOPE*MIN(1,MAX(0,R46))) | AE46: =IF(V7_USE_ISSUER=1,IFERROR(VLOOKUP(Q46,V7_ISSUER_TABLE,3,FALSE),1),1) | AF46: =PRODUCT(W46:AE46) | AG46: =MIN(V7_BASE_SMM*AF46,V7_SMM_CAP) | AH46: =1-(1-AG46)^12 | AI46: =IFERROR(LN(W46)/(LN(W46)+LN(X46)+LN(Y46)+LN(Z46)+LN(AA46)+LN(AB46)+LN(AC46)+LN(AD46))*(AH46-V7_BASE_CPR),0) | AJ46: =IFERROR(LN(X46)/(LN(W46)+LN(X46)+LN(Y46)+LN(Z46)+LN(AA46)+LN(AB46)+LN(AC46)+LN(AD46))*(AH46-V7_BASE_CPR),0) | AK46: =IFERROR(LN(Y46)/(LN(W46)+LN(X46)+LN(Y46)+LN(Z46)+LN(AA46)+LN(AB46)+LN(AC46)+LN(AD46))*(AH46-V7_BASE_CPR),0) | AL46: =IFERROR(LN(Z46)/(LN(W46)+LN(X46)+LN(Y46)+LN(Z46)+LN(AA46)+LN(AB46)+LN(AC46)+LN(AD46))*(AH46-V7_BASE_CPR),0) | AM46: =IFERROR(LN(AA46)/(LN(W46)+LN(X46)+LN(Y46)+LN(Z46)+LN(AA46)+LN(AB46)+LN(AC46)+LN(AD46))*(AH46-V7_BASE_CPR),0) | AN46: =IFERROR(LN(AB46)/(LN(W46)+LN(X46)+LN(Y46)+LN(Z46)+LN(AA46)+LN(AB46)+LN(AC46)+LN(AD46))*(AH46-V7_BASE_CPR),0) | AO46: =IFERROR(LN(AC46)/(LN(W46)+LN(X46)+LN(Y46)+LN(Z46)+LN(AA46)+LN(AB46)+LN(AC46)+LN(AD46))*(AH46-V7_BASE_CPR),0) | AP46: =IFERROR(LN(AD46)/(LN(W46)+LN(X46)+LN(Y46)+LN(Z46)+LN(AA46)+LN(AB46)+LN(AC46)+LN(AD46))*(AH46-V7_BASE_CPR),0) | AQ46: =V7_BASE_CPR+SUM(AI46:AP46)-AH46
A47: 3617AGRX1_000000007311922 | B47: BERKADIA_PRE21 | C47: 3617AGRX1 | D47: BERKADIA COMMERCIAL MORTGAGE, LLC | E47: 221d4 | F47: RP | G47: 2017 | H47: 202602 | I47: 137331.58 | J47: 4.25 | K47: 447 | L47: 3 | M47: 102 | N47: 36 | O47: 204712 | Q47: 4082 | R47: 0.35294118 | S47: 0 | T47: =LN(1+I47) | U47: =J47*100-K47 | V47: =U47-12.5*(L47+1) | W47: =IF(M47<=V7_AGE_KNOT_X_0,V7_AGE_KNOT_Y_0,IF(M47>=V7_AGE_KNOT_X_5,V7_AGE_KNOT_Y_5,IF(M47<=V7_AGE_KNOT_X_1,V7_AGE_KNOT_Y_0+(M47-V7_AGE_KNOT_X_0)/(V7_AGE_KNOT_X_1-V7_AGE_KNOT_X_0)*(V7_AGE_KNOT_Y_1-V7_AGE_KNOT_Y_0),IF(M47<=V7_AGE_KNOT_X_2,V7_AGE_KNOT_Y_1+(M47-V7_AGE_KNOT_X_1)/(V7_AGE_KNOT_X_2-V7_AGE_KNOT_X_1)*(V7_AGE_KNOT_Y_2-V7_AGE_KNOT_Y_1),IF(M47<=V7_AGE_KNOT_X_3,V7_AGE_KNOT_Y_2+(M47-V7_AGE_KNOT_X_2)/(V7_AGE_KNOT_X_3-V7_AGE_KNOT_X_2)*(V7_AGE_KNOT_Y_3-V7_AGE_KNOT_Y_2),IF(M47<=V7_AGE_KNOT_X_4,V7_AGE_KNOT_Y_3+(M47-V7_AGE_KNOT_X_3)/(V7_AGE_KNOT_X_4-V7_AGE_KNOT_X_3)*(V7_AGE_KNOT_Y_4-V7_AGE_KNOT_Y_3),V7_AGE_KNOT_Y_4+(M47-V7_AGE_KNOT_X_4)/(V7_AGE_KNOT_X_5-V7_AGE_KNOT_X_4)*(V7_AGE_KNOT_Y_5-V7_AGE_KNOT_Y_4))))))) | X47: =V7_RATE_FLOOR+V7_RATE_ASYMPTOTE/(1+EXP(-(V47-V7_RATE_MID)/V7_RATE_SLOPE)) | Y47: =MAX(V7_SIZE_LOW,MIN(V7_SIZE_HIGH,V7_SIZE_INTERCEPT+V7_SIZE_SLOPE*(T47-V7_SIZE_LOG_ANCHOR))) | Z47: =IF(ISNUMBER(SEARCH("232",E47)),VLOOKUP("232",V7_PROGRAM_TABLE,2,FALSE),IF(ISNUMBER(SEARCH("538",E47)),VLOOKUP("538",V7_PROGRAM_TABLE,2,FALSE),IF(ISNUMBER(SEARCH("223a7",E47)),VLOOKUP("223a7",V7_PROGRAM_TABLE,2,FALSE),IF(ISNUMBER(SEARCH("223f",E47)),VLOOKUP("223f",V7_PROGRAM_TABLE,2,FALSE),V7_PROGRAM_DEFAULT)))) | AA47: =IF(S47=1,1+V7_PURPOSE_NC_BUMP*MAX(0,1-ABS(M47-V7_PURPOSE_PEAK_AGE)/V7_PURPOSE_WIDTH),1) | AB47: =IF(AND(IF(OR(P47="",NOT(ISNUMBER(P47))),0,MAX(0,MIN(24,(INT(VALUE(H47)/100)-INT(P47/100))*12+MOD(VALUE(H47),100)-MOD(P47,100))))>0,IF(OR(P47="",NOT(ISNUMBER(P47))),0,MAX(0,MIN(24,(INT(VALUE(H47)/100)-INT(P47/100))*12+MOD(VALUE(H47),100)-MOD(P47,100))))<=12),1+V7_LOCKOUT_AMP*EXP(-(IF(OR(P47="",NOT(ISNUMBER(P47))),0,MAX(0,MIN(24,(INT(VALUE(H47)/100)-INT(P47/100))*12+MOD(VALUE(H47),100)-MOD(P47,100)))))/V7_LOCKOUT_TAU),1) | AC47: =IF(IF(OR(O47="",NOT(ISNUMBER(O47))),360,MAX(0,MIN(480,(INT(O47/100)-INT(VALUE(H47)/100))*12+MOD(O47,100)-MOD(VALUE(H47),100))))>0,1+V7_MTY_AMP*MAX(0,(V7_MTY_CUTOFF-(IF(OR(O47="",NOT(ISNUMBER(O47))),360,MAX(0,MIN(480,(INT(O47/100)-INT(VALUE(H47)/100))*12+MOD(O47,100)-MOD(VALUE(H47),100))))))/V7_MTY_CUTOFF),1) | AD47: =MAX(V7_BURN_FLOOR,1-V7_BURN_SLOPE*MIN(1,MAX(0,R47))) | AE47: =IF(V7_USE_ISSUER=1,IFERROR(VLOOKUP(Q47,V7_ISSUER_TABLE,3,FALSE),1),1) | AF47: =PRODUCT(W47:AE47) | AG47: =MIN(V7_BASE_SMM*AF47,V7_SMM_CAP) | AH47: =1-(1-AG47)^12 | AI47: =IFERROR(LN(W47)/(LN(W47)+LN(X47)+LN(Y47)+LN(Z47)+LN(AA47)+LN(AB47)+LN(AC47)+LN(AD47))*(AH47-V7_BASE_CPR),0) | AJ47: =IFERROR(LN(X47)/(LN(W47)+LN(X47)+LN(Y47)+LN(Z47)+LN(AA47)+LN(AB47)+LN(AC47)+LN(AD47))*(AH47-V7_BASE_CPR),0) | AK47: =IFERROR(LN(Y47)/(LN(W47)+LN(X47)+LN(Y47)+LN(Z47)+LN(AA47)+LN(AB47)+LN(AC47)+LN(AD47))*(AH47-V7_BASE_CPR),0) | AL47: =IFERROR(LN(Z47)/(LN(W47)+LN(X47)+LN(Y47)+LN(Z47)+LN(AA47)+LN(AB47)+LN(AC47)+LN(AD47))*(AH47-V7_BASE_CPR),0) | AM47: =IFERROR(LN(AA47)/(LN(W47)+LN(X47)+LN(Y47)+LN(Z47)+LN(AA47)+LN(AB47)+LN(AC47)+LN(AD47))*(AH47-V7_BASE_CPR),0) | AN47: =IFERROR(LN(AB47)/(LN(W47)+LN(X47)+LN(Y47)+LN(Z47)+LN(AA47)+LN(AB47)+LN(AC47)+LN(AD47))*(AH47-V7_BASE_CPR),0) | AO47: =IFERROR(LN(AC47)/(LN(W47)+LN(X47)+LN(Y47)+LN(Z47)+LN(AA47)+LN(AB47)+LN(AC47)+LN(AD47))*(AH47-V7_BASE_CPR),0) | AP47: =IFERROR(LN(AD47)/(LN(W47)+LN(X47)+LN(Y47)+LN(Z47)+LN(AA47)+LN(AB47)+LN(AC47)+LN(AD47))*(AH47-V7_BASE_CPR),0) | AQ47: =V7_BASE_CPR+SUM(AI47:AP47)-AH47
A48: 3617XJZZ6_000000011535902 | B48: BERKADIA_POST21 | C48: 3617XJZZ6 | D48: BERKADIA COMMERCIAL MORTGAGE, LLC | E48: 221d4 | F48: NC | G48: 2021 | H48: 202602 | I48: 45179300 | J48: 2.96 | K48: 447 | L48: 10 | M48: 50 | N48: 0 | O48: 206408 | Q48: 4082 | R48: 0 | S48: 1 | T48: =LN(1+I48) | U48: =J48*100-K48 | V48: =U48-12.5*(L48+1) | W48: =IF(M48<=V7_AGE_KNOT_X_0,V7_AGE_KNOT_Y_0,IF(M48>=V7_AGE_KNOT_X_5,V7_AGE_KNOT_Y_5,IF(M48<=V7_AGE_KNOT_X_1,V7_AGE_KNOT_Y_0+(M48-V7_AGE_KNOT_X_0)/(V7_AGE_KNOT_X_1-V7_AGE_KNOT_X_0)*(V7_AGE_KNOT_Y_1-V7_AGE_KNOT_Y_0),IF(M48<=V7_AGE_KNOT_X_2,V7_AGE_KNOT_Y_1+(M48-V7_AGE_KNOT_X_1)/(V7_AGE_KNOT_X_2-V7_AGE_KNOT_X_1)*(V7_AGE_KNOT_Y_2-V7_AGE_KNOT_Y_1),IF(M48<=V7_AGE_KNOT_X_3,V7_AGE_KNOT_Y_2+(M48-V7_AGE_KNOT_X_2)/(V7_AGE_KNOT_X_3-V7_AGE_KNOT_X_2)*(V7_AGE_KNOT_Y_3-V7_AGE_KNOT_Y_2),IF(M48<=V7_AGE_KNOT_X_4,V7_AGE_KNOT_Y_3+(M48-V7_AGE_KNOT_X_3)/(V7_AGE_KNOT_X_4-V7_AGE_KNOT_X_3)*(V7_AGE_KNOT_Y_4-V7_AGE_KNOT_Y_3),V7_AGE_KNOT_Y_4+(M48-V7_AGE_KNOT_X_4)/(V7_AGE_KNOT_X_5-V7_AGE_KNOT_X_4)*(V7_AGE_KNOT_Y_5-V7_AGE_KNOT_Y_4))))))) | X48: =V7_RATE_FLOOR+V7_RATE_ASYMPTOTE/(1+EXP(-(V48-V7_RATE_MID)/V7_RATE_SLOPE)) | Y48: =MAX(V7_SIZE_LOW,MIN(V7_SIZE_HIGH,V7_SIZE_INTERCEPT+V7_SIZE_SLOPE*(T48-V7_SIZE_LOG_ANCHOR))) | Z48: =IF(ISNUMBER(SEARCH("232",E48)),VLOOKUP("232",V7_PROGRAM_TABLE,2,FALSE),IF(ISNUMBER(SEARCH("538",E48)),VLOOKUP("538",V7_PROGRAM_TABLE,2,FALSE),IF(ISNUMBER(SEARCH("223a7",E48)),VLOOKUP("223a7",V7_PROGRAM_TABLE,2,FALSE),IF(ISNUMBER(SEARCH("223f",E48)),VLOOKUP("223f",V7_PROGRAM_TABLE,2,FALSE),V7_PROGRAM_DEFAULT)))) | AA48: =IF(S48=1,1+V7_PURPOSE_NC_BUMP*MAX(0,1-ABS(M48-V7_PURPOSE_PEAK_AGE)/V7_PURPOSE_WIDTH),1) | AB48: =IF(AND(IF(OR(P48="",NOT(ISNUMBER(P48))),0,MAX(0,MIN(24,(INT(VALUE(H48)/100)-INT(P48/100))*12+MOD(VALUE(H48),100)-MOD(P48,100))))>0,IF(OR(P48="",NOT(ISNUMBER(P48))),0,MAX(0,MIN(24,(INT(VALUE(H48)/100)-INT(P48/100))*12+MOD(VALUE(H48),100)-MOD(P48,100))))<=12),1+V7_LOCKOUT_AMP*EXP(-(IF(OR(P48="",NOT(ISNUMBER(P48))),0,MAX(0,MIN(24,(INT(VALUE(H48)/100)-INT(P48/100))*12+MOD(VALUE(H48),100)-MOD(P48,100)))))/V7_LOCKOUT_TAU),1) | AC48: =IF(IF(OR(O48="",NOT(ISNUMBER(O48))),360,MAX(0,MIN(480,(INT(O48/100)-INT(VALUE(H48)/100))*12+MOD(O48,100)-MOD(VALUE(H48),100))))>0,1+V7_MTY_AMP*MAX(0,(V7_MTY_CUTOFF-(IF(OR(O48="",NOT(ISNUMBER(O48))),360,MAX(0,MIN(480,(INT(O48/100)-INT(VALUE(H48)/100))*12+MOD(O48,100)-MOD(VALUE(H48),100))))))/V7_MTY_CUTOFF),1) | AD48: =MAX(V7_BURN_FLOOR,1-V7_BURN_SLOPE*MIN(1,MAX(0,R48))) | AE48: =IF(V7_USE_ISSUER=1,IFERROR(VLOOKUP(Q48,V7_ISSUER_TABLE,3,FALSE),1),1) | AF48: =PRODUCT(W48:AE48) | AG48: =MIN(V7_BASE_SMM*AF48,V7_SMM_CAP) | AH48: =1-(1-AG48)^12 | AI48: =IFERROR(LN(W48)/(LN(W48)+LN(X48)+LN(Y48)+LN(Z48)+LN(AA48)+LN(AB48)+LN(AC48)+LN(AD48))*(AH48-V7_BASE_CPR),0) | AJ48: =IFERROR(LN(X48)/(LN(W48)+LN(X48)+LN(Y48)+LN(Z48)+LN(AA48)+LN(AB48)+LN(AC48)+LN(AD48))*(AH48-V7_BASE_CPR),0) | AK48: =IFERROR(LN(Y48)/(LN(W48)+LN(X48)+LN(Y48)+LN(Z48)+LN(AA48)+LN(AB48)+LN(AC48)+LN(AD48))*(AH48-V7_BASE_CPR),0) | AL48: =IFERROR(LN(Z48)/(LN(W48)+LN(X48)+LN(Y48)+LN(Z48)+LN(AA48)+LN(AB48)+LN(AC48)+LN(AD48))*(AH48-V7_BASE_CPR),0) | AM48: =IFERROR(LN(AA48)/(LN(W48)+LN(X48)+LN(Y48)+LN(Z48)+LN(AA48)+LN(AB48)+LN(AC48)+LN(AD48))*(AH48-V7_BASE_CPR),0) | AN48: =IFERROR(LN(AB48)/(LN(W48)+LN(X48)+LN(Y48)+LN(Z48)+LN(AA48)+LN(AB48)+LN(AC48)+LN(AD48))*(AH48-V7_BASE_CPR),0) | AO48: =IFERROR(LN(AC48)/(LN(W48)+LN(X48)+LN(Y48)+LN(Z48)+LN(AA48)+LN(AB48)+LN(AC48)+LN(AD48))*(AH48-V7_BASE_CPR),0) | AP48: =IFERROR(LN(AD48)/(LN(W48)+LN(X48)+LN(Y48)+LN(Z48)+LN(AA48)+LN(AB48)+LN(AC48)+LN(AD48))*(AH48-V7_BASE_CPR),0) | AQ48: =V7_BASE_CPR+SUM(AI48:AP48)-AH48
A49: 3617BRLC8_000000005411156 | B49: BERKADIA_PRE21 | C49: 3617BRLC8 | D49: BERKADIA COMMERCIAL MORTGAGE, LLC | E49: 223f | F49: RP | G49: 2017 | H49: 202602 | I49: 3384137.4 | J49: 3.99 | K49: 447 | L49: 0 | M49: 99 | N49: 41 | O49: 204806 | Q49: 4082 | R49: 0.41414141 | S49: 0 | T49: =LN(1+I49) | U49: =J49*100-K49 | V49: =U49-12.5*(L49+1) | W49: =IF(M49<=V7_AGE_KNOT_X_0,V7_AGE_KNOT_Y_0,IF(M49>=V7_AGE_KNOT_X_5,V7_AGE_KNOT_Y_5,IF(M49<=V7_AGE_KNOT_X_1,V7_AGE_KNOT_Y_0+(M49-V7_AGE_KNOT_X_0)/(V7_AGE_KNOT_X_1-V7_AGE_KNOT_X_0)*(V7_AGE_KNOT_Y_1-V7_AGE_KNOT_Y_0),IF(M49<=V7_AGE_KNOT_X_2,V7_AGE_KNOT_Y_1+(M49-V7_AGE_KNOT_X_1)/(V7_AGE_KNOT_X_2-V7_AGE_KNOT_X_1)*(V7_AGE_KNOT_Y_2-V7_AGE_KNOT_Y_1),IF(M49<=V7_AGE_KNOT_X_3,V7_AGE_KNOT_Y_2+(M49-V7_AGE_KNOT_X_2)/(V7_AGE_KNOT_X_3-V7_AGE_KNOT_X_2)*(V7_AGE_KNOT_Y_3-V7_AGE_KNOT_Y_2),IF(M49<=V7_AGE_KNOT_X_4,V7_AGE_KNOT_Y_3+(M49-V7_AGE_KNOT_X_3)/(V7_AGE_KNOT_X_4-V7_AGE_KNOT_X_3)*(V7_AGE_KNOT_Y_4-V7_AGE_KNOT_Y_3),V7_AGE_KNOT_Y_4+(M49-V7_AGE_KNOT_X_4)/(V7_AGE_KNOT_X_5-V7_AGE_KNOT_X_4)*(V7_AGE_KNOT_Y_5-V7_AGE_KNOT_Y_4))))))) | X49: =V7_RATE_FLOOR+V7_RATE_ASYMPTOTE/(1+EXP(-(V49-V7_RATE_MID)/V7_RATE_SLOPE)) | Y49: =MAX(V7_SIZE_LOW,MIN(V7_SIZE_HIGH,V7_SIZE_INTERCEPT+V7_SIZE_SLOPE*(T49-V7_SIZE_LOG_ANCHOR))) | Z49: =IF(ISNUMBER(SEARCH("232",E49)),VLOOKUP("232",V7_PROGRAM_TABLE,2,FALSE),IF(ISNUMBER(SEARCH("538",E49)),VLOOKUP("538",V7_PROGRAM_TABLE,2,FALSE),IF(ISNUMBER(SEARCH("223a7",E49)),VLOOKUP("223a7",V7_PROGRAM_TABLE,2,FALSE),IF(ISNUMBER(SEARCH("223f",E49)),VLOOKUP("223f",V7_PROGRAM_TABLE,2,FALSE),V7_PROGRAM_DEFAULT)))) | AA49: =IF(S49=1,1+V7_PURPOSE_NC_BUMP*MAX(0,1-ABS(M49-V7_PURPOSE_PEAK_AGE)/V7_PURPOSE_WIDTH),1) | AB49: =IF(AND(IF(OR(P49="",NOT(ISNUMBER(P49))),0,MAX(0,MIN(24,(INT(VALUE(H49)/100)-INT(P49/100))*12+MOD(VALUE(H49),100)-MOD(P49,100))))>0,IF(OR(P49="",NOT(ISNUMBER(P49))),0,MAX(0,MIN(24,(INT(VALUE(H49)/100)-INT(P49/100))*12+MOD(VALUE(H49),100)-MOD(P49,100))))<=12),1+V7_LOCKOUT_AMP*EXP(-(IF(OR(P49="",NOT(ISNUMBER(P49))),0,MAX(0,MIN(24,(INT(VALUE(H49)/100)-INT(P49/100))*12+MOD(VALUE(H49),100)-MOD(P49,100)))))/V7_LOCKOUT_TAU),1) | AC49: =IF(IF(OR(O49="",NOT(ISNUMBER(O49))),360,MAX(0,MIN(480,(INT(O49/100)-INT(VALUE(H49)/100))*12+MOD(O49,100)-MOD(VALUE(H49),100))))>0,1+V7_MTY_AMP*MAX(0,(V7_MTY_CUTOFF-(IF(OR(O49="",NOT(ISNUMBER(O49))),360,MAX(0,MIN(480,(INT(O49/100)-INT(VALUE(H49)/100))*12+MOD(O49,100)-MOD(VALUE(H49),100))))))/V7_MTY_CUTOFF),1) | AD49: =MAX(V7_BURN_FLOOR,1-V7_BURN_SLOPE*MIN(1,MAX(0,R49))) | AE49: =IF(V7_USE_ISSUER=1,IFERROR(VLOOKUP(Q49,V7_ISSUER_TABLE,3,FALSE),1),1) | AF49: =PRODUCT(W49:AE49) | AG49: =MIN(V7_BASE_SMM*AF49,V7_SMM_CAP) | AH49: =1-(1-AG49)^12 | AI49: =IFERROR(LN(W49)/(LN(W49)+LN(X49)+LN(Y49)+LN(Z49)+LN(AA49)+LN(AB49)+LN(AC49)+LN(AD49))*(AH49-V7_BASE_CPR),0) | AJ49: =IFERROR(LN(X49)/(LN(W49)+LN(X49)+LN(Y49)+LN(Z49)+LN(AA49)+LN(AB49)+LN(AC49)+LN(AD49))*(AH49-V7_BASE_CPR),0) | AK49: =IFERROR(LN(Y49)/(LN(W49)+LN(X49)+LN(Y49)+LN(Z49)+LN(AA49)+LN(AB49)+LN(AC49)+LN(AD49))*(AH49-V7_BASE_CPR),0) | AL49: =IFERROR(LN(Z49)/(LN(W49)+LN(X49)+LN(Y49)+LN(Z49)+LN(AA49)+LN(AB49)+LN(AC49)+LN(AD49))*(AH49-V7_BASE_CPR),0) | AM49: =IFERROR(LN(AA49)/(LN(W49)+LN(X49)+LN(Y49)+LN(Z49)+LN(AA49)+LN(AB49)+LN(AC49)+LN(AD49))*(AH49-V7_BASE_CPR),0) | AN49: =IFERROR(LN(AB49)/(LN(W49)+LN(X49)+LN(Y49)+LN(Z49)+LN(AA49)+LN(AB49)+LN(AC49)+LN(AD49))*(AH49-V7_BASE_CPR),0) | AO49: =IFERROR(LN(AC49)/(LN(W49)+LN(X49)+LN(Y49)+LN(Z49)+LN(AA49)+LN(AB49)+LN(AC49)+LN(AD49))*(AH49-V7_BASE_CPR),0) | AP49: =IFERROR(LN(AD49)/(LN(W49)+LN(X49)+LN(Y49)+LN(Z49)+LN(AA49)+LN(AB49)+LN(AC49)+LN(AD49))*(AH49-V7_BASE_CPR),0) | AQ49: =V7_BASE_CPR+SUM(AI49:AP49)-AH49
A50: 3617XJ2D1_000000004711281 | B50: BERKADIA_POST21 | C50: 3617XJ2D1 | D50: BERKADIA COMMERCIAL MORTGAGE, LLC | E50: 223f | F50: RP | G50: 2021 | H50: 202602 | I50: 5205375.8 | J50: 2.49 | K50: 447 | L50: 8 | M50: 54 | N50: 0 | O50: 205604 | Q50: 4082 | R50: 0 | S50: 0 | T50: =LN(1+I50) | U50: =J50*100-K50 | V50: =U50-12.5*(L50+1) | W50: =IF(M50<=V7_AGE_KNOT_X_0,V7_AGE_KNOT_Y_0,IF(M50>=V7_AGE_KNOT_X_5,V7_AGE_KNOT_Y_5,IF(M50<=V7_AGE_KNOT_X_1,V7_AGE_KNOT_Y_0+(M50-V7_AGE_KNOT_X_0)/(V7_AGE_KNOT_X_1-V7_AGE_KNOT_X_0)*(V7_AGE_KNOT_Y_1-V7_AGE_KNOT_Y_0),IF(M50<=V7_AGE_KNOT_X_2,V7_AGE_KNOT_Y_1+(M50-V7_AGE_KNOT_X_1)/(V7_AGE_KNOT_X_2-V7_AGE_KNOT_X_1)*(V7_AGE_KNOT_Y_2-V7_AGE_KNOT_Y_1),IF(M50<=V7_AGE_KNOT_X_3,V7_AGE_KNOT_Y_2+(M50-V7_AGE_KNOT_X_2)/(V7_AGE_KNOT_X_3-V7_AGE_KNOT_X_2)*(V7_AGE_KNOT_Y_3-V7_AGE_KNOT_Y_2),IF(M50<=V7_AGE_KNOT_X_4,V7_AGE_KNOT_Y_3+(M50-V7_AGE_KNOT_X_3)/(V7_AGE_KNOT_X_4-V7_AGE_KNOT_X_3)*(V7_AGE_KNOT_Y_4-V7_AGE_KNOT_Y_3),V7_AGE_KNOT_Y_4+(M50-V7_AGE_KNOT_X_4)/(V7_AGE_KNOT_X_5-V7_AGE_KNOT_X_4)*(V7_AGE_KNOT_Y_5-V7_AGE_KNOT_Y_4))))))) | X50: =V7_RATE_FLOOR+V7_RATE_ASYMPTOTE/(1+EXP(-(V50-V7_RATE_MID)/V7_RATE_SLOPE)) | Y50: =MAX(V7_SIZE_LOW,MIN(V7_SIZE_HIGH,V7_SIZE_INTERCEPT+V7_SIZE_SLOPE*(T50-V7_SIZE_LOG_ANCHOR))) | Z50: =IF(ISNUMBER(SEARCH("232",E50)),VLOOKUP("232",V7_PROGRAM_TABLE,2,FALSE),IF(ISNUMBER(SEARCH("538",E50)),VLOOKUP("538",V7_PROGRAM_TABLE,2,FALSE),IF(ISNUMBER(SEARCH("223a7",E50)),VLOOKUP("223a7",V7_PROGRAM_TABLE,2,FALSE),IF(ISNUMBER(SEARCH("223f",E50)),VLOOKUP("223f",V7_PROGRAM_TABLE,2,FALSE),V7_PROGRAM_DEFAULT)))) | AA50: =IF(S50=1,1+V7_PURPOSE_NC_BUMP*MAX(0,1-ABS(M50-V7_PURPOSE_PEAK_AGE)/V7_PURPOSE_WIDTH),1) | AB50: =IF(AND(IF(OR(P50="",NOT(ISNUMBER(P50))),0,MAX(0,MIN(24,(INT(VALUE(H50)/100)-INT(P50/100))*12+MOD(VALUE(H50),100)-MOD(P50,100))))>0,IF(OR(P50="",NOT(ISNUMBER(P50))),0,MAX(0,MIN(24,(INT(VALUE(H50)/100)-INT(P50/100))*12+MOD(VALUE(H50),100)-MOD(P50,100))))<=12),1+V7_LOCKOUT_AMP*EXP(-(IF(OR(P50="",NOT(ISNUMBER(P50))),0,MAX(0,MIN(24,(INT(VALUE(H50)/100)-INT(P50/100))*12+MOD(VALUE(H50),100)-MOD(P50,100)))))/V7_LOCKOUT_TAU),1) | AC50: =IF(IF(OR(O50="",NOT(ISNUMBER(O50))),360,MAX(0,MIN(480,(INT(O50/100)-INT(VALUE(H50)/100))*12+MOD(O50,100)-MOD(VALUE(H50),100))))>0,1+V7_MTY_AMP*MAX(0,(V7_MTY_CUTOFF-(IF(OR(O50="",NOT(ISNUMBER(O50))),360,MAX(0,MIN(480,(INT(O50/100)-INT(VALUE(H50)/100))*12+MOD(O50,100)-MOD(VALUE(H50),100))))))/V7_MTY_CUTOFF),1) | AD50: =MAX(V7_BURN_FLOOR,1-V7_BURN_SLOPE*MIN(1,MAX(0,R50))) | AE50: =IF(V7_USE_ISSUER=1,IFERROR(VLOOKUP(Q50,V7_ISSUER_TABLE,3,FALSE),1),1) | AF50: =PRODUCT(W50:AE50) | AG50: =MIN(V7_BASE_SMM*AF50,V7_SMM_CAP) | AH50: =1-(1-AG50)^12 | AI50: =IFERROR(LN(W50)/(LN(W50)+LN(X50)+LN(Y50)+LN(Z50)+LN(AA50)+LN(AB50)+LN(AC50)+LN(AD50))*(AH50-V7_BASE_CPR),0) | AJ50: =IFERROR(LN(X50)/(LN(W50)+LN(X50)+LN(Y50)+LN(Z50)+LN(AA50)+LN(AB50)+LN(AC50)+LN(AD50))*(AH50-V7_BASE_CPR),0) | AK50: =IFERROR(LN(Y50)/(LN(W50)+LN(X50)+LN(Y50)+LN(Z50)+LN(AA50)+LN(AB50)+LN(AC50)+LN(AD50))*(AH50-V7_BASE_CPR),0) | AL50: =IFERROR(LN(Z50)/(LN(W50)+LN(X50)+LN(Y50)+LN(Z50)+LN(AA50)+LN(AB50)+LN(AC50)+LN(AD50))*(AH50-V7_BASE_CPR),0) | AM50: =IFERROR(LN(AA50)/(LN(W50)+LN(X50)+LN(Y50)+LN(Z50)+LN(AA50)+LN(AB50)+LN(AC50)+LN(AD50))*(AH50-V7_BASE_CPR),0) | AN50: =IFERROR(LN(AB50)/(LN(W50)+LN(X50)+LN(Y50)+LN(Z50)+LN(AA50)+LN(AB50)+LN(AC50)+LN(AD50))*(AH50-V7_BASE_CPR),0) | AO50: =IFERROR(LN(AC50)/(LN(W50)+LN(X50)+LN(Y50)+LN(Z50)+LN(AA50)+LN(AB50)+LN(AC50)+LN(AD50))*(AH50-V7_BASE_CPR),0) | AP50: =IFERROR(LN(AD50)/(LN(W50)+LN(X50)+LN(Y50)+LN(Z50)+LN(AA50)+LN(AB50)+LN(AC50)+LN(AD50))*(AH50-V7_BASE_CPR),0) | AQ50: =V7_BASE_CPR+SUM(AI50:AP50)-AH50
A51: 3617UNW83_000000005135817 | B51: BERKADIA_PRE21 | C51: 3617UNW83 | D51: BERKADIA COMMERCIAL MORTGAGE, LLC | E51: 221d4 | F51: RP | G51: 2020 | H51: 202602 | I51: 36370658 | J51: 2.3 | K51: 447 | L51: 7 | M51: 64 | N51: 12 | O51: 206103 | Q51: 4082 | R51: 0.1875 | S51: 0 | T51: =LN(1+I51) | U51: =J51*100-K51 | V51: =U51-12.5*(L51+1) | W51: =IF(M51<=V7_AGE_KNOT_X_0,V7_AGE_KNOT_Y_0,IF(M51>=V7_AGE_KNOT_X_5,V7_AGE_KNOT_Y_5,IF(M51<=V7_AGE_KNOT_X_1,V7_AGE_KNOT_Y_0+(M51-V7_AGE_KNOT_X_0)/(V7_AGE_KNOT_X_1-V7_AGE_KNOT_X_0)*(V7_AGE_KNOT_Y_1-V7_AGE_KNOT_Y_0),IF(M51<=V7_AGE_KNOT_X_2,V7_AGE_KNOT_Y_1+(M51-V7_AGE_KNOT_X_1)/(V7_AGE_KNOT_X_2-V7_AGE_KNOT_X_1)*(V7_AGE_KNOT_Y_2-V7_AGE_KNOT_Y_1),IF(M51<=V7_AGE_KNOT_X_3,V7_AGE_KNOT_Y_2+(M51-V7_AGE_KNOT_X_2)/(V7_AGE_KNOT_X_3-V7_AGE_KNOT_X_2)*(V7_AGE_KNOT_Y_3-V7_AGE_KNOT_Y_2),IF(M51<=V7_AGE_KNOT_X_4,V7_AGE_KNOT_Y_3+(M51-V7_AGE_KNOT_X_3)/(V7_AGE_KNOT_X_4-V7_AGE_KNOT_X_3)*(V7_AGE_KNOT_Y_4-V7_AGE_KNOT_Y_3),V7_AGE_KNOT_Y_4+(M51-V7_AGE_KNOT_X_4)/(V7_AGE_KNOT_X_5-V7_AGE_KNOT_X_4)*(V7_AGE_KNOT_Y_5-V7_AGE_KNOT_Y_4))))))) | X51: =V7_RATE_FLOOR+V7_RATE_ASYMPTOTE/(1+EXP(-(V51-V7_RATE_MID)/V7_RATE_SLOPE)) | Y51: =MAX(V7_SIZE_LOW,MIN(V7_SIZE_HIGH,V7_SIZE_INTERCEPT+V7_SIZE_SLOPE*(T51-V7_SIZE_LOG_ANCHOR))) | Z51: =IF(ISNUMBER(SEARCH("232",E51)),VLOOKUP("232",V7_PROGRAM_TABLE,2,FALSE),IF(ISNUMBER(SEARCH("538",E51)),VLOOKUP("538",V7_PROGRAM_TABLE,2,FALSE),IF(ISNUMBER(SEARCH("223a7",E51)),VLOOKUP("223a7",V7_PROGRAM_TABLE,2,FALSE),IF(ISNUMBER(SEARCH("223f",E51)),VLOOKUP("223f",V7_PROGRAM_TABLE,2,FALSE),V7_PROGRAM_DEFAULT)))) | AA51: =IF(S51=1,1+V7_PURPOSE_NC_BUMP*MAX(0,1-ABS(M51-V7_PURPOSE_PEAK_AGE)/V7_PURPOSE_WIDTH),1) | AB51: =IF(AND(IF(OR(P51="",NOT(ISNUMBER(P51))),0,MAX(0,MIN(24,(INT(VALUE(H51)/100)-INT(P51/100))*12+MOD(VALUE(H51),100)-MOD(P51,100))))>0,IF(OR(P51="",NOT(ISNUMBER(P51))),0,MAX(0,MIN(24,(INT(VALUE(H51)/100)-INT(P51/100))*12+MOD(VALUE(H51),100)-MOD(P51,100))))<=12),1+V7_LOCKOUT_AMP*EXP(-(IF(OR(P51="",NOT(ISNUMBER(P51))),0,MAX(0,MIN(24,(INT(VALUE(H51)/100)-INT(P51/100))*12+MOD(VALUE(H51),100)-MOD(P51,100)))))/V7_LOCKOUT_TAU),1) | AC51: =IF(IF(OR(O51="",NOT(ISNUMBER(O51))),360,MAX(0,MIN(480,(INT(O51/100)-INT(VALUE(H51)/100))*12+MOD(O51,100)-MOD(VALUE(H51),100))))>0,1+V7_MTY_AMP*MAX(0,(V7_MTY_CUTOFF-(IF(OR(O51="",NOT(ISNUMBER(O51))),360,MAX(0,MIN(480,(INT(O51/100)-INT(VALUE(H51)/100))*12+MOD(O51,100)-MOD(VALUE(H51),100))))))/V7_MTY_CUTOFF),1) | AD51: =MAX(V7_BURN_FLOOR,1-V7_BURN_SLOPE*MIN(1,MAX(0,R51))) | AE51: =IF(V7_USE_ISSUER=1,IFERROR(VLOOKUP(Q51,V7_ISSUER_TABLE,3,FALSE),1),1) | AF51: =PRODUCT(W51:AE51) | AG51: =MIN(V7_BASE_SMM*AF51,V7_SMM_CAP) | AH51: =1-(1-AG51)^12 | AI51: =IFERROR(LN(W51)/(LN(W51)+LN(X51)+LN(Y51)+LN(Z51)+LN(AA51)+LN(AB51)+LN(AC51)+LN(AD51))*(AH51-V7_BASE_CPR),0) | AJ51: =IFERROR(LN(X51)/(LN(W51)+LN(X51)+LN(Y51)+LN(Z51)+LN(AA51)+LN(AB51)+LN(AC51)+LN(AD51))*(AH51-V7_BASE_CPR),0) | AK51: =IFERROR(LN(Y51)/(LN(W51)+LN(X51)+LN(Y51)+LN(Z51)+LN(AA51)+LN(AB51)+LN(AC51)+LN(AD51))*(AH51-V7_BASE_CPR),0) | AL51: =IFERROR(LN(Z51)/(LN(W51)+LN(X51)+LN(Y51)+LN(Z51)+LN(AA51)+LN(AB51)+LN(AC51)+LN(AD51))*(AH51-V7_BASE_CPR),0) | AM51: =IFERROR(LN(AA51)/(LN(W51)+LN(X51)+LN(Y51)+LN(Z51)+LN(AA51)+LN(AB51)+LN(AC51)+LN(AD51))*(AH51-V7_BASE_CPR),0) | AN51: =IFERROR(LN(AB51)/(LN(W51)+LN(X51)+LN(Y51)+LN(Z51)+LN(AA51)+LN(AB51)+LN(AC51)+LN(AD51))*(AH51-V7_BASE_CPR),0) | AO51: =IFERROR(LN(AC51)/(LN(W51)+LN(X51)+LN(Y51)+LN(Z51)+LN(AA51)+LN(AB51)+LN(AC51)+LN(AD51))*(AH51-V7_BASE_CPR),0) | AP51: =IFERROR(LN(AD51)/(LN(W51)+LN(X51)+LN(Y51)+LN(Z51)+LN(AA51)+LN(AB51)+LN(AC51)+LN(AD51))*(AH51-V7_BASE_CPR),0) | AQ51: =V7_BASE_CPR+SUM(AI51:AP51)-AH51
A52: 3617F6YH5_000000010511134 | B52: BERKADIA_POST21 | C52: 3617F6YH5 | D52: BERKADIA COMMERCIAL MORTGAGE, LLC | E52: 223f | F52: RP | G52: 2022 | H52: 202602 | I52: 40172298 | J52: 3.68 | K52: 447 | L52: 8 | M52: 46 | N52: 0 | O52: 205709 | Q52: 4082 | R52: 0 | S52: 0 | T52: =LN(1+I52) | U52: =J52*100-K52 | V52: =U52-12.5*(L52+1) | W52: =IF(M52<=V7_AGE_KNOT_X_0,V7_AGE_KNOT_Y_0,IF(M52>=V7_AGE_KNOT_X_5,V7_AGE_KNOT_Y_5,IF(M52<=V7_AGE_KNOT_X_1,V7_AGE_KNOT_Y_0+(M52-V7_AGE_KNOT_X_0)/(V7_AGE_KNOT_X_1-V7_AGE_KNOT_X_0)*(V7_AGE_KNOT_Y_1-V7_AGE_KNOT_Y_0),IF(M52<=V7_AGE_KNOT_X_2,V7_AGE_KNOT_Y_1+(M52-V7_AGE_KNOT_X_1)/(V7_AGE_KNOT_X_2-V7_AGE_KNOT_X_1)*(V7_AGE_KNOT_Y_2-V7_AGE_KNOT_Y_1),IF(M52<=V7_AGE_KNOT_X_3,V7_AGE_KNOT_Y_2+(M52-V7_AGE_KNOT_X_2)/(V7_AGE_KNOT_X_3-V7_AGE_KNOT_X_2)*(V7_AGE_KNOT_Y_3-V7_AGE_KNOT_Y_2),IF(M52<=V7_AGE_KNOT_X_4,V7_AGE_KNOT_Y_3+(M52-V7_AGE_KNOT_X_3)/(V7_AGE_KNOT_X_4-V7_AGE_KNOT_X_3)*(V7_AGE_KNOT_Y_4-V7_AGE_KNOT_Y_3),V7_AGE_KNOT_Y_4+(M52-V7_AGE_KNOT_X_4)/(V7_AGE_KNOT_X_5-V7_AGE_KNOT_X_4)*(V7_AGE_KNOT_Y_5-V7_AGE_KNOT_Y_4))))))) | X52: =V7_RATE_FLOOR+V7_RATE_ASYMPTOTE/(1+EXP(-(V52-V7_RATE_MID)/V7_RATE_SLOPE)) | Y52: =MAX(V7_SIZE_LOW,MIN(V7_SIZE_HIGH,V7_SIZE_INTERCEPT+V7_SIZE_SLOPE*(T52-V7_SIZE_LOG_ANCHOR))) | Z52: =IF(ISNUMBER(SEARCH("232",E52)),VLOOKUP("232",V7_PROGRAM_TABLE,2,FALSE),IF(ISNUMBER(SEARCH("538",E52)),VLOOKUP("538",V7_PROGRAM_TABLE,2,FALSE),IF(ISNUMBER(SEARCH("223a7",E52)),VLOOKUP("223a7",V7_PROGRAM_TABLE,2,FALSE),IF(ISNUMBER(SEARCH("223f",E52)),VLOOKUP("223f",V7_PROGRAM_TABLE,2,FALSE),V7_PROGRAM_DEFAULT)))) | AA52: =IF(S52=1,1+V7_PURPOSE_NC_BUMP*MAX(0,1-ABS(M52-V7_PURPOSE_PEAK_AGE)/V7_PURPOSE_WIDTH),1) | AB52: =IF(AND(IF(OR(P52="",NOT(ISNUMBER(P52))),0,MAX(0,MIN(24,(INT(VALUE(H52)/100)-INT(P52/100))*12+MOD(VALUE(H52),100)-MOD(P52,100))))>0,IF(OR(P52="",NOT(ISNUMBER(P52))),0,MAX(0,MIN(24,(INT(VALUE(H52)/100)-INT(P52/100))*12+MOD(VALUE(H52),100)-MOD(P52,100))))<=12),1+V7_LOCKOUT_AMP*EXP(-(IF(OR(P52="",NOT(ISNUMBER(P52))),0,MAX(0,MIN(24,(INT(VALUE(H52)/100)-INT(P52/100))*12+MOD(VALUE(H52),100)-MOD(P52,100)))))/V7_LOCKOUT_TAU),1) | AC52: =IF(IF(OR(O52="",NOT(ISNUMBER(O52))),360,MAX(0,MIN(480,(INT(O52/100)-INT(VALUE(H52)/100))*12+MOD(O52,100)-MOD(VALUE(H52),100))))>0,1+V7_MTY_AMP*MAX(0,(V7_MTY_CUTOFF-(IF(OR(O52="",NOT(ISNUMBER(O52))),360,MAX(0,MIN(480,(INT(O52/100)-INT(VALUE(H52)/100))*12+MOD(O52,100)-MOD(VALUE(H52),100))))))/V7_MTY_CUTOFF),1) | AD52: =MAX(V7_BURN_FLOOR,1-V7_BURN_SLOPE*MIN(1,MAX(0,R52))) | AE52: =IF(V7_USE_ISSUER=1,IFERROR(VLOOKUP(Q52,V7_ISSUER_TABLE,3,FALSE),1),1) | AF52: =PRODUCT(W52:AE52) | AG52: =MIN(V7_BASE_SMM*AF52,V7_SMM_CAP) | AH52: =1-(1-AG52)^12 | AI52: =IFERROR(LN(W52)/(LN(W52)+LN(X52)+LN(Y52)+LN(Z52)+LN(AA52)+LN(AB52)+LN(AC52)+LN(AD52))*(AH52-V7_BASE_CPR),0) | AJ52: =IFERROR(LN(X52)/(LN(W52)+LN(X52)+LN(Y52)+LN(Z52)+LN(AA52)+LN(AB52)+LN(AC52)+LN(AD52))*(AH52-V7_BASE_CPR),0) | AK52: =IFERROR(LN(Y52)/(LN(W52)+LN(X52)+LN(Y52)+LN(Z52)+LN(AA52)+LN(AB52)+LN(AC52)+LN(AD52))*(AH52-V7_BASE_CPR),0) | AL52: =IFERROR(LN(Z52)/(LN(W52)+LN(X52)+LN(Y52)+LN(Z52)+LN(AA52)+LN(AB52)+LN(AC52)+LN(AD52))*(AH52-V7_BASE_CPR),0) | AM52: =IFERROR(LN(AA52)/(LN(W52)+LN(X52)+LN(Y52)+LN(Z52)+LN(AA52)+LN(AB52)+LN(AC52)+LN(AD52))*(AH52-V7_BASE_CPR),0) | AN52: =IFERROR(LN(AB52)/(LN(W52)+LN(X52)+LN(Y52)+LN(Z52)+LN(AA52)+LN(AB52)+LN(AC52)+LN(AD52))*(AH52-V7_BASE_CPR),0) | AO52: =IFERROR(LN(AC52)/(LN(W52)+LN(X52)+LN(Y52)+LN(Z52)+LN(AA52)+LN(AB52)+LN(AC52)+LN(AD52))*(AH52-V7_BASE_CPR),0) | AP52: =IFERROR(LN(AD52)/(LN(W52)+LN(X52)+LN(Y52)+LN(Z52)+LN(AA52)+LN(AB52)+LN(AC52)+LN(AD52))*(AH52-V7_BASE_CPR),0) | AQ52: =V7_BASE_CPR+SUM(AI52:AP52)-AH52
... A63: 3617W0B92_000000003111141 | B63: BERKADIA_POST21 | C63: 3617W0B92 | D63: BERKADIA COMMERCIAL MORTGAGE, LLC | E63: 223f | F63: RP | G63: 2021 | H63: 202602 | I63: 23902483 | J63: 2.58 | K63: 447 | L63: 7 | M63: 58 | N63: 6 | O63: 205610 | Q63: 4082 | R63: 0.10344828 | S63: 0 | T63: =LN(1+I63) | U63: =J63*100-K63 | V63: =U63-12.5*(L63+1) | W63: =IF(M63<=V7_AGE_KNOT_X_0,V7_AGE_KNOT_Y_0,IF(M63>=V7_AGE_KNOT_X_5,V7_AGE_KNOT_Y_5,IF(M63<=V7_AGE_KNOT_X_1,V7_AGE_KNOT_Y_0+(M63-V7_AGE_KNOT_X_0)/(V7_AGE_KNOT_X_1-V7_AGE_KNOT_X_0)*(V7_AGE_KNOT_Y_1-V7_AGE_KNOT_Y_0),IF(M63<=V7_AGE_KNOT_X_2,V7_AGE_KNOT_Y_1+(M63-V7_AGE_KNOT_X_1)/(V7_AGE_KNOT_X_2-V7_AGE_KNOT_X_1)*(V7_AGE_KNOT_Y_2-V7_AGE_KNOT_Y_1),IF(M63<=V7_AGE_KNOT_X_3,V7_AGE_KNOT_Y_2+(M63-V7_AGE_KNOT_X_2)/(V7_AGE_KNOT_X_3-V7_AGE_KNOT_X_2)*(V7_AGE_KNOT_Y_3-V7_AGE_KNOT_Y_2),IF(M63<=V7_AGE_KNOT_X_4,V7_AGE_KNOT_Y_3+(M63-V7_AGE_KNOT_X_3)/(V7_AGE_KNOT_X_4-V7_AGE_KNOT_X_3)*(V7_AGE_KNOT_Y_4-V7_AGE_KNOT_Y_3),V7_AGE_KNOT_Y_4+(M63-V7_AGE_KNOT_X_4)/(V7_AGE_KNOT_X_5-V7_AGE_KNOT_X_4)*(V7_AGE_KNOT_Y_5-V7_AGE_KNOT_Y_4))))))) | X63: =V7_RATE_FLOOR+V7_RATE_ASYMPTOTE/(1+EXP(-(V63-V7_RATE_MID)/V7_RATE_SLOPE)) | Y63: =MAX(V7_SIZE_LOW,MIN(V7_SIZE_HIGH,V7_SIZE_INTERCEPT+V7_SIZE_SLOPE*(T63-V7_SIZE_LOG_ANCHOR))) | Z63: =IF(ISNUMBER(SEARCH("232",E63)),VLOOKUP("232",V7_PROGRAM_TABLE,2,FALSE),IF(ISNUMBER(SEARCH("538",E63)),VLOOKUP("538",V7_PROGRAM_TABLE,2,FALSE),IF(ISNUMBER(SEARCH("223a7",E63)),VLOOKUP("223a7",V7_PROGRAM_TABLE,2,FALSE),IF(ISNUMBER(SEARCH("223f",E63)),VLOOKUP("223f",V7_PROGRAM_TABLE,2,FALSE),V7_PROGRAM_DEFAULT)))) | AA63: =IF(S63=1,1+V7_PURPOSE_NC_BUMP*MAX(0,1-ABS(M63-V7_PURPOSE_PEAK_AGE)/V7_PURPOSE_WIDTH),1) | AB63: =IF(AND(IF(OR(P63="",NOT(ISNUMBER(P63))),0,MAX(0,MIN(24,(INT(VALUE(H63)/100)-INT(P63/100))*12+MOD(VALUE(H63),100)-MOD(P63,100))))>0,IF(OR(P63="",NOT(ISNUMBER(P63))),0,MAX(0,MIN(24,(INT(VALUE(H63)/100)-INT(P63/100))*12+MOD(VALUE(H63),100)-MOD(P63,100))))<=12),1+V7_LOCKOUT_AMP*EXP(-(IF(OR(P63="",NOT(ISNUMBER(P63))),0,MAX(0,MIN(24,(INT(VALUE(H63)/100)-INT(P63/100))*12+MOD(VALUE(H63),100)-MOD(P63,100)))))/V7_LOCKOUT_TAU),1) | AC63: =IF(IF(OR(O63="",NOT(ISNUMBER(O63))),360,MAX(0,MIN(480,(INT(O63/100)-INT(VALUE(H63)/100))*12+MOD(O63,100)-MOD(VALUE(H63),100))))>0,1+V7_MTY_AMP*MAX(0,(V7_MTY_CUTOFF-(IF(OR(O63="",NOT(ISNUMBER(O63))),360,MAX(0,MIN(480,(INT(O63/100)-INT(VALUE(H63)/100))*12+MOD(O63,100)-MOD(VALUE(H63),100))))))/V7_MTY_CUTOFF),1) | AD63: =MAX(V7_BURN_FLOOR,1-V7_BURN_SLOPE*MIN(1,MAX(0,R63))) | AE63: =IF(V7_USE_ISSUER=1,IFERROR(VLOOKUP(Q63,V7_ISSUER_TABLE,3,FALSE),1),1) | AF63: =PRODUCT(W63:AE63) | AG63: =MIN(V7_BASE_SMM*AF63,V7_SMM_CAP) | AH63: =1-(1-AG63)^12 | AI63: =IFERROR(LN(W63)/(LN(W63)+LN(X63)+LN(Y63)+LN(Z63)+LN(AA63)+LN(AB63)+LN(AC63)+LN(AD63))*(AH63-V7_BASE_CPR),0) | AJ63: =IFERROR(LN(X63)/(LN(W63)+LN(X63)+LN(Y63)+LN(Z63)+LN(AA63)+LN(AB63)+LN(AC63)+LN(AD63))*(AH63-V7_BASE_CPR),0) | AK63: =IFERROR(LN(Y63)/(LN(W63)+LN(X63)+LN(Y63)+LN(Z63)+LN(AA63)+LN(AB63)+LN(AC63)+LN(AD63))*(AH63-V7_BASE_CPR),0) | AL63: =IFERROR(LN(Z63)/(LN(W63)+LN(X63)+LN(Y63)+LN(Z63)+LN(AA63)+LN(AB63)+LN(AC63)+LN(AD63))*(AH63-V7_BASE_CPR),0) | AM63: =IFERROR(LN(AA63)/(LN(W63)+LN(X63)+LN(Y63)+LN(Z63)+LN(AA63)+LN(AB63)+LN(AC63)+LN(AD63))*(AH63-V7_BASE_CPR),0) | AN63: =IFERROR(LN(AB63)/(LN(W63)+LN(X63)+LN(Y63)+LN(Z63)+LN(AA63)+LN(AB63)+LN(AC63)+LN(AD63))*(AH63-V7_BASE_CPR),0) | AO63: =IFERROR(LN(AC63)/(LN(W63)+LN(X63)+LN(Y63)+LN(Z63)+LN(AA63)+LN(AB63)+LN(AC63)+LN(AD63))*(AH63-V7_BASE_CPR),0) | AP63: =IFERROR(LN(AD63)/(LN(W63)+LN(X63)+LN(Y63)+LN(Z63)+LN(AA63)+LN(AB63)+LN(AC63)+LN(AD63))*(AH63-V7_BASE_CPR),0) | AQ63: =V7_BASE_CPR+SUM(AI63:AP63)-AH63
A64: 36296MNL8_000000001410045 | B64: BERKADIA_PRE21 | C64: 36296MNL8 | D64: BERKADIA COMMERCIAL MORTGAGE, LLC | E64: 241 | F64: NC | G64: 2009 | H64: 202602 | I64: 662700.64 | J64: 6.2 | K64: 447 | L64: 0 | M64: 197 | N64: 86 | O64: 203811 | P64: 201205 | Q64: 4082 | R64: 0.43654822 | S64: 1 | T64: =LN(1+I64) | U64: =J64*100-K64 | V64: =U64-12.5*(L64+1) | W64: =IF(M64<=V7_AGE_KNOT_X_0,V7_AGE_KNOT_Y_0,IF(M64>=V7_AGE_KNOT_X_5,V7_AGE_KNOT_Y_5,IF(M64<=V7_AGE_KNOT_X_1,V7_AGE_KNOT_Y_0+(M64-V7_AGE_KNOT_X_0)/(V7_AGE_KNOT_X_1-V7_AGE_KNOT_X_0)*(V7_AGE_KNOT_Y_1-V7_AGE_KNOT_Y_0),IF(M64<=V7_AGE_KNOT_X_2,V7_AGE_KNOT_Y_1+(M64-V7_AGE_KNOT_X_1)/(V7_AGE_KNOT_X_2-V7_AGE_KNOT_X_1)*(V7_AGE_KNOT_Y_2-V7_AGE_KNOT_Y_1),IF(M64<=V7_AGE_KNOT_X_3,V7_AGE_KNOT_Y_2+(M64-V7_AGE_KNOT_X_2)/(V7_AGE_KNOT_X_3-V7_AGE_KNOT_X_2)*(V7_AGE_KNOT_Y_3-V7_AGE_KNOT_Y_2),IF(M64<=V7_AGE_KNOT_X_4,V7_AGE_KNOT_Y_3+(M64-V7_AGE_KNOT_X_3)/(V7_AGE_KNOT_X_4-V7_AGE_KNOT_X_3)*(V7_AGE_KNOT_Y_4-V7_AGE_KNOT_Y_3),V7_AGE_KNOT_Y_4+(M64-V7_AGE_KNOT_X_4)/(V7_AGE_KNOT_X_5-V7_AGE_KNOT_X_4)*(V7_AGE_KNOT_Y_5-V7_AGE_KNOT_Y_4))))))) | X64: =V7_RATE_FLOOR+V7_RATE_ASYMPTOTE/(1+EXP(-(V64-V7_RATE_MID)/V7_RATE_SLOPE)) | Y64: =MAX(V7_SIZE_LOW,MIN(V7_SIZE_HIGH,V7_SIZE_INTERCEPT+V7_SIZE_SLOPE*(T64-V7_SIZE_LOG_ANCHOR))) | Z64: =IF(ISNUMBER(SEARCH("232",E64)),VLOOKUP("232",V7_PROGRAM_TABLE,2,FALSE),IF(ISNUMBER(SEARCH("538",E64)),VLOOKUP("538",V7_PROGRAM_TABLE,2,FALSE),IF(ISNUMBER(SEARCH("223a7",E64)),VLOOKUP("223a7",V7_PROGRAM_TABLE,2,FALSE),IF(ISNUMBER(SEARCH("223f",E64)),VLOOKUP("223f",V7_PROGRAM_TABLE,2,FALSE),V7_PROGRAM_DEFAULT)))) | AA64: =IF(S64=1,1+V7_PURPOSE_NC_BUMP*MAX(0,1-ABS(M64-V7_PURPOSE_PEAK_AGE)/V7_PURPOSE_WIDTH),1) | AB64: =IF(AND(IF(OR(P64="",NOT(ISNUMBER(P64))),0,MAX(0,MIN(24,(INT(VALUE(H64)/100)-INT(P64/100))*12+MOD(VALUE(H64),100)-MOD(P64,100))))>0,IF(OR(P64="",NOT(ISNUMBER(P64))),0,MAX(0,MIN(24,(INT(VALUE(H64)/100)-INT(P64/100))*12+MOD(VALUE(H64),100)-MOD(P64,100))))<=12),1+V7_LOCKOUT_AMP*EXP(-(IF(OR(P64="",NOT(ISNUMBER(P64))),0,MAX(0,MIN(24,(INT(VALUE(H64)/100)-INT(P64/100))*12+MOD(VALUE(H64),100)-MOD(P64,100)))))/V7_LOCKOUT_TAU),1) | AC64: =IF(IF(OR(O64="",NOT(ISNUMBER(O64))),360,MAX(0,MIN(480,(INT(O64/100)-INT(VALUE(H64)/100))*12+MOD(O64,100)-MOD(VALUE(H64),100))))>0,1+V7_MTY_AMP*MAX(0,(V7_MTY_CUTOFF-(IF(OR(O64="",NOT(ISNUMBER(O64))),360,MAX(0,MIN(480,(INT(O64/100)-INT(VALUE(H64)/100))*12+MOD(O64,100)-MOD(VALUE(H64),100))))))/V7_MTY_CUTOFF),1) | AD64: =MAX(V7_BURN_FLOOR,1-V7_BURN_SLOPE*MIN(1,MAX(0,R64))) | AE64: =IF(V7_USE_ISSUER=1,IFERROR(VLOOKUP(Q64,V7_ISSUER_TABLE,3,FALSE),1),1) | AF64: =PRODUCT(W64:AE64) | AG64: =MIN(V7_BASE_SMM*AF64,V7_SMM_CAP) | AH64: =1-(1-AG64)^12 | AI64: =IFERROR(LN(W64)/(LN(W64)+LN(X64)+LN(Y64)+LN(Z64)+LN(AA64)+LN(AB64)+LN(AC64)+LN(AD64))*(AH64-V7_BASE_CPR),0) | AJ64: =IFERROR(LN(X64)/(LN(W64)+LN(X64)+LN(Y64)+LN(Z64)+LN(AA64)+LN(AB64)+LN(AC64)+LN(AD64))*(AH64-V7_BASE_CPR),0) | AK64: =IFERROR(LN(Y64)/(LN(W64)+LN(X64)+LN(Y64)+LN(Z64)+LN(AA64)+LN(AB64)+LN(AC64)+LN(AD64))*(AH64-V7_BASE_CPR),0) | AL64: =IFERROR(LN(Z64)/(LN(W64)+LN(X64)+LN(Y64)+LN(Z64)+LN(AA64)+LN(AB64)+LN(AC64)+LN(AD64))*(AH64-V7_BASE_CPR),0) | AM64: =IFERROR(LN(AA64)/(LN(W64)+LN(X64)+LN(Y64)+LN(Z64)+LN(AA64)+LN(AB64)+LN(AC64)+LN(AD64))*(AH64-V7_BASE_CPR),0) | AN64: =IFERROR(LN(AB64)/(LN(W64)+LN(X64)+LN(Y64)+LN(Z64)+LN(AA64)+LN(AB64)+LN(AC64)+LN(AD64))*(AH64-V7_BASE_CPR),0) | AO64: =IFERROR(LN(AC64)/(LN(W64)+LN(X64)+LN(Y64)+LN(Z64)+LN(AA64)+LN(AB64)+LN(AC64)+LN(AD64))*(AH64-V7_BASE_CPR),0) | AP64: =IFERROR(LN(AD64)/(LN(W64)+LN(X64)+LN(Y64)+LN(Z64)+LN(AA64)+LN(AB64)+LN(AC64)+LN(AD64))*(AH64-V7_BASE_CPR),0) | AQ64: =V7_BASE_CPR+SUM(AI64:AP64)-AH64
A65: 3618A9ZB4_000000009335146 | B65: BERKADIA_POST21 | C65: 3618A9ZB4 | D65: BERKADIA COMMERCIAL MORTGAGE, LLC | E65: 221d4 | F65: NC | G65: 2022 | H65: 202602 | I65: 9907257.3 | J65: 4.6 | K65: 447 | L65: 10 | M65: 41 | N65: 0 | O65: 206404 | Q65: 4082 | R65: 0 | S65: 1 | T65: =LN(1+I65) | U65: =J65*100-K65 | V65: =U65-12.5*(L65+1) | W65: =IF(M65<=V7_AGE_KNOT_X_0,V7_AGE_KNOT_Y_0,IF(M65>=V7_AGE_KNOT_X_5,V7_AGE_KNOT_Y_5,IF(M65<=V7_AGE_KNOT_X_1,V7_AGE_KNOT_Y_0+(M65-V7_AGE_KNOT_X_0)/(V7_AGE_KNOT_X_1-V7_AGE_KNOT_X_0)*(V7_AGE_KNOT_Y_1-V7_AGE_KNOT_Y_0),IF(M65<=V7_AGE_KNOT_X_2,V7_AGE_KNOT_Y_1+(M65-V7_AGE_KNOT_X_1)/(V7_AGE_KNOT_X_2-V7_AGE_KNOT_X_1)*(V7_AGE_KNOT_Y_2-V7_AGE_KNOT_Y_1),IF(M65<=V7_AGE_KNOT_X_3,V7_AGE_KNOT_Y_2+(M65-V7_AGE_KNOT_X_2)/(V7_AGE_KNOT_X_3-V7_AGE_KNOT_X_2)*(V7_AGE_KNOT_Y_3-V7_AGE_KNOT_Y_2),IF(M65<=V7_AGE_KNOT_X_4,V7_AGE_KNOT_Y_3+(M65-V7_AGE_KNOT_X_3)/(V7_AGE_KNOT_X_4-V7_AGE_KNOT_X_3)*(V7_AGE_KNOT_Y_4-V7_AGE_KNOT_Y_3),V7_AGE_KNOT_Y_4+(M65-V7_AGE_KNOT_X_4)/(V7_AGE_KNOT_X_5-V7_AGE_KNOT_X_4)*(V7_AGE_KNOT_Y_5-V7_AGE_KNOT_Y_4))))))) | X65: =V7_RATE_FLOOR+V7_RATE_ASYMPTOTE/(1+EXP(-(V65-V7_RATE_MID)/V7_RATE_SLOPE)) | Y65: =MAX(V7_SIZE_LOW,MIN(V7_SIZE_HIGH,V7_SIZE_INTERCEPT+V7_SIZE_SLOPE*(T65-V7_SIZE_LOG_ANCHOR))) | Z65: =IF(ISNUMBER(SEARCH("232",E65)),VLOOKUP("232",V7_PROGRAM_TABLE,2,FALSE),IF(ISNUMBER(SEARCH("538",E65)),VLOOKUP("538",V7_PROGRAM_TABLE,2,FALSE),IF(ISNUMBER(SEARCH("223a7",E65)),VLOOKUP("223a7",V7_PROGRAM_TABLE,2,FALSE),IF(ISNUMBER(SEARCH("223f",E65)),VLOOKUP("223f",V7_PROGRAM_TABLE,2,FALSE),V7_PROGRAM_DEFAULT)))) | AA65: =IF(S65=1,1+V7_PURPOSE_NC_BUMP*MAX(0,1-ABS(M65-V7_PURPOSE_PEAK_AGE)/V7_PURPOSE_WIDTH),1) | AB65: =IF(AND(IF(OR(P65="",NOT(ISNUMBER(P65))),0,MAX(0,MIN(24,(INT(VALUE(H65)/100)-INT(P65/100))*12+MOD(VALUE(H65),100)-MOD(P65,100))))>0,IF(OR(P65="",NOT(ISNUMBER(P65))),0,MAX(0,MIN(24,(INT(VALUE(H65)/100)-INT(P65/100))*12+MOD(VALUE(H65),100)-MOD(P65,100))))<=12),1+V7_LOCKOUT_AMP*EXP(-(IF(OR(P65="",NOT(ISNUMBER(P65))),0,MAX(0,MIN(24,(INT(VALUE(H65)/100)-INT(P65/100))*12+MOD(VALUE(H65),100)-MOD(P65,100)))))/V7_LOCKOUT_TAU),1) | AC65: =IF(IF(OR(O65="",NOT(ISNUMBER(O65))),360,MAX(0,MIN(480,(INT(O65/100)-INT(VALUE(H65)/100))*12+MOD(O65,100)-MOD(VALUE(H65),100))))>0,1+V7_MTY_AMP*MAX(0,(V7_MTY_CUTOFF-(IF(OR(O65="",NOT(ISNUMBER(O65))),360,MAX(0,MIN(480,(INT(O65/100)-INT(VALUE(H65)/100))*12+MOD(O65,100)-MOD(VALUE(H65),100))))))/V7_MTY_CUTOFF),1) | AD65: =MAX(V7_BURN_FLOOR,1-V7_BURN_SLOPE*MIN(1,MAX(0,R65))) | AE65: =IF(V7_USE_ISSUER=1,IFERROR(VLOOKUP(Q65,V7_ISSUER_TABLE,3,FALSE),1),1) | AF65: =PRODUCT(W65:AE65) | AG65: =MIN(V7_BASE_SMM*AF65,V7_SMM_CAP) | AH65: =1-(1-AG65)^12 | AI65: =IFERROR(LN(W65)/(LN(W65)+LN(X65)+LN(Y65)+LN(Z65)+LN(AA65)+LN(AB65)+LN(AC65)+LN(AD65))*(AH65-V7_BASE_CPR),0) | AJ65: =IFERROR(LN(X65)/(LN(W65)+LN(X65)+LN(Y65)+LN(Z65)+LN(AA65)+LN(AB65)+LN(AC65)+LN(AD65))*(AH65-V7_BASE_CPR),0) | AK65: =IFERROR(LN(Y65)/(LN(W65)+LN(X65)+LN(Y65)+LN(Z65)+LN(AA65)+LN(AB65)+LN(AC65)+LN(AD65))*(AH65-V7_BASE_CPR),0) | AL65: =IFERROR(LN(Z65)/(LN(W65)+LN(X65)+LN(Y65)+LN(Z65)+LN(AA65)+LN(AB65)+LN(AC65)+LN(AD65))*(AH65-V7_BASE_CPR),0) | AM65: =IFERROR(LN(AA65)/(LN(W65)+LN(X65)+LN(Y65)+LN(Z65)+LN(AA65)+LN(AB65)+LN(AC65)+LN(AD65))*(AH65-V7_BASE_CPR),0) | AN65: =IFERROR(LN(AB65)/(LN(W65)+LN(X65)+LN(Y65)+LN(Z65)+LN(AA65)+LN(AB65)+LN(AC65)+LN(AD65))*(AH65-V7_BASE_CPR),0) | AO65: =IFERROR(LN(AC65)/(LN(W65)+LN(X65)+LN(Y65)+LN(Z65)+LN(AA65)+LN(AB65)+LN(AC65)+LN(AD65))*(AH65-V7_BASE_CPR),0) | AP65: =IFERROR(LN(AD65)/(LN(W65)+LN(X65)+LN(Y65)+LN(Z65)+LN(AA65)+LN(AB65)+LN(AC65)+LN(AD65))*(AH65-V7_BASE_CPR),0) | AQ65: =V7_BASE_CPR+SUM(AI65:AP65)-AH65
A66: 36178VAE1_000000005111250 | B66: BERKADIA_PRE21 | C66: 36178VAE1 | D66: BERKADIA COMMERCIAL MORTGAGE, LLC | E66: 223a7 | F66: RP | G66: 2012 | H66: 202602 | I66: 17841211 | J66: 3.05 | K66: 447 | L66: 0 | M66: 160 | N66: 26 | O66: 204801 | P66: 201402 | Q66: 4082 | R66: 0.1625 | S66: 0 | T66: =LN(1+I66) | U66: =J66*100-K66 | V66: =U66-12.5*(L66+1) | W66: =IF(M66<=V7_AGE_KNOT_X_0,V7_AGE_KNOT_Y_0,IF(M66>=V7_AGE_KNOT_X_5,V7_AGE_KNOT_Y_5,IF(M66<=V7_AGE_KNOT_X_1,V7_AGE_KNOT_Y_0+(M66-V7_AGE_KNOT_X_0)/(V7_AGE_KNOT_X_1-V7_AGE_KNOT_X_0)*(V7_AGE_KNOT_Y_1-V7_AGE_KNOT_Y_0),IF(M66<=V7_AGE_KNOT_X_2,V7_AGE_KNOT_Y_1+(M66-V7_AGE_KNOT_X_1)/(V7_AGE_KNOT_X_2-V7_AGE_KNOT_X_1)*(V7_AGE_KNOT_Y_2-V7_AGE_KNOT_Y_1),IF(M66<=V7_AGE_KNOT_X_3,V7_AGE_KNOT_Y_2+(M66-V7_AGE_KNOT_X_2)/(V7_AGE_KNOT_X_3-V7_AGE_KNOT_X_2)*(V7_AGE_KNOT_Y_3-V7_AGE_KNOT_Y_2),IF(M66<=V7_AGE_KNOT_X_4,V7_AGE_KNOT_Y_3+(M66-V7_AGE_KNOT_X_3)/(V7_AGE_KNOT_X_4-V7_AGE_KNOT_X_3)*(V7_AGE_KNOT_Y_4-V7_AGE_KNOT_Y_3),V7_AGE_KNOT_Y_4+(M66-V7_AGE_KNOT_X_4)/(V7_AGE_KNOT_X_5-V7_AGE_KNOT_X_4)*(V7_AGE_KNOT_Y_5-V7_AGE_KNOT_Y_4))))))) | X66: =V7_RATE_FLOOR+V7_RATE_ASYMPTOTE/(1+EXP(-(V66-V7_RATE_MID)/V7_RATE_SLOPE)) | Y66: =MAX(V7_SIZE_LOW,MIN(V7_SIZE_HIGH,V7_SIZE_INTERCEPT+V7_SIZE_SLOPE*(T66-V7_SIZE_LOG_ANCHOR))) | Z66: =IF(ISNUMBER(SEARCH("232",E66)),VLOOKUP("232",V7_PROGRAM_TABLE,2,FALSE),IF(ISNUMBER(SEARCH("538",E66)),VLOOKUP("538",V7_PROGRAM_TABLE,2,FALSE),IF(ISNUMBER(SEARCH("223a7",E66)),VLOOKUP("223a7",V7_PROGRAM_TABLE,2,FALSE),IF(ISNUMBER(SEARCH("223f",E66)),VLOOKUP("223f",V7_PROGRAM_TABLE,2,FALSE),V7_PROGRAM_DEFAULT)))) | AA66: =IF(S66=1,1+V7_PURPOSE_NC_BUMP*MAX(0,1-ABS(M66-V7_PURPOSE_PEAK_AGE)/V7_PURPOSE_WIDTH),1) | AB66: =IF(AND(IF(OR(P66="",NOT(ISNUMBER(P66))),0,MAX(0,MIN(24,(INT(VALUE(H66)/100)-INT(P66/100))*12+MOD(VALUE(H66),100)-MOD(P66,100))))>0,IF(OR(P66="",NOT(ISNUMBER(P66))),0,MAX(0,MIN(24,(INT(VALUE(H66)/100)-INT(P66/100))*12+MOD(VALUE(H66),100)-MOD(P66,100))))<=12),1+V7_LOCKOUT_AMP*EXP(-(IF(OR(P66="",NOT(ISNUMBER(P66))),0,MAX(0,MIN(24,(INT(VALUE(H66)/100)-INT(P66/100))*12+MOD(VALUE(H66),100)-MOD(P66,100)))))/V7_LOCKOUT_TAU),1) | AC66: =IF(IF(OR(O66="",NOT(ISNUMBER(O66))),360,MAX(0,MIN(480,(INT(O66/100)-INT(VALUE(H66)/100))*12+MOD(O66,100)-MOD(VALUE(H66),100))))>0,1+V7_MTY_AMP*MAX(0,(V7_MTY_CUTOFF-(IF(OR(O66="",NOT(ISNUMBER(O66))),360,MAX(0,MIN(480,(INT(O66/100)-INT(VALUE(H66)/100))*12+MOD(O66,100)-MOD(VALUE(H66),100))))))/V7_MTY_CUTOFF),1) | AD66: =MAX(V7_BURN_FLOOR,1-V7_BURN_SLOPE*MIN(1,MAX(0,R66))) | AE66: =IF(V7_USE_ISSUER=1,IFERROR(VLOOKUP(Q66,V7_ISSUER_TABLE,3,FALSE),1),1) | AF66: =PRODUCT(W66:AE66) | AG66: =MIN(V7_BASE_SMM*AF66,V7_SMM_CAP) | AH66: =1-(1-AG66)^12 | AI66: =IFERROR(LN(W66)/(LN(W66)+LN(X66)+LN(Y66)+LN(Z66)+LN(AA66)+LN(AB66)+LN(AC66)+LN(AD66))*(AH66-V7_BASE_CPR),0) | AJ66: =IFERROR(LN(X66)/(LN(W66)+LN(X66)+LN(Y66)+LN(Z66)+LN(AA66)+LN(AB66)+LN(AC66)+LN(AD66))*(AH66-V7_BASE_CPR),0) | AK66: =IFERROR(LN(Y66)/(LN(W66)+LN(X66)+LN(Y66)+LN(Z66)+LN(AA66)+LN(AB66)+LN(AC66)+LN(AD66))*(AH66-V7_BASE_CPR),0) | AL66: =IFERROR(LN(Z66)/(LN(W66)+LN(X66)+LN(Y66)+LN(Z66)+LN(AA66)+LN(AB66)+LN(AC66)+LN(AD66))*(AH66-V7_BASE_CPR),0) | AM66: =IFERROR(LN(AA66)/(LN(W66)+LN(X66)+LN(Y66)+LN(Z66)+LN(AA66)+LN(AB66)+LN(AC66)+LN(AD66))*(AH66-V7_BASE_CPR),0) | AN66: =IFERROR(LN(AB66)/(LN(W66)+LN(X66)+LN(Y66)+LN(Z66)+LN(AA66)+LN(AB66)+LN(AC66)+LN(AD66))*(AH66-V7_BASE_CPR),0) | AO66: =IFERROR(LN(AC66)/(LN(W66)+LN(X66)+LN(Y66)+LN(Z66)+LN(AA66)+LN(AB66)+LN(AC66)+LN(AD66))*(AH66-V7_BASE_CPR),0) | AP66: =IFERROR(LN(AD66)/(LN(W66)+LN(X66)+LN(Y66)+LN(Z66)+LN(AA66)+LN(AB66)+LN(AC66)+LN(AD66))*(AH66-V7_BASE_CPR),0) | AQ66: =V7_BASE_CPR+SUM(AI66:AP66)-AH66
A67: 3617M16P1_000000011422098 | B67: BERKADIA_PRE21 | C67: 3617M16P1 | D67: BERKADIA COMMERCIAL MORTGAGE, LLC | E67: 232 | F67: RP | G67: 2020 | H67: 202602 | I67: 6103063.3 | J67: 2.63 | K67: 447 | L67: 6 | M67: 71 | N67: 13 | O67: 205506 | Q67: 4082 | R67: 0.18309859 | S67: 0 | T67: =LN(1+I67) | U67: =J67*100-K67 | V67: =U67-12.5*(L67+1) | W67: =IF(M67<=V7_AGE_KNOT_X_0,V7_AGE_KNOT_Y_0,IF(M67>=V7_AGE_KNOT_X_5,V7_AGE_KNOT_Y_5,IF(M67<=V7_AGE_KNOT_X_1,V7_AGE_KNOT_Y_0+(M67-V7_AGE_KNOT_X_0)/(V7_AGE_KNOT_X_1-V7_AGE_KNOT_X_0)*(V7_AGE_KNOT_Y_1-V7_AGE_KNOT_Y_0),IF(M67<=V7_AGE_KNOT_X_2,V7_AGE_KNOT_Y_1+(M67-V7_AGE_KNOT_X_1)/(V7_AGE_KNOT_X_2-V7_AGE_KNOT_X_1)*(V7_AGE_KNOT_Y_2-V7_AGE_KNOT_Y_1),IF(M67<=V7_AGE_KNOT_X_3,V7_AGE_KNOT_Y_2+(M67-V7_AGE_KNOT_X_2)/(V7_AGE_KNOT_X_3-V7_AGE_KNOT_X_2)*(V7_AGE_KNOT_Y_3-V7_AGE_KNOT_Y_2),IF(M67<=V7_AGE_KNOT_X_4,V7_AGE_KNOT_Y_3+(M67-V7_AGE_KNOT_X_3)/(V7_AGE_KNOT_X_4-V7_AGE_KNOT_X_3)*(V7_AGE_KNOT_Y_4-V7_AGE_KNOT_Y_3),V7_AGE_KNOT_Y_4+(M67-V7_AGE_KNOT_X_4)/(V7_AGE_KNOT_X_5-V7_AGE_KNOT_X_4)*(V7_AGE_KNOT_Y_5-V7_AGE_KNOT_Y_4))))))) | X67: =V7_RATE_FLOOR+V7_RATE_ASYMPTOTE/(1+EXP(-(V67-V7_RATE_MID)/V7_RATE_SLOPE)) | Y67: =MAX(V7_SIZE_LOW,MIN(V7_SIZE_HIGH,V7_SIZE_INTERCEPT+V7_SIZE_SLOPE*(T67-V7_SIZE_LOG_ANCHOR))) | Z67: =IF(ISNUMBER(SEARCH("232",E67)),VLOOKUP("232",V7_PROGRAM_TABLE,2,FALSE),IF(ISNUMBER(SEARCH("538",E67)),VLOOKUP("538",V7_PROGRAM_TABLE,2,FALSE),IF(ISNUMBER(SEARCH("223a7",E67)),VLOOKUP("223a7",V7_PROGRAM_TABLE,2,FALSE),IF(ISNUMBER(SEARCH("223f",E67)),VLOOKUP("223f",V7_PROGRAM_TABLE,2,FALSE),V7_PROGRAM_DEFAULT)))) | AA67: =IF(S67=1,1+V7_PURPOSE_NC_BUMP*MAX(0,1-ABS(M67-V7_PURPOSE_PEAK_AGE)/V7_PURPOSE_WIDTH),1) | AB67: =IF(AND(IF(OR(P67="",NOT(ISNUMBER(P67))),0,MAX(0,MIN(24,(INT(VALUE(H67)/100)-INT(P67/100))*12+MOD(VALUE(H67),100)-MOD(P67,100))))>0,IF(OR(P67="",NOT(ISNUMBER(P67))),0,MAX(0,MIN(24,(INT(VALUE(H67)/100)-INT(P67/100))*12+MOD(VALUE(H67),100)-MOD(P67,100))))<=12),1+V7_LOCKOUT_AMP*EXP(-(IF(OR(P67="",NOT(ISNUMBER(P67))),0,MAX(0,MIN(24,(INT(VALUE(H67)/100)-INT(P67/100))*12+MOD(VALUE(H67),100)-MOD(P67,100)))))/V7_LOCKOUT_TAU),1) | AC67: =IF(IF(OR(O67="",NOT(ISNUMBER(O67))),360,MAX(0,MIN(480,(INT(O67/100)-INT(VALUE(H67)/100))*12+MOD(O67,100)-MOD(VALUE(H67),100))))>0,1+V7_MTY_AMP*MAX(0,(V7_MTY_CUTOFF-(IF(OR(O67="",NOT(ISNUMBER(O67))),360,MAX(0,MIN(480,(INT(O67/100)-INT(VALUE(H67)/100))*12+MOD(O67,100)-MOD(VALUE(H67),100))))))/V7_MTY_CUTOFF),1) | AD67: =MAX(V7_BURN_FLOOR,1-V7_BURN_SLOPE*MIN(1,MAX(0,R67))) | AE67: =IF(V7_USE_ISSUER=1,IFERROR(VLOOKUP(Q67,V7_ISSUER_TABLE,3,FALSE),1),1) | AF67: =PRODUCT(W67:AE67) | AG67: =MIN(V7_BASE_SMM*AF67,V7_SMM_CAP) | AH67: =1-(1-AG67)^12 | AI67: =IFERROR(LN(W67)/(LN(W67)+LN(X67)+LN(Y67)+LN(Z67)+LN(AA67)+LN(AB67)+LN(AC67)+LN(AD67))*(AH67-V7_BASE_CPR),0) | AJ67: =IFERROR(LN(X67)/(LN(W67)+LN(X67)+LN(Y67)+LN(Z67)+LN(AA67)+LN(AB67)+LN(AC67)+LN(AD67))*(AH67-V7_BASE_CPR),0) | AK67: =IFERROR(LN(Y67)/(LN(W67)+LN(X67)+LN(Y67)+LN(Z67)+LN(AA67)+LN(AB67)+LN(AC67)+LN(AD67))*(AH67-V7_BASE_CPR),0) | AL67: =IFERROR(LN(Z67)/(LN(W67)+LN(X67)+LN(Y67)+LN(Z67)+LN(AA67)+LN(AB67)+LN(AC67)+LN(AD67))*(AH67-V7_BASE_CPR),0) | AM67: =IFERROR(LN(AA67)/(LN(W67)+LN(X67)+LN(Y67)+LN(Z67)+LN(AA67)+LN(AB67)+LN(AC67)+LN(AD67))*(AH67-V7_BASE_CPR),0) | AN67: =IFERROR(LN(AB67)/(LN(W67)+LN(X67)+LN(Y67)+LN(Z67)+LN(AA67)+LN(AB67)+LN(AC67)+LN(AD67))*(AH67-V7_BASE_CPR),0) | AO67: =IFERROR(LN(AC67)/(LN(W67)+LN(X67)+LN(Y67)+LN(Z67)+LN(AA67)+LN(AB67)+LN(AC67)+LN(AD67))*(AH67-V7_BASE_CPR),0) | AP67: =IFERROR(LN(AD67)/(LN(W67)+LN(X67)+LN(Y67)+LN(Z67)+LN(AA67)+LN(AB67)+LN(AC67)+LN(AD67))*(AH67-V7_BASE_CPR),0) | AQ67: =V7_BASE_CPR+SUM(AI67:AP67)-AH67
A68: 36194RP61_000000007111200 | B68: WALKER_PRE21 | C68: 36194RP61 | D68: WALKER & DUNLOP, LLC | E68: 223f | F68: RP | G68: 2010 | H68: 202602 | I68: 3987517.4 | J68: 3.65 | K68: 447 | L68: 1 | M68: 188 | N68: 29 | O68: 204507 | Q68: 4080 | R68: 0.15425532 | S68: 0 | T68: =LN(1+I68) | U68: =J68*100-K68 | V68: =U68-12.5*(L68+1) | W68: =IF(M68<=V7_AGE_KNOT_X_0,V7_AGE_KNOT_Y_0,IF(M68>=V7_AGE_KNOT_X_5,V7_AGE_KNOT_Y_5,IF(M68<=V7_AGE_KNOT_X_1,V7_AGE_KNOT_Y_0+(M68-V7_AGE_KNOT_X_0)/(V7_AGE_KNOT_X_1-V7_AGE_KNOT_X_0)*(V7_AGE_KNOT_Y_1-V7_AGE_KNOT_Y_0),IF(M68<=V7_AGE_KNOT_X_2,V7_AGE_KNOT_Y_1+(M68-V7_AGE_KNOT_X_1)/(V7_AGE_KNOT_X_2-V7_AGE_KNOT_X_1)*(V7_AGE_KNOT_Y_2-V7_AGE_KNOT_Y_1),IF(M68<=V7_AGE_KNOT_X_3,V7_AGE_KNOT_Y_2+(M68-V7_AGE_KNOT_X_2)/(V7_AGE_KNOT_X_3-V7_AGE_KNOT_X_2)*(V7_AGE_KNOT_Y_3-V7_AGE_KNOT_Y_2),IF(M68<=V7_AGE_KNOT_X_4,V7_AGE_KNOT_Y_3+(M68-V7_AGE_KNOT_X_3)/(V7_AGE_KNOT_X_4-V7_AGE_KNOT_X_3)*(V7_AGE_KNOT_Y_4-V7_AGE_KNOT_Y_3),V7_AGE_KNOT_Y_4+(M68-V7_AGE_KNOT_X_4)/(V7_AGE_KNOT_X_5-V7_AGE_KNOT_X_4)*(V7_AGE_KNOT_Y_5-V7_AGE_KNOT_Y_4))))))) | X68: =V7_RATE_FLOOR+V7_RATE_ASYMPTOTE/(1+EXP(-(V68-V7_RATE_MID)/V7_RATE_SLOPE)) | Y68: =MAX(V7_SIZE_LOW,MIN(V7_SIZE_HIGH,V7_SIZE_INTERCEPT+V7_SIZE_SLOPE*(T68-V7_SIZE_LOG_ANCHOR))) | Z68: =IF(ISNUMBER(SEARCH("232",E68)),VLOOKUP("232",V7_PROGRAM_TABLE,2,FALSE),IF(ISNUMBER(SEARCH("538",E68)),VLOOKUP("538",V7_PROGRAM_TABLE,2,FALSE),IF(ISNUMBER(SEARCH("223a7",E68)),VLOOKUP("223a7",V7_PROGRAM_TABLE,2,FALSE),IF(ISNUMBER(SEARCH("223f",E68)),VLOOKUP("223f",V7_PROGRAM_TABLE,2,FALSE),V7_PROGRAM_DEFAULT)))) | AA68: =IF(S68=1,1+V7_PURPOSE_NC_BUMP*MAX(0,1-ABS(M68-V7_PURPOSE_PEAK_AGE)/V7_PURPOSE_WIDTH),1) | AB68: =IF(AND(IF(OR(P68="",NOT(ISNUMBER(P68))),0,MAX(0,MIN(24,(INT(VALUE(H68)/100)-INT(P68/100))*12+MOD(VALUE(H68),100)-MOD(P68,100))))>0,IF(OR(P68="",NOT(ISNUMBER(P68))),0,MAX(0,MIN(24,(INT(VALUE(H68)/100)-INT(P68/100))*12+MOD(VALUE(H68),100)-MOD(P68,100))))<=12),1+V7_LOCKOUT_AMP*EXP(-(IF(OR(P68="",NOT(ISNUMBER(P68))),0,MAX(0,MIN(24,(INT(VALUE(H68)/100)-INT(P68/100))*12+MOD(VALUE(H68),100)-MOD(P68,100)))))/V7_LOCKOUT_TAU),1) | AC68: =IF(IF(OR(O68="",NOT(ISNUMBER(O68))),360,MAX(0,MIN(480,(INT(O68/100)-INT(VALUE(H68)/100))*12+MOD(O68,100)-MOD(VALUE(H68),100))))>0,1+V7_MTY_AMP*MAX(0,(V7_MTY_CUTOFF-(IF(OR(O68="",NOT(ISNUMBER(O68))),360,MAX(0,MIN(480,(INT(O68/100)-INT(VALUE(H68)/100))*12+MOD(O68,100)-MOD(VALUE(H68),100))))))/V7_MTY_CUTOFF),1) | AD68: =MAX(V7_BURN_FLOOR,1-V7_BURN_SLOPE*MIN(1,MAX(0,R68))) | AE68: =IF(V7_USE_ISSUER=1,IFERROR(VLOOKUP(Q68,V7_ISSUER_TABLE,3,FALSE),1),1) | AF68: =PRODUCT(W68:AE68) | AG68: =MIN(V7_BASE_SMM*AF68,V7_SMM_CAP) | AH68: =1-(1-AG68)^12 | AI68: =IFERROR(LN(W68)/(LN(W68)+LN(X68)+LN(Y68)+LN(Z68)+LN(AA68)+LN(AB68)+LN(AC68)+LN(AD68))*(AH68-V7_BASE_CPR),0) | AJ68: =IFERROR(LN(X68)/(LN(W68)+LN(X68)+LN(Y68)+LN(Z68)+LN(AA68)+LN(AB68)+LN(AC68)+LN(AD68))*(AH68-V7_BASE_CPR),0) | AK68: =IFERROR(LN(Y68)/(LN(W68)+LN(X68)+LN(Y68)+LN(Z68)+LN(AA68)+LN(AB68)+LN(AC68)+LN(AD68))*(AH68-V7_BASE_CPR),0) | AL68: =IFERROR(LN(Z68)/(LN(W68)+LN(X68)+LN(Y68)+LN(Z68)+LN(AA68)+LN(AB68)+LN(AC68)+LN(AD68))*(AH68-V7_BASE_CPR),0) | AM68: =IFERROR(LN(AA68)/(LN(W68)+LN(X68)+LN(Y68)+LN(Z68)+LN(AA68)+LN(AB68)+LN(AC68)+LN(AD68))*(AH68-V7_BASE_CPR),0) | AN68: =IFERROR(LN(AB68)/(LN(W68)+LN(X68)+LN(Y68)+LN(Z68)+LN(AA68)+LN(AB68)+LN(AC68)+LN(AD68))*(AH68-V7_BASE_CPR),0) | AO68: =IFERROR(LN(AC68)/(LN(W68)+LN(X68)+LN(Y68)+LN(Z68)+LN(AA68)+LN(AB68)+LN(AC68)+LN(AD68))*(AH68-V7_BASE_CPR),0) | AP68: =IFERROR(LN(AD68)/(LN(W68)+LN(X68)+LN(Y68)+LN(Z68)+LN(AA68)+LN(AB68)+LN(AC68)+LN(AD68))*(AH68-V7_BASE_CPR),0) | AQ68: =V7_BASE_CPR+SUM(AI68:AP68)-AH68
A69: 3617X5EB2_000000011311435 | B69: WALKER_POST21 | C69: 3617X5EB2 | D69: WALKER & DUNLOP, LLC | E69: 223f | F69: RP | G69: 2021 | H69: 202602 | I69: 17646197 | J69: 2.33 | K69: 447 | L69: 6 | M69: 51 | N69: 0 | O69: 205612 | Q69: 4080 | R69: 0 | S69: 0 | T69: =LN(1+I69) | U69: =J69*100-K69 | V69: =U69-12.5*(L69+1) | W69: =IF(M69<=V7_AGE_KNOT_X_0,V7_AGE_KNOT_Y_0,IF(M69>=V7_AGE_KNOT_X_5,V7_AGE_KNOT_Y_5,IF(M69<=V7_AGE_KNOT_X_1,V7_AGE_KNOT_Y_0+(M69-V7_AGE_KNOT_X_0)/(V7_AGE_KNOT_X_1-V7_AGE_KNOT_X_0)*(V7_AGE_KNOT_Y_1-V7_AGE_KNOT_Y_0),IF(M69<=V7_AGE_KNOT_X_2,V7_AGE_KNOT_Y_1+(M69-V7_AGE_KNOT_X_1)/(V7_AGE_KNOT_X_2-V7_AGE_KNOT_X_1)*(V7_AGE_KNOT_Y_2-V7_AGE_KNOT_Y_1),IF(M69<=V7_AGE_KNOT_X_3,V7_AGE_KNOT_Y_2+(M69-V7_AGE_KNOT_X_2)/(V7_AGE_KNOT_X_3-V7_AGE_KNOT_X_2)*(V7_AGE_KNOT_Y_3-V7_AGE_KNOT_Y_2),IF(M69<=V7_AGE_KNOT_X_4,V7_AGE_KNOT_Y_3+(M69-V7_AGE_KNOT_X_3)/(V7_AGE_KNOT_X_4-V7_AGE_KNOT_X_3)*(V7_AGE_KNOT_Y_4-V7_AGE_KNOT_Y_3),V7_AGE_KNOT_Y_4+(M69-V7_AGE_KNOT_X_4)/(V7_AGE_KNOT_X_5-V7_AGE_KNOT_X_4)*(V7_AGE_KNOT_Y_5-V7_AGE_KNOT_Y_4))))))) | X69: =V7_RATE_FLOOR+V7_RATE_ASYMPTOTE/(1+EXP(-(V69-V7_RATE_MID)/V7_RATE_SLOPE)) | Y69: =MAX(V7_SIZE_LOW,MIN(V7_SIZE_HIGH,V7_SIZE_INTERCEPT+V7_SIZE_SLOPE*(T69-V7_SIZE_LOG_ANCHOR))) | Z69: =IF(ISNUMBER(SEARCH("232",E69)),VLOOKUP("232",V7_PROGRAM_TABLE,2,FALSE),IF(ISNUMBER(SEARCH("538",E69)),VLOOKUP("538",V7_PROGRAM_TABLE,2,FALSE),IF(ISNUMBER(SEARCH("223a7",E69)),VLOOKUP("223a7",V7_PROGRAM_TABLE,2,FALSE),IF(ISNUMBER(SEARCH("223f",E69)),VLOOKUP("223f",V7_PROGRAM_TABLE,2,FALSE),V7_PROGRAM_DEFAULT)))) | AA69: =IF(S69=1,1+V7_PURPOSE_NC_BUMP*MAX(0,1-ABS(M69-V7_PURPOSE_PEAK_AGE)/V7_PURPOSE_WIDTH),1) | AB69: =IF(AND(IF(OR(P69="",NOT(ISNUMBER(P69))),0,MAX(0,MIN(24,(INT(VALUE(H69)/100)-INT(P69/100))*12+MOD(VALUE(H69),100)-MOD(P69,100))))>0,IF(OR(P69="",NOT(ISNUMBER(P69))),0,MAX(0,MIN(24,(INT(VALUE(H69)/100)-INT(P69/100))*12+MOD(VALUE(H69),100)-MOD(P69,100))))<=12),1+V7_LOCKOUT_AMP*EXP(-(IF(OR(P69="",NOT(ISNUMBER(P69))),0,MAX(0,MIN(24,(INT(VALUE(H69)/100)-INT(P69/100))*12+MOD(VALUE(H69),100)-MOD(P69,100)))))/V7_LOCKOUT_TAU),1) | AC69: =IF(IF(OR(O69="",NOT(ISNUMBER(O69))),360,MAX(0,MIN(480,(INT(O69/100)-INT(VALUE(H69)/100))*12+MOD(O69,100)-MOD(VALUE(H69),100))))>0,1+V7_MTY_AMP*MAX(0,(V7_MTY_CUTOFF-(IF(OR(O69="",NOT(ISNUMBER(O69))),360,MAX(0,MIN(480,(INT(O69/100)-INT(VALUE(H69)/100))*12+MOD(O69,100)-MOD(VALUE(H69),100))))))/V7_MTY_CUTOFF),1) | AD69: =MAX(V7_BURN_FLOOR,1-V7_BURN_SLOPE*MIN(1,MAX(0,R69))) | AE69: =IF(V7_USE_ISSUER=1,IFERROR(VLOOKUP(Q69,V7_ISSUER_TABLE,3,FALSE),1),1) | AF69: =PRODUCT(W69:AE69) | AG69: =MIN(V7_BASE_SMM*AF69,V7_SMM_CAP) | AH69: =1-(1-AG69)^12 | AI69: =IFERROR(LN(W69)/(LN(W69)+LN(X69)+LN(Y69)+LN(Z69)+LN(AA69)+LN(AB69)+LN(AC69)+LN(AD69))*(AH69-V7_BASE_CPR),0) | AJ69: =IFERROR(LN(X69)/(LN(W69)+LN(X69)+LN(Y69)+LN(Z69)+LN(AA69)+LN(AB69)+LN(AC69)+LN(AD69))*(AH69-V7_BASE_CPR),0) | AK69: =IFERROR(LN(Y69)/(LN(W69)+LN(X69)+LN(Y69)+LN(Z69)+LN(AA69)+LN(AB69)+LN(AC69)+LN(AD69))*(AH69-V7_BASE_CPR),0) | AL69: =IFERROR(LN(Z69)/(LN(W69)+LN(X69)+LN(Y69)+LN(Z69)+LN(AA69)+LN(AB69)+LN(AC69)+LN(AD69))*(AH69-V7_BASE_CPR),0) | AM69: =IFERROR(LN(AA69)/(LN(W69)+LN(X69)+LN(Y69)+LN(Z69)+LN(AA69)+LN(AB69)+LN(AC69)+LN(AD69))*(AH69-V7_BASE_CPR),0) | AN69: =IFERROR(LN(AB69)/(LN(W69)+LN(X69)+LN(Y69)+LN(Z69)+LN(AA69)+LN(AB69)+LN(AC69)+LN(AD69))*(AH69-V7_BASE_CPR),0) | AO69: =IFERROR(LN(AC69)/(LN(W69)+LN(X69)+LN(Y69)+LN(Z69)+LN(AA69)+LN(AB69)+LN(AC69)+LN(AD69))*(AH69-V7_BASE_CPR),0) | AP69: =IFERROR(LN(AD69)/(LN(W69)+LN(X69)+LN(Y69)+LN(Z69)+LN(AA69)+LN(AB69)+LN(AC69)+LN(AD69))*(AH69-V7_BASE_CPR),0) | AQ69: =V7_BASE_CPR+SUM(AI69:AP69)-AH69
A70: 3617UQNP8_000000005111489 | B70: WALKER_POST21 | C70: 3617UQNP8 | D70: WALKER & DUNLOP, LLC | E70: 223a7 | F70: RP | G70: 2021 | H70: 202602 | I70: 5985368.1 | J70: 2.29 | K70: 447 | L70: 6 | M70: 60 | N70: 0 | O70: 205103 | Q70: 4080 | R70: 0 | S70: 0 | T70: =LN(1+I70) | U70: =J70*100-K70 | V70: =U70-12.5*(L70+1) | W70: =IF(M70<=V7_AGE_KNOT_X_0,V7_AGE_KNOT_Y_0,IF(M70>=V7_AGE_KNOT_X_5,V7_AGE_KNOT_Y_5,IF(M70<=V7_AGE_KNOT_X_1,V7_AGE_KNOT_Y_0+(M70-V7_AGE_KNOT_X_0)/(V7_AGE_KNOT_X_1-V7_AGE_KNOT_X_0)*(V7_AGE_KNOT_Y_1-V7_AGE_KNOT_Y_0),IF(M70<=V7_AGE_KNOT_X_2,V7_AGE_KNOT_Y_1+(M70-V7_AGE_KNOT_X_1)/(V7_AGE_KNOT_X_2-V7_AGE_KNOT_X_1)*(V7_AGE_KNOT_Y_2-V7_AGE_KNOT_Y_1),IF(M70<=V7_AGE_KNOT_X_3,V7_AGE_KNOT_Y_2+(M70-V7_AGE_KNOT_X_2)/(V7_AGE_KNOT_X_3-V7_AGE_KNOT_X_2)*(V7_AGE_KNOT_Y_3-V7_AGE_KNOT_Y_2),IF(M70<=V7_AGE_KNOT_X_4,V7_AGE_KNOT_Y_3+(M70-V7_AGE_KNOT_X_3)/(V7_AGE_KNOT_X_4-V7_AGE_KNOT_X_3)*(V7_AGE_KNOT_Y_4-V7_AGE_KNOT_Y_3),V7_AGE_KNOT_Y_4+(M70-V7_AGE_KNOT_X_4)/(V7_AGE_KNOT_X_5-V7_AGE_KNOT_X_4)*(V7_AGE_KNOT_Y_5-V7_AGE_KNOT_Y_4))))))) | X70: =V7_RATE_FLOOR+V7_RATE_ASYMPTOTE/(1+EXP(-(V70-V7_RATE_MID)/V7_RATE_SLOPE)) | Y70: =MAX(V7_SIZE_LOW,MIN(V7_SIZE_HIGH,V7_SIZE_INTERCEPT+V7_SIZE_SLOPE*(T70-V7_SIZE_LOG_ANCHOR))) | Z70: =IF(ISNUMBER(SEARCH("232",E70)),VLOOKUP("232",V7_PROGRAM_TABLE,2,FALSE),IF(ISNUMBER(SEARCH("538",E70)),VLOOKUP("538",V7_PROGRAM_TABLE,2,FALSE),IF(ISNUMBER(SEARCH("223a7",E70)),VLOOKUP("223a7",V7_PROGRAM_TABLE,2,FALSE),IF(ISNUMBER(SEARCH("223f",E70)),VLOOKUP("223f",V7_PROGRAM_TABLE,2,FALSE),V7_PROGRAM_DEFAULT)))) | AA70: =IF(S70=1,1+V7_PURPOSE_NC_BUMP*MAX(0,1-ABS(M70-V7_PURPOSE_PEAK_AGE)/V7_PURPOSE_WIDTH),1) | AB70: =IF(AND(IF(OR(P70="",NOT(ISNUMBER(P70))),0,MAX(0,MIN(24,(INT(VALUE(H70)/100)-INT(P70/100))*12+MOD(VALUE(H70),100)-MOD(P70,100))))>0,IF(OR(P70="",NOT(ISNUMBER(P70))),0,MAX(0,MIN(24,(INT(VALUE(H70)/100)-INT(P70/100))*12+MOD(VALUE(H70),100)-MOD(P70,100))))<=12),1+V7_LOCKOUT_AMP*EXP(-(IF(OR(P70="",NOT(ISNUMBER(P70))),0,MAX(0,MIN(24,(INT(VALUE(H70)/100)-INT(P70/100))*12+MOD(VALUE(H70),100)-MOD(P70,100)))))/V7_LOCKOUT_TAU),1) | AC70: =IF(IF(OR(O70="",NOT(ISNUMBER(O70))),360,MAX(0,MIN(480,(INT(O70/100)-INT(VALUE(H70)/100))*12+MOD(O70,100)-MOD(VALUE(H70),100))))>0,1+V7_MTY_AMP*MAX(0,(V7_MTY_CUTOFF-(IF(OR(O70="",NOT(ISNUMBER(O70))),360,MAX(0,MIN(480,(INT(O70/100)-INT(VALUE(H70)/100))*12+MOD(O70,100)-MOD(VALUE(H70),100))))))/V7_MTY_CUTOFF),1) | AD70: =MAX(V7_BURN_FLOOR,1-V7_BURN_SLOPE*MIN(1,MAX(0,R70))) | AE70: =IF(V7_USE_ISSUER=1,IFERROR(VLOOKUP(Q70,V7_ISSUER_TABLE,3,FALSE),1),1) | AF70: =PRODUCT(W70:AE70) | AG70: =MIN(V7_BASE_SMM*AF70,V7_SMM_CAP) | AH70: =1-(1-AG70)^12 | AI70: =IFERROR(LN(W70)/(LN(W70)+LN(X70)+LN(Y70)+LN(Z70)+LN(AA70)+LN(AB70)+LN(AC70)+LN(AD70))*(AH70-V7_BASE_CPR),0) | AJ70: =IFERROR(LN(X70)/(LN(W70)+LN(X70)+LN(Y70)+LN(Z70)+LN(AA70)+LN(AB70)+LN(AC70)+LN(AD70))*(AH70-V7_BASE_CPR),0) | AK70: =IFERROR(LN(Y70)/(LN(W70)+LN(X70)+LN(Y70)+LN(Z70)+LN(AA70)+LN(AB70)+LN(AC70)+LN(AD70))*(AH70-V7_BASE_CPR),0) | AL70: =IFERROR(LN(Z70)/(LN(W70)+LN(X70)+LN(Y70)+LN(Z70)+LN(AA70)+LN(AB70)+LN(AC70)+LN(AD70))*(AH70-V7_BASE_CPR),0) | AM70: =IFERROR(LN(AA70)/(LN(W70)+LN(X70)+LN(Y70)+LN(Z70)+LN(AA70)+LN(AB70)+LN(AC70)+LN(AD70))*(AH70-V7_BASE_CPR),0) | AN70: =IFERROR(LN(AB70)/(LN(W70)+LN(X70)+LN(Y70)+LN(Z70)+LN(AA70)+LN(AB70)+LN(AC70)+LN(AD70))*(AH70-V7_BASE_CPR),0) | AO70: =IFERROR(LN(AC70)/(LN(W70)+LN(X70)+LN(Y70)+LN(Z70)+LN(AA70)+LN(AB70)+LN(AC70)+LN(AD70))*(AH70-V7_BASE_CPR),0) | AP70: =IFERROR(LN(AD70)/(LN(W70)+LN(X70)+LN(Y70)+LN(Z70)+LN(AA70)+LN(AB70)+LN(AC70)+LN(AD70))*(AH70-V7_BASE_CPR),0) | AQ70: =V7_BASE_CPR+SUM(AI70:AP70)-AH70
A71: 3620ANPX2_000000004322064 | B71: WALKER_PRE21 | C71: 3620ANPX2 | D71: WALKER & DUNLOP, LLC | E71: 232 | F71: RP | G71: 2011 | H71: 202602 | I71: 4469240.9 | J71: 3.73 | K71: 447 | L71: 0 | M71: 172 | N71: 38 | O71: 204611 | P71: 201312 | Q71: 4080 | R71: 0.22093023 | S71: 0 | T71: =LN(1+I71) | U71: =J71*100-K71 | V71: =U71-12.5*(L71+1) | W71: =IF(M71<=V7_AGE_KNOT_X_0,V7_AGE_KNOT_Y_0,IF(M71>=V7_AGE_KNOT_X_5,V7_AGE_KNOT_Y_5,IF(M71<=V7_AGE_KNOT_X_1,V7_AGE_KNOT_Y_0+(M71-V7_AGE_KNOT_X_0)/(V7_AGE_KNOT_X_1-V7_AGE_KNOT_X_0)*(V7_AGE_KNOT_Y_1-V7_AGE_KNOT_Y_0),IF(M71<=V7_AGE_KNOT_X_2,V7_AGE_KNOT_Y_1+(M71-V7_AGE_KNOT_X_1)/(V7_AGE_KNOT_X_2-V7_AGE_KNOT_X_1)*(V7_AGE_KNOT_Y_2-V7_AGE_KNOT_Y_1),IF(M71<=V7_AGE_KNOT_X_3,V7_AGE_KNOT_Y_2+(M71-V7_AGE_KNOT_X_2)/(V7_AGE_KNOT_X_3-V7_AGE_KNOT_X_2)*(V7_AGE_KNOT_Y_3-V7_AGE_KNOT_Y_2),IF(M71<=V7_AGE_KNOT_X_4,V7_AGE_KNOT_Y_3+(M71-V7_AGE_KNOT_X_3)/(V7_AGE_KNOT_X_4-V7_AGE_KNOT_X_3)*(V7_AGE_KNOT_Y_4-V7_AGE_KNOT_Y_3),V7_AGE_KNOT_Y_4+(M71-V7_AGE_KNOT_X_4)/(V7_AGE_KNOT_X_5-V7_AGE_KNOT_X_4)*(V7_AGE_KNOT_Y_5-V7_AGE_KNOT_Y_4))))))) | X71: =V7_RATE_FLOOR+V7_RATE_ASYMPTOTE/(1+EXP(-(V71-V7_RATE_MID)/V7_RATE_SLOPE)) | Y71: =MAX(V7_SIZE_LOW,MIN(V7_SIZE_HIGH,V7_SIZE_INTERCEPT+V7_SIZE_SLOPE*(T71-V7_SIZE_LOG_ANCHOR))) | Z71: =IF(ISNUMBER(SEARCH("232",E71)),VLOOKUP("232",V7_PROGRAM_TABLE,2,FALSE),IF(ISNUMBER(SEARCH("538",E71)),VLOOKUP("538",V7_PROGRAM_TABLE,2,FALSE),IF(ISNUMBER(SEARCH("223a7",E71)),VLOOKUP("223a7",V7_PROGRAM_TABLE,2,FALSE),IF(ISNUMBER(SEARCH("223f",E71)),VLOOKUP("223f",V7_PROGRAM_TABLE,2,FALSE),V7_PROGRAM_DEFAULT)))) | AA71: =IF(S71=1,1+V7_PURPOSE_NC_BUMP*MAX(0,1-ABS(M71-V7_PURPOSE_PEAK_AGE)/V7_PURPOSE_WIDTH),1) | AB71: =IF(AND(IF(OR(P71="",NOT(ISNUMBER(P71))),0,MAX(0,MIN(24,(INT(VALUE(H71)/100)-INT(P71/100))*12+MOD(VALUE(H71),100)-MOD(P71,100))))>0,IF(OR(P71="",NOT(ISNUMBER(P71))),0,MAX(0,MIN(24,(INT(VALUE(H71)/100)-INT(P71/100))*12+MOD(VALUE(H71),100)-MOD(P71,100))))<=12),1+V7_LOCKOUT_AMP*EXP(-(IF(OR(P71="",NOT(ISNUMBER(P71))),0,MAX(0,MIN(24,(INT(VALUE(H71)/100)-INT(P71/100))*12+MOD(VALUE(H71),100)-MOD(P71,100)))))/V7_LOCKOUT_TAU),1) | AC71: =IF(IF(OR(O71="",NOT(ISNUMBER(O71))),360,MAX(0,MIN(480,(INT(O71/100)-INT(VALUE(H71)/100))*12+MOD(O71,100)-MOD(VALUE(H71),100))))>0,1+V7_MTY_AMP*MAX(0,(V7_MTY_CUTOFF-(IF(OR(O71="",NOT(ISNUMBER(O71))),360,MAX(0,MIN(480,(INT(O71/100)-INT(VALUE(H71)/100))*12+MOD(O71,100)-MOD(VALUE(H71),100))))))/V7_MTY_CUTOFF),1) | AD71: =MAX(V7_BURN_FLOOR,1-V7_BURN_SLOPE*MIN(1,MAX(0,R71))) | AE71: =IF(V7_USE_ISSUER=1,IFERROR(VLOOKUP(Q71,V7_ISSUER_TABLE,3,FALSE),1),1) | AF71: =PRODUCT(W71:AE71) | AG71: =MIN(V7_BASE_SMM*AF71,V7_SMM_CAP) | AH71: =1-(1-AG71)^12 | AI71: =IFERROR(LN(W71)/(LN(W71)+LN(X71)+LN(Y71)+LN(Z71)+LN(AA71)+LN(AB71)+LN(AC71)+LN(AD71))*(AH71-V7_BASE_CPR),0) | AJ71: =IFERROR(LN(X71)/(LN(W71)+LN(X71)+LN(Y71)+LN(Z71)+LN(AA71)+LN(AB71)+LN(AC71)+LN(AD71))*(AH71-V7_BASE_CPR),0) | AK71: =IFERROR(LN(Y71)/(LN(W71)+LN(X71)+LN(Y71)+LN(Z71)+LN(AA71)+LN(AB71)+LN(AC71)+LN(AD71))*(AH71-V7_BASE_CPR),0) | AL71: =IFERROR(LN(Z71)/(LN(W71)+LN(X71)+LN(Y71)+LN(Z71)+LN(AA71)+LN(AB71)+LN(AC71)+LN(AD71))*(AH71-V7_BASE_CPR),0) | AM71: =IFERROR(LN(AA71)/(LN(W71)+LN(X71)+LN(Y71)+LN(Z71)+LN(AA71)+LN(AB71)+LN(AC71)+LN(AD71))*(AH71-V7_BASE_CPR),0) | AN71: =IFERROR(LN(AB71)/(LN(W71)+LN(X71)+LN(Y71)+LN(Z71)+LN(AA71)+LN(AB71)+LN(AC71)+LN(AD71))*(AH71-V7_BASE_CPR),0) | AO71: =IFERROR(LN(AC71)/(LN(W71)+LN(X71)+LN(Y71)+LN(Z71)+LN(AA71)+LN(AB71)+LN(AC71)+LN(AD71))*(AH71-V7_BASE_CPR),0) | AP71: =IFERROR(LN(AD71)/(LN(W71)+LN(X71)+LN(Y71)+LN(Z71)+LN(AA71)+LN(AB71)+LN(AC71)+LN(AD71))*(AH71-V7_BASE_CPR),0) | AQ71: =V7_BASE_CPR+SUM(AI71:AP71)-AH71
A72: 36195LZX3_000000004722066 | B72: WALKER_PRE21 | C72: 36195LZX3 | D72: WALKER & DUNLOP, LLC | E72: 232 | F72: RP | G72: 2011 | H72: 202602 | I72: 1687095.6 | J72: 3.58 | K72: 447 | L72: 1 | M72: 176 | N72: 27 | O72: 204107 | Q72: 4080 | R72: 0.15340909 | S72: 0 | T72: =LN(1+I72) | U72: =J72*100-K72 | V72: =U72-12.5*(L72+1) | W72: =IF(M72<=V7_AGE_KNOT_X_0,V7_AGE_KNOT_Y_0,IF(M72>=V7_AGE_KNOT_X_5,V7_AGE_KNOT_Y_5,IF(M72<=V7_AGE_KNOT_X_1,V7_AGE_KNOT_Y_0+(M72-V7_AGE_KNOT_X_0)/(V7_AGE_KNOT_X_1-V7_AGE_KNOT_X_0)*(V7_AGE_KNOT_Y_1-V7_AGE_KNOT_Y_0),IF(M72<=V7_AGE_KNOT_X_2,V7_AGE_KNOT_Y_1+(M72-V7_AGE_KNOT_X_1)/(V7_AGE_KNOT_X_2-V7_AGE_KNOT_X_1)*(V7_AGE_KNOT_Y_2-V7_AGE_KNOT_Y_1),IF(M72<=V7_AGE_KNOT_X_3,V7_AGE_KNOT_Y_2+(M72-V7_AGE_KNOT_X_2)/(V7_AGE_KNOT_X_3-V7_AGE_KNOT_X_2)*(V7_AGE_KNOT_Y_3-V7_AGE_KNOT_Y_2),IF(M72<=V7_AGE_KNOT_X_4,V7_AGE_KNOT_Y_3+(M72-V7_AGE_KNOT_X_3)/(V7_AGE_KNOT_X_4-V7_AGE_KNOT_X_3)*(V7_AGE_KNOT_Y_4-V7_AGE_KNOT_Y_3),V7_AGE_KNOT_Y_4+(M72-V7_AGE_KNOT_X_4)/(V7_AGE_KNOT_X_5-V7_AGE_KNOT_X_4)*(V7_AGE_KNOT_Y_5-V7_AGE_KNOT_Y_4))))))) | X72: =V7_RATE_FLOOR+V7_RATE_ASYMPTOTE/(1+EXP(-(V72-V7_RATE_MID)/V7_RATE_SLOPE)) | Y72: =MAX(V7_SIZE_LOW,MIN(V7_SIZE_HIGH,V7_SIZE_INTERCEPT+V7_SIZE_SLOPE*(T72-V7_SIZE_LOG_ANCHOR))) | Z72: =IF(ISNUMBER(SEARCH("232",E72)),VLOOKUP("232",V7_PROGRAM_TABLE,2,FALSE),IF(ISNUMBER(SEARCH("538",E72)),VLOOKUP("538",V7_PROGRAM_TABLE,2,FALSE),IF(ISNUMBER(SEARCH("223a7",E72)),VLOOKUP("223a7",V7_PROGRAM_TABLE,2,FALSE),IF(ISNUMBER(SEARCH("223f",E72)),VLOOKUP("223f",V7_PROGRAM_TABLE,2,FALSE),V7_PROGRAM_DEFAULT)))) | AA72: =IF(S72=1,1+V7_PURPOSE_NC_BUMP*MAX(0,1-ABS(M72-V7_PURPOSE_PEAK_AGE)/V7_PURPOSE_WIDTH),1) | AB72: =IF(AND(IF(OR(P72="",NOT(ISNUMBER(P72))),0,MAX(0,MIN(24,(INT(VALUE(H72)/100)-INT(P72/100))*12+MOD(VALUE(H72),100)-MOD(P72,100))))>0,IF(OR(P72="",NOT(ISNUMBER(P72))),0,MAX(0,MIN(24,(INT(VALUE(H72)/100)-INT(P72/100))*12+MOD(VALUE(H72),100)-MOD(P72,100))))<=12),1+V7_LOCKOUT_AMP*EXP(-(IF(OR(P72="",NOT(ISNUMBER(P72))),0,MAX(0,MIN(24,(INT(VALUE(H72)/100)-INT(P72/100))*12+MOD(VALUE(H72),100)-MOD(P72,100)))))/V7_LOCKOUT_TAU),1) | AC72: =IF(IF(OR(O72="",NOT(ISNUMBER(O72))),360,MAX(0,MIN(480,(INT(O72/100)-INT(VALUE(H72)/100))*12+MOD(O72,100)-MOD(VALUE(H72),100))))>0,1+V7_MTY_AMP*MAX(0,(V7_MTY_CUTOFF-(IF(OR(O72="",NOT(ISNUMBER(O72))),360,MAX(0,MIN(480,(INT(O72/100)-INT(VALUE(H72)/100))*12+MOD(O72,100)-MOD(VALUE(H72),100))))))/V7_MTY_CUTOFF),1) | AD72: =MAX(V7_BURN_FLOOR,1-V7_BURN_SLOPE*MIN(1,MAX(0,R72))) | AE72: =IF(V7_USE_ISSUER=1,IFERROR(VLOOKUP(Q72,V7_ISSUER_TABLE,3,FALSE),1),1) | AF72: =PRODUCT(W72:AE72) | AG72: =MIN(V7_BASE_SMM*AF72,V7_SMM_CAP) | AH72: =1-(1-AG72)^12 | AI72: =IFERROR(LN(W72)/(LN(W72)+LN(X72)+LN(Y72)+LN(Z72)+LN(AA72)+LN(AB72)+LN(AC72)+LN(AD72))*(AH72-V7_BASE_CPR),0) | AJ72: =IFERROR(LN(X72)/(LN(W72)+LN(X72)+LN(Y72)+LN(Z72)+LN(AA72)+LN(AB72)+LN(AC72)+LN(AD72))*(AH72-V7_BASE_CPR),0) | AK72: =IFERROR(LN(Y72)/(LN(W72)+LN(X72)+LN(Y72)+LN(Z72)+LN(AA72)+LN(AB72)+LN(AC72)+LN(AD72))*(AH72-V7_BASE_CPR),0) | AL72: =IFERROR(LN(Z72)/(LN(W72)+LN(X72)+LN(Y72)+LN(Z72)+LN(AA72)+LN(AB72)+LN(AC72)+LN(AD72))*(AH72-V7_BASE_CPR),0) | AM72: =IFERROR(LN(AA72)/(LN(W72)+LN(X72)+LN(Y72)+LN(Z72)+LN(AA72)+LN(AB72)+LN(AC72)+LN(AD72))*(AH72-V7_BASE_CPR),0) | AN72: =IFERROR(LN(AB72)/(LN(W72)+LN(X72)+LN(Y72)+LN(Z72)+LN(AA72)+LN(AB72)+LN(AC72)+LN(AD72))*(AH72-V7_BASE_CPR),0) | AO72: =IFERROR(LN(AC72)/(LN(W72)+LN(X72)+LN(Y72)+LN(Z72)+LN(AA72)+LN(AB72)+LN(AC72)+LN(AD72))*(AH72-V7_BASE_CPR),0) | AP72: =IFERROR(LN(AD72)/(LN(W72)+LN(X72)+LN(Y72)+LN(Z72)+LN(AA72)+LN(AB72)+LN(AC72)+LN(AD72))*(AH72-V7_BASE_CPR),0) | AQ72: =V7_BASE_CPR+SUM(AI72:AP72)-AH72
A73: 3617NYVC9_000000002311566 | B73: WALKER_PRE21 | C73: 3617NYVC9 | D73: WALKER & DUNLOP, LLC | E73: 223f | F73: RP | G73: 2020 | H73: 202602 | I73: 13589484 | J73: 2.25 | K73: 447 | L73: 5 | M73: 65 | N73: 0 | O73: 205510 | Q73: 4080 | R73: 0 | S73: 0 | T73: =LN(1+I73) | U73: =J73*100-K73 | V73: =U73-12.5*(L73+1) | W73: =IF(M73<=V7_AGE_KNOT_X_0,V7_AGE_KNOT_Y_0,IF(M73>=V7_AGE_KNOT_X_5,V7_AGE_KNOT_Y_5,IF(M73<=V7_AGE_KNOT_X_1,V7_AGE_KNOT_Y_0+(M73-V7_AGE_KNOT_X_0)/(V7_AGE_KNOT_X_1-V7_AGE_KNOT_X_0)*(V7_AGE_KNOT_Y_1-V7_AGE_KNOT_Y_0),IF(M73<=V7_AGE_KNOT_X_2,V7_AGE_KNOT_Y_1+(M73-V7_AGE_KNOT_X_1)/(V7_AGE_KNOT_X_2-V7_AGE_KNOT_X_1)*(V7_AGE_KNOT_Y_2-V7_AGE_KNOT_Y_1),IF(M73<=V7_AGE_KNOT_X_3,V7_AGE_KNOT_Y_2+(M73-V7_AGE_KNOT_X_2)/(V7_AGE_KNOT_X_3-V7_AGE_KNOT_X_2)*(V7_AGE_KNOT_Y_3-V7_AGE_KNOT_Y_2),IF(M73<=V7_AGE_KNOT_X_4,V7_AGE_KNOT_Y_3+(M73-V7_AGE_KNOT_X_3)/(V7_AGE_KNOT_X_4-V7_AGE_KNOT_X_3)*(V7_AGE_KNOT_Y_4-V7_AGE_KNOT_Y_3),V7_AGE_KNOT_Y_4+(M73-V7_AGE_KNOT_X_4)/(V7_AGE_KNOT_X_5-V7_AGE_KNOT_X_4)*(V7_AGE_KNOT_Y_5-V7_AGE_KNOT_Y_4))))))) | X73: =V7_RATE_FLOOR+V7_RATE_ASYMPTOTE/(1+EXP(-(V73-V7_RATE_MID)/V7_RATE_SLOPE)) | Y73: =MAX(V7_SIZE_LOW,MIN(V7_SIZE_HIGH,V7_SIZE_INTERCEPT+V7_SIZE_SLOPE*(T73-V7_SIZE_LOG_ANCHOR))) | Z73: =IF(ISNUMBER(SEARCH("232",E73)),VLOOKUP("232",V7_PROGRAM_TABLE,2,FALSE),IF(ISNUMBER(SEARCH("538",E73)),VLOOKUP("538",V7_PROGRAM_TABLE,2,FALSE),IF(ISNUMBER(SEARCH("223a7",E73)),VLOOKUP("223a7",V7_PROGRAM_TABLE,2,FALSE),IF(ISNUMBER(SEARCH("223f",E73)),VLOOKUP("223f",V7_PROGRAM_TABLE,2,FALSE),V7_PROGRAM_DEFAULT)))) | AA73: =IF(S73=1,1+V7_PURPOSE_NC_BUMP*MAX(0,1-ABS(M73-V7_PURPOSE_PEAK_AGE)/V7_PURPOSE_WIDTH),1) | AB73: =IF(AND(IF(OR(P73="",NOT(ISNUMBER(P73))),0,MAX(0,MIN(24,(INT(VALUE(H73)/100)-INT(P73/100))*12+MOD(VALUE(H73),100)-MOD(P73,100))))>0,IF(OR(P73="",NOT(ISNUMBER(P73))),0,MAX(0,MIN(24,(INT(VALUE(H73)/100)-INT(P73/100))*12+MOD(VALUE(H73),100)-MOD(P73,100))))<=12),1+V7_LOCKOUT_AMP*EXP(-(IF(OR(P73="",NOT(ISNUMBER(P73))),0,MAX(0,MIN(24,(INT(VALUE(H73)/100)-INT(P73/100))*12+MOD(VALUE(H73),100)-MOD(P73,100)))))/V7_LOCKOUT_TAU),1) | AC73: =IF(IF(OR(O73="",NOT(ISNUMBER(O73))),360,MAX(0,MIN(480,(INT(O73/100)-INT(VALUE(H73)/100))*12+MOD(O73,100)-MOD(VALUE(H73),100))))>0,1+V7_MTY_AMP*MAX(0,(V7_MTY_CUTOFF-(IF(OR(O73="",NOT(ISNUMBER(O73))),360,MAX(0,MIN(480,(INT(O73/100)-INT(VALUE(H73)/100))*12+MOD(O73,100)-MOD(VALUE(H73),100))))))/V7_MTY_CUTOFF),1) | AD73: =MAX(V7_BURN_FLOOR,1-V7_BURN_SLOPE*MIN(1,MAX(0,R73))) | AE73: =IF(V7_USE_ISSUER=1,IFERROR(VLOOKUP(Q73,V7_ISSUER_TABLE,3,FALSE),1),1) | AF73: =PRODUCT(W73:AE73) | AG73: =MIN(V7_BASE_SMM*AF73,V7_SMM_CAP) | AH73: =1-(1-AG73)^12 | AI73: =IFERROR(LN(W73)/(LN(W73)+LN(X73)+LN(Y73)+LN(Z73)+LN(AA73)+LN(AB73)+LN(AC73)+LN(AD73))*(AH73-V7_BASE_CPR),0) | AJ73: =IFERROR(LN(X73)/(LN(W73)+LN(X73)+LN(Y73)+LN(Z73)+LN(AA73)+LN(AB73)+LN(AC73)+LN(AD73))*(AH73-V7_BASE_CPR),0) | AK73: =IFERROR(LN(Y73)/(LN(W73)+LN(X73)+LN(Y73)+LN(Z73)+LN(AA73)+LN(AB73)+LN(AC73)+LN(AD73))*(AH73-V7_BASE_CPR),0) | AL73: =IFERROR(LN(Z73)/(LN(W73)+LN(X73)+LN(Y73)+LN(Z73)+LN(AA73)+LN(AB73)+LN(AC73)+LN(AD73))*(AH73-V7_BASE_CPR),0) | AM73: =IFERROR(LN(AA73)/(LN(W73)+LN(X73)+LN(Y73)+LN(Z73)+LN(AA73)+LN(AB73)+LN(AC73)+LN(AD73))*(AH73-V7_BASE_CPR),0) | AN73: =IFERROR(LN(AB73)/(LN(W73)+LN(X73)+LN(Y73)+LN(Z73)+LN(AA73)+LN(AB73)+LN(AC73)+LN(AD73))*(AH73-V7_BASE_CPR),0) | AO73: =IFERROR(LN(AC73)/(LN(W73)+LN(X73)+LN(Y73)+LN(Z73)+LN(AA73)+LN(AB73)+LN(AC73)+LN(AD73))*(AH73-V7_BASE_CPR),0) | AP73: =IFERROR(LN(AD73)/(LN(W73)+LN(X73)+LN(Y73)+LN(Z73)+LN(AA73)+LN(AB73)+LN(AC73)+LN(AD73))*(AH73-V7_BASE_CPR),0) | AQ73: =V7_BASE_CPR+SUM(AI73:AP73)-AH73
A74: 3617N1EE6_000000004211125 | B74: WALKER_PRE21 | C74: 3617N1EE6 | D74: WALKER & DUNLOP, LLC | E74: 223f | F74: RP | G74: 2009 | H74: 202602 | I74: 2401815 | J74: 3.65 | K74: 447 | L74: 5 | M74: 203 | N74: 21 | O74: 204404 | Q74: 4080 | R74: 0.10344828 | S74: 0 | T74: =LN(1+I74) | U74: =J74*100-K74 | V74: =U74-12.5*(L74+1) | W74: =IF(M74<=V7_AGE_KNOT_X_0,V7_AGE_KNOT_Y_0,IF(M74>=V7_AGE_KNOT_X_5,V7_AGE_KNOT_Y_5,IF(M74<=V7_AGE_KNOT_X_1,V7_AGE_KNOT_Y_0+(M74-V7_AGE_KNOT_X_0)/(V7_AGE_KNOT_X_1-V7_AGE_KNOT_X_0)*(V7_AGE_KNOT_Y_1-V7_AGE_KNOT_Y_0),IF(M74<=V7_AGE_KNOT_X_2,V7_AGE_KNOT_Y_1+(M74-V7_AGE_KNOT_X_1)/(V7_AGE_KNOT_X_2-V7_AGE_KNOT_X_1)*(V7_AGE_KNOT_Y_2-V7_AGE_KNOT_Y_1),IF(M74<=V7_AGE_KNOT_X_3,V7_AGE_KNOT_Y_2+(M74-V7_AGE_KNOT_X_2)/(V7_AGE_KNOT_X_3-V7_AGE_KNOT_X_2)*(V7_AGE_KNOT_Y_3-V7_AGE_KNOT_Y_2),IF(M74<=V7_AGE_KNOT_X_4,V7_AGE_KNOT_Y_3+(M74-V7_AGE_KNOT_X_3)/(V7_AGE_KNOT_X_4-V7_AGE_KNOT_X_3)*(V7_AGE_KNOT_Y_4-V7_AGE_KNOT_Y_3),V7_AGE_KNOT_Y_4+(M74-V7_AGE_KNOT_X_4)/(V7_AGE_KNOT_X_5-V7_AGE_KNOT_X_4)*(V7_AGE_KNOT_Y_5-V7_AGE_KNOT_Y_4))))))) | X74: =V7_RATE_FLOOR+V7_RATE_ASYMPTOTE/(1+EXP(-(V74-V7_RATE_MID)/V7_RATE_SLOPE)) | Y74: =MAX(V7_SIZE_LOW,MIN(V7_SIZE_HIGH,V7_SIZE_INTERCEPT+V7_SIZE_SLOPE*(T74-V7_SIZE_LOG_ANCHOR))) | Z74: =IF(ISNUMBER(SEARCH("232",E74)),VLOOKUP("232",V7_PROGRAM_TABLE,2,FALSE),IF(ISNUMBER(SEARCH("538",E74)),VLOOKUP("538",V7_PROGRAM_TABLE,2,FALSE),IF(ISNUMBER(SEARCH("223a7",E74)),VLOOKUP("223a7",V7_PROGRAM_TABLE,2,FALSE),IF(ISNUMBER(SEARCH("223f",E74)),VLOOKUP("223f",V7_PROGRAM_TABLE,2,FALSE),V7_PROGRAM_DEFAULT)))) | AA74: =IF(S74=1,1+V7_PURPOSE_NC_BUMP*MAX(0,1-ABS(M74-V7_PURPOSE_PEAK_AGE)/V7_PURPOSE_WIDTH),1) | AB74: =IF(AND(IF(OR(P74="",NOT(ISNUMBER(P74))),0,MAX(0,MIN(24,(INT(VALUE(H74)/100)-INT(P74/100))*12+MOD(VALUE(H74),100)-MOD(P74,100))))>0,IF(OR(P74="",NOT(ISNUMBER(P74))),0,MAX(0,MIN(24,(INT(VALUE(H74)/100)-INT(P74/100))*12+MOD(VALUE(H74),100)-MOD(P74,100))))<=12),1+V7_LOCKOUT_AMP*EXP(-(IF(OR(P74="",NOT(ISNUMBER(P74))),0,MAX(0,MIN(24,(INT(VALUE(H74)/100)-INT(P74/100))*12+MOD(VALUE(H74),100)-MOD(P74,100)))))/V7_LOCKOUT_TAU),1) | AC74: =IF(IF(OR(O74="",NOT(ISNUMBER(O74))),360,MAX(0,MIN(480,(INT(O74/100)-INT(VALUE(H74)/100))*12+MOD(O74,100)-MOD(VALUE(H74),100))))>0,1+V7_MTY_AMP*MAX(0,(V7_MTY_CUTOFF-(IF(OR(O74="",NOT(ISNUMBER(O74))),360,MAX(0,MIN(480,(INT(O74/100)-INT(VALUE(H74)/100))*12+MOD(O74,100)-MOD(VALUE(H74),100))))))/V7_MTY_CUTOFF),1) | AD74: =MAX(V7_BURN_FLOOR,1-V7_BURN_SLOPE*MIN(1,MAX(0,R74))) | AE74: =IF(V7_USE_ISSUER=1,IFERROR(VLOOKUP(Q74,V7_ISSUER_TABLE,3,FALSE),1),1) | AF74: =PRODUCT(W74:AE74) | AG74: =MIN(V7_BASE_SMM*AF74,V7_SMM_CAP) | AH74: =1-(1-AG74)^12 | AI74: =IFERROR(LN(W74)/(LN(W74)+LN(X74)+LN(Y74)+LN(Z74)+LN(AA74)+LN(AB74)+LN(AC74)+LN(AD74))*(AH74-V7_BASE_CPR),0) | AJ74: =IFERROR(LN(X74)/(LN(W74)+LN(X74)+LN(Y74)+LN(Z74)+LN(AA74)+LN(AB74)+LN(AC74)+LN(AD74))*(AH74-V7_BASE_CPR),0) | AK74: =IFERROR(LN(Y74)/(LN(W74)+LN(X74)+LN(Y74)+LN(Z74)+LN(AA74)+LN(AB74)+LN(AC74)+LN(AD74))*(AH74-V7_BASE_CPR),0) | AL74: =IFERROR(LN(Z74)/(LN(W74)+LN(X74)+LN(Y74)+LN(Z74)+LN(AA74)+LN(AB74)+LN(AC74)+LN(AD74))*(AH74-V7_BASE_CPR),0) | AM74: =IFERROR(LN(AA74)/(LN(W74)+LN(X74)+LN(Y74)+LN(Z74)+LN(AA74)+LN(AB74)+LN(AC74)+LN(AD74))*(AH74-V7_BASE_CPR),0) | AN74: =IFERROR(LN(AB74)/(LN(W74)+LN(X74)+LN(Y74)+LN(Z74)+LN(AA74)+LN(AB74)+LN(AC74)+LN(AD74))*(AH74-V7_BASE_CPR),0) | AO74: =IFERROR(LN(AC74)/(LN(W74)+LN(X74)+LN(Y74)+LN(Z74)+LN(AA74)+LN(AB74)+LN(AC74)+LN(AD74))*(AH74-V7_BASE_CPR),0) | AP74: =IFERROR(LN(AD74)/(LN(W74)+LN(X74)+LN(Y74)+LN(Z74)+LN(AA74)+LN(AB74)+LN(AC74)+LN(AD74))*(AH74-V7_BASE_CPR),0) | AQ74: =V7_BASE_CPR+SUM(AI74:AP74)-AH74
A75: 3617UDKP0_000000007111196 | B75: WALKER_PRE21 | C75: 3617UDKP0 | D75: WALKER & DUNLOP, LLC | E75: 223f | F75: RP | G75: 2010 | H75: 202602 | I75: 3458376.6 | J75: 3.49 | K75: 447 | L75: 6 | M75: 190 | N75: 12 | O75: 204505 | Q75: 4080 | R75: 0.063157895 | S75: 0 | T75: =LN(1+I75) | U75: =J75*100-K75 | V75: =U75-12.5*(L75+1) | W75: =IF(M75<=V7_AGE_KNOT_X_0,V7_AGE_KNOT_Y_0,IF(M75>=V7_AGE_KNOT_X_5,V7_AGE_KNOT_Y_5,IF(M75<=V7_AGE_KNOT_X_1,V7_AGE_KNOT_Y_0+(M75-V7_AGE_KNOT_X_0)/(V7_AGE_KNOT_X_1-V7_AGE_KNOT_X_0)*(V7_AGE_KNOT_Y_1-V7_AGE_KNOT_Y_0),IF(M75<=V7_AGE_KNOT_X_2,V7_AGE_KNOT_Y_1+(M75-V7_AGE_KNOT_X_1)/(V7_AGE_KNOT_X_2-V7_AGE_KNOT_X_1)*(V7_AGE_KNOT_Y_2-V7_AGE_KNOT_Y_1),IF(M75<=V7_AGE_KNOT_X_3,V7_AGE_KNOT_Y_2+(M75-V7_AGE_KNOT_X_2)/(V7_AGE_KNOT_X_3-V7_AGE_KNOT_X_2)*(V7_AGE_KNOT_Y_3-V7_AGE_KNOT_Y_2),IF(M75<=V7_AGE_KNOT_X_4,V7_AGE_KNOT_Y_3+(M75-V7_AGE_KNOT_X_3)/(V7_AGE_KNOT_X_4-V7_AGE_KNOT_X_3)*(V7_AGE_KNOT_Y_4-V7_AGE_KNOT_Y_3),V7_AGE_KNOT_Y_4+(M75-V7_AGE_KNOT_X_4)/(V7_AGE_KNOT_X_5-V7_AGE_KNOT_X_4)*(V7_AGE_KNOT_Y_5-V7_AGE_KNOT_Y_4))))))) | X75: =V7_RATE_FLOOR+V7_RATE_ASYMPTOTE/(1+EXP(-(V75-V7_RATE_MID)/V7_RATE_SLOPE)) | Y75: =MAX(V7_SIZE_LOW,MIN(V7_SIZE_HIGH,V7_SIZE_INTERCEPT+V7_SIZE_SLOPE*(T75-V7_SIZE_LOG_ANCHOR))) | Z75: =IF(ISNUMBER(SEARCH("232",E75)),VLOOKUP("232",V7_PROGRAM_TABLE,2,FALSE),IF(ISNUMBER(SEARCH("538",E75)),VLOOKUP("538",V7_PROGRAM_TABLE,2,FALSE),IF(ISNUMBER(SEARCH("223a7",E75)),VLOOKUP("223a7",V7_PROGRAM_TABLE,2,FALSE),IF(ISNUMBER(SEARCH("223f",E75)),VLOOKUP("223f",V7_PROGRAM_TABLE,2,FALSE),V7_PROGRAM_DEFAULT)))) | AA75: =IF(S75=1,1+V7_PURPOSE_NC_BUMP*MAX(0,1-ABS(M75-V7_PURPOSE_PEAK_AGE)/V7_PURPOSE_WIDTH),1) | AB75: =IF(AND(IF(OR(P75="",NOT(ISNUMBER(P75))),0,MAX(0,MIN(24,(INT(VALUE(H75)/100)-INT(P75/100))*12+MOD(VALUE(H75),100)-MOD(P75,100))))>0,IF(OR(P75="",NOT(ISNUMBER(P75))),0,MAX(0,MIN(24,(INT(VALUE(H75)/100)-INT(P75/100))*12+MOD(VALUE(H75),100)-MOD(P75,100))))<=12),1+V7_LOCKOUT_AMP*EXP(-(IF(OR(P75="",NOT(ISNUMBER(P75))),0,MAX(0,MIN(24,(INT(VALUE(H75)/100)-INT(P75/100))*12+MOD(VALUE(H75),100)-MOD(P75,100)))))/V7_LOCKOUT_TAU),1) | AC75: =IF(IF(OR(O75="",NOT(ISNUMBER(O75))),360,MAX(0,MIN(480,(INT(O75/100)-INT(VALUE(H75)/100))*12+MOD(O75,100)-MOD(VALUE(H75),100))))>0,1+V7_MTY_AMP*MAX(0,(V7_MTY_CUTOFF-(IF(OR(O75="",NOT(ISNUMBER(O75))),360,MAX(0,MIN(480,(INT(O75/100)-INT(VALUE(H75)/100))*12+MOD(O75,100)-MOD(VALUE(H75),100))))))/V7_MTY_CUTOFF),1) | AD75: =MAX(V7_BURN_FLOOR,1-V7_BURN_SLOPE*MIN(1,MAX(0,R75))) | AE75: =IF(V7_USE_ISSUER=1,IFERROR(VLOOKUP(Q75,V7_ISSUER_TABLE,3,FALSE),1),1) | AF75: =PRODUCT(W75:AE75) | AG75: =MIN(V7_BASE_SMM*AF75,V7_SMM_CAP) | AH75: =1-(1-AG75)^12 | AI75: =IFERROR(LN(W75)/(LN(W75)+LN(X75)+LN(Y75)+LN(Z75)+LN(AA75)+LN(AB75)+LN(AC75)+LN(AD75))*(AH75-V7_BASE_CPR),0) | AJ75: =IFERROR(LN(X75)/(LN(W75)+LN(X75)+LN(Y75)+LN(Z75)+LN(AA75)+LN(AB75)+LN(AC75)+LN(AD75))*(AH75-V7_BASE_CPR),0) | AK75: =IFERROR(LN(Y75)/(LN(W75)+LN(X75)+LN(Y75)+LN(Z75)+LN(AA75)+LN(AB75)+LN(AC75)+LN(AD75))*(AH75-V7_BASE_CPR),0) | AL75: =IFERROR(LN(Z75)/(LN(W75)+LN(X75)+LN(Y75)+LN(Z75)+LN(AA75)+LN(AB75)+LN(AC75)+LN(AD75))*(AH75-V7_BASE_CPR),0) | AM75: =IFERROR(LN(AA75)/(LN(W75)+LN(X75)+LN(Y75)+LN(Z75)+LN(AA75)+LN(AB75)+LN(AC75)+LN(AD75))*(AH75-V7_BASE_CPR),0) | AN75: =IFERROR(LN(AB75)/(LN(W75)+LN(X75)+LN(Y75)+LN(Z75)+LN(AA75)+LN(AB75)+LN(AC75)+LN(AD75))*(AH75-V7_BASE_CPR),0) | AO75: =IFERROR(LN(AC75)/(LN(W75)+LN(X75)+LN(Y75)+LN(Z75)+LN(AA75)+LN(AB75)+LN(AC75)+LN(AD75))*(AH75-V7_BASE_CPR),0) | AP75: =IFERROR(LN(AD75)/(LN(W75)+LN(X75)+LN(Y75)+LN(Z75)+LN(AA75)+LN(AB75)+LN(AC75)+LN(AD75))*(AH75-V7_BASE_CPR),0) | AQ75: =V7_BASE_CPR+SUM(AI75:AP75)-AH75
A76: 36179ARA6_000000010222049 | B76: WALKER_PRE21 | C76: 36179ARA6 | D76: WALKER & DUNLOP, LLC | E76: 232 | F76: RP | G76: 2012 | H76: 202602 | I76: 9942041.3 | J76: 3.35 | K76: 447 | L76: 0 | M76: 158 | N76: 32 | O76: 204801 | P76: 201401 | Q76: 4080 | R76: 0.20253165 | S76: 0 | T76: =LN(1+I76) | U76: =J76*100-K76 | V76: =U76-12.5*(L76+1) | W76: =IF(M76<=V7_AGE_KNOT_X_0,V7_AGE_KNOT_Y_0,IF(M76>=V7_AGE_KNOT_X_5,V7_AGE_KNOT_Y_5,IF(M76<=V7_AGE_KNOT_X_1,V7_AGE_KNOT_Y_0+(M76-V7_AGE_KNOT_X_0)/(V7_AGE_KNOT_X_1-V7_AGE_KNOT_X_0)*(V7_AGE_KNOT_Y_1-V7_AGE_KNOT_Y_0),IF(M76<=V7_AGE_KNOT_X_2,V7_AGE_KNOT_Y_1+(M76-V7_AGE_KNOT_X_1)/(V7_AGE_KNOT_X_2-V7_AGE_KNOT_X_1)*(V7_AGE_KNOT_Y_2-V7_AGE_KNOT_Y_1),IF(M76<=V7_AGE_KNOT_X_3,V7_AGE_KNOT_Y_2+(M76-V7_AGE_KNOT_X_2)/(V7_AGE_KNOT_X_3-V7_AGE_KNOT_X_2)*(V7_AGE_KNOT_Y_3-V7_AGE_KNOT_Y_2),IF(M76<=V7_AGE_KNOT_X_4,V7_AGE_KNOT_Y_3+(M76-V7_AGE_KNOT_X_3)/(V7_AGE_KNOT_X_4-V7_AGE_KNOT_X_3)*(V7_AGE_KNOT_Y_4-V7_AGE_KNOT_Y_3),V7_AGE_KNOT_Y_4+(M76-V7_AGE_KNOT_X_4)/(V7_AGE_KNOT_X_5-V7_AGE_KNOT_X_4)*(V7_AGE_KNOT_Y_5-V7_AGE_KNOT_Y_4))))))) | X76: =V7_RATE_FLOOR+V7_RATE_ASYMPTOTE/(1+EXP(-(V76-V7_RATE_MID)/V7_RATE_SLOPE)) | Y76: =MAX(V7_SIZE_LOW,MIN(V7_SIZE_HIGH,V7_SIZE_INTERCEPT+V7_SIZE_SLOPE*(T76-V7_SIZE_LOG_ANCHOR))) | Z76: =IF(ISNUMBER(SEARCH("232",E76)),VLOOKUP("232",V7_PROGRAM_TABLE,2,FALSE),IF(ISNUMBER(SEARCH("538",E76)),VLOOKUP("538",V7_PROGRAM_TABLE,2,FALSE),IF(ISNUMBER(SEARCH("223a7",E76)),VLOOKUP("223a7",V7_PROGRAM_TABLE,2,FALSE),IF(ISNUMBER(SEARCH("223f",E76)),VLOOKUP("223f",V7_PROGRAM_TABLE,2,FALSE),V7_PROGRAM_DEFAULT)))) | AA76: =IF(S76=1,1+V7_PURPOSE_NC_BUMP*MAX(0,1-ABS(M76-V7_PURPOSE_PEAK_AGE)/V7_PURPOSE_WIDTH),1) | AB76: =IF(AND(IF(OR(P76="",NOT(ISNUMBER(P76))),0,MAX(0,MIN(24,(INT(VALUE(H76)/100)-INT(P76/100))*12+MOD(VALUE(H76),100)-MOD(P76,100))))>0,IF(OR(P76="",NOT(ISNUMBER(P76))),0,MAX(0,MIN(24,(INT(VALUE(H76)/100)-INT(P76/100))*12+MOD(VALUE(H76),100)-MOD(P76,100))))<=12),1+V7_LOCKOUT_AMP*EXP(-(IF(OR(P76="",NOT(ISNUMBER(P76))),0,MAX(0,MIN(24,(INT(VALUE(H76)/100)-INT(P76/100))*12+MOD(VALUE(H76),100)-MOD(P76,100)))))/V7_LOCKOUT_TAU),1) | AC76: =IF(IF(OR(O76="",NOT(ISNUMBER(O76))),360,MAX(0,MIN(480,(INT(O76/100)-INT(VALUE(H76)/100))*12+MOD(O76,100)-MOD(VALUE(H76),100))))>0,1+V7_MTY_AMP*MAX(0,(V7_MTY_CUTOFF-(IF(OR(O76="",NOT(ISNUMBER(O76))),360,MAX(0,MIN(480,(INT(O76/100)-INT(VALUE(H76)/100))*12+MOD(O76,100)-MOD(VALUE(H76),100))))))/V7_MTY_CUTOFF),1) | AD76: =MAX(V7_BURN_FLOOR,1-V7_BURN_SLOPE*MIN(1,MAX(0,R76))) | AE76: =IF(V7_USE_ISSUER=1,IFERROR(VLOOKUP(Q76,V7_ISSUER_TABLE,3,FALSE),1),1) | AF76: =PRODUCT(W76:AE76) | AG76: =MIN(V7_BASE_SMM*AF76,V7_SMM_CAP) | AH76: =1-(1-AG76)^12 | AI76: =IFERROR(LN(W76)/(LN(W76)+LN(X76)+LN(Y76)+LN(Z76)+LN(AA76)+LN(AB76)+LN(AC76)+LN(AD76))*(AH76-V7_BASE_CPR),0) | AJ76: =IFERROR(LN(X76)/(LN(W76)+LN(X76)+LN(Y76)+LN(Z76)+LN(AA76)+LN(AB76)+LN(AC76)+LN(AD76))*(AH76-V7_BASE_CPR),0) | AK76: =IFERROR(LN(Y76)/(LN(W76)+LN(X76)+LN(Y76)+LN(Z76)+LN(AA76)+LN(AB76)+LN(AC76)+LN(AD76))*(AH76-V7_BASE_CPR),0) | AL76: =IFERROR(LN(Z76)/(LN(W76)+LN(X76)+LN(Y76)+LN(Z76)+LN(AA76)+LN(AB76)+LN(AC76)+LN(AD76))*(AH76-V7_BASE_CPR),0) | AM76: =IFERROR(LN(AA76)/(LN(W76)+LN(X76)+LN(Y76)+LN(Z76)+LN(AA76)+LN(AB76)+LN(AC76)+LN(AD76))*(AH76-V7_BASE_CPR),0) | AN76: =IFERROR(LN(AB76)/(LN(W76)+LN(X76)+LN(Y76)+LN(Z76)+LN(AA76)+LN(AB76)+LN(AC76)+LN(AD76))*(AH76-V7_BASE_CPR),0) | AO76: =IFERROR(LN(AC76)/(LN(W76)+LN(X76)+LN(Y76)+LN(Z76)+LN(AA76)+LN(AB76)+LN(AC76)+LN(AD76))*(AH76-V7_BASE_CPR),0) | AP76: =IFERROR(LN(AD76)/(LN(W76)+LN(X76)+LN(Y76)+LN(Z76)+LN(AA76)+LN(AB76)+LN(AC76)+LN(AD76))*(AH76-V7_BASE_CPR),0) | AQ76: =V7_BASE_CPR+SUM(AI76:AP76)-AH76
A77: 36200EL25_000000001711151 | B77: WALKER_PRE21 | C77: 36200EL25 | D77: WALKER & DUNLOP, LLC | E77: 223f | F77: RP | G77: 2012 | H77: 202602 | I77: 1567346.2 | J77: 3.33 | K77: 447 | L77: 0 | M77: 167 | N77: 35 | O77: 204705 | P77: 201305 | Q77: 4080 | R77: 0.20958084 | S77: 0 | T77: =LN(1+I77) | U77: =J77*100-K77 | V77: =U77-12.5*(L77+1) | W77: =IF(M77<=V7_AGE_KNOT_X_0,V7_AGE_KNOT_Y_0,IF(M77>=V7_AGE_KNOT_X_5,V7_AGE_KNOT_Y_5,IF(M77<=V7_AGE_KNOT_X_1,V7_AGE_KNOT_Y_0+(M77-V7_AGE_KNOT_X_0)/(V7_AGE_KNOT_X_1-V7_AGE_KNOT_X_0)*(V7_AGE_KNOT_Y_1-V7_AGE_KNOT_Y_0),IF(M77<=V7_AGE_KNOT_X_2,V7_AGE_KNOT_Y_1+(M77-V7_AGE_KNOT_X_1)/(V7_AGE_KNOT_X_2-V7_AGE_KNOT_X_1)*(V7_AGE_KNOT_Y_2-V7_AGE_KNOT_Y_1),IF(M77<=V7_AGE_KNOT_X_3,V7_AGE_KNOT_Y_2+(M77-V7_AGE_KNOT_X_2)/(V7_AGE_KNOT_X_3-V7_AGE_KNOT_X_2)*(V7_AGE_KNOT_Y_3-V7_AGE_KNOT_Y_2),IF(M77<=V7_AGE_KNOT_X_4,V7_AGE_KNOT_Y_3+(M77-V7_AGE_KNOT_X_3)/(V7_AGE_KNOT_X_4-V7_AGE_KNOT_X_3)*(V7_AGE_KNOT_Y_4-V7_AGE_KNOT_Y_3),V7_AGE_KNOT_Y_4+(M77-V7_AGE_KNOT_X_4)/(V7_AGE_KNOT_X_5-V7_AGE_KNOT_X_4)*(V7_AGE_KNOT_Y_5-V7_AGE_KNOT_Y_4))))))) | X77: =V7_RATE_FLOOR+V7_RATE_ASYMPTOTE/(1+EXP(-(V77-V7_RATE_MID)/V7_RATE_SLOPE)) | Y77: =MAX(V7_SIZE_LOW,MIN(V7_SIZE_HIGH,V7_SIZE_INTERCEPT+V7_SIZE_SLOPE*(T77-V7_SIZE_LOG_ANCHOR))) | Z77: =IF(ISNUMBER(SEARCH("232",E77)),VLOOKUP("232",V7_PROGRAM_TABLE,2,FALSE),IF(ISNUMBER(SEARCH("538",E77)),VLOOKUP("538",V7_PROGRAM_TABLE,2,FALSE),IF(ISNUMBER(SEARCH("223a7",E77)),VLOOKUP("223a7",V7_PROGRAM_TABLE,2,FALSE),IF(ISNUMBER(SEARCH("223f",E77)),VLOOKUP("223f",V7_PROGRAM_TABLE,2,FALSE),V7_PROGRAM_DEFAULT)))) | AA77: =IF(S77=1,1+V7_PURPOSE_NC_BUMP*MAX(0,1-ABS(M77-V7_PURPOSE_PEAK_AGE)/V7_PURPOSE_WIDTH),1) | AB77: =IF(AND(IF(OR(P77="",NOT(ISNUMBER(P77))),0,MAX(0,MIN(24,(INT(VALUE(H77)/100)-INT(P77/100))*12+MOD(VALUE(H77),100)-MOD(P77,100))))>0,IF(OR(P77="",NOT(ISNUMBER(P77))),0,MAX(0,MIN(24,(INT(VALUE(H77)/100)-INT(P77/100))*12+MOD(VALUE(H77),100)-MOD(P77,100))))<=12),1+V7_LOCKOUT_AMP*EXP(-(IF(OR(P77="",NOT(ISNUMBER(P77))),0,MAX(0,MIN(24,(INT(VALUE(H77)/100)-INT(P77/100))*12+MOD(VALUE(H77),100)-MOD(P77,100)))))/V7_LOCKOUT_TAU),1) | AC77: =IF(IF(OR(O77="",NOT(ISNUMBER(O77))),360,MAX(0,MIN(480,(INT(O77/100)-INT(VALUE(H77)/100))*12+MOD(O77,100)-MOD(VALUE(H77),100))))>0,1+V7_MTY_AMP*MAX(0,(V7_MTY_CUTOFF-(IF(OR(O77="",NOT(ISNUMBER(O77))),360,MAX(0,MIN(480,(INT(O77/100)-INT(VALUE(H77)/100))*12+MOD(O77,100)-MOD(VALUE(H77),100))))))/V7_MTY_CUTOFF),1) | AD77: =MAX(V7_BURN_FLOOR,1-V7_BURN_SLOPE*MIN(1,MAX(0,R77))) | AE77: =IF(V7_USE_ISSUER=1,IFERROR(VLOOKUP(Q77,V7_ISSUER_TABLE,3,FALSE),1),1) | AF77: =PRODUCT(W77:AE77) | AG77: =MIN(V7_BASE_SMM*AF77,V7_SMM_CAP) | AH77: =1-(1-AG77)^12 | AI77: =IFERROR(LN(W77)/(LN(W77)+LN(X77)+LN(Y77)+LN(Z77)+LN(AA77)+LN(AB77)+LN(AC77)+LN(AD77))*(AH77-V7_BASE_CPR),0) | AJ77: =IFERROR(LN(X77)/(LN(W77)+LN(X77)+LN(Y77)+LN(Z77)+LN(AA77)+LN(AB77)+LN(AC77)+LN(AD77))*(AH77-V7_BASE_CPR),0) | AK77: =IFERROR(LN(Y77)/(LN(W77)+LN(X77)+LN(Y77)+LN(Z77)+LN(AA77)+LN(AB77)+LN(AC77)+LN(AD77))*(AH77-V7_BASE_CPR),0) | AL77: =IFERROR(LN(Z77)/(LN(W77)+LN(X77)+LN(Y77)+LN(Z77)+LN(AA77)+LN(AB77)+LN(AC77)+LN(AD77))*(AH77-V7_BASE_CPR),0) | AM77: =IFERROR(LN(AA77)/(LN(W77)+LN(X77)+LN(Y77)+LN(Z77)+LN(AA77)+LN(AB77)+LN(AC77)+LN(AD77))*(AH77-V7_BASE_CPR),0) | AN77: =IFERROR(LN(AB77)/(LN(W77)+LN(X77)+LN(Y77)+LN(Z77)+LN(AA77)+LN(AB77)+LN(AC77)+LN(AD77))*(AH77-V7_BASE_CPR),0) | AO77: =IFERROR(LN(AC77)/(LN(W77)+LN(X77)+LN(Y77)+LN(Z77)+LN(AA77)+LN(AB77)+LN(AC77)+LN(AD77))*(AH77-V7_BASE_CPR),0) | AP77: =IFERROR(LN(AD77)/(LN(W77)+LN(X77)+LN(Y77)+LN(Z77)+LN(AA77)+LN(AB77)+LN(AC77)+LN(AD77))*(AH77-V7_BASE_CPR),0) | AQ77: =V7_BASE_CPR+SUM(AI77:AP77)-AH77
A78: 36180GT83_000000012111176 | B78: WALKER_PRE21 | C78: 36180GT83 | D78: WALKER & DUNLOP, LLC | E78: 223f | F78: RP | G78: 2013 | H78: 202602 | I78: 4626699.6 | J78: 4.35 | K78: 447 | L78: 0 | M78: 146 | N78: 41 | O78: 204904 | P78: 201605 | Q78: 4080 | R78: 0.28082192 | S78: 0 | T78: =LN(1+I78) | U78: =J78*100-K78 | V78: =U78-12.5*(L78+1) | W78: =IF(M78<=V7_AGE_KNOT_X_0,V7_AGE_KNOT_Y_0,IF(M78>=V7_AGE_KNOT_X_5,V7_AGE_KNOT_Y_5,IF(M78<=V7_AGE_KNOT_X_1,V7_AGE_KNOT_Y_0+(M78-V7_AGE_KNOT_X_0)/(V7_AGE_KNOT_X_1-V7_AGE_KNOT_X_0)*(V7_AGE_KNOT_Y_1-V7_AGE_KNOT_Y_0),IF(M78<=V7_AGE_KNOT_X_2,V7_AGE_KNOT_Y_1+(M78-V7_AGE_KNOT_X_1)/(V7_AGE_KNOT_X_2-V7_AGE_KNOT_X_1)*(V7_AGE_KNOT_Y_2-V7_AGE_KNOT_Y_1),IF(M78<=V7_AGE_KNOT_X_3,V7_AGE_KNOT_Y_2+(M78-V7_AGE_KNOT_X_2)/(V7_AGE_KNOT_X_3-V7_AGE_KNOT_X_2)*(V7_AGE_KNOT_Y_3-V7_AGE_KNOT_Y_2),IF(M78<=V7_AGE_KNOT_X_4,V7_AGE_KNOT_Y_3+(M78-V7_AGE_KNOT_X_3)/(V7_AGE_KNOT_X_4-V7_AGE_KNOT_X_3)*(V7_AGE_KNOT_Y_4-V7_AGE_KNOT_Y_3),V7_AGE_KNOT_Y_4+(M78-V7_AGE_KNOT_X_4)/(V7_AGE_KNOT_X_5-V7_AGE_KNOT_X_4)*(V7_AGE_KNOT_Y_5-V7_AGE_KNOT_Y_4))))))) | X78: =V7_RATE_FLOOR+V7_RATE_ASYMPTOTE/(1+EXP(-(V78-V7_RATE_MID)/V7_RATE_SLOPE)) | Y78: =MAX(V7_SIZE_LOW,MIN(V7_SIZE_HIGH,V7_SIZE_INTERCEPT+V7_SIZE_SLOPE*(T78-V7_SIZE_LOG_ANCHOR))) | Z78: =IF(ISNUMBER(SEARCH("232",E78)),VLOOKUP("232",V7_PROGRAM_TABLE,2,FALSE),IF(ISNUMBER(SEARCH("538",E78)),VLOOKUP("538",V7_PROGRAM_TABLE,2,FALSE),IF(ISNUMBER(SEARCH("223a7",E78)),VLOOKUP("223a7",V7_PROGRAM_TABLE,2,FALSE),IF(ISNUMBER(SEARCH("223f",E78)),VLOOKUP("223f",V7_PROGRAM_TABLE,2,FALSE),V7_PROGRAM_DEFAULT)))) | AA78: =IF(S78=1,1+V7_PURPOSE_NC_BUMP*MAX(0,1-ABS(M78-V7_PURPOSE_PEAK_AGE)/V7_PURPOSE_WIDTH),1) | AB78: =IF(AND(IF(OR(P78="",NOT(ISNUMBER(P78))),0,MAX(0,MIN(24,(INT(VALUE(H78)/100)-INT(P78/100))*12+MOD(VALUE(H78),100)-MOD(P78,100))))>0,IF(OR(P78="",NOT(ISNUMBER(P78))),0,MAX(0,MIN(24,(INT(VALUE(H78)/100)-INT(P78/100))*12+MOD(VALUE(H78),100)-MOD(P78,100))))<=12),1+V7_LOCKOUT_AMP*EXP(-(IF(OR(P78="",NOT(ISNUMBER(P78))),0,MAX(0,MIN(24,(INT(VALUE(H78)/100)-INT(P78/100))*12+MOD(VALUE(H78),100)-MOD(P78,100)))))/V7_LOCKOUT_TAU),1) | AC78: =IF(IF(OR(O78="",NOT(ISNUMBER(O78))),360,MAX(0,MIN(480,(INT(O78/100)-INT(VALUE(H78)/100))*12+MOD(O78,100)-MOD(VALUE(H78),100))))>0,1+V7_MTY_AMP*MAX(0,(V7_MTY_CUTOFF-(IF(OR(O78="",NOT(ISNUMBER(O78))),360,MAX(0,MIN(480,(INT(O78/100)-INT(VALUE(H78)/100))*12+MOD(O78,100)-MOD(VALUE(H78),100))))))/V7_MTY_CUTOFF),1) | AD78: =MAX(V7_BURN_FLOOR,1-V7_BURN_SLOPE*MIN(1,MAX(0,R78))) | AE78: =IF(V7_USE_ISSUER=1,IFERROR(VLOOKUP(Q78,V7_ISSUER_TABLE,3,FALSE),1),1) | AF78: =PRODUCT(W78:AE78) | AG78: =MIN(V7_BASE_SMM*AF78,V7_SMM_CAP) | AH78: =1-(1-AG78)^12 | AI78: =IFERROR(LN(W78)/(LN(W78)+LN(X78)+LN(Y78)+LN(Z78)+LN(AA78)+LN(AB78)+LN(AC78)+LN(AD78))*(AH78-V7_BASE_CPR),0) | AJ78: =IFERROR(LN(X78)/(LN(W78)+LN(X78)+LN(Y78)+LN(Z78)+LN(AA78)+LN(AB78)+LN(AC78)+LN(AD78))*(AH78-V7_BASE_CPR),0) | AK78: =IFERROR(LN(Y78)/(LN(W78)+LN(X78)+LN(Y78)+LN(Z78)+LN(AA78)+LN(AB78)+LN(AC78)+LN(AD78))*(AH78-V7_BASE_CPR),0) | AL78: =IFERROR(LN(Z78)/(LN(W78)+LN(X78)+LN(Y78)+LN(Z78)+LN(AA78)+LN(AB78)+LN(AC78)+LN(AD78))*(AH78-V7_BASE_CPR),0) | AM78: =IFERROR(LN(AA78)/(LN(W78)+LN(X78)+LN(Y78)+LN(Z78)+LN(AA78)+LN(AB78)+LN(AC78)+LN(AD78))*(AH78-V7_BASE_CPR),0) | AN78: =IFERROR(LN(AB78)/(LN(W78)+LN(X78)+LN(Y78)+LN(Z78)+LN(AA78)+LN(AB78)+LN(AC78)+LN(AD78))*(AH78-V7_BASE_CPR),0) | AO78: =IFERROR(LN(AC78)/(LN(W78)+LN(X78)+LN(Y78)+LN(Z78)+LN(AA78)+LN(AB78)+LN(AC78)+LN(AD78))*(AH78-V7_BASE_CPR),0) | AP78: =IFERROR(LN(AD78)/(LN(W78)+LN(X78)+LN(Y78)+LN(Z78)+LN(AA78)+LN(AB78)+LN(AC78)+LN(AD78))*(AH78-V7_BASE_CPR),0) | AQ78: =V7_BASE_CPR+SUM(AI78:AP78)-AH78
A79: 36178FVA1_000000012722086 | B79: WALKER_PRE21 | C79: 36178FVA1 | D79: WALKER & DUNLOP, LLC | E79: 232 | F79: RP | G79: 2012 | H79: 202602 | I79: 2391566.6 | J79: 2.8 | K79: 447 | L79: 0 | M79: 164 | N79: 26 | O79: 203708 | P79: 201308 | Q79: 4080 | R79: 0.15853659 | S79: 0 | T79: =LN(1+I79) | U79: =J79*100-K79 | V79: =U79-12.5*(L79+1) | W79: =IF(M79<=V7_AGE_KNOT_X_0,V7_AGE_KNOT_Y_0,IF(M79>=V7_AGE_KNOT_X_5,V7_AGE_KNOT_Y_5,IF(M79<=V7_AGE_KNOT_X_1,V7_AGE_KNOT_Y_0+(M79-V7_AGE_KNOT_X_0)/(V7_AGE_KNOT_X_1-V7_AGE_KNOT_X_0)*(V7_AGE_KNOT_Y_1-V7_AGE_KNOT_Y_0),IF(M79<=V7_AGE_KNOT_X_2,V7_AGE_KNOT_Y_1+(M79-V7_AGE_KNOT_X_1)/(V7_AGE_KNOT_X_2-V7_AGE_KNOT_X_1)*(V7_AGE_KNOT_Y_2-V7_AGE_KNOT_Y_1),IF(M79<=V7_AGE_KNOT_X_3,V7_AGE_KNOT_Y_2+(M79-V7_AGE_KNOT_X_2)/(V7_AGE_KNOT_X_3-V7_AGE_KNOT_X_2)*(V7_AGE_KNOT_Y_3-V7_AGE_KNOT_Y_2),IF(M79<=V7_AGE_KNOT_X_4,V7_AGE_KNOT_Y_3+(M79-V7_AGE_KNOT_X_3)/(V7_AGE_KNOT_X_4-V7_AGE_KNOT_X_3)*(V7_AGE_KNOT_Y_4-V7_AGE_KNOT_Y_3),V7_AGE_KNOT_Y_4+(M79-V7_AGE_KNOT_X_4)/(V7_AGE_KNOT_X_5-V7_AGE_KNOT_X_4)*(V7_AGE_KNOT_Y_5-V7_AGE_KNOT_Y_4))))))) | X79: =V7_RATE_FLOOR+V7_RATE_ASYMPTOTE/(1+EXP(-(V79-V7_RATE_MID)/V7_RATE_SLOPE)) | Y79: =MAX(V7_SIZE_LOW,MIN(V7_SIZE_HIGH,V7_SIZE_INTERCEPT+V7_SIZE_SLOPE*(T79-V7_SIZE_LOG_ANCHOR))) | Z79: =IF(ISNUMBER(SEARCH("232",E79)),VLOOKUP("232",V7_PROGRAM_TABLE,2,FALSE),IF(ISNUMBER(SEARCH("538",E79)),VLOOKUP("538",V7_PROGRAM_TABLE,2,FALSE),IF(ISNUMBER(SEARCH("223a7",E79)),VLOOKUP("223a7",V7_PROGRAM_TABLE,2,FALSE),IF(ISNUMBER(SEARCH("223f",E79)),VLOOKUP("223f",V7_PROGRAM_TABLE,2,FALSE),V7_PROGRAM_DEFAULT)))) | AA79: =IF(S79=1,1+V7_PURPOSE_NC_BUMP*MAX(0,1-ABS(M79-V7_PURPOSE_PEAK_AGE)/V7_PURPOSE_WIDTH),1) | AB79: =IF(AND(IF(OR(P79="",NOT(ISNUMBER(P79))),0,MAX(0,MIN(24,(INT(VALUE(H79)/100)-INT(P79/100))*12+MOD(VALUE(H79),100)-MOD(P79,100))))>0,IF(OR(P79="",NOT(ISNUMBER(P79))),0,MAX(0,MIN(24,(INT(VALUE(H79)/100)-INT(P79/100))*12+MOD(VALUE(H79),100)-MOD(P79,100))))<=12),1+V7_LOCKOUT_AMP*EXP(-(IF(OR(P79="",NOT(ISNUMBER(P79))),0,MAX(0,MIN(24,(INT(VALUE(H79)/100)-INT(P79/100))*12+MOD(VALUE(H79),100)-MOD(P79,100)))))/V7_LOCKOUT_TAU),1) | AC79: =IF(IF(OR(O79="",NOT(ISNUMBER(O79))),360,MAX(0,MIN(480,(INT(O79/100)-INT(VALUE(H79)/100))*12+MOD(O79,100)-MOD(VALUE(H79),100))))>0,1+V7_MTY_AMP*MAX(0,(V7_MTY_CUTOFF-(IF(OR(O79="",NOT(ISNUMBER(O79))),360,MAX(0,MIN(480,(INT(O79/100)-INT(VALUE(H79)/100))*12+MOD(O79,100)-MOD(VALUE(H79),100))))))/V7_MTY_CUTOFF),1) | AD79: =MAX(V7_BURN_FLOOR,1-V7_BURN_SLOPE*MIN(1,MAX(0,R79))) | AE79: =IF(V7_USE_ISSUER=1,IFERROR(VLOOKUP(Q79,V7_ISSUER_TABLE,3,FALSE),1),1) | AF79: =PRODUCT(W79:AE79) | AG79: =MIN(V7_BASE_SMM*AF79,V7_SMM_CAP) | AH79: =1-(1-AG79)^12 | AI79: =IFERROR(LN(W79)/(LN(W79)+LN(X79)+LN(Y79)+LN(Z79)+LN(AA79)+LN(AB79)+LN(AC79)+LN(AD79))*(AH79-V7_BASE_CPR),0) | AJ79: =IFERROR(LN(X79)/(LN(W79)+LN(X79)+LN(Y79)+LN(Z79)+LN(AA79)+LN(AB79)+LN(AC79)+LN(AD79))*(AH79-V7_BASE_CPR),0) | AK79: =IFERROR(LN(Y79)/(LN(W79)+LN(X79)+LN(Y79)+LN(Z79)+LN(AA79)+LN(AB79)+LN(AC79)+LN(AD79))*(AH79-V7_BASE_CPR),0) | AL79: =IFERROR(LN(Z79)/(LN(W79)+LN(X79)+LN(Y79)+LN(Z79)+LN(AA79)+LN(AB79)+LN(AC79)+LN(AD79))*(AH79-V7_BASE_CPR),0) | AM79: =IFERROR(LN(AA79)/(LN(W79)+LN(X79)+LN(Y79)+LN(Z79)+LN(AA79)+LN(AB79)+LN(AC79)+LN(AD79))*(AH79-V7_BASE_CPR),0) | AN79: =IFERROR(LN(AB79)/(LN(W79)+LN(X79)+LN(Y79)+LN(Z79)+LN(AA79)+LN(AB79)+LN(AC79)+LN(AD79))*(AH79-V7_BASE_CPR),0) | AO79: =IFERROR(LN(AC79)/(LN(W79)+LN(X79)+LN(Y79)+LN(Z79)+LN(AA79)+LN(AB79)+LN(AC79)+LN(AD79))*(AH79-V7_BASE_CPR),0) | AP79: =IFERROR(LN(AD79)/(LN(W79)+LN(X79)+LN(Y79)+LN(Z79)+LN(AA79)+LN(AB79)+LN(AC79)+LN(AD79))*(AH79-V7_BASE_CPR),0) | AQ79: =V7_BASE_CPR+SUM(AI79:AP79)-AH79
